{
  "library": "String Functions",
  "title": "DELETE (Function)",
  "url": "https://content.helpme-codesys.com/en/libs/String Functions/Current/StrFunc/Functions/DELETE.html",
  "page_title": "DELETE (FUN)",
  "text": "Library Information\nGetLibVersion (Function)\nGetLibVersionNumber (Function)\nIsLibReleased (Function)\nStrFunc\nAliases\nIString (Alias)\nEnums\nERROR (Enum)\nFunctions\nCONCAT (Function)\nCOUNT (Function)\nDELETE (Function)\nFIND (Function)\nINSERT (Function)\nLEFT (Function)\nLEN (Function)\nMID (Function)\nREPLACE (Function)\nRIGHT (Function)\nFile and Project Information\nLibrary Reference\nString Segments\nLibrary Identification\nLibrary Properties\nSysMem\nLibrary Identification\nLibrary Properties\nUTF-8 Encoding Support\nLibrary Identification\nLibrary Properties\nString Functions\nDocs\n»\nStrFunc\n»\nFunctions\n»\nDELETE (FUN)\nDELETE (FUN)\nÂ¶\nFUNCTION DELETE :\nIString\nDeletes a number of runes from a string\nReturns 0 in case of\neErrorID\n<>\nERROR.NO_ERROR\nInOut:\nScope\nName\nType\nComment\nReturn\nDELETE\nIString\nInput\nitfString\nIString\nThe original String, will not be modified\nudiCount\nUDINT\nLength of the partial string to be deleted, number of runes\nudiStart\nUDINT\nPosition in\nitfString\nafter which the deletion starts\nRunes counted from left\nMust be greater than 0 (See\nRIGHT\n, if the right part of a string is needed)\nitfResource\nIString\nThe resource that this function is working on. It will\ncontain the result after the function call and will also be\nreturned by this function so it can be used in nested calls.\nOutput\neErrorID\nERROR",
  "tables": [
    {
      "headers": [
        "Scope",
        "Name",
        "Type",
        "Comment"
      ],
      "rows": [
        {
          "Scope": "Return",
          "Name": "DELETE",
          "Type": "IString",
          "Comment": ""
        },
        {
          "Scope": "Input",
          "Name": "itfString",
          "Type": "IString",
          "Comment": "The original String, will not be modified"
        },
        [
          "udiCount",
          "UDINT",
          "Length of the partial string to be deleted, number of runes"
        ],
        [
          "udiStart",
          "UDINT",
          "Position initfStringafter which the deletion startsRunes counted from leftMust be greater than 0 (SeeRIGHT, if the right part of a string is needed)"
        ],
        [
          "itfResource",
          "IString",
          "The resource that this function is working on. It will\ncontain the result after the function call and will also be\nreturned by this function so it can be used in nested calls."
        ],
        {
          "Scope": "Output",
          "Name": "eErrorID",
          "Type": "ERROR",
          "Comment": ""
        }
      ]
    }
  ]
}