{
  "library": "SM3_CNC",
  "title": "SMC_ExtendedVelocityChecks (FunctionBlock)",
  "url": "https://content.helpme-codesys.com/en/libs/SM3_CNC/Current/SM_CNC_POUs/SoftMotion-CNC/SoftMotion-Function-Blocks/SMC_ExtendedVelocityChecks.html",
  "page_title": "SMC_ExtendedVelocityChecks (FB)",
  "text": "GlobalTextList (GlobalTextList)\nImagePool_cnc_sm3 (ImagePool)\nImages\nLibrary Information\nGetLibVersion (Function)\nGetLibVersionNumber (Function)\nIsLibReleased (Function)\nProjektinformationen\nGetBooleanProperty (Function)\nGetCompany (Function)\nGetNumberProperty (Function)\nGetTextProperty (Function)\nGetTextProperty2 (Function)\nGetTitle (Function)\nGetVersion (Function)\nGetVersionProperty (Function)\nSM3_CNC_GetVersion (Function)\nSMC_CNC_LibParams (ParamList)\nSM_CNC_Data types\nFile\nSMC_SINGLEVAR (Struct)\nSMC_TOKENTYPE (Enum)\nSMC_VARLIST (Struct)\nSMC_VARTYPE (Enum)\nSoftMotion CNC\nSMC_ABC_SLOPES_AT_STOP (Enum)\nSMC_ABC_SLOPES_NO_STOP (Enum)\nSMC_ADDAXIS (Enum)\nSMC_AL_STATUS (Enum)\nSMC_CNC_REF (FunctionBlock)\nSMC_DEC_STATUS (Enum)\nSMC_DIRECTION (Enum)\nSMC_GAddress (Alias)\nSMC_GCODEVIEWER_DATA (Struct)\nSMC_GCODE_TEXT (Struct)\nSMC_GCODE_WORD (Struct)\nSMC_GCodeObjectId (Struct)\nSMC_GEOINFO (Struct)\nSMC_GWord (Struct)\nSMC_INT_STATUS (Enum)\nSMC_INT_VELMODE (Enum)\nSMC_LINE_3D (Struct)\nSMC_MOVTYP (Enum)\nSMC_M_PARAMETERS (Struct)\nSMC_OBJECTSPLITTERMODE (Enum)\nSMC_ORI_CONVENTION (Enum)\nSMC_OUTQUEUE (FunctionBlock)\nbFull (Property)\nSMC_PLANE_H (Struct)\nSMC_POSINFO (Struct)\nSMC_SEGMENT (Struct)\nSMC_SEGMENTTYPE (Enum)\nSMC_SMOOTHBSPLINE_MODE (Enum)\nSMC_SMOOTHPATHADDAXMODE (Enum)\nSMC_SMOOTHPATHMODE (Enum)\nSMC_Seg (Struct)\nSMC_TC_STATUS (Enum)\nSMC_TOOLCORRMODE (Enum)\nSMC_VECTOR6D (Struct)\nSM_CNC_POUs\nFile\nReadNCFile\nSMC_ReadNCFile (FunctionBlock)\nStream\nToken\nSMC_ReadNCQueue (FunctionBlock)\nCloseFile (Action)\nhelp functions\nSMC_StringBuffer (FunctionBlock)\nNC2\nGSentence\nSMC_GExpToken_Iterator (FunctionBlock)\nSMC_GJUMP_COMMAND (Enum)\nSMC_GJUMP_TARGET (Union)\nSMC_GSentence (Struct)\nSMC_GSentenceQueue (FunctionBlock)\nSMC_GSentence_DynCall (Struct)\nSMC_GSentence_GWords (Struct)\nSMC_GSentence_GWords_Create (Function)\nSMC_GSentence_Iterator (FunctionBlock)\nSMC_GSentence_Let (Struct)\nSMC_GSentence_SubCall (Struct)\nSMC_GSentence_SubRet (Struct)\nSMC_GSentence_Type (Enum)\nSMC_GSentence_Union (Union)\nSMC_GVarDecl (Struct)\nSMC_GVar_Type (Enum)\nSMC_GWord_Iterator (FunctionBlock)\nSMC_NC_CopySentence (Function)\nSMC_NC_CopySentenceChecked (Function)\nGSentenceJumpBuffer\nSMC_GSentenceJumpBuffer (FunctionBlock)\nInterpreter\nCallstack\nSMC_NCInterpreter (FunctionBlock)\nParser\nExpressions\nSMC_NCTokenParser (FunctionBlock)\nSMC_NC_SourcePosition (Struct)\nSymbolTable\nReadNCFile2\nSMC_IGSentenceModifier (Interface)\nSMC_INCLookup (Interface)\nSMC_ITokenModifier (Interface)\nSMC_NCLookupFile (FunctionBlock)\nSMC_NCNavigator (FunctionBlock)\nSMC_NC_CanProcessTokens (Function)\nSMC_NC_FindProgramFile (Function)\nSMC_NC_PrependDefaults (FunctionBlock)\nSMC_NC_TokenQueue_Completed (Function)\nSMC_ReadNCFile2 (FunctionBlock)\nSMC_ReadNCFromStream (FunctionBlock)\nSoftMotion CNC\nCoordinate Transformations\nSMC_CoordinateTransformation3D (FunctionBlock)\nSMC_DetermineCuboidBearing (FunctionBlock)\nSMC_InvCoordinateTransformation3D (FunctionBlock)\nSMC_TeachCoordinateSystem (FunctionBlock)\nSMC_UnitVectorToRPY (FunctionBlock)\nDirect Axis Control\nSMC_ControlAxisByPos (FunctionBlock)\nSMC_ControlAxisByPosVel (FunctionBlock)\nSMC_ControlAxisByVel (FunctionBlock)\nGCode Viewer\nSMC_GCodeViewer (FunctionBlock)\nGeoInfo Help Functions\nSMC_AdaptHelpMarks (Function)\nSMC_CalcEndPnt (Function)\nSMC_CalcLengthGeo (Function)\nSMC_CalcStartPnt (Function)\nSMC_CutEnd (Function)\nSMC_CutStart (Function)\nSMC_GeoinfoInit (Function)\nSMC_GetAccVec (Function)\nSMC_GetAddAxValue (Function)\nSMC_GetClosestPnt (Function)\nSMC_GetLengthOfPrefix (Function)\nSMC_GetPnt (Function)\nSMC_GetPntPI (Function)\nSMC_GetTanVec (Function)\nSMC_GetTanVec3D (Function)\nSMC_InvertDirection (Function)\nSMC_RampInCorr (Function)\nSMC_RampOutCorr (Function)\nSMC_RecalculateHelpMarks (Function)\nSMC_SingleCorr (Function)\nOutQueue Functions\nSMC_AppendObj (Function)\nSMC_DeleteObj (Function)\nSMC_GetCount (Function)\nSMC_GetHistoryCount (Function)\nSMC_GetLastObj (Function)\nSMC_GetObj (Function)\nSMC_GetObjFromEnd (Function)\nSMC_GetObjFromHistory (Function)\nSMC_OutQueueInit (Function)\nSMC_OutQueueIsSyncing (Function)\nSMC_OutQueue_IsFull (Function)\nSMC_RestoreQueue (Function)\nSMC_SetObj (Function)\nSMC_SetQueueCapacity (Function)\nPosinfo Functions\nSMC_PosInfo_Trf_Inverse (Function)\nSMC_PosInfo_Trf_Mult (Function)\nQueue manipulation\nSMC_QueueSetReservedEntries (FunctionBlock)\nSMC_RotateQueue2D (FunctionBlock)\nSMC_ScaleQueue3D (FunctionBlock)\nSMC_TranslateQueue3D (FunctionBlock)\nSoftMotion Function Blocks\nBlockSearch\nDecoderBuffer\nInterpolator_Help_Functions\nM_Functions\nNCDecoder_Help_Functions\nSMC_AddGCodeState (Struct)\nSMC_AvoidLoop (FunctionBlock)\nSMC_CheckForLimits (FunctionBlock)\nSMC_CheckVelocities (FunctionBlock)\nSMC_ExtendedVelocityChecks (FunctionBlock)\nSMC_Interpolator (FunctionBlock)\nSMC_Interpolator2Dir (FunctionBlock)\nSMC_Interpolator2Dir_SlowTask (FunctionBlock)\nSMC_LimitCircularVelocity (FunctionBlock)\nSMC_LimitDynamics (FunctionBlock)\nSMC_NCDecoder (FunctionBlock)\nSMC_ObjectSplitter (FunctionBlock)\nSMC_ReadAdditionalIpoState (FunctionBlock)\nSMC_RecomputeABCSlopes (FunctionBlock)\nSMC_ReduceVelEndAtCorner (FunctionBlock)\nSMC_RoundPath (FunctionBlock)\nSMC_SegmentAnalyzer (FunctionBlock)\nSMC_SetInterpreterStartPosition (FunctionBlock)\nSMC_SmoothAddAxes (FunctionBlock)\nSMC_SmoothBSpline (FunctionBlock)\nSMC_SmoothMerge (FunctionBlock)\nSMC_SmoothPath (FunctionBlock)\nSMC_ToolCorr (FunctionBlock)\nSMC_ToolLengthCorr (FunctionBlock)\nSMC_ToolRadiusCorr (FunctionBlock)\nSMC_XInterpolator (FunctionBlock)\nSM_Trafo_Data types\nSMC_ArticulatedRobot_6DOF_J0_State (Enum)\nSMC_ArticulatedRobot_6DOF_J1_State (Enum)\nSMC_ArticulatedRobot_6DOF_J4_State (Enum)\nSMC_TrafoConfig_4AxisPalletizer (Struct)\nSMC_TrafoConfig_ArticulatedRobot_6DOF (Struct)\nSMC_TrafoResult_4AxisPalletizer (Enum)\nSMC_TrafoResult_ArticulatedRobot_6DOF (Enum)\nSMC_VECTORDIR (Enum)\nSM_Trafo_POUs\nForward and inverse transformation\nSMC_TRAFOV_\nSoftMotion Transformations\nGantry systems\nParallel Systems\nRobot Kinematiks\nScara System\nWrapper\nadditional FBs\nVisu_Templates\nFile\nCNC\nSM_CNC_Visualizations\nFBs\nCNC\nDirect Axis Control\nTranslation & Rotation & Scaling\nhelp visu\nSM_Trafo_Visualizations\nTrafo templates\nGantry\nParallel\nRobot\nScara\nVisu_Templates_New\nFramed Visu Helpers\nTextListForCombobox_MC_DIRECTION (TextList)\nTextListForCombobox_SMC_ABC_SLOPES_AT_STOP (TextList)\nTextListForCombobox_SMC_ABC_SLOPES_NO_STOP (TextList)\nTextListForCombobox_SMC_AL_STATUS (TextList)\nTextListForCombobox_SMC_DEC_STATUS (TextList)\nTextListForCombobox_SMC_DIRECTION (TextList)\nTextListForCombobox_SMC_ERROR (TextList)\nTextListForCombobox_SMC_INT_STATUS (TextList)\nTextListForCombobox_SMC_INT_VELMODE (TextList)\nTextListForCombobox_SMC_ORI_CONVENTION (TextList)\nTextListForCombobox_SMC_SMOOTHBSPLINE_MODE (TextList)\nTextListForCombobox_SMC_SMOOTHPATHADDAXMODE (TextList)\nTextListForCombobox_SMC_SMOOTHPATHMODE (TextList)\nTextListForCombobox_SMC_TC_STATUS (TextList)\nTextListForCombobox_SMC_TOOLCORRMODE (TextList)\nFile and Project Information\nLibrary Reference\n3SLicense\nLibrary Identification\nLibrary Properties\nBase Interfaces\nLibrary Identification\nLibrary Properties\nCmpLog\nLibrary Identification\nLibrary Properties\nFloatingPointUtils\nLibrary Identification\nLibrary Properties\nMatrix\nLibrary Identification\nLibrary Properties\nSM3_Basic\nLibrary Identification\nLibrary Properties\nLibrary Parameter\nSM3_RBase\nLibrary Identification\nLibrary Properties\nSM3_Shared\nLibrary Identification\nLibrary Properties\nSM3_Transformation\nLibrary Identification\nLibrary Properties\nStandard\nLibrary Identification\nLibrary Properties\nSysFile\nLibrary Identification\nLibrary Properties\nSysMem\nLibrary Identification\nLibrary Properties\nSysTarget\nLibrary Identification\nLibrary Properties\nSysTypes2 Interfaces\nLibrary Identification\nLibrary Properties\nVisuElem3DPath\nLibrary Identification\nLibrary Properties\nLibrary Parameter\nVisuElemCamDisplayer\nLibrary Identification\nLibrary Properties\nLibrary Parameter\nVisuElemMeter\nLibrary Identification\nLibrary Properties\nVisuElemTextEditor\nLibrary Identification\nLibrary Properties\nVisuElemTrace\nLibrary Identification\nLibrary Properties\nVisuElems\nLibrary Identification\nLibrary Properties\nVisuElemsAlarm\nLibrary Identification\nLibrary Properties\nVisuElemsDateTime\nLibrary Identification\nLibrary Properties\nVisuElemsSpecialControls\nLibrary Identification\nLibrary Properties\nVisuElemsWinControls\nLibrary Identification\nLibrary Properties\nVisuInputs\nLibrary Identification\nLibrary Properties\nVisuNativeControl\nLibrary Identification\nLibrary Properties\nSM3_CNC\nDocs\n»\nSM_CNC_POUs\n»\nSoftMotion\nCNC\n»\nSoftMotion\nFunction\nBlocks\n»\nSMC_ExtendedVelocityChecks (FB)\nSMC_ExtendedVelocityChecks (FB)\nÂ¶\nFUNCTION_BLOCK SMC_ExtendedVelocityChecks\nThis function limits the velocity, acceleration and deceleration\nof the path so that the resulting velocity, acceleration and\ndeceleration for the additional axes\n(P, Q, U, V, W, A, B, C and additionally Z for in 2D mode)\ndo not exceed the values set in\nF<Axis>\nand\nE<Axis>\n.\nThese limits are typically defined in the G-code by using the\nG-code words FZ, FP, FQ, FU, FV, FW, FA, FB, FC, and\nEZ, EP, EQ, EU, EV, EW, EA, eB, EC.\nFZ0, FP0, â¦, FC0 reset the velocity limit of the additional axis.\nEZ0, EP0, â¦, EC0 reset the limitation of acceleration or\ndeceleration of the additional axis.\nFZ and EZ are only valid in the 2D-mode.\nExample\nIn sentence N0, the acceleration of additional axis P is\nlimited to 10, the deceleration is limited to 13. In sentence N1, the\nlimitations on additional axis P are reset again (EP0).\nG-Code\n:\nN0\nG1\nX100\nEP10\nEP\n-13\nP100\nN1\nG1\nX200\nEP0\nP0\nE<axis>/F<axis>\nThe following code is used to define velocity/acceleration/deceleration\nof a additional axes <axis> by E<axis>/F<axis>.\nG-Code\nN20 M9\nN030 F10 E40.0 E-40.0\nN040 M8\nN050 G92 X0.0 Y0.0 Z570.0 U35.0 V225.0 W20.0 P382.0 (Starting position)\nN060 G1 X0.0 Y0.0 Z570.0 U35.0 V225.0 W20.0 P382.0\nN230 G0 X0.0 F200.0 E200.0 E-200.0\nN240 M7\nN250 F50.0 E40.0 E-40.0\nN260 G0 U100.0 V158.0 W100.0 P260.0 Y100.0 Z400.0 F50.0\nN270 G0 V125.0 P260.0 Z400.0 FV1.25 EV500 EV-500 (additional axis V is set)\nN280 G0 V170.0 P260.0 Z400.0 FV50.0\nN285 G0 V170.0 P260.0 Z400.0 FP100.0 EP500 EP-500 (additional axis P is set)\nN290 G0 X0.0 F200.0 E200.0 E-200.0\nN300 M7\nN310 F50.0 E40.0 E-40.0\nN320 G0 U100.0 V158.0 W100.0 P260.0 Y100.0 Z400.0 F50.0\nN330 G0 V125.0 P260.0 Z400.0 F1.25\nN340 G0 V170.0 P260.0 Z400.0 F50.0\nN350 M8\nInOut:\nScope\nName\nType\nComment\nInput\nbExecute\nBOOL\nExecution starts on the rising edge.\nbAbort\nBOOL\nIf\nFALSE\nat a rising edge of\nbExecute\n,\nthe output queue\npoqDataOut\nis emptied\nbAppend\nBOOL\nIf\nFALSE\nat a rising edge of\nbExecute\n,\nthe output queue\npoqDataOut\nis emptied\npoqDataIn\nPOINTER TO\nSMC_OUTQUEUE\nThis input points to the\nSMC_OUTQUEUE\nstructure object,\nwhich describes the\nSMC_GEOINFO\nobjects of the path;\ntypically it points to the output\npoqDataOut\nof the\npreceding module (e.g.\nSMC_NCDecoder\n/\nSMC_SmoothPath\n).\nnSizeOutQueue\nUDINT\nThis variable contains the size of the data buffer,\nthe list of\nSMC_GEOINFO\nstructure objects will be written to.\nThis buffer must be able to hold at least five\nSMC_GEOINFO\nobjects.\nOtherwise, the function block will not execute any actions at all.\nIts size may be predefined, but may be modified later only during a reset.\nIt is recommended to create the buffer as described by the example below:\nExampleBuf:\nARRAY[1..50]\nOF\nSMC_GEOINFO\nThe appropriate buffer size will then be retrieved\nby use of the operator\nsizeof(ExampleBuf)\n.\npbyBufferOutQueue\nPOINTER TO ARRAY [0..0]\nOF SMC_GEOINFO\nThis input must point to the first byte of the memory area\nthat is allocated for the\nSMC_OUTQUEUE\nstructure.\nThis area must be at least as big as defined in\nnSizeOutQueue\n.\nTypically the allocation of the memory buffer is done in the\ndeclaration part of the IEC-program by defining an array\nof\nSMC_GEOINFO\ne.g.\nBUF:\nARRAY[1..50]\nOF\nSMC_GEOINFO\n;\nfor a buffer that can store 50 path elements).\nThe value may be predefined, but may be modified later on only during a reset.\nbStrictlyHoldAccDecABC\nBOOL\nIf TRUE, the maximal accelerations and decelerations of A, B, C are strictly held.\nOtherwise, we use a heuristic that may lead to quicker profiles, but occasionally violate\nthe A/B/C-acceleration-limit, if A/B/C move quickly while\nthere is an ac- / deceleration on the path.\nOutput\nbDone\nBOOL\nbBusy\nBOOL\nTRUE\n, while execution of function block is not finished\nand the process on the path object is still running\nbError\nBOOL\nSignals that an error has occurred within the function block\nwErrorID\nSMC_ERROR\nError identification\npoqDataOut\nPOINTER TO\nSMC_OUTQUEUE\nThis variable points to a\nSMC_OUTQUEUE\nstructure,\nwhich manages the\nSMC_GEOINFO\nobjects of the loopless path.\nStructure:\nSMC_DoBeforeLeave (Action)\nSMC_ExtendedVelocityChecksInit (Action)",
  "tables": [
    {
      "headers": [
        "Scope",
        "Name",
        "Type",
        "Comment"
      ],
      "rows": [
        {
          "Scope": "Input",
          "Name": "bExecute",
          "Type": "BOOL",
          "Comment": "Execution starts on the rising edge."
        },
        [
          "bAbort",
          "BOOL",
          "IfFALSEat a rising edge ofbExecute,\nthe output queuepoqDataOutis emptied"
        ],
        [
          "bAppend",
          "BOOL",
          "IfFALSEat a rising edge ofbExecute,\nthe output queuepoqDataOutis emptied"
        ],
        [
          "poqDataIn",
          "POINTER TOSMC_OUTQUEUE",
          "This input points to theSMC_OUTQUEUEstructure object,\nwhich describes theSMC_GEOINFOobjects of the path;\ntypically it points to the outputpoqDataOutof the\npreceding module (e.g.SMC_NCDecoder/SMC_SmoothPath)."
        ],
        [
          "nSizeOutQueue",
          "UDINT",
          "This variable contains the size of the data buffer,\nthe list ofSMC_GEOINFOstructure objects will be written to.\nThis buffer must be able to hold at least fiveSMC_GEOINFOobjects.\nOtherwise, the function block will not execute any actions at all.\nIts size may be predefined, but may be modified later only during a reset.\nIt is recommended to create the buffer as described by the example below:ExampleBuf:ARRAY[1..50]OFSMC_GEOINFOThe appropriate buffer size will then be retrieved\nby use of the operatorsizeof(ExampleBuf)."
        ],
        [
          "pbyBufferOutQueue",
          "POINTER TO ARRAY [0..0]\nOF SMC_GEOINFO",
          "This input must point to the first byte of the memory area\nthat is allocated for theSMC_OUTQUEUEstructure.\nThis area must be at least as big as defined innSizeOutQueue.\nTypically the allocation of the memory buffer is done in the\ndeclaration part of the IEC-program by defining an array\nofSMC_GEOINFOe.g.BUF:ARRAY[1..50]OFSMC_GEOINFO;\nfor a buffer that can store 50 path elements).\nThe value may be predefined, but may be modified later on only during a reset."
        ],
        [
          "bStrictlyHoldAccDecABC",
          "BOOL",
          "If TRUE, the maximal accelerations and decelerations of A, B, C are strictly held.\nOtherwise, we use a heuristic that may lead to quicker profiles, but occasionally violate\nthe A/B/C-acceleration-limit, if A/B/C move quickly while\nthere is an ac- / deceleration on the path."
        ],
        {
          "Scope": "Output",
          "Name": "bDone",
          "Type": "BOOL",
          "Comment": ""
        },
        [
          "bBusy",
          "BOOL",
          "TRUE, while execution of function block is not finished\nand the process on the path object is still running"
        ],
        [
          "bError",
          "BOOL",
          "Signals that an error has occurred within the function block"
        ],
        [
          "wErrorID",
          "SMC_ERROR",
          "Error identification"
        ],
        [
          "poqDataOut",
          "POINTER TOSMC_OUTQUEUE",
          "This variable points to aSMC_OUTQUEUEstructure,\nwhich manages theSMC_GEOINFOobjects of the loopless path."
        ]
      ]
    }
  ]
}