{
  "library": "SM3_CNC",
  "title": "SMC_SmoothAddAxes (FunctionBlock)",
  "url": "https://content.helpme-codesys.com/en/libs/SM3_CNC/Current/SM_CNC_POUs/SoftMotion-CNC/SoftMotion-Function-Blocks/SMC_SmoothAddAxes.html",
  "page_title": "SMC_SmoothAddAxes (FB)",
  "text": "GlobalTextList (GlobalTextList)\nImagePool_cnc_sm3 (ImagePool)\nImages\nLibrary Information\nGetLibVersion (Function)\nGetLibVersionNumber (Function)\nIsLibReleased (Function)\nProjektinformationen\nGetBooleanProperty (Function)\nGetCompany (Function)\nGetNumberProperty (Function)\nGetTextProperty (Function)\nGetTextProperty2 (Function)\nGetTitle (Function)\nGetVersion (Function)\nGetVersionProperty (Function)\nSM3_CNC_GetVersion (Function)\nSMC_CNC_LibParams (ParamList)\nSM_CNC_Data types\nFile\nSMC_SINGLEVAR (Struct)\nSMC_TOKENTYPE (Enum)\nSMC_VARLIST (Struct)\nSMC_VARTYPE (Enum)\nSoftMotion CNC\nSMC_ABC_SLOPES_AT_STOP (Enum)\nSMC_ABC_SLOPES_NO_STOP (Enum)\nSMC_ADDAXIS (Enum)\nSMC_AL_STATUS (Enum)\nSMC_CNC_REF (FunctionBlock)\nSMC_DEC_STATUS (Enum)\nSMC_DIRECTION (Enum)\nSMC_GAddress (Alias)\nSMC_GCODEVIEWER_DATA (Struct)\nSMC_GCODE_TEXT (Struct)\nSMC_GCODE_WORD (Struct)\nSMC_GCodeObjectId (Struct)\nSMC_GEOINFO (Struct)\nSMC_GWord (Struct)\nSMC_INT_STATUS (Enum)\nSMC_INT_VELMODE (Enum)\nSMC_LINE_3D (Struct)\nSMC_MOVTYP (Enum)\nSMC_M_PARAMETERS (Struct)\nSMC_OBJECTSPLITTERMODE (Enum)\nSMC_ORI_CONVENTION (Enum)\nSMC_OUTQUEUE (FunctionBlock)\nbFull (Property)\nSMC_PLANE_H (Struct)\nSMC_POSINFO (Struct)\nSMC_SEGMENT (Struct)\nSMC_SEGMENTTYPE (Enum)\nSMC_SMOOTHBSPLINE_MODE (Enum)\nSMC_SMOOTHPATHADDAXMODE (Enum)\nSMC_SMOOTHPATHMODE (Enum)\nSMC_Seg (Struct)\nSMC_TC_STATUS (Enum)\nSMC_TOOLCORRMODE (Enum)\nSMC_VECTOR6D (Struct)\nSM_CNC_POUs\nFile\nReadNCFile\nSMC_ReadNCFile (FunctionBlock)\nStream\nToken\nSMC_ReadNCQueue (FunctionBlock)\nCloseFile (Action)\nhelp functions\nSMC_StringBuffer (FunctionBlock)\nNC2\nGSentence\nSMC_GExpToken_Iterator (FunctionBlock)\nSMC_GJUMP_COMMAND (Enum)\nSMC_GJUMP_TARGET (Union)\nSMC_GSentence (Struct)\nSMC_GSentenceQueue (FunctionBlock)\nSMC_GSentence_DynCall (Struct)\nSMC_GSentence_GWords (Struct)\nSMC_GSentence_GWords_Create (Function)\nSMC_GSentence_Iterator (FunctionBlock)\nSMC_GSentence_Let (Struct)\nSMC_GSentence_SubCall (Struct)\nSMC_GSentence_SubRet (Struct)\nSMC_GSentence_Type (Enum)\nSMC_GSentence_Union (Union)\nSMC_GVarDecl (Struct)\nSMC_GVar_Type (Enum)\nSMC_GWord_Iterator (FunctionBlock)\nSMC_NC_CopySentence (Function)\nSMC_NC_CopySentenceChecked (Function)\nGSentenceJumpBuffer\nSMC_GSentenceJumpBuffer (FunctionBlock)\nInterpreter\nCallstack\nSMC_NCInterpreter (FunctionBlock)\nParser\nExpressions\nSMC_NCTokenParser (FunctionBlock)\nSMC_NC_SourcePosition (Struct)\nSymbolTable\nReadNCFile2\nSMC_IGSentenceModifier (Interface)\nSMC_INCLookup (Interface)\nSMC_ITokenModifier (Interface)\nSMC_NCLookupFile (FunctionBlock)\nSMC_NCNavigator (FunctionBlock)\nSMC_NC_CanProcessTokens (Function)\nSMC_NC_FindProgramFile (Function)\nSMC_NC_PrependDefaults (FunctionBlock)\nSMC_NC_TokenQueue_Completed (Function)\nSMC_ReadNCFile2 (FunctionBlock)\nSMC_ReadNCFromStream (FunctionBlock)\nSoftMotion CNC\nCoordinate Transformations\nSMC_CoordinateTransformation3D (FunctionBlock)\nSMC_DetermineCuboidBearing (FunctionBlock)\nSMC_InvCoordinateTransformation3D (FunctionBlock)\nSMC_TeachCoordinateSystem (FunctionBlock)\nSMC_UnitVectorToRPY (FunctionBlock)\nDirect Axis Control\nSMC_ControlAxisByPos (FunctionBlock)\nSMC_ControlAxisByPosVel (FunctionBlock)\nSMC_ControlAxisByVel (FunctionBlock)\nGCode Viewer\nSMC_GCodeViewer (FunctionBlock)\nGeoInfo Help Functions\nSMC_AdaptHelpMarks (Function)\nSMC_CalcEndPnt (Function)\nSMC_CalcLengthGeo (Function)\nSMC_CalcStartPnt (Function)\nSMC_CutEnd (Function)\nSMC_CutStart (Function)\nSMC_GeoinfoInit (Function)\nSMC_GetAccVec (Function)\nSMC_GetAddAxValue (Function)\nSMC_GetClosestPnt (Function)\nSMC_GetLengthOfPrefix (Function)\nSMC_GetPnt (Function)\nSMC_GetPntPI (Function)\nSMC_GetTanVec (Function)\nSMC_GetTanVec3D (Function)\nSMC_InvertDirection (Function)\nSMC_RampInCorr (Function)\nSMC_RampOutCorr (Function)\nSMC_RecalculateHelpMarks (Function)\nSMC_SingleCorr (Function)\nOutQueue Functions\nSMC_AppendObj (Function)\nSMC_DeleteObj (Function)\nSMC_GetCount (Function)\nSMC_GetHistoryCount (Function)\nSMC_GetLastObj (Function)\nSMC_GetObj (Function)\nSMC_GetObjFromEnd (Function)\nSMC_GetObjFromHistory (Function)\nSMC_OutQueueInit (Function)\nSMC_OutQueueIsSyncing (Function)\nSMC_OutQueue_IsFull (Function)\nSMC_RestoreQueue (Function)\nSMC_SetObj (Function)\nSMC_SetQueueCapacity (Function)\nPosinfo Functions\nSMC_PosInfo_Trf_Inverse (Function)\nSMC_PosInfo_Trf_Mult (Function)\nQueue manipulation\nSMC_QueueSetReservedEntries (FunctionBlock)\nSMC_RotateQueue2D (FunctionBlock)\nSMC_ScaleQueue3D (FunctionBlock)\nSMC_TranslateQueue3D (FunctionBlock)\nSoftMotion Function Blocks\nBlockSearch\nDecoderBuffer\nInterpolator_Help_Functions\nM_Functions\nNCDecoder_Help_Functions\nSMC_AddGCodeState (Struct)\nSMC_AvoidLoop (FunctionBlock)\nSMC_CheckForLimits (FunctionBlock)\nSMC_CheckVelocities (FunctionBlock)\nSMC_ExtendedVelocityChecks (FunctionBlock)\nSMC_Interpolator (FunctionBlock)\nSMC_Interpolator2Dir (FunctionBlock)\nSMC_Interpolator2Dir_SlowTask (FunctionBlock)\nSMC_LimitCircularVelocity (FunctionBlock)\nSMC_LimitDynamics (FunctionBlock)\nSMC_NCDecoder (FunctionBlock)\nSMC_ObjectSplitter (FunctionBlock)\nSMC_ReadAdditionalIpoState (FunctionBlock)\nSMC_RecomputeABCSlopes (FunctionBlock)\nSMC_ReduceVelEndAtCorner (FunctionBlock)\nSMC_RoundPath (FunctionBlock)\nSMC_SegmentAnalyzer (FunctionBlock)\nSMC_SetInterpreterStartPosition (FunctionBlock)\nSMC_SmoothAddAxes (FunctionBlock)\nSMC_SmoothBSpline (FunctionBlock)\nSMC_SmoothMerge (FunctionBlock)\nSMC_SmoothPath (FunctionBlock)\nSMC_ToolCorr (FunctionBlock)\nSMC_ToolLengthCorr (FunctionBlock)\nSMC_ToolRadiusCorr (FunctionBlock)\nSMC_XInterpolator (FunctionBlock)\nSM_Trafo_Data types\nSMC_ArticulatedRobot_6DOF_J0_State (Enum)\nSMC_ArticulatedRobot_6DOF_J1_State (Enum)\nSMC_ArticulatedRobot_6DOF_J4_State (Enum)\nSMC_TrafoConfig_4AxisPalletizer (Struct)\nSMC_TrafoConfig_ArticulatedRobot_6DOF (Struct)\nSMC_TrafoResult_4AxisPalletizer (Enum)\nSMC_TrafoResult_ArticulatedRobot_6DOF (Enum)\nSMC_VECTORDIR (Enum)\nSM_Trafo_POUs\nForward and inverse transformation\nSMC_TRAFOV_\nSoftMotion Transformations\nGantry systems\nParallel Systems\nRobot Kinematiks\nScara System\nWrapper\nadditional FBs\nVisu_Templates\nFile\nCNC\nSM_CNC_Visualizations\nFBs\nCNC\nDirect Axis Control\nTranslation & Rotation & Scaling\nhelp visu\nSM_Trafo_Visualizations\nTrafo templates\nGantry\nParallel\nRobot\nScara\nVisu_Templates_New\nFramed Visu Helpers\nTextListForCombobox_MC_DIRECTION (TextList)\nTextListForCombobox_SMC_ABC_SLOPES_AT_STOP (TextList)\nTextListForCombobox_SMC_ABC_SLOPES_NO_STOP (TextList)\nTextListForCombobox_SMC_AL_STATUS (TextList)\nTextListForCombobox_SMC_DEC_STATUS (TextList)\nTextListForCombobox_SMC_DIRECTION (TextList)\nTextListForCombobox_SMC_ERROR (TextList)\nTextListForCombobox_SMC_INT_STATUS (TextList)\nTextListForCombobox_SMC_INT_VELMODE (TextList)\nTextListForCombobox_SMC_ORI_CONVENTION (TextList)\nTextListForCombobox_SMC_SMOOTHBSPLINE_MODE (TextList)\nTextListForCombobox_SMC_SMOOTHPATHADDAXMODE (TextList)\nTextListForCombobox_SMC_SMOOTHPATHMODE (TextList)\nTextListForCombobox_SMC_TC_STATUS (TextList)\nTextListForCombobox_SMC_TOOLCORRMODE (TextList)\nFile and Project Information\nLibrary Reference\n3SLicense\nLibrary Identification\nLibrary Properties\nBase Interfaces\nLibrary Identification\nLibrary Properties\nCmpLog\nLibrary Identification\nLibrary Properties\nFloatingPointUtils\nLibrary Identification\nLibrary Properties\nMatrix\nLibrary Identification\nLibrary Properties\nSM3_Basic\nLibrary Identification\nLibrary Properties\nLibrary Parameter\nSM3_RBase\nLibrary Identification\nLibrary Properties\nSM3_Shared\nLibrary Identification\nLibrary Properties\nSM3_Transformation\nLibrary Identification\nLibrary Properties\nStandard\nLibrary Identification\nLibrary Properties\nSysFile\nLibrary Identification\nLibrary Properties\nSysMem\nLibrary Identification\nLibrary Properties\nSysTarget\nLibrary Identification\nLibrary Properties\nSysTypes2 Interfaces\nLibrary Identification\nLibrary Properties\nVisuElem3DPath\nLibrary Identification\nLibrary Properties\nLibrary Parameter\nVisuElemCamDisplayer\nLibrary Identification\nLibrary Properties\nLibrary Parameter\nVisuElemMeter\nLibrary Identification\nLibrary Properties\nVisuElemTextEditor\nLibrary Identification\nLibrary Properties\nVisuElemTrace\nLibrary Identification\nLibrary Properties\nVisuElems\nLibrary Identification\nLibrary Properties\nVisuElemsAlarm\nLibrary Identification\nLibrary Properties\nVisuElemsDateTime\nLibrary Identification\nLibrary Properties\nVisuElemsSpecialControls\nLibrary Identification\nLibrary Properties\nVisuElemsWinControls\nLibrary Identification\nLibrary Properties\nVisuInputs\nLibrary Identification\nLibrary Properties\nVisuNativeControl\nLibrary Identification\nLibrary Properties\nSM3_CNC\nDocs\n»\nSM_CNC_POUs\n»\nSoftMotion\nCNC\n»\nSoftMotion\nFunction\nBlocks\n»\nSMC_SmoothAddAxes (FB)\nSMC_SmoothAddAxes (FB)\nÂ¶\nFUNCTION_BLOCK SMC_SmoothAddAxes\nThis function smoothes motions of additional axes distributed over several objects.\nThis leads to a constant slope of the additional axes P, Q, U, V, W and to\nthe usage of an optimized polynomial motion profile by the axes A, B and C.\nActivation of smoothing\nSmoothing must be enabled and disabled in G-Code using G71 and G70.\nG71 starts the smoothing, G70 ends the smoothing. The additional axes that should\nbe smoothed are defined by the parameter L<Additional axis number>.\nDefinition of the additional axis number:\nParameter\nAdditional Axis\nL4\nA\nL5\nB\nL6\nC\nL7\nP\nL8\nQ\nL9\nU\nL10\nV\nL11\nW\nExample G-Code\nN0 G1 X100 A0 Q100 F100\nN10 G71 L8    (Turn on smoothing for Q)\nN20 G1 X200\nN30 G71 L4    (Turn on smoothing for A)\nN40 G1 X250\nN50 G1 X300\nN60 G1 X350\nN70 G1 X400 A100\nN80 G70 L4    (Turn off smoothing for A)\nN90 G1 X500 Q0\nN100 G70 L8   (Turn off smoothing for Q)\nNote\nThe output data buffer available to the function block must be large\nenough to contain a complete smoothing range.\nIf the output data buffer has space for n objects, no more than n-3\ninput objects can be smoothed. Otherwise, smoothing is exited with error.\nPROBE movements such as G31 are not supported. The error\nSMC_PROBE_G31_NOT_ALLOWED\nis reported if a PROBE movement\nis encountered while additional axis smoothing is active.\nInOut:\nScope\nName\nType\nInitial\nComment\nInput\nbExecute\nBOOL\nExecution starts on the rising edge.\nbAbort\nBOOL\nIf\nTRUE\n, the current processing of this function block\nis aborted\nbAppend\nBOOL\nAs long as this input is set to\nFALSE\n, the DataOut-queue will be\ncleared at each reset.\nAs long as it is set to\nTRUE\n, newly incoming data will be written\nto the end of the DataOut-queue.\npoqDataIn\nPOINTER TO\nSMC_OUTQUEUE\nThis input path queue\ndSmoothingPart\nLREAL\n0.5\nIn case of the additional axes A, B and C the user can determine,\nwhich part of the path is provided to the additional axes for\nacceleration/deceleration and which part is to operate with a\nconstant velocity.\n0\n: No acceleration/deceleration phase is set.\n1\n: No constant motion is to be created.\n0.5\n: The acceleration phase plus the deceleration phase requires\nthe same time than the constant motion.\ndAngleTol\nLREAL\n0.001\nFor a correct parametrization of the additional axes A, B and C it is\nimportant to know, whether a object crossing leads to a stop.\nThe input\ndAngleTol\n, which is also used in the function block\nSMC_CheckVelocities\nand in other preprocessing function blocks,\nis also required here. It should be occupied with always the same value.\nnSizeOutQueue\nUDINT\nThe size of pbyBufferOutQueue in bytes.\npbyBufferOutQueue\nPOINTER TO ARRAY [0..0]\nOF SMC_GEOINFO\nThis input must point to the first byte of the memory area being\nallocated for the\nSMC_OUTQUEUE\nstructure.\nThis area must be at least as big as defined in\nnSizeOutQueue\n.\nTypically the allocation of the memory buffer is done within the\ndeclaration part of the IEC-program by defining a byte-array\n(ExampleBuf:\nARRAY[1..50]\nOF\nSMC_GEOINFO;\n).\nThe value may be predefined, but may then be modified during a reset only.\nOutput\nbDone\nBOOL\nThis output will be set to\nTRUE\nas soon as the input path\nhas been processed completely.The function block\nwill not perform any further actions until it gets reset.\nbBusy\nBOOL\nTRUE\n, while execution of function block is not finished\nbError\nBOOL\nSignals, that an error has occurred within the function\nblock\nwErrorID\nSMC_ERROR\nError identification\npoqDataOut\nPOINTER TO\nSMC_OUTQUEUE\nThe output path queue\nStructure:\nDoBeforeLeave (Action)\nInitAction (Action)",
  "tables": [
    {
      "headers": [
        "Parameter",
        "Additional Axis"
      ],
      "rows": [
        {
          "Parameter": "L4",
          "Additional Axis": "A"
        },
        {
          "Parameter": "L5",
          "Additional Axis": "B"
        },
        {
          "Parameter": "L6",
          "Additional Axis": "C"
        },
        {
          "Parameter": "L7",
          "Additional Axis": "P"
        },
        {
          "Parameter": "L8",
          "Additional Axis": "Q"
        },
        {
          "Parameter": "L9",
          "Additional Axis": "U"
        },
        {
          "Parameter": "L10",
          "Additional Axis": "V"
        },
        {
          "Parameter": "L11",
          "Additional Axis": "W"
        }
      ]
    },
    {
      "headers": [
        "Scope",
        "Name",
        "Type",
        "Initial",
        "Comment"
      ],
      "rows": [
        {
          "Scope": "Input",
          "Name": "bExecute",
          "Type": "BOOL",
          "Initial": "",
          "Comment": "Execution starts on the rising edge."
        },
        [
          "bAbort",
          "BOOL",
          "",
          "IfTRUE, the current processing of this function block\nis aborted"
        ],
        [
          "bAppend",
          "BOOL",
          "",
          "As long as this input is set toFALSE, the DataOut-queue will be\ncleared at each reset.\nAs long as it is set toTRUE, newly incoming data will be written\nto the end of the DataOut-queue."
        ],
        [
          "poqDataIn",
          "POINTER TOSMC_OUTQUEUE",
          "",
          "This input path queue"
        ],
        [
          "dSmoothingPart",
          "LREAL",
          "0.5",
          "In case of the additional axes A, B and C the user can determine,\nwhich part of the path is provided to the additional axes for\nacceleration/deceleration and which part is to operate with a\nconstant velocity.0: No acceleration/deceleration phase is set.1: No constant motion is to be created.0.5: The acceleration phase plus the deceleration phase requiresthe same time than the constant motion."
        ],
        [
          "dAngleTol",
          "LREAL",
          "0.001",
          "For a correct parametrization of the additional axes A, B and C it is\nimportant to know, whether a object crossing leads to a stop.\nThe inputdAngleTol, which is also used in the function blockSMC_CheckVelocitiesand in other preprocessing function blocks,\nis also required here. It should be occupied with always the same value."
        ],
        [
          "nSizeOutQueue",
          "UDINT",
          "",
          "The size of pbyBufferOutQueue in bytes."
        ],
        [
          "pbyBufferOutQueue",
          "POINTER TO ARRAY [0..0]\nOF SMC_GEOINFO",
          "",
          "This input must point to the first byte of the memory area being\nallocated for theSMC_OUTQUEUEstructure.\nThis area must be at least as big as defined innSizeOutQueue.\nTypically the allocation of the memory buffer is done within the\ndeclaration part of the IEC-program by defining a byte-array\n(ExampleBuf:ARRAY[1..50]OFSMC_GEOINFO;).\nThe value may be predefined, but may then be modified during a reset only."
        ],
        {
          "Scope": "Output",
          "Name": "bDone",
          "Type": "BOOL",
          "Initial": "",
          "Comment": "This output will be set toTRUEas soon as the input path\nhas been processed completely.The function block\nwill not perform any further actions until it gets reset."
        },
        [
          "bBusy",
          "BOOL",
          "",
          "TRUE, while execution of function block is not finished"
        ],
        [
          "bError",
          "BOOL",
          "",
          "Signals, that an error has occurred within the function\nblock"
        ],
        [
          "wErrorID",
          "SMC_ERROR",
          "",
          "Error identification"
        ],
        [
          "poqDataOut",
          "POINTER TOSMC_OUTQUEUE",
          "",
          "The output path queue"
        ]
      ]
    }
  ]
}