{
  "library": "PLCopen Safety FBs",
  "title": "FBS_MODESEL (Enum)",
  "url": "https://content.helpme-codesys.com/en/libs/PLCopen Safety FBs/Current/PLCopenSafetyFBs/Enums/FBS_MODESEL.html",
  "page_title": "FBS_MODESEL (ENUM)",
  "text": "PLCopenSafetyFBs\nEnums\nFBS_ANTI (Enum)\nFBS_EDM (Enum)\nFBS_ENSWITCH (Enum)\nFBS_ENSWITCH2 (Enum)\nFBS_EQUI (Enum)\nFBS_ESPE (Enum)\nFBS_ESTOP (Enum)\nFBS_GUARD (Enum)\nFBS_GUARDLOCK2 (Enum)\nFBS_MODESEL (Enum)\nFBS_OUTCONTROL (Enum)\nFBS_PSE (Enum)\nFBS_RESBUT (Enum)\nFBS_SAFEREQ (Enum)\nFBS_TESTSEN (Enum)\nFBS_TWOHAND (Enum)\nFunction Blocks\nSF_Antivalent (FunctionBlock)\nSF_EDM (FunctionBlock)\nSF_ESPE (FunctionBlock)\nSF_EmergencyStop (FunctionBlock)\nSF_EnableSwitch (FunctionBlock)\nSF_EnableSwitch_2 (FunctionBlock)\nSF_Equivalent (FunctionBlock)\nSF_Guard (FunctionBlock)\nSF_GuardLocking_2 (FunctionBlock)\nSF_ModeSelector (FunctionBlock)\nSF_OutControl (FunctionBlock)\nSF_PSE (FunctionBlock)\nSF_ResetButton (FunctionBlock)\nSF_SafetyRequest (FunctionBlock)\nSF_TestableSafetySensor (FunctionBlock)\nSF_TwoHandControlTypeII (FunctionBlock)\nSF_TwoHandControlTypeIII (FunctionBlock)\nFile and Project Information\nLibrary Reference\nStandard\nLibrary Identification\nLibrary Properties\nSysTimeCore\nLibrary Identification\nLibrary Properties\nPLCopen Safety FBs\nDocs\n»\nPLCopenSafetyFBs\n»\nEnums\n»\nFBS_MODESEL (ENUM)\nFBS_MODESEL (ENUM)\nÂ¶\nTYPE FBS_MODESEL :\nDefinition of SF_ModeSelector function block states and its diagnostic values.\nAttributes:\nqualified_only\nInOut:\nName\nInitial\nComment\nIDLE\n16#0\nThe function block is not active (initial state).\nMODE_SELECTED\n16#8000\nValid mode selection, but NOT yet locked.\nMODE_LOCKED\n16#8010\nValid mode selection is locked.\nMODE_CHANGED\n16#8802\nState after activation or when S_ModeX has changed (unless\nlocked) or after Reset of an error state.\nERR_SHORTCIRCUIT\n16#C010\nThe FB detected that two or more S_ModeX are TRUE, e.g.,\nshort-circuit of cables.\nERR_SHORTCIRCUIT_RESREQ\n16#C410\nNo more short short-circuit of cables (Only one S_ModeX OR\nno S_ModeX), the error can be reset\nERR_OPENCIRCUIT\n16#C020\nThe FB detected that all S_ModeX are FALSE: The period\nfollowing a falling S_ModeX trigger exceeds ModeMonitorTime,\ne.g. open-circuit of cables.\nERR_OPENCIRCUIT_RESREQ\n16#C420\nNo more One S_ModeX is TRUE, the error can be reset\nERR_RESET_1\n16#C011\nStatic Reset signal detected in state C410.\nERR_RESET_2\n16#C021\nStatic Reset signal detected in state C420.",
  "tables": [
    {
      "headers": [
        "Name",
        "Initial",
        "Comment"
      ],
      "rows": [
        {
          "Name": "IDLE",
          "Initial": "16#0",
          "Comment": "The function block is not active (initial state)."
        },
        {
          "Name": "MODE_SELECTED",
          "Initial": "16#8000",
          "Comment": "Valid mode selection, but NOT yet locked."
        },
        {
          "Name": "MODE_LOCKED",
          "Initial": "16#8010",
          "Comment": "Valid mode selection is locked."
        },
        {
          "Name": "MODE_CHANGED",
          "Initial": "16#8802",
          "Comment": "State after activation or when S_ModeX has changed (unless\nlocked) or after Reset of an error state."
        },
        {
          "Name": "ERR_SHORTCIRCUIT",
          "Initial": "16#C010",
          "Comment": "The FB detected that two or more S_ModeX are TRUE, e.g.,\nshort-circuit of cables."
        },
        {
          "Name": "ERR_SHORTCIRCUIT_RESREQ",
          "Initial": "16#C410",
          "Comment": "No more short short-circuit of cables (Only one S_ModeX OR\nno S_ModeX), the error can be reset"
        },
        {
          "Name": "ERR_OPENCIRCUIT",
          "Initial": "16#C020",
          "Comment": "The FB detected that all S_ModeX are FALSE: The period\nfollowing a falling S_ModeX trigger exceeds ModeMonitorTime,\ne.g. open-circuit of cables."
        },
        {
          "Name": "ERR_OPENCIRCUIT_RESREQ",
          "Initial": "16#C420",
          "Comment": "No more One S_ModeX is TRUE, the error can be reset"
        },
        {
          "Name": "ERR_RESET_1",
          "Initial": "16#C011",
          "Comment": "Static Reset signal detected in state C410."
        },
        {
          "Name": "ERR_RESET_2",
          "Initial": "16#C021",
          "Comment": "Static Reset signal detected in state C420."
        }
      ]
    }
  ]
}