{
  "library": "PLCopen Safety FBs",
  "title": "FBS_EQUI (Enum)",
  "url": "https://content.helpme-codesys.com/en/libs/PLCopen Safety FBs/Current/PLCopenSafetyFBs/Enums/FBS_EQUI.html",
  "page_title": "FBS_EQUI (ENUM)",
  "text": "PLCopenSafetyFBs\nEnums\nFBS_ANTI (Enum)\nFBS_EDM (Enum)\nFBS_ENSWITCH (Enum)\nFBS_ENSWITCH2 (Enum)\nFBS_EQUI (Enum)\nFBS_ESPE (Enum)\nFBS_ESTOP (Enum)\nFBS_GUARD (Enum)\nFBS_GUARDLOCK2 (Enum)\nFBS_MODESEL (Enum)\nFBS_OUTCONTROL (Enum)\nFBS_PSE (Enum)\nFBS_RESBUT (Enum)\nFBS_SAFEREQ (Enum)\nFBS_TESTSEN (Enum)\nFBS_TWOHAND (Enum)\nFunction Blocks\nSF_Antivalent (FunctionBlock)\nSF_EDM (FunctionBlock)\nSF_ESPE (FunctionBlock)\nSF_EmergencyStop (FunctionBlock)\nSF_EnableSwitch (FunctionBlock)\nSF_EnableSwitch_2 (FunctionBlock)\nSF_Equivalent (FunctionBlock)\nSF_Guard (FunctionBlock)\nSF_GuardLocking_2 (FunctionBlock)\nSF_ModeSelector (FunctionBlock)\nSF_OutControl (FunctionBlock)\nSF_PSE (FunctionBlock)\nSF_ResetButton (FunctionBlock)\nSF_SafetyRequest (FunctionBlock)\nSF_TestableSafetySensor (FunctionBlock)\nSF_TwoHandControlTypeII (FunctionBlock)\nSF_TwoHandControlTypeIII (FunctionBlock)\nFile and Project Information\nLibrary Reference\nStandard\nLibrary Identification\nLibrary Properties\nSysTimeCore\nLibrary Identification\nLibrary Properties\nPLCopen Safety FBs\nDocs\n»\nPLCopenSafetyFBs\n»\nEnums\n»\nFBS_EQUI (ENUM)\nFBS_EQUI (ENUM)\nÂ¶\nTYPE FBS_EQUI :\nDefinition of SF_Equivalent function block states and its diagnostic values.\nAttributes:\nqualified_only\nInOut:\nName\nInitial\nComment\nIDLE\n16#0\nThe function block is not active (initial state).\nINIT\n16#8801\nAn activation has been detected by the FB and the FB is now\nactivated.\nOUT_ENABLED\n16#8000\nThe inputs switched to TRUE in equivalent mode.\nWAIT_FOR_CH_B\n16#8802\nChannel A has been switched to TRUE - waiting for Channel B;\ndiscrepancy timer started.\nWAIT_FOR_CH_A\n16#8804\nChannel B has been switched to TRUE - waiting for Channel A;\ndiscrepancy timer started.\nFROM_ACTIVE_WAIT\n16#8806\nOne channel has been switched to FALSE; waiting for the\nsecond channel to be switched to FALSE, discrepancy timer\nstarted.\nERROR_1\n16#C010\nDiscrepancy time elapsed in state WAIT_FOR_CH_B.\nERROR_2\n16#C020\nDiscrepancy time elapsed in state WAIT_FOR_CH_A.\nERROR_3\n16#C030\nDiscrepancy time elapsed in state FROM_ACTIVE_WAIT.",
  "tables": [
    {
      "headers": [
        "Name",
        "Initial",
        "Comment"
      ],
      "rows": [
        {
          "Name": "IDLE",
          "Initial": "16#0",
          "Comment": "The function block is not active (initial state)."
        },
        {
          "Name": "INIT",
          "Initial": "16#8801",
          "Comment": "An activation has been detected by the FB and the FB is now\nactivated."
        },
        {
          "Name": "OUT_ENABLED",
          "Initial": "16#8000",
          "Comment": "The inputs switched to TRUE in equivalent mode."
        },
        {
          "Name": "WAIT_FOR_CH_B",
          "Initial": "16#8802",
          "Comment": "Channel A has been switched to TRUE - waiting for Channel B;\ndiscrepancy timer started."
        },
        {
          "Name": "WAIT_FOR_CH_A",
          "Initial": "16#8804",
          "Comment": "Channel B has been switched to TRUE - waiting for Channel A;\ndiscrepancy timer started."
        },
        {
          "Name": "FROM_ACTIVE_WAIT",
          "Initial": "16#8806",
          "Comment": "One channel has been switched to FALSE; waiting for the\nsecond channel to be switched to FALSE, discrepancy timer\nstarted."
        },
        {
          "Name": "ERROR_1",
          "Initial": "16#C010",
          "Comment": "Discrepancy time elapsed in state WAIT_FOR_CH_B."
        },
        {
          "Name": "ERROR_2",
          "Initial": "16#C020",
          "Comment": "Discrepancy time elapsed in state WAIT_FOR_CH_A."
        },
        {
          "Name": "ERROR_3",
          "Initial": "16#C030",
          "Comment": "Discrepancy time elapsed in state FROM_ACTIVE_WAIT."
        }
      ]
    }
  ]
}