{
  "library": "PLCopen Safety FBs",
  "title": "FBS_EDM (Enum)",
  "url": "https://content.helpme-codesys.com/en/libs/PLCopen Safety FBs/Current/PLCopenSafetyFBs/Enums/FBS_EDM.html",
  "page_title": "FBS_EDM (ENUM)",
  "text": "PLCopenSafetyFBs\nEnums\nFBS_ANTI (Enum)\nFBS_EDM (Enum)\nFBS_ENSWITCH (Enum)\nFBS_ENSWITCH2 (Enum)\nFBS_EQUI (Enum)\nFBS_ESPE (Enum)\nFBS_ESTOP (Enum)\nFBS_GUARD (Enum)\nFBS_GUARDLOCK2 (Enum)\nFBS_MODESEL (Enum)\nFBS_OUTCONTROL (Enum)\nFBS_PSE (Enum)\nFBS_RESBUT (Enum)\nFBS_SAFEREQ (Enum)\nFBS_TESTSEN (Enum)\nFBS_TWOHAND (Enum)\nFunction Blocks\nSF_Antivalent (FunctionBlock)\nSF_EDM (FunctionBlock)\nSF_ESPE (FunctionBlock)\nSF_EmergencyStop (FunctionBlock)\nSF_EnableSwitch (FunctionBlock)\nSF_EnableSwitch_2 (FunctionBlock)\nSF_Equivalent (FunctionBlock)\nSF_Guard (FunctionBlock)\nSF_GuardLocking_2 (FunctionBlock)\nSF_ModeSelector (FunctionBlock)\nSF_OutControl (FunctionBlock)\nSF_PSE (FunctionBlock)\nSF_ResetButton (FunctionBlock)\nSF_SafetyRequest (FunctionBlock)\nSF_TestableSafetySensor (FunctionBlock)\nSF_TwoHandControlTypeII (FunctionBlock)\nSF_TwoHandControlTypeIII (FunctionBlock)\nFile and Project Information\nLibrary Reference\nStandard\nLibrary Identification\nLibrary Properties\nSysTimeCore\nLibrary Identification\nLibrary Properties\nPLCopen Safety FBs\nDocs\n»\nPLCopenSafetyFBs\n»\nEnums\n»\nFBS_EDM (ENUM)\nFBS_EDM (ENUM)\nÂ¶\nTYPE FBS_EDM :\nDefinition of SF_EDM function block states and its diagnostic values.\nAttributes:\nqualified_only\nInOut:\nName\nInitial\nComment\nIDLE\n16#0\nThe function block is not active (initial state).\nINIT\n16#8401\nBlock activation startup inhibit is active. Reset required.\nOUT_DISABLE\n16#8810\nEDM control is not active. Timer starts when state is\nentered\nOUT_ENABLE\n16#8000\nEDM control is active. Timer starts when state is entered\nERR_RESET_1\n16#C001\nStatic Reset signal in state 16#8401.\nERR_INIT\n16#C100\nSimilar signals at S_OutControl and Reset (R_TRIG at same\ncycle) detected (may be a programming error).\nERR_EDM_11\n16#C010\nThe signal at EDM1 is not valid in the initial actuator\nstate. In state 16#8810 the EDM1 signal is FALSE when\nenabling S_OutControl.\nERR_EDM_12\n16#C020\nThe signal at EDM2 is not valid in the initial actuator\nstate. In state 16#8810 the EDM2 signal is FALSE when\nenabling S_OutControl.\nERR_EDM_13\n16#C030\nThe signals at EDM1 and EDM2 are not valid in the initial\nactuator states. In state 16#8810 the EDM1 and EDM2 signals\nare FALSE when enabling S_OutControl.\nERR_EDM_21\n16#C040\nThe signal at EDM1 is not valid in the initial actuator\nstate. In state 16#8810 the EDM1 signal is FALSE and the\nmonitoring time has elapsed.\nERR_EDM_22\n16#C050\nThe signal at EDM2 is not valid in the initial actuator\nstate. In state 16#8810 the EDM2 signal is FALSE and the\nmonitoring time has elapsed.\nERR_EDM_23\n16#C060\nThe signals at EDM1 and EDM2 are not valid in the initial\nactuator states. In state 16#8810 the EDM1 and EDM2 signals\nare FALSE and the monitoring time has elapsed.\nERR_EDM_31\n16#C070\nThe signal at EDM1 is not valid in the actuator switching\nstate. In state 16#8000 the EDM1 signal is TRUE and the\nmonitoring time has elapsed.\nERR_EDM_32\n16#C080\nThe signal at EDM2 is not valid in the actuator switching\nstate. In state 16#8000 the EDM2 signal is TRUE and the\nmonitoring time has elapsed.\nERR_EDM_33\n16#C090\nThe signals at EDM1 and EDM2 are not valid in the actuator\nswitching state. In state 16#8000 the EDM1 and EDM2 signals\nare TRUE and the monitoring time has elapsed.\nERR_RESET_21\n16#C011\nStatic Reset signal or same signals at EDM1 and Reset\n(rising trigger at Reset and EDM1 at the same time) in state\n16#C010.\nERR_RESET_22\n16#C021\nStatic Reset signal or same signals at EDM2 and Reset\n(rising trigger at Reset and EDM2 at the same time) in state\n16#C020.\nERR_RESET_23\n16#C031\nStatic Reset signal or same signals at EDM1, EDM2, and Reset\n(rising trigger at Reset, EDM1, and EDM2 at the same time)\nin state 16#C030.\nERR_RESET_31\n16#C041\nStatic Reset signal or same signals at EDM1 and Reset\n(rising trigger at Reset and EDM1 at the same time) in state\n16#C040.\nERR_RESET_32\n16#C051\nStatic Reset signal or same signals at EDM2 and Reset\n(rising trigger at Reset and EDM2 at the same time) in state\n16#C050.\nERR_RESET_33\n16#C061\nStatic Reset signal or same signals at EDM1, EDM2, and Reset\n(rising trigger at Reset, EDM1, and EDM2 at the same time)\nin state 16#C060.\nERR_RESET_41\n16#C071\nStatic Reset signal in state 16#C070.\nERR_RESET_42\n16#C081\nStatic Reset signal in state 16#C080.\nERR_RESET_43\n16#C091\nStatic Reset signal in state 16#C090.",
  "tables": [
    {
      "headers": [
        "Name",
        "Initial",
        "Comment"
      ],
      "rows": [
        {
          "Name": "IDLE",
          "Initial": "16#0",
          "Comment": "The function block is not active (initial state)."
        },
        {
          "Name": "INIT",
          "Initial": "16#8401",
          "Comment": "Block activation startup inhibit is active. Reset required."
        },
        {
          "Name": "OUT_DISABLE",
          "Initial": "16#8810",
          "Comment": "EDM control is not active. Timer starts when state is\nentered"
        },
        {
          "Name": "OUT_ENABLE",
          "Initial": "16#8000",
          "Comment": "EDM control is active. Timer starts when state is entered"
        },
        {
          "Name": "ERR_RESET_1",
          "Initial": "16#C001",
          "Comment": "Static Reset signal in state 16#8401."
        },
        {
          "Name": "ERR_INIT",
          "Initial": "16#C100",
          "Comment": "Similar signals at S_OutControl and Reset (R_TRIG at same\ncycle) detected (may be a programming error)."
        },
        {
          "Name": "ERR_EDM_11",
          "Initial": "16#C010",
          "Comment": "The signal at EDM1 is not valid in the initial actuator\nstate. In state 16#8810 the EDM1 signal is FALSE when\nenabling S_OutControl."
        },
        {
          "Name": "ERR_EDM_12",
          "Initial": "16#C020",
          "Comment": "The signal at EDM2 is not valid in the initial actuator\nstate. In state 16#8810 the EDM2 signal is FALSE when\nenabling S_OutControl."
        },
        {
          "Name": "ERR_EDM_13",
          "Initial": "16#C030",
          "Comment": "The signals at EDM1 and EDM2 are not valid in the initial\nactuator states. In state 16#8810 the EDM1 and EDM2 signals\nare FALSE when enabling S_OutControl."
        },
        {
          "Name": "ERR_EDM_21",
          "Initial": "16#C040",
          "Comment": "The signal at EDM1 is not valid in the initial actuator\nstate. In state 16#8810 the EDM1 signal is FALSE and the\nmonitoring time has elapsed."
        },
        {
          "Name": "ERR_EDM_22",
          "Initial": "16#C050",
          "Comment": "The signal at EDM2 is not valid in the initial actuator\nstate. In state 16#8810 the EDM2 signal is FALSE and the\nmonitoring time has elapsed."
        },
        {
          "Name": "ERR_EDM_23",
          "Initial": "16#C060",
          "Comment": "The signals at EDM1 and EDM2 are not valid in the initial\nactuator states. In state 16#8810 the EDM1 and EDM2 signals\nare FALSE and the monitoring time has elapsed."
        },
        {
          "Name": "ERR_EDM_31",
          "Initial": "16#C070",
          "Comment": "The signal at EDM1 is not valid in the actuator switching\nstate. In state 16#8000 the EDM1 signal is TRUE and the\nmonitoring time has elapsed."
        },
        {
          "Name": "ERR_EDM_32",
          "Initial": "16#C080",
          "Comment": "The signal at EDM2 is not valid in the actuator switching\nstate. In state 16#8000 the EDM2 signal is TRUE and the\nmonitoring time has elapsed."
        },
        {
          "Name": "ERR_EDM_33",
          "Initial": "16#C090",
          "Comment": "The signals at EDM1 and EDM2 are not valid in the actuator\nswitching state. In state 16#8000 the EDM1 and EDM2 signals\nare TRUE and the monitoring time has elapsed."
        },
        {
          "Name": "ERR_RESET_21",
          "Initial": "16#C011",
          "Comment": "Static Reset signal or same signals at EDM1 and Reset\n(rising trigger at Reset and EDM1 at the same time) in state\n16#C010."
        },
        {
          "Name": "ERR_RESET_22",
          "Initial": "16#C021",
          "Comment": "Static Reset signal or same signals at EDM2 and Reset\n(rising trigger at Reset and EDM2 at the same time) in state\n16#C020."
        },
        {
          "Name": "ERR_RESET_23",
          "Initial": "16#C031",
          "Comment": "Static Reset signal or same signals at EDM1, EDM2, and Reset\n(rising trigger at Reset, EDM1, and EDM2 at the same time)\nin state 16#C030."
        },
        {
          "Name": "ERR_RESET_31",
          "Initial": "16#C041",
          "Comment": "Static Reset signal or same signals at EDM1 and Reset\n(rising trigger at Reset and EDM1 at the same time) in state\n16#C040."
        },
        {
          "Name": "ERR_RESET_32",
          "Initial": "16#C051",
          "Comment": "Static Reset signal or same signals at EDM2 and Reset\n(rising trigger at Reset and EDM2 at the same time) in state\n16#C050."
        },
        {
          "Name": "ERR_RESET_33",
          "Initial": "16#C061",
          "Comment": "Static Reset signal or same signals at EDM1, EDM2, and Reset\n(rising trigger at Reset, EDM1, and EDM2 at the same time)\nin state 16#C060."
        },
        {
          "Name": "ERR_RESET_41",
          "Initial": "16#C071",
          "Comment": "Static Reset signal in state 16#C070."
        },
        {
          "Name": "ERR_RESET_42",
          "Initial": "16#C081",
          "Comment": "Static Reset signal in state 16#C080."
        },
        {
          "Name": "ERR_RESET_43",
          "Initial": "16#C091",
          "Comment": "Static Reset signal in state 16#C090."
        }
      ]
    }
  ]
}