{
  "library": "PLCopen Safety FBs",
  "title": "FBS_ENSWITCH2 (Enum)",
  "url": "https://content.helpme-codesys.com/en/libs/PLCopen Safety FBs/Current/PLCopenSafetyFBs/Enums/FBS_ENSWITCH2.html",
  "page_title": "FBS_ENSWITCH2 (ENUM)",
  "text": "PLCopenSafetyFBs\nEnums\nFBS_ANTI (Enum)\nFBS_EDM (Enum)\nFBS_ENSWITCH (Enum)\nFBS_ENSWITCH2 (Enum)\nFBS_EQUI (Enum)\nFBS_ESPE (Enum)\nFBS_ESTOP (Enum)\nFBS_GUARD (Enum)\nFBS_GUARDLOCK2 (Enum)\nFBS_MODESEL (Enum)\nFBS_OUTCONTROL (Enum)\nFBS_PSE (Enum)\nFBS_RESBUT (Enum)\nFBS_SAFEREQ (Enum)\nFBS_TESTSEN (Enum)\nFBS_TWOHAND (Enum)\nFunction Blocks\nSF_Antivalent (FunctionBlock)\nSF_EDM (FunctionBlock)\nSF_ESPE (FunctionBlock)\nSF_EmergencyStop (FunctionBlock)\nSF_EnableSwitch (FunctionBlock)\nSF_EnableSwitch_2 (FunctionBlock)\nSF_Equivalent (FunctionBlock)\nSF_Guard (FunctionBlock)\nSF_GuardLocking_2 (FunctionBlock)\nSF_ModeSelector (FunctionBlock)\nSF_OutControl (FunctionBlock)\nSF_PSE (FunctionBlock)\nSF_ResetButton (FunctionBlock)\nSF_SafetyRequest (FunctionBlock)\nSF_TestableSafetySensor (FunctionBlock)\nSF_TwoHandControlTypeII (FunctionBlock)\nSF_TwoHandControlTypeIII (FunctionBlock)\nFile and Project Information\nLibrary Reference\nStandard\nLibrary Identification\nLibrary Properties\nSysTimeCore\nLibrary Identification\nLibrary Properties\nPLCopen Safety FBs\nDocs\n»\nPLCopenSafetyFBs\n»\nEnums\n»\nFBS_ENSWITCH2 (ENUM)\nFBS_ENSWITCH2 (ENUM)\nÂ¶\nTYPE FBS_ENSWITCH2 :\nDefinition of SF_EnableSwitch_2 function block states and its diagnostic values.\nAttributes:\nqualified_only\nInOut:\nName\nInitial\nComment\nIDLE\n16#0\nThe function block is not active (initial state).\nBASIC_OPMODE\n16#8002\nSafe operation mode is not active.\nSAFE_OPMODE\n16#8004\nSafe operation mode is active.\nNOT_ENABLED\n16#8802\nSafe operation mode is active and the enable switch is in\nposition 1 or 3.\nENABLED\n16#8000\nSafe operation mode is active and the enable switch is in\nposition 2.\nERR_OPERATION\n16#C010\nEnable switch not in position 1 during activation of\nS_SafetyActive. S_EnableIn = TRUE\nERR_OPERATION_RESREQ\n16#C410\nEnable switch not in position 1 during activation of\nS_SafetyActive. S_EnableIn = FALSE\nERR_RESET_1\n16#C001\nStatic Reset signal detected in state Cx10.",
  "tables": [
    {
      "headers": [
        "Name",
        "Initial",
        "Comment"
      ],
      "rows": [
        {
          "Name": "IDLE",
          "Initial": "16#0",
          "Comment": "The function block is not active (initial state)."
        },
        {
          "Name": "BASIC_OPMODE",
          "Initial": "16#8002",
          "Comment": "Safe operation mode is not active."
        },
        {
          "Name": "SAFE_OPMODE",
          "Initial": "16#8004",
          "Comment": "Safe operation mode is active."
        },
        {
          "Name": "NOT_ENABLED",
          "Initial": "16#8802",
          "Comment": "Safe operation mode is active and the enable switch is in\nposition 1 or 3."
        },
        {
          "Name": "ENABLED",
          "Initial": "16#8000",
          "Comment": "Safe operation mode is active and the enable switch is in\nposition 2."
        },
        {
          "Name": "ERR_OPERATION",
          "Initial": "16#C010",
          "Comment": "Enable switch not in position 1 during activation of\nS_SafetyActive. S_EnableIn = TRUE"
        },
        {
          "Name": "ERR_OPERATION_RESREQ",
          "Initial": "16#C410",
          "Comment": "Enable switch not in position 1 during activation of\nS_SafetyActive. S_EnableIn = FALSE"
        },
        {
          "Name": "ERR_RESET_1",
          "Initial": "16#C001",
          "Comment": "Static Reset signal detected in state Cx10."
        }
      ]
    }
  ]
}