{
  "library": "SM3_Robotics",
  "title": "MC_GroupStop (FunctionBlock)",
  "url": "https://content.helpme-codesys.com/en/libs/SM3_Robotics/Current/SM3_Robotics/POUs/Movement/MC_GroupStop.html",
  "page_title": "MC_GroupStop (FB)",
  "text": "Library Information\nGetLibVersion (Function)\nGetLibVersionNumber (Function)\nGetVersion (Function)\nIsLibReleased (Function)\nSM3_Robotics\nBasic types\nIDENT_IN_GROUP_REF_SM3 (Alias)\nMC_CIRC_PATHCHOICE (Enum)\nMC_COORD_REF (Struct)\nMC_EXECUTION_MODE (Enum)\nMC_TRANSITION_MODE (Enum)\nSMC_AXIS_GROUP_COMPATIBILITY_OPTIONS (Struct)\nSMC_AXIS_GROUP_CONTINUE_DATA (FunctionBlock)\nSMC_AXIS_GROUP_STATE (Enum)\nSMC_CIRC_MODE (Enum)\nSMC_DYN_LIMITS (Alias)\nSMC_IDynamicCS (Interface)\nSMC_ORIENTATION_MODE (Enum)\nSMC_POS_REF (Union)\nSMC_PTP_MOVEMENT_TYPE (Enum)\nSMC_READ_TOOL_MODE (Enum)\nPOUs\nAdditional\nSMC_AxisDistanceAxes (Enum)\nSMC_AxisDistanceSubMode (Enum)\nSMC_AxisDistanceTransition (FunctionBlock)\nSMC_AxisDistanceTransitionParam (Function)\nSMC_CornerDistance (FunctionBlock)\nSMC_CornerDistanceTransitionParam (Function)\nSMC_StartVelocity (FunctionBlock)\nSMC_StartVelocityAxes (Enum)\nSMC_StartVelocityTransitionParam (Function)\nSMC_StartupAxisGroup (FunctionBlock)\nAdministrative/Configuration\nAxisGroup\nComputation\nCoordinate systems\nDynamics\nKinematics\nTrigger\nAxisGroup\nAXIS_GROUP_REF_SM3 (FunctionBlock)\nHelpers\nMovements\nDiagnostics\nMC_GroupReadActualAcceleration (FunctionBlock)\nMC_GroupReadActualPosition (FunctionBlock)\nMC_GroupReadActualVelocity (FunctionBlock)\nMC_GroupReadConfiguration (FunctionBlock)\nMC_GroupReadError (FunctionBlock)\nMC_GroupReadStatus (FunctionBlock)\nMC_ReadCoordinateTransform (FunctionBlock)\nMC_ReadKinTransform (FunctionBlock)\nSMC_GroupAddOffset (FunctionBlock)\nSMC_GroupAdditionalAxesTargetPositions (FunctionBlock)\nSMC_GroupConvertPosition (FunctionBlock)\nSMC_GroupGetContinuePosition (FunctionBlock)\nSMC_GroupGetContinueToolOffset (FunctionBlock)\nSMC_GroupReadPathAcceleration (FunctionBlock)\nSMC_GroupReadPathDynamics (FunctionBlock)\nSMC_GroupReadPathVelocity (FunctionBlock)\nSMC_GroupReadPlanningStatistics (FunctionBlock)\nSMC_GroupReadPositionInMovement (FunctionBlock)\nSMC_GroupReadRemainingTrajectoryDuration (FunctionBlock)\nSMC_GroupReadSetAcceleration (FunctionBlock)\nSMC_GroupReadSetJerk (FunctionBlock)\nSMC_GroupReadSetPosition (FunctionBlock)\nSMC_GroupReadSetVelocity (FunctionBlock)\nSMC_GroupTargetPosition (FunctionBlock)\nSMC_ReadKinTransformForAxis (FunctionBlock)\nMovement\nAdditionalAxes\nGroupInterrupt\nMC_GroupContinue (FunctionBlock)\nMC_GroupHalt (FunctionBlock)\nMC_GroupInterrupt (FunctionBlock)\nMC_GroupStop (FunctionBlock)\nMC_MoveCircularAbsolute (FunctionBlock)\nMC_MoveCircularRelative (FunctionBlock)\nMC_MoveDirectAbsolute (FunctionBlock)\nMC_MoveDirectRelative (FunctionBlock)\nMC_MoveLinearAbsolute (FunctionBlock)\nMC_MoveLinearRelative (FunctionBlock)\nSMC_GroupEnableResumeAfterError (FunctionBlock)\nSMC_GroupJog (FunctionBlock)\nSMC_GroupJog2 (FunctionBlock)\nSMC_GroupUpdateContinueData (FunctionBlock)\nSMC_GroupWait (FunctionBlock)\nSMC_MoveAdditionalAxes (FunctionBlock)\ninternal\nDivers\nKernel_CP\nFile and Project Information\nLibrary Reference\n3SLicense\nLibrary Identification\nLibrary Properties\nCmpApp\nLibrary Identification\nLibrary Properties\nCmpIecTask\nLibrary Identification\nLibrary Properties\nCmpLog\nLibrary Identification\nLibrary Properties\nFloatingPointUtils\nLibrary Identification\nLibrary Properties\nSM3_Basic\nLibrary Identification\nLibrary Properties\nLibrary Parameter\nSM3_CPKernelDefaults\nLibrary Identification\nLibrary Properties\nLibrary Parameter\nSM3_CommonPublic\nLibrary Identification\nLibrary Properties\nSM3_Dynamics\nLibrary Identification\nLibrary Properties\nSM3_Error\nLibrary Identification\nLibrary Properties\nSM3_RBase\nLibrary Identification\nLibrary Properties\nSM3_RCP\nLibrary Identification\nLibrary Properties\nSM3_RError\nLibrary Identification\nLibrary Properties\nSM3_Ramps\nLibrary Identification\nLibrary Properties\nSM3_Shared\nLibrary Identification\nLibrary Properties\nSM3_StringUtils\nLibrary Identification\nLibrary Properties\nSM3_TrajectoryGeneration\nLibrary Identification\nLibrary Properties\nSM3_Transformation\nLibrary Identification\nLibrary Properties\nStandard\nLibrary Identification\nLibrary Properties\nSysMem\nLibrary Identification\nLibrary Properties\nSysTarget\nLibrary Identification\nLibrary Properties\nSysTime\nLibrary Identification\nLibrary Properties\nSysTypes2 Interfaces\nLibrary Identification\nLibrary Properties\nSM3_Robotics\nDocs\n»\nSM3_Robotics\n»\nPOUs\n»\nMovement\n»\nMC_GroupStop (FB)\nMC_GroupStop (FB)\nÂ¶\nFUNCTION_BLOCK FINAL MC_GroupStop\nThis function block commands a controlled motion stop and\ntransfers the axis group to the state\nGroupStopping\n.\nIt aborts any other motion command.\nWhile the axis group is in state GroupStopping, no other FB can\nperform any motion on the same axis group. After the axis group\nhas reached standstill, the\nDone\noutput is set to\nTRUE\nimmediately.\nThe axis group remains in the state\nGroupStopping\nas long as\nExecute\nis still\nTRUE\nor the axes are not yet in standstill.\nAs soon as\nDone\nis set and\nExecute\nis\nFALSE\n, the axis group\ngoes to  state\nGroupStandBy\n. The command can only be aborted by\nMC_Power\n.\nNote\nThe effective limits for deceleration and jerk are determined by the\ninputs\nDeceleration\n,\nJerk\n,\nAccFactor\n, and\nJerkFactor\n.\nThese limits can be exceeded in order to stay on the commanded path.\nNote\nIn contrast to\nMC_GroupHalt\nthe given dynamic limits are neither\ninfluenced by an override set using\nMC_GroupSetOverride\n, nor by\naxis limit factors set using\nSMC_GroupSetAxisLimitFactors\n, nor by\nancillary limits set using\nSMC_GroupSetAncillaryPathLimits\nand\nSMC_GroupSetAncillaryAxisLimits\nrespectively.\nFor halting point-to-point movements:\nthe velocity/acc-/deceleration/jerk of each axis are properties\nof each axis and not specified within this function block.\nSee also inputs\nAccFactor\nand\nJerkFactor\n.\nSMC_GroupSaveContinueData\nand\nMC_GroupContinue\ncan be used to\ncontinue on the original path after a stop, if\nClearMovements\nis\nset to FALSE.\nThe first movement after an\nMC_GroupStop\noverwrites the state of the\naxis group, so\nSMC_GroupSaveContinueData\nhas to be called before any\nnew movement is commanded.\nIf\nClearMovements\nis set to FALSE and there are any movements in a dynamic\ncoordinate system (see\nMC_TrackConveyorBelt\n,\nMC_TrackRotaryTable\n,\nMC_SetDynCoordTransform\n, or\nSMC_SetDynCoordTransformEx\n) that are not yet\nDone\nwhen\nMC_GroupStop\nis executed, the coordinate systems will remain\nInUse\neven after\nMC_GroupStop\nis\nDone\n.\nInOut:\nScope\nName\nType\nInitial\nComment\nInout\nAxisGroup\nAXIS_GROUP_REF_SM3\nReference to a group of axes\nInput\nExecute\nBOOL\nStart the action at rising edge\nDeceleration\nLREAL\nValue of the deceleration [u/sÂ²].\nOnly used if a continuous-path movement is halted.\nJerk\nLREAL\nValue of the jerk [u/sÂ³].\nOnly used if a continuous-path movement is halted.\nAccFactor\nLREAL\n1\nThe maximum deceleration of each axis is multiplied by this factor, which\nmust be in the range ]0, 1].\nJerkFactor\nLREAL\n1\nThe maximum jerk of each axis is multiplied by this factor, which\nmust be in the range ]0, 1].\nTorqueFactor\nLREAL\n1\nThe maximum torque of each axis is multiplied by this factor, which\nmust be in the range ]0, 1].  A dynamic model must have been set using\nSMC_GroupSetDynamics\nfor this factor to have an effect.\nClearMovements\nBOOL\nTRUE\nIf set to TRUE, all movements commanded before\nMC_GroupStop\nare cleared\nafter the axis group reaches standstill.  In order to be able to continue the\nprevious movements from the stop position using\nSMC_GroupSaveContinueData\nand\nMC_GroupContinue\n,\nClearMovements\nhas to be set to FALSE.\nName\nSTRING\nâMC_GroupStopâ\nThe name of the movement.\nOutput\nDone\nBOOL\nStandstill has been reached\nBusy\nBOOL\nThe FB is not finished\nActive\nBOOL\nIndicates that the FB has control on the axis\nCommandAborted\nBOOL\nCommand is aborted by disabling MC-Power of one or more\nof the axes in the group. The state changes to\nGroupDisabled\nCommandAccepted\nBOOL\nThe command has been accepted by the axis group.\nIf the output becomes\nTRUE\n, the function block instance can be used to\ncommand the next movement with a new rising edge on\nExecute\n.\nWhile the output is\nFALSE\n, keep calling the function block without\na new rising edge of\nExecute\n.\nThe output is reset to\nFALSE\non a falling edge of\nExecute\n.\nError\nBOOL\nSignals that an error has occurred within the function block\nErrorID\nSMC_ERROR\nError identification\nMovementId\nSMC_Movement_Id\nThe unique identifier of the movement.  Valid if\nCommandAccepted\nor\nDone\nis\nTRUE\n.",
  "tables": [
    {
      "headers": [
        "Scope",
        "Name",
        "Type",
        "Initial",
        "Comment"
      ],
      "rows": [
        {
          "Scope": "Inout",
          "Name": "AxisGroup",
          "Type": "AXIS_GROUP_REF_SM3",
          "Initial": "",
          "Comment": "Reference to a group of axes"
        },
        {
          "Scope": "Input",
          "Name": "Execute",
          "Type": "BOOL",
          "Initial": "",
          "Comment": "Start the action at rising edge"
        },
        [
          "Deceleration",
          "LREAL",
          "",
          "Value of the deceleration [u/sÂ²].\nOnly used if a continuous-path movement is halted."
        ],
        [
          "Jerk",
          "LREAL",
          "",
          "Value of the jerk [u/sÂ³].\nOnly used if a continuous-path movement is halted."
        ],
        [
          "AccFactor",
          "LREAL",
          "1",
          "The maximum deceleration of each axis is multiplied by this factor, which\nmust be in the range ]0, 1]."
        ],
        [
          "JerkFactor",
          "LREAL",
          "1",
          "The maximum jerk of each axis is multiplied by this factor, which\nmust be in the range ]0, 1]."
        ],
        [
          "TorqueFactor",
          "LREAL",
          "1",
          "The maximum torque of each axis is multiplied by this factor, which\nmust be in the range ]0, 1].  A dynamic model must have been set usingSMC_GroupSetDynamicsfor this factor to have an effect."
        ],
        [
          "ClearMovements",
          "BOOL",
          "TRUE",
          "If set to TRUE, all movements commanded beforeMC_GroupStopare cleared\nafter the axis group reaches standstill.  In order to be able to continue the\nprevious movements from the stop position usingSMC_GroupSaveContinueDataandMC_GroupContinue,ClearMovementshas to be set to FALSE."
        ],
        [
          "Name",
          "STRING",
          "âMC_GroupStopâ",
          "The name of the movement."
        ],
        {
          "Scope": "Output",
          "Name": "Done",
          "Type": "BOOL",
          "Initial": "",
          "Comment": "Standstill has been reached"
        },
        [
          "Busy",
          "BOOL",
          "",
          "The FB is not finished"
        ],
        [
          "Active",
          "BOOL",
          "",
          "Indicates that the FB has control on the axis"
        ],
        [
          "CommandAborted",
          "BOOL",
          "",
          "Command is aborted by disabling MC-Power of one or more\nof the axes in the group. The state changes toGroupDisabled"
        ],
        [
          "CommandAccepted",
          "BOOL",
          "",
          "The command has been accepted by the axis group.\nIf the output becomesTRUE, the function block instance can be used to\ncommand the next movement with a new rising edge onExecute.\nWhile the output isFALSE, keep calling the function block without\na new rising edge ofExecute.\nThe output is reset toFALSEon a falling edge ofExecute."
        ],
        [
          "Error",
          "BOOL",
          "",
          "Signals that an error has occurred within the function block"
        ],
        [
          "ErrorID",
          "SMC_ERROR",
          "",
          "Error identification"
        ],
        [
          "MovementId",
          "SMC_Movement_Id",
          "",
          "The unique identifier of the movement.  Valid ifCommandAcceptedorDoneisTRUE."
        ]
      ]
    }
  ]
}