{
  "library": "SM3_Robotics",
  "title": "MC_TrackRotaryTable (FunctionBlock)",
  "url": "https://content.helpme-codesys.com/en/libs/SM3_Robotics/Current/SM3_Robotics/POUs/AdministrativeConfiguration/Coordinate-systems/MC_TrackRotaryTable.html",
  "page_title": "MC_TrackRotaryTable (FB)",
  "text": "Library Information\nGetLibVersion (Function)\nGetLibVersionNumber (Function)\nGetVersion (Function)\nIsLibReleased (Function)\nSM3_Robotics\nBasic types\nIDENT_IN_GROUP_REF_SM3 (Alias)\nMC_CIRC_PATHCHOICE (Enum)\nMC_COORD_REF (Struct)\nMC_EXECUTION_MODE (Enum)\nMC_TRANSITION_MODE (Enum)\nSMC_AXIS_GROUP_COMPATIBILITY_OPTIONS (Struct)\nSMC_AXIS_GROUP_CONTINUE_DATA (FunctionBlock)\nSMC_AXIS_GROUP_STATE (Enum)\nSMC_CIRC_MODE (Enum)\nSMC_DYN_LIMITS (Alias)\nSMC_IDynamicCS (Interface)\nSMC_ORIENTATION_MODE (Enum)\nSMC_POS_REF (Union)\nSMC_PTP_MOVEMENT_TYPE (Enum)\nSMC_READ_TOOL_MODE (Enum)\nPOUs\nAdditional\nSMC_AxisDistanceAxes (Enum)\nSMC_AxisDistanceSubMode (Enum)\nSMC_AxisDistanceTransition (FunctionBlock)\nSMC_AxisDistanceTransitionParam (Function)\nSMC_CornerDistance (FunctionBlock)\nSMC_CornerDistanceTransitionParam (Function)\nSMC_StartVelocity (FunctionBlock)\nSMC_StartVelocityAxes (Enum)\nSMC_StartVelocityTransitionParam (Function)\nSMC_StartupAxisGroup (FunctionBlock)\nAdministrative/Configuration\nAxisGroup\nComputation\nCoordinate systems\nDynamics\nKinematics\nTrigger\nAxisGroup\nAXIS_GROUP_REF_SM3 (FunctionBlock)\nHelpers\nMovements\nDiagnostics\nMC_GroupReadActualAcceleration (FunctionBlock)\nMC_GroupReadActualPosition (FunctionBlock)\nMC_GroupReadActualVelocity (FunctionBlock)\nMC_GroupReadConfiguration (FunctionBlock)\nMC_GroupReadError (FunctionBlock)\nMC_GroupReadStatus (FunctionBlock)\nMC_ReadCoordinateTransform (FunctionBlock)\nMC_ReadKinTransform (FunctionBlock)\nSMC_GroupAddOffset (FunctionBlock)\nSMC_GroupAdditionalAxesTargetPositions (FunctionBlock)\nSMC_GroupConvertPosition (FunctionBlock)\nSMC_GroupGetContinuePosition (FunctionBlock)\nSMC_GroupGetContinueToolOffset (FunctionBlock)\nSMC_GroupReadPathAcceleration (FunctionBlock)\nSMC_GroupReadPathDynamics (FunctionBlock)\nSMC_GroupReadPathVelocity (FunctionBlock)\nSMC_GroupReadPlanningStatistics (FunctionBlock)\nSMC_GroupReadPositionInMovement (FunctionBlock)\nSMC_GroupReadRemainingTrajectoryDuration (FunctionBlock)\nSMC_GroupReadSetAcceleration (FunctionBlock)\nSMC_GroupReadSetJerk (FunctionBlock)\nSMC_GroupReadSetPosition (FunctionBlock)\nSMC_GroupReadSetVelocity (FunctionBlock)\nSMC_GroupTargetPosition (FunctionBlock)\nSMC_ReadKinTransformForAxis (FunctionBlock)\nMovement\nAdditionalAxes\nGroupInterrupt\nMC_GroupContinue (FunctionBlock)\nMC_GroupHalt (FunctionBlock)\nMC_GroupInterrupt (FunctionBlock)\nMC_GroupStop (FunctionBlock)\nMC_MoveCircularAbsolute (FunctionBlock)\nMC_MoveCircularRelative (FunctionBlock)\nMC_MoveDirectAbsolute (FunctionBlock)\nMC_MoveDirectRelative (FunctionBlock)\nMC_MoveLinearAbsolute (FunctionBlock)\nMC_MoveLinearRelative (FunctionBlock)\nSMC_GroupEnableResumeAfterError (FunctionBlock)\nSMC_GroupJog (FunctionBlock)\nSMC_GroupJog2 (FunctionBlock)\nSMC_GroupUpdateContinueData (FunctionBlock)\nSMC_GroupWait (FunctionBlock)\nSMC_MoveAdditionalAxes (FunctionBlock)\ninternal\nDivers\nKernel_CP\nFile and Project Information\nLibrary Reference\n3SLicense\nLibrary Identification\nLibrary Properties\nCmpApp\nLibrary Identification\nLibrary Properties\nCmpIecTask\nLibrary Identification\nLibrary Properties\nCmpLog\nLibrary Identification\nLibrary Properties\nFloatingPointUtils\nLibrary Identification\nLibrary Properties\nSM3_Basic\nLibrary Identification\nLibrary Properties\nLibrary Parameter\nSM3_CPKernelDefaults\nLibrary Identification\nLibrary Properties\nLibrary Parameter\nSM3_CommonPublic\nLibrary Identification\nLibrary Properties\nSM3_Dynamics\nLibrary Identification\nLibrary Properties\nSM3_Error\nLibrary Identification\nLibrary Properties\nSM3_RBase\nLibrary Identification\nLibrary Properties\nSM3_RCP\nLibrary Identification\nLibrary Properties\nSM3_RError\nLibrary Identification\nLibrary Properties\nSM3_Ramps\nLibrary Identification\nLibrary Properties\nSM3_Shared\nLibrary Identification\nLibrary Properties\nSM3_StringUtils\nLibrary Identification\nLibrary Properties\nSM3_TrajectoryGeneration\nLibrary Identification\nLibrary Properties\nSM3_Transformation\nLibrary Identification\nLibrary Properties\nStandard\nLibrary Identification\nLibrary Properties\nSysMem\nLibrary Identification\nLibrary Properties\nSysTarget\nLibrary Identification\nLibrary Properties\nSysTime\nLibrary Identification\nLibrary Properties\nSysTypes2 Interfaces\nLibrary Identification\nLibrary Properties\nSM3_Robotics\nDocs\n»\nSM3_Robotics\n»\nPOUs\n»\nAdministrative/Configuration\n»\nCoordinate\nsystems\n»\nMC_TrackRotaryTable (FB)\nMC_TrackRotaryTable (FB)\nÂ¶\nFUNCTION_BLOCK MC_TrackRotaryTable\nThis function block tracks a piece on a rotary table.\nBased on the position and orientation of the rotary table\nand on the position and orientation of the piece relative to the\ntable, the tracking is performed using\nSMC_SetDynCoordTransformEx\n.\nThe rotation, angular velocity, etc. of the rotary table is given by a\nsingle axis.\nThis FB may be called with a new rising edge on Execute only after the\nconfigured dynamic coordinate system is no longer in use by any movement,\notherwise error SMC_AXIS_GROUP_PCS_STILL_IN_USE will be returned.\nSee output\nInUse\n.\nNote\nNo dead time compensation is done. In case the axis is an encoder,\nit is recommended to use a logical axis to account for the dead time.\nSee also\nMC_TrackConveyorBelt\n.\nThe function block\nSMC_SetDynCoordTransformEx\nprovides a more\ngeneral interface.\nThis FB does not start a movement (administrative FB). The movement is\ninitiated by a command in PCS.\nInOut:\nScope\nName\nType\nComment\nInout\nAxisGroup\nAXIS_GROUP_REF_SM3\nReference to the axis group.\nRotaryTable\nAXIS_REF_SM3\nReference to the axis of the rotary table.\nThe user units of the axis must be angle degrees (0Â°..360Â°).\nIf\nRotaryTable.bRegulatorOn\nis set when the FB is started,\nthe set values will be used.  Otherwise the act values will\nbe used.\nInput\nExecute\nBOOL\nStart the action at rising edge\nRotaryTableOrigin\nMC_COORD_REF\nSpecifies the position and orientation of the rotary table\nin world coordinates (WCS).\nThis defines the coordinate system of the rotary table in\nwhich the position of an object lying on the table\ncan be specified.\nThe z-axis of the coordinate system is the axis of rotation\nof the table.\nInitialObjectPosition\nMC_COORD_REF\nSpecifies the position and orientation of an object lying on\nthe rotary table relative to the table.\nCoordSystem\nSMC_COORD_SYSTEM\nWhich PCS is to be set (PCS_1 or PCS_2)\nName\nSTRING\nThe name of the coordinate system.\nOutput\nDone\nBOOL\nThe transformation has been set successfully\nBusy\nBOOL\nThe FB is not finished\nInUse\nBOOL\nSignals that the axis group still needs the\nreferenced dynamic coordinate system.\nA new rising edge of\nExecute\nwill lead to the error\nSMC_AXIS_GROUP_PCS_STILL_IN_USE\n.\nFor this information to be up-to-date, the function block\nhas to be called continuously\n(even if already\nDone\n).\nA dynamic coordinate system becomes\nInUse\nwhen a movement\nto a position in the coordinate system is commanded.\nIt remains\nInUse\nuntil the target position of a movement to\na different coordinate system has been reached.\nError\nBOOL\nSignals that an error has occurred within the function block\nErrorID\nSMC_ERROR\nError identification",
  "tables": [
    {
      "headers": [
        "Scope",
        "Name",
        "Type",
        "Comment"
      ],
      "rows": [
        {
          "Scope": "Inout",
          "Name": "AxisGroup",
          "Type": "AXIS_GROUP_REF_SM3",
          "Comment": "Reference to the axis group."
        },
        [
          "RotaryTable",
          "AXIS_REF_SM3",
          "Reference to the axis of the rotary table.\nThe user units of the axis must be angle degrees (0Â°..360Â°).\nIfRotaryTable.bRegulatorOnis set when the FB is started,\nthe set values will be used.  Otherwise the act values will\nbe used."
        ],
        {
          "Scope": "Input",
          "Name": "Execute",
          "Type": "BOOL",
          "Comment": "Start the action at rising edge"
        },
        [
          "RotaryTableOrigin",
          "MC_COORD_REF",
          "Specifies the position and orientation of the rotary table\nin world coordinates (WCS).\nThis defines the coordinate system of the rotary table in\nwhich the position of an object lying on the table\ncan be specified.\nThe z-axis of the coordinate system is the axis of rotation\nof the table."
        ],
        [
          "InitialObjectPosition",
          "MC_COORD_REF",
          "Specifies the position and orientation of an object lying on\nthe rotary table relative to the table."
        ],
        [
          "CoordSystem",
          "SMC_COORD_SYSTEM",
          "Which PCS is to be set (PCS_1 or PCS_2)"
        ],
        [
          "Name",
          "STRING",
          "The name of the coordinate system."
        ],
        {
          "Scope": "Output",
          "Name": "Done",
          "Type": "BOOL",
          "Comment": "The transformation has been set successfully"
        },
        [
          "Busy",
          "BOOL",
          "The FB is not finished"
        ],
        [
          "InUse",
          "BOOL",
          "Signals that the axis group still needs the\nreferenced dynamic coordinate system.\nA new rising edge ofExecutewill lead to the errorSMC_AXIS_GROUP_PCS_STILL_IN_USE.\nFor this information to be up-to-date, the function block\nhas to be called continuously\n(even if alreadyDone).\nA dynamic coordinate system becomesInUsewhen a movement\nto a position in the coordinate system is commanded.\nIt remainsInUseuntil the target position of a movement to\na different coordinate system has been reached."
        ],
        [
          "Error",
          "BOOL",
          "Signals that an error has occurred within the function block"
        ],
        [
          "ErrorID",
          "SMC_ERROR",
          "Error identification"
        ]
      ]
    }
  ]
}