{
  "library": "SM3_Robotics",
  "title": "SMC_GroupSetAxisLimitFactors (FunctionBlock)",
  "url": "https://content.helpme-codesys.com/en/libs/SM3_Robotics/Current/SM3_Robotics/POUs/AdministrativeConfiguration/Dynamics/SMC_GroupSetAxisLimitFactors.html",
  "page_title": "SMC_GroupSetAxisLimitFactors (FB)",
  "text": "Library Information\nGetLibVersion (Function)\nGetLibVersionNumber (Function)\nGetVersion (Function)\nIsLibReleased (Function)\nSM3_Robotics\nBasic types\nIDENT_IN_GROUP_REF_SM3 (Alias)\nMC_CIRC_PATHCHOICE (Enum)\nMC_COORD_REF (Struct)\nMC_EXECUTION_MODE (Enum)\nMC_TRANSITION_MODE (Enum)\nSMC_AXIS_GROUP_COMPATIBILITY_OPTIONS (Struct)\nSMC_AXIS_GROUP_CONTINUE_DATA (FunctionBlock)\nSMC_AXIS_GROUP_STATE (Enum)\nSMC_CIRC_MODE (Enum)\nSMC_DYN_LIMITS (Alias)\nSMC_IDynamicCS (Interface)\nSMC_ORIENTATION_MODE (Enum)\nSMC_POS_REF (Union)\nSMC_PTP_MOVEMENT_TYPE (Enum)\nSMC_READ_TOOL_MODE (Enum)\nPOUs\nAdditional\nSMC_AxisDistanceAxes (Enum)\nSMC_AxisDistanceSubMode (Enum)\nSMC_AxisDistanceTransition (FunctionBlock)\nSMC_AxisDistanceTransitionParam (Function)\nSMC_CornerDistance (FunctionBlock)\nSMC_CornerDistanceTransitionParam (Function)\nSMC_StartVelocity (FunctionBlock)\nSMC_StartVelocityAxes (Enum)\nSMC_StartVelocityTransitionParam (Function)\nSMC_StartupAxisGroup (FunctionBlock)\nAdministrative/Configuration\nAxisGroup\nComputation\nCoordinate systems\nDynamics\nKinematics\nTrigger\nAxisGroup\nAXIS_GROUP_REF_SM3 (FunctionBlock)\nHelpers\nMovements\nDiagnostics\nMC_GroupReadActualAcceleration (FunctionBlock)\nMC_GroupReadActualPosition (FunctionBlock)\nMC_GroupReadActualVelocity (FunctionBlock)\nMC_GroupReadConfiguration (FunctionBlock)\nMC_GroupReadError (FunctionBlock)\nMC_GroupReadStatus (FunctionBlock)\nMC_ReadCoordinateTransform (FunctionBlock)\nMC_ReadKinTransform (FunctionBlock)\nSMC_GroupAddOffset (FunctionBlock)\nSMC_GroupAdditionalAxesTargetPositions (FunctionBlock)\nSMC_GroupConvertPosition (FunctionBlock)\nSMC_GroupGetContinuePosition (FunctionBlock)\nSMC_GroupGetContinueToolOffset (FunctionBlock)\nSMC_GroupReadPathAcceleration (FunctionBlock)\nSMC_GroupReadPathDynamics (FunctionBlock)\nSMC_GroupReadPathVelocity (FunctionBlock)\nSMC_GroupReadPlanningStatistics (FunctionBlock)\nSMC_GroupReadPositionInMovement (FunctionBlock)\nSMC_GroupReadRemainingTrajectoryDuration (FunctionBlock)\nSMC_GroupReadSetAcceleration (FunctionBlock)\nSMC_GroupReadSetJerk (FunctionBlock)\nSMC_GroupReadSetPosition (FunctionBlock)\nSMC_GroupReadSetVelocity (FunctionBlock)\nSMC_GroupTargetPosition (FunctionBlock)\nSMC_ReadKinTransformForAxis (FunctionBlock)\nMovement\nAdditionalAxes\nGroupInterrupt\nMC_GroupContinue (FunctionBlock)\nMC_GroupHalt (FunctionBlock)\nMC_GroupInterrupt (FunctionBlock)\nMC_GroupStop (FunctionBlock)\nMC_MoveCircularAbsolute (FunctionBlock)\nMC_MoveCircularRelative (FunctionBlock)\nMC_MoveDirectAbsolute (FunctionBlock)\nMC_MoveDirectRelative (FunctionBlock)\nMC_MoveLinearAbsolute (FunctionBlock)\nMC_MoveLinearRelative (FunctionBlock)\nSMC_GroupEnableResumeAfterError (FunctionBlock)\nSMC_GroupJog (FunctionBlock)\nSMC_GroupJog2 (FunctionBlock)\nSMC_GroupUpdateContinueData (FunctionBlock)\nSMC_GroupWait (FunctionBlock)\nSMC_MoveAdditionalAxes (FunctionBlock)\ninternal\nDivers\nKernel_CP\nFile and Project Information\nLibrary Reference\n3SLicense\nLibrary Identification\nLibrary Properties\nCmpApp\nLibrary Identification\nLibrary Properties\nCmpIecTask\nLibrary Identification\nLibrary Properties\nCmpLog\nLibrary Identification\nLibrary Properties\nFloatingPointUtils\nLibrary Identification\nLibrary Properties\nSM3_Basic\nLibrary Identification\nLibrary Properties\nLibrary Parameter\nSM3_CPKernelDefaults\nLibrary Identification\nLibrary Properties\nLibrary Parameter\nSM3_CommonPublic\nLibrary Identification\nLibrary Properties\nSM3_Dynamics\nLibrary Identification\nLibrary Properties\nSM3_Error\nLibrary Identification\nLibrary Properties\nSM3_RBase\nLibrary Identification\nLibrary Properties\nSM3_RCP\nLibrary Identification\nLibrary Properties\nSM3_RError\nLibrary Identification\nLibrary Properties\nSM3_Ramps\nLibrary Identification\nLibrary Properties\nSM3_Shared\nLibrary Identification\nLibrary Properties\nSM3_StringUtils\nLibrary Identification\nLibrary Properties\nSM3_TrajectoryGeneration\nLibrary Identification\nLibrary Properties\nSM3_Transformation\nLibrary Identification\nLibrary Properties\nStandard\nLibrary Identification\nLibrary Properties\nSysMem\nLibrary Identification\nLibrary Properties\nSysTarget\nLibrary Identification\nLibrary Properties\nSysTime\nLibrary Identification\nLibrary Properties\nSysTypes2 Interfaces\nLibrary Identification\nLibrary Properties\nSM3_Robotics\nDocs\n»\nSM3_Robotics\n»\nPOUs\n»\nAdministrative/Configuration\n»\nDynamics\n»\nSMC_GroupSetAxisLimitFactors (FB)\nSMC_GroupSetAxisLimitFactors (FB)\nÂ¶\nFUNCTION_BLOCK SMC_GroupSetAxisLimitFactors\nThis function block sets limit factors for the maximum velocity,\nacceleration, and jerk of each axis. The limits are effective only\nfor movements commanded after this function block returns done.\nCalling this function block does not cause any movement and does\nnot influence the ongoing motion of the axis group.\nThe factors for all axes currently configured in the axis group need\nto be provided. Each individual factor needs to be positive and not\ngreater than 1.\nInitially, all factors are 1. The factors are not reset when the\naxis group is disabled or enabled.  If an axis is removed from\nthe group, the limit factors for this axis are reset.  If the\naxis is added again, later, then the limit factors are 1.\nThe axis group must not be in state GroupDisabled or GroupErrorStop\nwhen this FB receives the rising edge on execute.\nThe factors can be read with\nSMC_GroupReadAxisLimitFactors\n.\nThe factors are used in combination with the ancillary limits, the\nglobal limits, the factors given at the movement function blocks,\nand the override as follows:\nG: the global axis limits stored in the axis configuration,\nM: the factors given at the movement function blocks (inputs\nVelFactor, AccFactor, â¦),\nF: the factors set with this function block,\nO: the current override factors, and\nA: the ancillary axis limits set with\nSMC_GroupSetAncillaryAxisLimits\n.\nThe effective axis limits L are computed from these inputs as\nL = O * min(A, M * F * G).\nInOut:\nScope\nName\nType\nInitial\nComment\nInout\nAxisGroup\nAXIS_GROUP_REF_SM3\nReference to an axis group\nInput\nExecute\nBOOL\nSets the factors on rising edge.\nVelFactors\nARRAY\n[0..(SMRB.MAX_TOTAL_AXES\n- 1)] OF LREAL\nThe velocity factors for all axes.  The first n factors are for\nthe axes of the groupâs kinematics. All subsequent factors are for\nthe groupâs additional axes.\nAccFactors\nARRAY\n[0..(SMRB.MAX_TOTAL_AXES\n- 1)] OF LREAL\nThe acceleration factors for all axes.  The first n factors are for\nthe axes of the groupâs kinematics. All subsequent factors are for\nthe groupâs additional axes.\nJerkFactors\nARRAY\n[0..(SMRB.MAX_TOTAL_AXES\n- 1)] OF LREAL\nThe jerk factors for all axes.  The first n factors are for\nthe axes of the groupâs kinematics. All subsequent factors are for\nthe groupâs additional axes.\nTorqueFactors\nARRAY\n[0..(SMRB.MAX_TOTAL_AXES\n- 1)] OF LREAL\n[SMRB.MAX_TOTAL_AXES(1)]\nThe torque factors for all axes.  A dynamic model must have been set using\nSMC_GroupSetDynamics\nfor these factors to have an effect.  The first n\nfactors are for the axes of the groupâs kinematics. All subsequent factors\nare for the groupâs additional axes.\nOutput\nDone\nBOOL\nThe limits have been set successfully.\nBusy\nBOOL\nThe FB is not finished.\nError\nBOOL\nSignals that an error has occurred within the function\nblock.\nErrorID\nSMC_ERROR\nError identification",
  "tables": [
    {
      "headers": [
        "Scope",
        "Name",
        "Type",
        "Initial",
        "Comment"
      ],
      "rows": [
        {
          "Scope": "Inout",
          "Name": "AxisGroup",
          "Type": "AXIS_GROUP_REF_SM3",
          "Initial": "",
          "Comment": "Reference to an axis group"
        },
        {
          "Scope": "Input",
          "Name": "Execute",
          "Type": "BOOL",
          "Initial": "",
          "Comment": "Sets the factors on rising edge."
        },
        [
          "VelFactors",
          "ARRAY\n[0..(SMRB.MAX_TOTAL_AXES\n- 1)] OF LREAL",
          "",
          "The velocity factors for all axes.  The first n factors are for\nthe axes of the groupâs kinematics. All subsequent factors are for\nthe groupâs additional axes."
        ],
        [
          "AccFactors",
          "ARRAY\n[0..(SMRB.MAX_TOTAL_AXES\n- 1)] OF LREAL",
          "",
          "The acceleration factors for all axes.  The first n factors are for\nthe axes of the groupâs kinematics. All subsequent factors are for\nthe groupâs additional axes."
        ],
        [
          "JerkFactors",
          "ARRAY\n[0..(SMRB.MAX_TOTAL_AXES\n- 1)] OF LREAL",
          "",
          "The jerk factors for all axes.  The first n factors are for\nthe axes of the groupâs kinematics. All subsequent factors are for\nthe groupâs additional axes."
        ],
        [
          "TorqueFactors",
          "ARRAY\n[0..(SMRB.MAX_TOTAL_AXES\n- 1)] OF LREAL",
          "[SMRB.MAX_TOTAL_AXES(1)]",
          "The torque factors for all axes.  A dynamic model must have been set usingSMC_GroupSetDynamicsfor these factors to have an effect.  The first n\nfactors are for the axes of the groupâs kinematics. All subsequent factors\nare for the groupâs additional axes."
        ],
        {
          "Scope": "Output",
          "Name": "Done",
          "Type": "BOOL",
          "Initial": "",
          "Comment": "The limits have been set successfully."
        },
        [
          "Busy",
          "BOOL",
          "",
          "The FB is not finished."
        ],
        [
          "Error",
          "BOOL",
          "",
          "Signals that an error has occurred within the function\nblock."
        ],
        [
          "ErrorID",
          "SMC_ERROR",
          "",
          "Error identification"
        ]
      ]
    }
  ]
}