{
  "library": "3SLicense",
  "title": "GetUserLicenseValue (Method)",
  "url": "https://content.helpme-codesys.com/en/libs/3SLicense/Current/pou-OLM_OnlineLicenseManager/GetUserLicenseValue.html",
  "page_title": "OLM_OnlineLicenseManager.GetUserLicenseValue (METH)",
  "text": "OLM_OnlineLicenseManager (FunctionBlock)\nDemoModeExpiredID (Method)\nDemoModeStartedID (Method)\nGetUserLicenseValue (Method)\nLicenseMissingID (Method)\nFile and Project Information\nLibrary Reference\nCAA Types Extern\nLibrary Identification\nLibrary Properties\nCmpApp\nLibrary Identification\nLibrary Properties\nCmpCodeMeter\nLibrary Identification\nLibrary Properties\nCmpErrors2 Interfaces\nLibrary Identification\nLibrary Properties\nCmpEventMgr\nLibrary Identification\nLibrary Properties\nCmpLog\nLibrary Identification\nLibrary Properties\nComponent Manager\nLibrary Identification\nLibrary Properties\nStandard\nLibrary Identification\nLibrary Properties\nSysCpuHandling\nLibrary Identification\nLibrary Properties\nSysTypes2 Interfaces\nLibrary Identification\nLibrary Properties\n3SLicense\nDocs\n»\nOLM_OnlineLicenseManager\n(FB)\n»\nOLM_OnlineLicenseManager.GetUserLicenseValue (METH)\nOLM_OnlineLicenseManager.GetUserLicenseValue (METH)\nÂ¶\nMETHOD GetUserLicenseValue : UDINT\nThis method allows to ask for the license value of a component (specified by udiLicenseID)\nInOut:\nScope\nName\nType\nComment\nReturn\nGetUserLicenseValue\nUDINT\nPossible values:\n0\nno valid license installed\n16#FFFFFFFF\ndemo mode (lasts for 30 min)\nelse\nlicense value; interpretation depends on component\nInput\nudiLicenseID\nUDINT\nID of the component that asks for its license value\n(centrally assigned by 3S)",
  "tables": [
    {
      "headers": [
        "Scope",
        "Name",
        "Type",
        "Comment"
      ],
      "rows": [
        [
          "Return",
          "GetUserLicenseValue",
          "UDINT",
          "Possible values:0no valid license installed16#FFFFFFFFdemo mode (lasts for 30 min)elselicense value; interpretation depends on component",
          "0",
          "no valid license installed",
          "16#FFFFFFFF",
          "demo mode (lasts for 30 min)",
          "else",
          "license value; interpretation depends on component"
        ],
        [
          "0",
          "no valid license installed"
        ],
        [
          "16#FFFFFFFF",
          "demo mode (lasts for 30 min)"
        ],
        [
          "else",
          "license value; interpretation depends on component"
        ],
        {
          "Scope": "Input",
          "Name": "udiLicenseID",
          "Type": "UDINT",
          "Comment": "ID of the component that asks for its license value\n(centrally assigned by 3S)"
        }
      ]
    },
    {
      "headers": [
        "0",
        "no valid license installed"
      ],
      "rows": [
        {
          "0": "16#FFFFFFFF",
          "no valid license installed": "demo mode (lasts for 30 min)"
        },
        {
          "0": "else",
          "no valid license installed": "license value; interpretation depends on component"
        }
      ]
    }
  ]
}