{
  "library": "MQTT Client SL",
  "title": "MQTTPublish (FunctionBlock)",
  "url": "https://content.helpme-codesys.com/en/libs/MQTT Client SL/Current/MQTT-Client/Common/Function-Blocks/MQTTPublish.html",
  "page_title": "MQTTPublish (FB)",
  "text": "MQTT Client\nCommon\nEnums\nCOMMUNICATION_MODE (Enum)\nFILTER_MODE (Enum)\nMQTT_ERROR (Enum)\nMQTT_QOS (Enum)\nMQTT_VERSION (Enum)\nV5\nFunction Blocks\nMQTTClient (FunctionBlock)\nMQTTPublish (FunctionBlock)\nMQTTSubscribe (FunctionBlock)\nParams\nMQTTParam (ParamList)\nStructs\nMQTTV5\nUTF-8\nConvertUTF16toUTF8 (Function)\nConvertUTF8toUTF16 (Function)\nFile and Project Information\nLibrary Reference\n3SLicense\nLibrary Identification\nLibrary Properties\nCAA FB Factory\nLibrary Identification\nLibrary Properties\nCAA Types Extern\nLibrary Identification\nLibrary Properties\nCmpCrypto\nLibrary Identification\nLibrary Properties\nCmpErrors2 Interfaces\nLibrary Identification\nLibrary Properties\nCmpLog\nLibrary Identification\nLibrary Properties\nCmpSchedule\nLibrary Identification\nLibrary Properties\nCmpX509Cert\nLibrary Identification\nLibrary Properties\nCommon Behaviour Model\nLibrary Identification\nLibrary Properties\nComponent Manager\nLibrary Identification\nLibrary Properties\nElement Collections\nLibrary Identification\nLibrary Properties\nMemoryUtils\nLibrary Identification\nLibrary Properties\nNet Base Services\nLibrary Identification\nLibrary Properties\nStandard\nLibrary Identification\nLibrary Properties\nStringUtils\nLibrary Identification\nLibrary Properties\nSysMem\nLibrary Identification\nLibrary Properties\nSysSocket2\nLibrary Identification\nLibrary Properties\nSysSocket2 Implementation\nLibrary Identification\nLibrary Properties\nSysTime\nLibrary Identification\nLibrary Properties\nSysTypes2 Interfaces\nLibrary Identification\nLibrary Properties\nWeb Socket Client SL\nLibrary Identification\nLibrary Properties\nMQTT Client SL\nDocs\n»\nMQTT\nClient\n»\nCommon\n»\nFunction\nBlocks\n»\nMQTTPublish (FB)\nMQTTPublish (FB)\nÂ¶\nFUNCTION_BLOCK MQTTPublish EXTENDS CBML.ETrigTo IMPLEMENTS IClientAction\nFunction block to publish (send) messages to a MQTT broker\nUse the input udiTimeout (see CBML.ETrigTo) to set the time in Âµs in which an acknowledgement\nmust be received (relevant for QoS1 and QoS2). Default: 1s\nInOut:\nScope\nName\nType\nComment\nInherited from\nInput\nxExecute\nBOOL\nRising edge: Starts defined operation\nFALSE\n: Resets the defined operation after ready condition was reached\nETrigTo\nudiTimeOut\nUDINT\nMax. operating time for executing\n[Âµs], 0: No operating time limit\nETrigTo\nOutput\nxDone\nBOOL\nReady condition reached\nETrigTo\nxBusy\nBOOL\nOperation is running\nETrigTo\nxError\nBOOL\nError condition reached\nETrigTo\nInput\neQoS\nMQTT_QOS\nQoS Level of message\nxReDelivery\nBOOL\nTRUE: When packet got already send and now should got\nresend, FALSE: First time\nxRetain\nBOOL\nTRUE: Stores the message on server\npbPayload\nPOINTER TO BYTE\nPointer to the message\nudiPayloadSize\nUDINT\nSize of message\nmQTTPublishProperties\nREFERENCE TO\nMQTTPublishProperties\nOptional publish properties (MQTT V5 only)\nInout\nmqttClient\nMQTTClient\nFunction block MQTTClient\nwsTopicName\nWSTRING(1024)\nTopic Name of message\nOutput\neMQTTError\nMQTT_ERROR\nMQTT Error type",
  "tables": [
    {
      "headers": [
        "Scope",
        "Name",
        "Type",
        "Comment",
        "Inherited from"
      ],
      "rows": [
        {
          "Scope": "Input",
          "Name": "xExecute",
          "Type": "BOOL",
          "Comment": "Rising edge: Starts defined operationFALSE: Resets the defined operation after ready condition was reached",
          "Inherited from": "ETrigTo"
        },
        [
          "udiTimeOut",
          "UDINT",
          "Max. operating time for executing\n[Âµs], 0: No operating time limit",
          "ETrigTo"
        ],
        {
          "Scope": "Output",
          "Name": "xDone",
          "Type": "BOOL",
          "Comment": "Ready condition reached",
          "Inherited from": "ETrigTo"
        },
        [
          "xBusy",
          "BOOL",
          "Operation is running",
          "ETrigTo"
        ],
        [
          "xError",
          "BOOL",
          "Error condition reached",
          "ETrigTo"
        ],
        {
          "Scope": "Input",
          "Name": "eQoS",
          "Type": "MQTT_QOS",
          "Comment": "QoS Level of message",
          "Inherited from": ""
        },
        [
          "xReDelivery",
          "BOOL",
          "TRUE: When packet got already send and now should got\nresend, FALSE: First time",
          ""
        ],
        [
          "xRetain",
          "BOOL",
          "TRUE: Stores the message on server",
          ""
        ],
        [
          "pbPayload",
          "POINTER TO BYTE",
          "Pointer to the message",
          ""
        ],
        [
          "udiPayloadSize",
          "UDINT",
          "Size of message",
          ""
        ],
        [
          "mQTTPublishProperties",
          "REFERENCE TOMQTTPublishProperties",
          "Optional publish properties (MQTT V5 only)",
          ""
        ],
        {
          "Scope": "Inout",
          "Name": "mqttClient",
          "Type": "MQTTClient",
          "Comment": "Function block MQTTClient",
          "Inherited from": ""
        },
        [
          "wsTopicName",
          "WSTRING(1024)",
          "Topic Name of message",
          ""
        ],
        {
          "Scope": "Output",
          "Name": "eMQTTError",
          "Type": "MQTT_ERROR",
          "Comment": "MQTT Error type",
          "Inherited from": ""
        }
      ]
    }
  ]
}