{
  "library": "MQTT Client SL",
  "title": "SendAuthPacket (Method)",
  "url": "https://content.helpme-codesys.com/en/libs/MQTT Client SL/Current/MQTT-Client/Common/Function-Blocks/pou-MQTTClient/SendAuthPacket.html",
  "page_title": "MQTTClient.SendAuthPacket (METH)",
  "text": "MQTT Client\nCommon\nEnums\nCOMMUNICATION_MODE (Enum)\nFILTER_MODE (Enum)\nMQTT_ERROR (Enum)\nMQTT_QOS (Enum)\nMQTT_VERSION (Enum)\nV5\nFunction Blocks\nMQTTClient (FunctionBlock)\nMQTTPublish (FunctionBlock)\nMQTTSubscribe (FunctionBlock)\nParams\nMQTTParam (ParamList)\nStructs\nMQTTV5\nUTF-8\nConvertUTF16toUTF8 (Function)\nConvertUTF8toUTF16 (Function)\nFile and Project Information\nLibrary Reference\n3SLicense\nLibrary Identification\nLibrary Properties\nCAA FB Factory\nLibrary Identification\nLibrary Properties\nCAA Types Extern\nLibrary Identification\nLibrary Properties\nCmpCrypto\nLibrary Identification\nLibrary Properties\nCmpErrors2 Interfaces\nLibrary Identification\nLibrary Properties\nCmpLog\nLibrary Identification\nLibrary Properties\nCmpSchedule\nLibrary Identification\nLibrary Properties\nCmpX509Cert\nLibrary Identification\nLibrary Properties\nCommon Behaviour Model\nLibrary Identification\nLibrary Properties\nComponent Manager\nLibrary Identification\nLibrary Properties\nElement Collections\nLibrary Identification\nLibrary Properties\nMemoryUtils\nLibrary Identification\nLibrary Properties\nNet Base Services\nLibrary Identification\nLibrary Properties\nStandard\nLibrary Identification\nLibrary Properties\nStringUtils\nLibrary Identification\nLibrary Properties\nSysMem\nLibrary Identification\nLibrary Properties\nSysSocket2\nLibrary Identification\nLibrary Properties\nSysSocket2 Implementation\nLibrary Identification\nLibrary Properties\nSysTime\nLibrary Identification\nLibrary Properties\nSysTypes2 Interfaces\nLibrary Identification\nLibrary Properties\nWeb Socket Client SL\nLibrary Identification\nLibrary Properties\nMQTT Client SL\nDocs\n»\nMQTT\nClient\n»\nCommon\n»\nFunction\nBlocks\n»\nMQTTClient\n(FB)\n»\nMQTTClient.SendAuthPacket (METH)\nMQTTClient.SendAuthPacket (METH)\nÂ¶\nMETHOD SendAuthPacket : BOOL\nMethod to send AUTH packets to the server (MQTT V5 only).\nThis method can be called to send an AUTH response to the server if a AUTH packet has been received.\nsee MQTTClient.mQTTConnackProperties.xAuthPacketReceived\nInOut:\nScope\nName\nType\nComment\nReturn\nSendAuthPacket\nBOOL\nInput\nxSendAuthPacket\nBOOL\nA rising egde will send the AUTH packet\neReasonCode\nMQTT_REASON_CODE\nThe reason code to send.\nInout\nmQTTAuthProperties\nMQTTAuthProperties\nAUTH properties\nOutput\neError\nMQTT_ERROR",
  "tables": [
    {
      "headers": [
        "Scope",
        "Name",
        "Type",
        "Comment"
      ],
      "rows": [
        {
          "Scope": "Return",
          "Name": "SendAuthPacket",
          "Type": "BOOL",
          "Comment": ""
        },
        {
          "Scope": "Input",
          "Name": "xSendAuthPacket",
          "Type": "BOOL",
          "Comment": "A rising egde will send the AUTH packet"
        },
        [
          "eReasonCode",
          "MQTT_REASON_CODE",
          "The reason code to send."
        ],
        {
          "Scope": "Inout",
          "Name": "mQTTAuthProperties",
          "Type": "MQTTAuthProperties",
          "Comment": "AUTH properties"
        },
        {
          "Scope": "Output",
          "Name": "eError",
          "Type": "MQTT_ERROR",
          "Comment": ""
        }
      ]
    }
  ]
}