{
  "library": "String Builder Base",
  "title": "Constants (GVL)",
  "url": "https://content.helpme-codesys.com/en/libs/String Builder Base/Current/BuilderBase/Aliases/Constants.html",
  "page_title": "Constants (GVL)",
  "text": "BuilderBase\nAliases\nConstants (GVL)\nIStringRepresentation (Alias)\nRUNE (Alias)\nEnums\nENCODING (Enum)\nERROR (Enum)\nFunction Blocks\nRange (FunctionBlock)\nIRange\nSetInitialValue (Method)\nFunctions\nCreateRange (Function)\nCreateRangePool (Function)\nInterfaces\nIBuilder (Interface)\nGetBuilderStats (Method)\nReset (Method)\nSegments\nWriteIString (Method)\nWriteMemSegment (Method)\nWriteRune (Method)\nWriteString (Method)\nWriteWString (Method)\nICharmap (Interface)\nDecode (Method)\nEncode (Method)\nInternals\n_RangePool (FunctionBlock)\nProtected\nStructs\nSTATS (Struct)\nLibrary Information\nGetLibVersion (Function)\nGetLibVersionNumber (Function)\nIsLibReleased (Function)\nFile and Project Information\nLibrary Reference\nMemory Block Manager\nLibrary Identification\nLibrary Properties\nString Segments\nLibrary Identification\nLibrary Properties\nUTF-8 Encoding Support\nLibrary Identification\nLibrary Properties\nString Builder Base\nDocs\n»\nBuilderBase\n»\nAliases\n»\nConstants (GVL)\nConstants (GVL)\nÂ¶\nInOut:\nScope\nName\nType\nInitial\nComment\nConstant\nc_diRuneError\nRUNE\nUTF8.c_diRuneError\nThe âerrorâ Rune or âUnicode replacement characterâ\nc_diMaxRune\nDINT\nUTF8.c_diMaxRune",
  "tables": [
    {
      "headers": [
        "Scope",
        "Name",
        "Type",
        "Initial",
        "Comment"
      ],
      "rows": [
        {
          "Scope": "Constant",
          "Name": "c_diRuneError",
          "Type": "RUNE",
          "Initial": "UTF8.c_diRuneError",
          "Comment": "The âerrorâ Rune or âUnicode replacement characterâ"
        },
        [
          "c_diMaxRune",
          "DINT",
          "UTF8.c_diMaxRune",
          ""
        ]
      ]
    }
  ]
}