{
  "library": "String Builder Base",
  "title": "CreateRange (Function)",
  "url": "https://content.helpme-codesys.com/en/libs/String Builder Base/Current/BuilderBase/Functions/CreateRange.html",
  "page_title": "CreateRange (FUN)",
  "text": "BuilderBase\nAliases\nConstants (GVL)\nIStringRepresentation (Alias)\nRUNE (Alias)\nEnums\nENCODING (Enum)\nERROR (Enum)\nFunction Blocks\nRange (FunctionBlock)\nIRange\nSetInitialValue (Method)\nFunctions\nCreateRange (Function)\nCreateRangePool (Function)\nInterfaces\nIBuilder (Interface)\nGetBuilderStats (Method)\nReset (Method)\nSegments\nWriteIString (Method)\nWriteMemSegment (Method)\nWriteRune (Method)\nWriteString (Method)\nWriteWString (Method)\nICharmap (Interface)\nDecode (Method)\nEncode (Method)\nInternals\n_RangePool (FunctionBlock)\nProtected\nStructs\nSTATS (Struct)\nLibrary Information\nGetLibVersion (Function)\nGetLibVersionNumber (Function)\nIsLibReleased (Function)\nFile and Project Information\nLibrary Reference\nMemory Block Manager\nLibrary Identification\nLibrary Properties\nString Segments\nLibrary Identification\nLibrary Properties\nUTF-8 Encoding Support\nLibrary Identification\nLibrary Properties\nString Builder Base\nDocs\n»\nBuilderBase\n»\nFunctions\n»\nCreateRange (FUN)\nCreateRange (FUN)\nÂ¶\nFUNCTION CreateRange : STR.IRange\nReturns a\nSTR.IRange\ninstance placed in the memory area given by the parameters\nInOut:\nScope\nName\nType\nReturn\nCreateRange\nSTR.IRange\nInput\npbyMemory\nPOINTER TO BYTE\nudiMemSize\nUDINT\nOutput\neErrorID\nSTR.ERROR",
  "tables": [
    {
      "headers": [
        "Scope",
        "Name",
        "Type"
      ],
      "rows": [
        {
          "Scope": "Return",
          "Name": "CreateRange",
          "Type": "STR.IRange"
        },
        {
          "Scope": "Input",
          "Name": "pbyMemory",
          "Type": "POINTER TO BYTE"
        },
        [
          "udiMemSize",
          "UDINT"
        ],
        {
          "Scope": "Output",
          "Name": "eErrorID",
          "Type": "STR.ERROR"
        }
      ]
    }
  ]
}