{
  "library": "String Builder Base",
  "title": "GetCurrentSegment (Method)",
  "url": "https://content.helpme-codesys.com/en/libs/String Builder Base/Current/BuilderBase/Interfaces/pou-IBuilder/Segments/GetCurrentSegment.html",
  "page_title": "IBuilder.GetCurrentSegment (METH)",
  "text": "BuilderBase\nAliases\nConstants (GVL)\nIStringRepresentation (Alias)\nRUNE (Alias)\nEnums\nENCODING (Enum)\nERROR (Enum)\nFunction Blocks\nRange (FunctionBlock)\nIRange\nSetInitialValue (Method)\nFunctions\nCreateRange (Function)\nCreateRangePool (Function)\nInterfaces\nIBuilder (Interface)\nGetBuilderStats (Method)\nReset (Method)\nSegments\nWriteIString (Method)\nWriteMemSegment (Method)\nWriteRune (Method)\nWriteString (Method)\nWriteWString (Method)\nICharmap (Interface)\nDecode (Method)\nEncode (Method)\nInternals\n_RangePool (FunctionBlock)\nProtected\nStructs\nSTATS (Struct)\nLibrary Information\nGetLibVersion (Function)\nGetLibVersionNumber (Function)\nIsLibReleased (Function)\nFile and Project Information\nLibrary Reference\nMemory Block Manager\nLibrary Identification\nLibrary Properties\nString Segments\nLibrary Identification\nLibrary Properties\nUTF-8 Encoding Support\nLibrary Identification\nLibrary Properties\nString Builder Base\nDocs\n»\nBuilderBase\n»\nInterfaces\n»\nIBuilder\n(ITF)\n»\nSegments\n»\nIBuilder.GetCurrentSegment (METH)\nIBuilder.GetCurrentSegment (METH)\nÂ¶\nMETHOD GetCurrentSegment :\nERROR\nInOut:\nScope\nName\nType\nReturn\nGetCurrentSegment\nERROR\nOutput\npbyData\nPOINTER TO BYTE\nudiSize\nUDINT",
  "tables": [
    {
      "headers": [
        "Scope",
        "Name",
        "Type"
      ],
      "rows": [
        {
          "Scope": "Return",
          "Name": "GetCurrentSegment",
          "Type": "ERROR"
        },
        {
          "Scope": "Output",
          "Name": "pbyData",
          "Type": "POINTER TO BYTE"
        },
        [
          "udiSize",
          "UDINT"
        ]
      ]
    }
  ]
}