{
  "library": "String Builder Base",
  "title": "NewRange (Method)",
  "url": "https://content.helpme-codesys.com/en/libs/String Builder Base/Current/BuilderBase/Internals/pou-_RangePool/Protected/NewRange.html",
  "page_title": "_RangePool.NewRange (METH)",
  "text": "BuilderBase\nAliases\nConstants (GVL)\nIStringRepresentation (Alias)\nRUNE (Alias)\nEnums\nENCODING (Enum)\nERROR (Enum)\nFunction Blocks\nRange (FunctionBlock)\nIRange\nSetInitialValue (Method)\nFunctions\nCreateRange (Function)\nCreateRangePool (Function)\nInterfaces\nIBuilder (Interface)\nGetBuilderStats (Method)\nReset (Method)\nSegments\nWriteIString (Method)\nWriteMemSegment (Method)\nWriteRune (Method)\nWriteString (Method)\nWriteWString (Method)\nICharmap (Interface)\nDecode (Method)\nEncode (Method)\nInternals\n_RangePool (FunctionBlock)\nProtected\nStructs\nSTATS (Struct)\nLibrary Information\nGetLibVersion (Function)\nGetLibVersionNumber (Function)\nIsLibReleased (Function)\nFile and Project Information\nLibrary Reference\nMemory Block Manager\nLibrary Identification\nLibrary Properties\nString Segments\nLibrary Identification\nLibrary Properties\nUTF-8 Encoding Support\nLibrary Identification\nLibrary Properties\nString Builder Base\nDocs\n»\nBuilderBase\n»\nInternals\n»\n_RangePool\n(FB)\n»\nProtected\n»\n_RangePool.NewRange (METH)\n_RangePool.NewRange (METH)\nÂ¶\nMETHOD PROTECTED NewRange : STR.IRange\nInOut:\nScope\nName\nType\nReturn\nNewRange\nSTR.IRange\nInput\nitfStrRep\nSTR.IStringRepresentation\npbyMemory\nPOINTER TO BYTE\nudiMemSize\nUDINT\nOutput\neErrorID\nSTR.ERROR",
  "tables": [
    {
      "headers": [
        "Scope",
        "Name",
        "Type"
      ],
      "rows": [
        {
          "Scope": "Return",
          "Name": "NewRange",
          "Type": "STR.IRange"
        },
        {
          "Scope": "Input",
          "Name": "itfStrRep",
          "Type": "STR.IStringRepresentation"
        },
        [
          "pbyMemory",
          "POINTER TO BYTE"
        ],
        [
          "udiMemSize",
          "UDINT"
        ],
        {
          "Scope": "Output",
          "Name": "eErrorID",
          "Type": "STR.ERROR"
        }
      ]
    }
  ]
}