{
  "library": "String Builder Base",
  "title": "WriteWString (Method)",
  "url": "https://content.helpme-codesys.com/en/libs/String Builder Base/Current/BuilderBase/Interfaces/pou-IBuilder/WriteWString.html",
  "page_title": "IBuilder.WriteWString (METH)",
  "text": "BuilderBase\nAliases\nConstants (GVL)\nIStringRepresentation (Alias)\nRUNE (Alias)\nEnums\nENCODING (Enum)\nERROR (Enum)\nFunction Blocks\nRange (FunctionBlock)\nIRange\nSetInitialValue (Method)\nFunctions\nCreateRange (Function)\nCreateRangePool (Function)\nInterfaces\nIBuilder (Interface)\nGetBuilderStats (Method)\nReset (Method)\nSegments\nWriteIString (Method)\nWriteMemSegment (Method)\nWriteRune (Method)\nWriteString (Method)\nWriteWString (Method)\nICharmap (Interface)\nDecode (Method)\nEncode (Method)\nInternals\n_RangePool (FunctionBlock)\nProtected\nStructs\nSTATS (Struct)\nLibrary Information\nGetLibVersion (Function)\nGetLibVersionNumber (Function)\nIsLibReleased (Function)\nFile and Project Information\nLibrary Reference\nMemory Block Manager\nLibrary Identification\nLibrary Properties\nString Segments\nLibrary Identification\nLibrary Properties\nUTF-8 Encoding Support\nLibrary Identification\nLibrary Properties\nString Builder Base\nDocs\n»\nBuilderBase\n»\nInterfaces\n»\nIBuilder\n(ITF)\n»\nIBuilder.WriteWString (METH)\nIBuilder.WriteWString (METH)\nÂ¶\nMETHOD WriteWString : UDINT\nAppends the contents of\nwsValue\nto the buffer.\nIt returns the number of bytes written.\nInOut:\nScope\nName\nType\nComment\nReturn\nWriteWString\nUDINT\nInout Const\nwsValue\nWSTRING(255)\nEncoding UCS-2\nOutput\neErrorID\nERROR",
  "tables": [
    {
      "headers": [
        "Scope",
        "Name",
        "Type",
        "Comment"
      ],
      "rows": [
        {
          "Scope": "Return",
          "Name": "WriteWString",
          "Type": "UDINT",
          "Comment": ""
        },
        {
          "Scope": "Inout Const",
          "Name": "wsValue",
          "Type": "WSTRING(255)",
          "Comment": "Encoding UCS-2"
        },
        {
          "Scope": "Output",
          "Name": "eErrorID",
          "Type": "ERROR",
          "Comment": ""
        }
      ]
    }
  ]
}