{
  "library": "Standard64",
  "title": "WFIND (Function)",
  "url": "https://content.helpme-codesys.com/en/libs/Standard64/Current/String-Functions/WFIND.html",
  "page_title": "WFIND (FUN)",
  "text": "Deutsch\nEnglish\nFrançais\nEspañol\nItaliano\nРусский\n日本語\n中文\nMenu\nSearch\nDeutsch\nEnglish\nFrançais\nEspañol\nItaliano\nРусский\n日本語\n中文\nAtomic Read-Write Functions\nAtomicReadLInt (Function)\nAtomicReadLReal (Function)\nAtomicReadLTime (Function)\nAtomicReadLWord (Function)\nAtomicReadULInt (Function)\nAtomicWriteLInt (Function)\nAtomicWriteLReal (Function)\nAtomicWriteLTime (Function)\nAtomicWriteLWord (Function)\nAtomicWriteULInt (Function)\nCounter\nLCTD (FunctionBlock)\nLCTU (FunctionBlock)\nLCTUD (FunctionBlock)\nString Functions\nWCONCAT (Function)\nWDELETE (Function)\nWFIND (Function)\nWINSERT (Function)\nWLEFT (Function)\nWLEN (Function)\nWMID (Function)\nWREPLACE (Function)\nWRIGHT (Function)\nTimer\nLTOF (FunctionBlock)\nLTON (FunctionBlock)\nLTP (FunctionBlock)\nFile and Project Information\nLibrary Reference\nStandard64\nDocs\n»\nString\nFunctions\n»\nWFIND (FUN)\nWFIND (FUN)\nÂ¶\nFUNCTION WFIND : INT\nFind the wcharacter position of the beginning of\nthe first occurence of STR2 in STR1.\nIf no occurence of STR1 is found, then\nthe result is 0.\nInOut:\nScope\nName\nType\nReturn\nWFIND\nINT\nInput\nSTR1\nWSTRING(255)\nSTR2\nWSTRING(255)\ntop\nCODESYS Group | We\nsoftware\nAutomation.\nto software\n['sɒftwɛər]\ntransitive verb\n__softwared/softwaring\n: to develop software\n// to software automation: to develop software for automation purposes\nThe CODESYS Group is the manufacturer of CODESYS, the leading hardware-independent\n                                    IEC 61131-3 automation software for developing and engineering controller\n                                    applications.\nCODESYS® is a registered trademark.\nCODESYS GmbH\nA member of the CODESYS Group\nMemminger Straße 151, 87439 Kempten\nGermany\nTel.:\n+49-831-54031-0\ninfo@codesys.com\nLegal Notice\nPrivacy Policy\nLinkedIn\nYoutube\nRSS\nDownloads\nLogin\nCODESYS Store\n© 2022 CODESYS GmbH\n| A member of the CODESYS Group",
  "tables": [
    {
      "headers": [
        "Scope",
        "Name",
        "Type"
      ],
      "rows": [
        {
          "Scope": "Return",
          "Name": "WFIND",
          "Type": "INT"
        },
        {
          "Scope": "Input",
          "Name": "STR1",
          "Type": "WSTRING(255)"
        },
        [
          "STR2",
          "WSTRING(255)"
        ]
      ]
    }
  ]
}