{
  "library": "SM3_Drive_ETC",
  "title": "SMC_ETC_InterpolateAxisPosition (Function)",
  "url": "https://content.helpme-codesys.com/en/libs/SM3_Drive_ETC/Current/SMC_ETC_InterpolateAxisPosition.html",
  "page_title": "SMC_ETC_InterpolateAxisPosition (FUN)",
  "text": "AXIS_REF_ETC_BASE_SM3 (FunctionBlock)\nParameterAccess\nGetSlaveId (Method)\nGlobalTextList (GlobalTextList)\nSMC3_ETC\nvisu templates\nSMC_ETC_InterpolateAxisPosition (Function)\nSMC_ETC_Params (ParamList)\nSMC_ETC_Timestamp_32bitTo64bit (Function)\nSMC_Set_ETC_DCSyncSupervision (FunctionBlock)\nFile and Project Information\nLibrary Reference\nCmpErrors2 Interfaces\nLibrary Identification\nLibrary Properties\nCmpIecTask\nLibrary Identification\nLibrary Properties\nCmpLog\nLibrary Identification\nLibrary Properties\nIoStandard\nLibrary Identification\nLibrary Properties\nSM3_Basic\nLibrary Identification\nLibrary Properties\nLibrary Parameter\nSM3_ETC_ITF\nLibrary Identification\nLibrary Properties\nSM3_RBase\nLibrary Identification\nLibrary Properties\nSM3_Shared\nLibrary Identification\nLibrary Properties\nSM3_StringUtils\nLibrary Identification\nLibrary Properties\nStandard\nLibrary Identification\nLibrary Properties\nSysTypes2 Interfaces\nLibrary Identification\nLibrary Properties\nVisuElem3DPath\nLibrary Identification\nLibrary Properties\nLibrary Parameter\nVisuElemCamDisplayer\nLibrary Identification\nLibrary Properties\nLibrary Parameter\nVisuElemMeter\nLibrary Identification\nLibrary Properties\nVisuElemTextEditor\nLibrary Identification\nLibrary Properties\nVisuElemTrace\nLibrary Identification\nLibrary Properties\nVisuElems\nLibrary Identification\nLibrary Properties\nVisuElemsAlarm\nLibrary Identification\nLibrary Properties\nVisuElemsDateTime\nLibrary Identification\nLibrary Properties\nVisuElemsSpecialControls\nLibrary Identification\nLibrary Properties\nVisuElemsWinControls\nLibrary Identification\nLibrary Properties\nVisuInputs\nLibrary Identification\nLibrary Properties\nVisuNativeControl\nLibrary Identification\nLibrary Properties\nSM3_Drive_ETC\nDocs\n»\nSMC_ETC_InterpolateAxisPosition (FUN)\nSMC_ETC_InterpolateAxisPosition (FUN)\nÂ¶\nFUNCTION SMC_ETC_InterpolateAxisPosition : SMC_Error\nDetermines the axis position at a given time.\nThe time is given as a EtherCAT distributed clock (DC) system time.\nNote\nThe actual position at\nTimestamp_ns\n, optionally adjusted by the\nDelay\n,\nhas to be contained in the act value buffer of the\nAxis\n.  The size of this\nbuffer can be adjusted using the\ngc_SMC_ACT_VALUE_BUFFER_SIZE_BASE2_EXP\nlibrary parameter of SM3_Basic.\nIf the timestamp is too old (not found in the act value buffer) or too new\n(more than one task interval higher than the timestamp of the latest\nreceived actual position), the error SMC_INVALID_TIMESTAMP is returned.\nThe actual velocity is used if (and only if)  it is transmitted by PDO.\nIn this case, cubic interpolation is used, otherwise linear interpolation.\nFor increased accuracy, transmitting the actual velocity is recommended.\nIf the underlying EtherCAT stack does not support querying the DC\nsystem time, the error SMC_NOT_IMPLEMENTED will be reported.\nInOut:\nScope\nName\nType\nInitial\nComment\nInout Const\nAxis\nAXIS_REF_SM3\nInput\nTimestamp_ns\nULINT\nThe timestamp at which the axis position is requested.\nThis is the EtherCAT DC system time in nanoseconds.\nThe timestamp must lie within the time span between the oldest available\nactual position (depending on the buffer size; see above) and the timestamp\nof the most recently received actual position plus one task cycle.\nDelay\nLREAL\n0.0\nOptional delay in seconds that is subtracted from the timestamp.\nNegative values are not supported.\nReturn\nSMC_ETC_InterpolateAxisPosition\nSMC_Error\nOutput\nPosition\nLREAL\nThe position of the axis at the given timestamp.",
  "tables": [
    {
      "headers": [
        "Scope",
        "Name",
        "Type",
        "Initial",
        "Comment"
      ],
      "rows": [
        {
          "Scope": "Inout Const",
          "Name": "Axis",
          "Type": "AXIS_REF_SM3",
          "Initial": "",
          "Comment": ""
        },
        {
          "Scope": "Input",
          "Name": "Timestamp_ns",
          "Type": "ULINT",
          "Initial": "",
          "Comment": "The timestamp at which the axis position is requested.\nThis is the EtherCAT DC system time in nanoseconds.\nThe timestamp must lie within the time span between the oldest available\nactual position (depending on the buffer size; see above) and the timestamp\nof the most recently received actual position plus one task cycle."
        },
        [
          "Delay",
          "LREAL",
          "0.0",
          "Optional delay in seconds that is subtracted from the timestamp.\nNegative values are not supported."
        ],
        {
          "Scope": "Return",
          "Name": "SMC_ETC_InterpolateAxisPosition",
          "Type": "SMC_Error",
          "Initial": "",
          "Comment": ""
        },
        {
          "Scope": "Output",
          "Name": "Position",
          "Type": "LREAL",
          "Initial": "",
          "Comment": "The position of the axis at the given timestamp."
        }
      ]
    }
  ]
}