{
  "library": "3S Storage",
  "title": "StorageGetIndexId (Method)",
  "url": "https://content.helpme-codesys.com/en/libs/3S Storage/Current/_3SStorage/Instances/pou-Storage/IStorage2/StorageGetIndexId.html",
  "page_title": "Storage.StorageGetIndexId (METH)",
  "text": "Deutsch\nEnglish\nFrançais\nEspañol\nItaliano\nРусский\n日本語\n中文\nMenu\nSearch\nDeutsch\nEnglish\nFrançais\nEspañol\nItaliano\nРусский\n日本語\n中文\n_3SStorage\nExternal\nFunctions\nStorage\nInstances\nStorage (FunctionBlock)\nIStorage2\nStorageClear (Method)\nStorageClose (Method)\nStorageEncoding (Property)\nStorageGetMetrics (Method)\nStorageGetPath (Method)\nStorageIsReadOnly (Property)\nStorageLockingState (Property)\nStorageNumOfTables (Property)\nStorageOpenFile (Method)\nStorageReorg (Method)\nStorageSchemaVersion (Property)\nStorageUserVersion (Property)\nStorageVersion (Property)\nTableOpen (Method)\nTransactionBegin (Method)\nUtilityGetCurrentDateAndTime (Method)\nUtilityRandomness (Method)\n_3SStorageVersionConstants (GVL)\nFile and Project Information\nLibrary Reference\nCAA FB Factory\nLibrary Identification\nLibrary Properties\nCAA Storage\nLibrary Identification\nLibrary Properties\nCAA Types Extern\nLibrary Identification\nLibrary Properties\n3S Storage\nDocs\n»\n_3SStorage\n»\nInstances\n»\nStorage\n(FB)\n»\nIStorage2\n»\nStorage.StorageGetIndexId (METH)\nStorage.StorageGetIndexId (METH)\nÂ¶\nMETHOD StorageGetIndexId : STO.ERROR\nDetermines the id of an index of a table.\nInOut:\nScope\nName\nType\nComment\nReturn\nStorageGetIndexId\nSTO.ERROR\nThe error code. Can return ERROR.NOT_IMPLEMENTED for non-\nsqlite implementations\nInout\nsIndex\nSTRING\nThe name of the index\nsTable\nSTRING\nThe name of the table the index belongs to\nOutput\nidIndex\nCAA.IDENT\nReturns id of the index.\ntop\nCODESYS Group | We\nsoftware\nAutomation.\nto software\n['sɒftwɛər]\ntransitive verb\n__softwared/softwaring\n: to develop software\n// to software automation: to develop software for automation purposes\nThe CODESYS Group is the manufacturer of CODESYS, the leading hardware-independent\n                                    IEC 61131-3 automation software for developing and engineering controller\n                                    applications.\nCODESYS® is a registered trademark.\nCODESYS GmbH\nA member of the CODESYS Group\nMemminger Straße 151, 87439 Kempten\nGermany\nTel.:\n+49-831-54031-0\ninfo@codesys.com\nLegal Notice\nPrivacy Policy\nLinkedIn\nYoutube\nRSS\nDownloads\nLogin\nCODESYS Store\n© 2022 CODESYS GmbH\n| A member of the CODESYS Group",
  "tables": [
    {
      "headers": [
        "Scope",
        "Name",
        "Type",
        "Comment"
      ],
      "rows": [
        {
          "Scope": "Return",
          "Name": "StorageGetIndexId",
          "Type": "STO.ERROR",
          "Comment": "The error code. Can return ERROR.NOT_IMPLEMENTED for non-\nsqlite implementations"
        },
        {
          "Scope": "Inout",
          "Name": "sIndex",
          "Type": "STRING",
          "Comment": "The name of the index"
        },
        [
          "sTable",
          "STRING",
          "The name of the table the index belongs to"
        ],
        {
          "Scope": "Output",
          "Name": "idIndex",
          "Type": "CAA.IDENT",
          "Comment": "Returns id of the index."
        }
      ]
    }
  ]
}