{
  "library": "AC_Alarming",
  "title": "Init2 (Method)",
  "url": "https://content.helpme-codesys.com/en/libs/AC_Alarming/Current/ExtenderFB/pou-IACAlarmExtender2/Init2.html",
  "page_title": "IACAlarmExtender2.Init2 (METH)",
  "text": "ExtenderFB\nACAlarmExtender (FunctionBlock)\nAcknowledgeAllAlarmsOfModule (Method)\nExecute (Method)\nGetActiveAlarmsOfModule (Method)\nGetEventAlarmID (Method)\nGetID (Property)\nInit (Method)\nInit2 (Method)\nInitSortedModuleAlarms (Method)\nAlarmInfo (Struct)\nAlarmingCall (Enum)\nIACAlarmExtender (Interface)\nInit (Method)\nIACAlarmExtender2 (Interface)\nGetEventAlarmID (Method)\nInit2 (Method)\nIACAlarmExtender3 (Interface)\nAcknowledgeAllAlarmsOfModule (Method)\nGetActiveAlarmsOfModule (Method)\nInitSortedModuleAlarms (Method)\nModuleAlarmInfo (Struct)\nModuleCall (Struct)\nModuleEvent (Struct)\nFunctions\nRaiseModuleEvent (Function)\nReplaceAlarmPlaceholderString (Function)\nGlobalTextList (GlobalTextList)\nModuleInterface\nIModuleAlarming (Interface)\nConsumeModuleAlarm (Method)\nVisualization\nFile and Project Information\nLibrary Reference\nAC_ModuleBase\nLibrary Identification\nLibrary Properties\nAlarmManager\nLibrary Identification\nLibrary Properties\nLibrary Parameter\nStringUtils\nLibrary Identification\nLibrary Properties\nVisuElem3DPath\nLibrary Identification\nLibrary Properties\nLibrary Parameter\nVisuElemCamDisplayer\nLibrary Identification\nLibrary Properties\nLibrary Parameter\nVisuElemMeter\nLibrary Identification\nLibrary Properties\nVisuElemTextEditor\nLibrary Identification\nLibrary Properties\nVisuElemTrace\nLibrary Identification\nLibrary Properties\nVisuElemXYChart\nLibrary Identification\nLibrary Properties\nVisuElems\nLibrary Identification\nLibrary Properties\nVisuElemsAlarm\nLibrary Identification\nLibrary Properties\nVisuElemsDateTime\nLibrary Identification\nLibrary Properties\nVisuElemsSpecialControls\nLibrary Identification\nLibrary Properties\nVisuElemsWinControls\nLibrary Identification\nLibrary Properties\nVisuNativeControl\nLibrary Identification\nLibrary Properties\nAC_Alarming\nDocs\n»\nExtenderFB\n»\nIACAlarmExtender2\n(ITF)\n»\nIACAlarmExtender2.Init2 (METH)\nIACAlarmExtender2.Init2 (METH)\nÂ¶\nMETHOD Init2\nInitialization function to initialize the environment extender of the\nalarm generator. This function is called by code generated by the alarm\ngenerator.\nInOut:\nScope\nName\nType\nComment\nInput\npModCall\nPOINTER TO\nModuleCall\nA pointer to a list of all module calls available under an application.\nThe latter list is created by the alarm generator during an application\ncomposer generation.\nuiModCall\nUINT\nThe number of module call defined in the list pointed to by\npModCall.\npModEvents\nPOINTER TO\nModuleEvent\nA pointer to a list of all module events available under an application.\nThe latter list is created by the alarm generator during an application\ncomposer generation.\nuiModEvents\nUINT\nThe number of module events defined in the list pointed to\nby\npModEvents\n.",
  "tables": [
    {
      "headers": [
        "Scope",
        "Name",
        "Type",
        "Comment"
      ],
      "rows": [
        {
          "Scope": "Input",
          "Name": "pModCall",
          "Type": "POINTER TOModuleCall",
          "Comment": "A pointer to a list of all module calls available under an application.\nThe latter list is created by the alarm generator during an application\ncomposer generation."
        },
        [
          "uiModCall",
          "UINT",
          "The number of module call defined in the list pointed to by\npModCall."
        ],
        [
          "pModEvents",
          "POINTER TOModuleEvent",
          "A pointer to a list of all module events available under an application.\nThe latter list is created by the alarm generator during an application\ncomposer generation."
        ],
        [
          "uiModEvents",
          "UINT",
          "The number of module events defined in the list pointed to\nbypModEvents."
        ]
      ]
    }
  ]
}