{
  "library": "CmpBACnet",
  "title": "BACnetWriteProperty (Function)",
  "url": "https://content.helpme-codesys.com/en/libs/CmpBACnet/Current/BACnetClientAPI/BACnetWriteProperty.html",
  "page_title": "BACnetWriteProperty (FUN)",
  "text": "Deutsch\nEnglish\nFrançais\nEspañol\nItaliano\nРусский\n日本語\n中文\nMenu\nSearch\nDeutsch\nEnglish\nFrançais\nEspañol\nItaliano\nРусский\n日本語\n中文\nBACnetAsyncTransactionToken (Struct)\nBACnetClientAPI\nBACnetAcknowledgeAlarm (Function)\nBACnetAddListElement (Function)\nBACnetCancelPendingConfirmedRequest (Function)\nBACnetConfPrivateTransfer (Function)\nBACnetConfTextMessage (Function)\nBACnetCreateObject (Function)\nBACnetCreateObjectResult (Struct)\nBACnetDeleteObject (Function)\nBACnetDeviceCommControl (Function)\nBACnetGetAlarmSummary (Function)\nBACnetGetEnrollmentSummary (Function)\nBACnetGetEventInfo (Function)\nBACnetLifeSafetyOperation (Function)\nBACnetReadAllPropertyDataContents (Function)\nBACnetReadFile (Function)\nBACnetReadProperty (Function)\nBACnetReadPropertyMultiple (Function)\nBACnetReadRange (Function)\nBACnetReinitializeDevice (Function)\nBACnetRemoveListElement (Function)\nBACnetSubscribeCOV (Function)\nBACnetSubscribeCOVProperty (Function)\nBACnetUnconfPrivateTransfer (Function)\nBACnetUnconfTextMessage (Function)\nBACnetWhoHas (Function)\nBACnetWhoIs (Function)\nBACnetWriteFile (Function)\nBACnetWriteGroup (Function)\nBACnetWriteProperty (Function)\nBACnetWritePropertyMultiple (Function)\nadvanced\nBACnetBackupBACnetDevice (Function)\nBACnetCloseClientCustomer (Function)\nBACnetGetClientDeviceCommunication (Function)\nBACnetOpenClientCustomer (Function)\nBACnetRegisterClientCommunicationStateCallback (Function)\nBACnetRegisterClientDataPoint (Function)\nBACnetRegisterClientEventNotification (Function)\nBACnetRegisterClientUnsubscribeCompletionCallback (Function)\nBACnetRestartAllClients (Function)\nBACnetRestoreBACnetDevice (Function)\nBACnetSetClientDeviceCommunication (Function)\nBACnetSetClientDeviceFixAddress (Function)\nBACnetSetClientDeviceFixSubscribeCovTime (Function)\nBACnetSetClientGlobalCommTimingParameters (Function)\nBACnetSetClientGlobalMaxDeviceActions (Function)\nBACnetUnregisterClientDataPoint (Function)\nBACnetUnregisterClientEventNotification (Function)\nFile and Project Information\nLibrary Reference\n3SLicense\nLibrary Identification\nLibrary Properties\nCAA Ressource Manager Extern\nLibrary Identification\nLibrary Properties\nCAA Types Extern\nLibrary Identification\nLibrary Properties\nCmpErrors2 Interfaces\nLibrary Identification\nLibrary Properties\nCmpEventMgr\nLibrary Identification\nLibrary Properties\nCmpLog\nLibrary Identification\nLibrary Properties\nCmpSettings\nLibrary Identification\nLibrary Properties\nComponent Manager\nLibrary Identification\nLibrary Properties\nIoStandard\nLibrary Identification\nLibrary Properties\nStandard\nLibrary Identification\nLibrary Properties\nSysMem\nLibrary Identification\nLibrary Properties\nSysTarget\nLibrary Identification\nLibrary Properties\nSysTask\nLibrary Identification\nLibrary Properties\nSysTypes2 Interfaces\nLibrary Identification\nLibrary Properties\nCmpBACnet\nDocs\n»\nBACnetClientAPI\n»\nBACnetWriteProperty (FUN)\nBACnetWriteProperty (FUN)\nÂ¶\nFUNCTION BACnetWriteProperty :\nIEC_BACNET_STATUS\nSends a WriteProperty request\nSends a request to write a value to a property of an object. This routine may\ncontrol APDU properties like APDU length, segmentation, and timeout for both request\nand in response. This routine can execute asynchronously, i.e. this routine will return\nto the caller before the BACnet reply comes so that the applications can keep running.\nIn this case the response information will be received by the thread which is responsible\nfor receiving asynchronous responses. An optional BACNET_SIMPLE_ACK_COMPLETE_CB routine,\nwhich is provided by the application, shall be used to process this information. If a\nnumber of asynchronous requests are sent, the responses shall be queued and identified\nby the transaction handles. If the application does not supply the\nBACNET_SIMPLE_ACK_COMPLETE_CB routine; then the routine sends a request and waits\nfor the reply.\nAsynchron call. As soon as pResultStatus is\nIEC_BACNET_STATUS.BACNET_STATUS_OK\nthe\ncall was successfully completed.\nInOut:\nScope\nName\nType\nComment\nReturn\nBACnetWriteProperty\nIEC_BACNET_STATUS\nA status indicating whether the operation worked.\nInput\npSourceAddress\nPOINTER TO\nIEC_BACNET_ADDRESS\nIF the BACnet application has only one device constructed AND installed, THIS can\nbe 0. In this case the MAC address of this device will be used. Otherwise this\nshall be the MAC address returned on device object construction.\npDestinationAddress\nPOINTER TO\nIEC_BACNET_ADDRESS\nThis is the MAC address of the device to which the request\nshould be sent.\npWriteInfo\nPOINTER TO\nIEC_BACNET_WRITE_INFO\nA pointer to the service information data structure. This data structure identifies\nthe property within the device and includes the object ID, property ID array index\nand also a property contents buffer with the value to be written.\npAPDUParams\nPOINTER TO\nIEC_BACNET_APDU_PROPERTIES\nA pointer to the APDU-Properties structure which sets APDU properties for this\ntransaction only. This does not change global defaults or settings for the application\nAPDU Properties. This argument may be 0. In this case APDU properties  are used\nwhich were specified in the device object properties of the applications device which\nsends the request.\npTransactionToken\nPOINTER TO\nBACnetAsyncTransactionToken\nTransaction token of the asynchronous call - see\nBACnetAsyncTransactionToken\n.\npError\nPOINTER TO\nIEC_BACNET_ERROR\nA pointer to a structure to hold BACnet Error information. pError may be 0 if the\napplication isnât interested in detailed error information.\ntop\nCODESYS Group | We\nsoftware\nAutomation.\nto software\n['sɒftwɛər]\ntransitive verb\n__softwared/softwaring\n: to develop software\n// to software automation: to develop software for automation purposes\nThe CODESYS Group is the manufacturer of CODESYS, the leading hardware-independent\n                                    IEC 61131-3 automation software for developing and engineering controller\n                                    applications.\nCODESYS® is a registered trademark.\nCODESYS GmbH\nA member of the CODESYS Group\nMemminger Straße 151, 87439 Kempten\nGermany\nTel.:\n+49-831-54031-0\ninfo@codesys.com\nLegal Notice\nPrivacy Policy\nLinkedIn\nYoutube\nRSS\nDownloads\nLogin\nCODESYS Store\n© 2022 CODESYS GmbH\n| A member of the CODESYS Group",
  "tables": [
    {
      "headers": [
        "Scope",
        "Name",
        "Type",
        "Comment"
      ],
      "rows": [
        {
          "Scope": "Return",
          "Name": "BACnetWriteProperty",
          "Type": "IEC_BACNET_STATUS",
          "Comment": "A status indicating whether the operation worked."
        },
        {
          "Scope": "Input",
          "Name": "pSourceAddress",
          "Type": "POINTER TOIEC_BACNET_ADDRESS",
          "Comment": "IF the BACnet application has only one device constructed AND installed, THIS can\nbe 0. In this case the MAC address of this device will be used. Otherwise this\nshall be the MAC address returned on device object construction."
        },
        [
          "pDestinationAddress",
          "POINTER TOIEC_BACNET_ADDRESS",
          "This is the MAC address of the device to which the request\nshould be sent."
        ],
        [
          "pWriteInfo",
          "POINTER TOIEC_BACNET_WRITE_INFO",
          "A pointer to the service information data structure. This data structure identifies\nthe property within the device and includes the object ID, property ID array index\nand also a property contents buffer with the value to be written."
        ],
        [
          "pAPDUParams",
          "POINTER TOIEC_BACNET_APDU_PROPERTIES",
          "A pointer to the APDU-Properties structure which sets APDU properties for this\ntransaction only. This does not change global defaults or settings for the application\nAPDU Properties. This argument may be 0. In this case APDU properties  are used\nwhich were specified in the device object properties of the applications device which\nsends the request."
        ],
        [
          "pTransactionToken",
          "POINTER TOBACnetAsyncTransactionToken",
          "Transaction token of the asynchronous call - seeBACnetAsyncTransactionToken."
        ],
        [
          "pError",
          "POINTER TOIEC_BACNET_ERROR",
          "A pointer to a structure to hold BACnet Error information. pError may be 0 if the\napplication isnât interested in detailed error information."
        ]
      ]
    }
  ]
}