{
  "library": "CmpBACnet",
  "title": "BACnetBackupBACnetDevice (Function)",
  "url": "https://content.helpme-codesys.com/en/libs/CmpBACnet/Current/BACnetClientAPI/advanced/BACnetBackupBACnetDevice.html",
  "page_title": "BACnetBackupBACnetDevice (FUN)",
  "text": "Deutsch\nEnglish\nFrançais\nEspañol\nItaliano\nРусский\n日本語\n中文\nMenu\nSearch\nDeutsch\nEnglish\nFrançais\nEspañol\nItaliano\nРусский\n日本語\n中文\nBACnetAsyncTransactionToken (Struct)\nBACnetClientAPI\nBACnetAcknowledgeAlarm (Function)\nBACnetAddListElement (Function)\nBACnetCancelPendingConfirmedRequest (Function)\nBACnetConfPrivateTransfer (Function)\nBACnetConfTextMessage (Function)\nBACnetCreateObject (Function)\nBACnetCreateObjectResult (Struct)\nBACnetDeleteObject (Function)\nBACnetDeviceCommControl (Function)\nBACnetGetAlarmSummary (Function)\nBACnetGetEnrollmentSummary (Function)\nBACnetGetEventInfo (Function)\nBACnetLifeSafetyOperation (Function)\nBACnetReadAllPropertyDataContents (Function)\nBACnetReadFile (Function)\nBACnetReadProperty (Function)\nBACnetReadPropertyMultiple (Function)\nBACnetReadRange (Function)\nBACnetReinitializeDevice (Function)\nBACnetRemoveListElement (Function)\nBACnetSubscribeCOV (Function)\nBACnetSubscribeCOVProperty (Function)\nBACnetUnconfPrivateTransfer (Function)\nBACnetUnconfTextMessage (Function)\nBACnetWhoHas (Function)\nBACnetWhoIs (Function)\nBACnetWriteFile (Function)\nBACnetWriteGroup (Function)\nBACnetWriteProperty (Function)\nBACnetWritePropertyMultiple (Function)\nadvanced\nBACnetBackupBACnetDevice (Function)\nBACnetCloseClientCustomer (Function)\nBACnetGetClientDeviceCommunication (Function)\nBACnetOpenClientCustomer (Function)\nBACnetRegisterClientCommunicationStateCallback (Function)\nBACnetRegisterClientDataPoint (Function)\nBACnetRegisterClientEventNotification (Function)\nBACnetRegisterClientUnsubscribeCompletionCallback (Function)\nBACnetRestartAllClients (Function)\nBACnetRestoreBACnetDevice (Function)\nBACnetSetClientDeviceCommunication (Function)\nBACnetSetClientDeviceFixAddress (Function)\nBACnetSetClientDeviceFixSubscribeCovTime (Function)\nBACnetSetClientGlobalCommTimingParameters (Function)\nBACnetSetClientGlobalMaxDeviceActions (Function)\nBACnetUnregisterClientDataPoint (Function)\nBACnetUnregisterClientEventNotification (Function)\nFile and Project Information\nLibrary Reference\n3SLicense\nLibrary Identification\nLibrary Properties\nCAA Ressource Manager Extern\nLibrary Identification\nLibrary Properties\nCAA Types Extern\nLibrary Identification\nLibrary Properties\nCmpErrors2 Interfaces\nLibrary Identification\nLibrary Properties\nCmpEventMgr\nLibrary Identification\nLibrary Properties\nCmpLog\nLibrary Identification\nLibrary Properties\nCmpSettings\nLibrary Identification\nLibrary Properties\nComponent Manager\nLibrary Identification\nLibrary Properties\nIoStandard\nLibrary Identification\nLibrary Properties\nStandard\nLibrary Identification\nLibrary Properties\nSysMem\nLibrary Identification\nLibrary Properties\nSysTarget\nLibrary Identification\nLibrary Properties\nSysTask\nLibrary Identification\nLibrary Properties\nSysTypes2 Interfaces\nLibrary Identification\nLibrary Properties\nCmpBACnet\nDocs\n»\nBACnetClientAPI\n»\nadvanced\n»\nBACnetBackupBACnetDevice (FUN)\nBACnetBackupBACnetDevice (FUN)\nÂ¶\nFUNCTION BACnetBackupBACnetDevice :\nIEC_BACNET_STATUS\nFunction initiates a backup for an BACnet device.\nThis function will start an backup procedure for the specified device.\nInOut:\nScope\nName\nType\nComment\nReturn\nBACnetBackupBACnetDevice\nIEC_BACNET_STATUS\nInput\npInfo\nPOINTER TO\nIEC_BACNET_BACKUPRESTORE_INFO\nPointer to information which specifies which device should be backuped and\nwhere the file object data should be stored to be backuped.\npICallback\nCmpEventMgr.ICmpEventCallback\nA pointer to the event-callback interface to inform about failures\nand progress information during the procedure execution.\npAPDUParams\nPOINTER TO\nIEC_BACNET_APDU_PROPERTIES\nA pointer to the APDU-Properties structure which sets APDU properties for this\ntransaction only. This does not change global defaults or settings for the application\nAPDU Properties. This argument may be NULL. In this case APDU properties  are used\nwhich were specified in the device object properties of the applications device which\nsends the request.\nphTransaction\nPOINTER TO BYTE\nThe handle which identifies the transaction handled by the user application. The\ngiven handle has to be unique, in case the application needs to separate multiple\npending requests. This handle is transparent for the BACnet API and is returned\nunchanged to the user application in the completion routine callback. This handle may\nbe NULL, but the user application will be unable to cancel pending requests by a call\nto\nBACnetCancelPendingConfirmedRequest\nor to separate them in the callback if multiple\ncompletions are pending in such case.\ntop\nCODESYS Group | We\nsoftware\nAutomation.\nto software\n['sɒftwɛər]\ntransitive verb\n__softwared/softwaring\n: to develop software\n// to software automation: to develop software for automation purposes\nThe CODESYS Group is the manufacturer of CODESYS, the leading hardware-independent\n                                    IEC 61131-3 automation software for developing and engineering controller\n                                    applications.\nCODESYS® is a registered trademark.\nCODESYS GmbH\nA member of the CODESYS Group\nMemminger Straße 151, 87439 Kempten\nGermany\nTel.:\n+49-831-54031-0\ninfo@codesys.com\nLegal Notice\nPrivacy Policy\nLinkedIn\nYoutube\nRSS\nDownloads\nLogin\nCODESYS Store\n© 2022 CODESYS GmbH\n| A member of the CODESYS Group",
  "tables": [
    {
      "headers": [
        "Scope",
        "Name",
        "Type",
        "Comment"
      ],
      "rows": [
        {
          "Scope": "Return",
          "Name": "BACnetBackupBACnetDevice",
          "Type": "IEC_BACNET_STATUS",
          "Comment": ""
        },
        {
          "Scope": "Input",
          "Name": "pInfo",
          "Type": "POINTER TOIEC_BACNET_BACKUPRESTORE_INFO",
          "Comment": "Pointer to information which specifies which device should be backuped and\nwhere the file object data should be stored to be backuped."
        },
        [
          "pICallback",
          "CmpEventMgr.ICmpEventCallback",
          "A pointer to the event-callback interface to inform about failures\nand progress information during the procedure execution."
        ],
        [
          "pAPDUParams",
          "POINTER TOIEC_BACNET_APDU_PROPERTIES",
          "A pointer to the APDU-Properties structure which sets APDU properties for this\ntransaction only. This does not change global defaults or settings for the application\nAPDU Properties. This argument may be NULL. In this case APDU properties  are used\nwhich were specified in the device object properties of the applications device which\nsends the request."
        ],
        [
          "phTransaction",
          "POINTER TO BYTE",
          "The handle which identifies the transaction handled by the user application. The\ngiven handle has to be unique, in case the application needs to separate multiple\npending requests. This handle is transparent for the BACnet API and is returned\nunchanged to the user application in the completion routine callback. This handle may\nbe NULL, but the user application will be unable to cancel pending requests by a call\ntoBACnetCancelPendingConfirmedRequestor to separate them in the callback if multiple\ncompletions are pending in such case."
        ]
      ]
    }
  ]
}