{
  "library": "CmpBACnet",
  "title": "BACnetAddListElement (Function)",
  "url": "https://content.helpme-codesys.com/en/libs/CmpBACnet/Current/BACnetClientAPI/BACnetAddListElement.html",
  "page_title": "BACnetAddListElement (FUN)",
  "text": "Deutsch\nEnglish\nFrançais\nEspañol\nItaliano\nРусский\n日本語\n中文\nMenu\nSearch\nDeutsch\nEnglish\nFrançais\nEspañol\nItaliano\nРусский\n日本語\n中文\nBACnetAsyncTransactionToken (Struct)\nBACnetClientAPI\nBACnetAcknowledgeAlarm (Function)\nBACnetAddListElement (Function)\nBACnetCancelPendingConfirmedRequest (Function)\nBACnetConfPrivateTransfer (Function)\nBACnetConfTextMessage (Function)\nBACnetCreateObject (Function)\nBACnetCreateObjectResult (Struct)\nBACnetDeleteObject (Function)\nBACnetDeviceCommControl (Function)\nBACnetGetAlarmSummary (Function)\nBACnetGetEnrollmentSummary (Function)\nBACnetGetEventInfo (Function)\nBACnetLifeSafetyOperation (Function)\nBACnetReadAllPropertyDataContents (Function)\nBACnetReadFile (Function)\nBACnetReadProperty (Function)\nBACnetReadPropertyMultiple (Function)\nBACnetReadRange (Function)\nBACnetReinitializeDevice (Function)\nBACnetRemoveListElement (Function)\nBACnetSubscribeCOV (Function)\nBACnetSubscribeCOVProperty (Function)\nBACnetUnconfPrivateTransfer (Function)\nBACnetUnconfTextMessage (Function)\nBACnetWhoHas (Function)\nBACnetWhoIs (Function)\nBACnetWriteFile (Function)\nBACnetWriteGroup (Function)\nBACnetWriteProperty (Function)\nBACnetWritePropertyMultiple (Function)\nadvanced\nBACnetBackupBACnetDevice (Function)\nBACnetCloseClientCustomer (Function)\nBACnetGetClientDeviceCommunication (Function)\nBACnetOpenClientCustomer (Function)\nBACnetRegisterClientCommunicationStateCallback (Function)\nBACnetRegisterClientDataPoint (Function)\nBACnetRegisterClientEventNotification (Function)\nBACnetRegisterClientUnsubscribeCompletionCallback (Function)\nBACnetRestartAllClients (Function)\nBACnetRestoreBACnetDevice (Function)\nBACnetSetClientDeviceCommunication (Function)\nBACnetSetClientDeviceFixAddress (Function)\nBACnetSetClientDeviceFixSubscribeCovTime (Function)\nBACnetSetClientGlobalCommTimingParameters (Function)\nBACnetSetClientGlobalMaxDeviceActions (Function)\nBACnetUnregisterClientDataPoint (Function)\nBACnetUnregisterClientEventNotification (Function)\nFile and Project Information\nLibrary Reference\n3SLicense\nLibrary Identification\nLibrary Properties\nCAA Ressource Manager Extern\nLibrary Identification\nLibrary Properties\nCAA Types Extern\nLibrary Identification\nLibrary Properties\nCmpErrors2 Interfaces\nLibrary Identification\nLibrary Properties\nCmpEventMgr\nLibrary Identification\nLibrary Properties\nCmpLog\nLibrary Identification\nLibrary Properties\nCmpSettings\nLibrary Identification\nLibrary Properties\nComponent Manager\nLibrary Identification\nLibrary Properties\nIoStandard\nLibrary Identification\nLibrary Properties\nStandard\nLibrary Identification\nLibrary Properties\nSysMem\nLibrary Identification\nLibrary Properties\nSysTarget\nLibrary Identification\nLibrary Properties\nSysTask\nLibrary Identification\nLibrary Properties\nSysTypes2 Interfaces\nLibrary Identification\nLibrary Properties\nCmpBACnet\nDocs\n»\nBACnetClientAPI\n»\nBACnetAddListElement (FUN)\nBACnetAddListElement (FUN)\nÂ¶\nFUNCTION BACnetAddListElement :\nIEC_BACNET_STATUS\nSends an Add-List-Element request.\nSends an Add-List-Element request to add one or more list elements to an object\nproperty which is a list. This routine sends Add-List-Element request using address\ninstead of device handle to identify destination device. This routine allows to\ncontrol APDU properties like APDU length and segmentation and timeout for both\nrequest and response. This routine can execute asynchronously, i.e. this routine\nwill return to the caller before the BACnet reply comes so that the application can\nkeep running. In this case the response information will be received by the thread\nwhich is responsible for receiving asynchronous responses. An optional\nBACNET_CHANGE_LIST_COMPLETE_CB routine, which is provided by the BACnet application,\nshall be used to process this information. If a number of asynchronous service\nrequests are sent, the responses shall be queued and identified by the transaction\nhandles. If the application does not supply BACNET_CHANGE_LIST_COMPLETE_CB, then the\nBACnetAddListElement routine sends a request and waits for the reply.\nInOut:\nScope\nName\nType\nComment\nReturn\nBACnetAddListElement\nIEC_BACNET_STATUS\nA status indicating if the operation worked.\nInput\npSourceAddress\nPOINTER TO\nIEC_BACNET_ADDRESS\nIf the BACnet application has only one device constructed and installed, this can\nbe 0. In this case the MAC address of this device will be used. Otherwise this\nshall be the MAC address returned on device object construction.\npDestinationAddress\nPOINTER TO\nIEC_BACNET_ADDRESS\nThis is the MAC address of the device to which the request\nshould be sent.\npAddInfo\nPOINTER TO\nIEC_BACNET_CHANGE_LIST_INFO\nA pointer to the service information data structure. This data structure contains\nthe objectID, ePropertyID, nIndex and a buffer in which the Property Contents\ndatatype list is placed.\npAPDUParams\nPOINTER TO\nIEC_BACNET_APDU_PROPERTIES\nA pointer to the APDU-Properties structure which sets APDU properties for this\ntransaction only. This does not change global defaults or settings for the application\nAPDU Properties. This argument may be NULL. In this case APDU properties  are used\nwhich were specified in the device object properties of the applications device which\nsends the request.\npTransactionToken\nPOINTER TO\nBACnetAsyncTransactionToken\nTransaction token of the asynchronous call - see\nBACnetAsyncTransactionToken\n.\npError\nPOINTER TO\nIEC_BACNET_ERROR\nA pointer to a structure to hold BACnet Error information. pError may be 0 if the\napplication isnât interested in detailed error information.\npFirstFailed\nPOINTER TO\nIEC_BACNET_UNSIGNED\nA pointer to a buffer in which to place the sequence number of the first element\nin the pElements list which cannot be added to the property. pFirstFailed may be\n0.\ntop\nCODESYS Group | We\nsoftware\nAutomation.\nto software\n['sɒftwɛər]\ntransitive verb\n__softwared/softwaring\n: to develop software\n// to software automation: to develop software for automation purposes\nThe CODESYS Group is the manufacturer of CODESYS, the leading hardware-independent\n                                    IEC 61131-3 automation software for developing and engineering controller\n                                    applications.\nCODESYS® is a registered trademark.\nCODESYS GmbH\nA member of the CODESYS Group\nMemminger Straße 151, 87439 Kempten\nGermany\nTel.:\n+49-831-54031-0\ninfo@codesys.com\nLegal Notice\nPrivacy Policy\nLinkedIn\nYoutube\nRSS\nDownloads\nLogin\nCODESYS Store\n© 2022 CODESYS GmbH\n| A member of the CODESYS Group",
  "tables": [
    {
      "headers": [
        "Scope",
        "Name",
        "Type",
        "Comment"
      ],
      "rows": [
        {
          "Scope": "Return",
          "Name": "BACnetAddListElement",
          "Type": "IEC_BACNET_STATUS",
          "Comment": "A status indicating if the operation worked."
        },
        {
          "Scope": "Input",
          "Name": "pSourceAddress",
          "Type": "POINTER TOIEC_BACNET_ADDRESS",
          "Comment": "If the BACnet application has only one device constructed and installed, this can\nbe 0. In this case the MAC address of this device will be used. Otherwise this\nshall be the MAC address returned on device object construction."
        },
        [
          "pDestinationAddress",
          "POINTER TOIEC_BACNET_ADDRESS",
          "This is the MAC address of the device to which the request\nshould be sent."
        ],
        [
          "pAddInfo",
          "POINTER TOIEC_BACNET_CHANGE_LIST_INFO",
          "A pointer to the service information data structure. This data structure contains\nthe objectID, ePropertyID, nIndex and a buffer in which the Property Contents\ndatatype list is placed."
        ],
        [
          "pAPDUParams",
          "POINTER TOIEC_BACNET_APDU_PROPERTIES",
          "A pointer to the APDU-Properties structure which sets APDU properties for this\ntransaction only. This does not change global defaults or settings for the application\nAPDU Properties. This argument may be NULL. In this case APDU properties  are used\nwhich were specified in the device object properties of the applications device which\nsends the request."
        ],
        [
          "pTransactionToken",
          "POINTER TOBACnetAsyncTransactionToken",
          "Transaction token of the asynchronous call - seeBACnetAsyncTransactionToken."
        ],
        [
          "pError",
          "POINTER TOIEC_BACNET_ERROR",
          "A pointer to a structure to hold BACnet Error information. pError may be 0 if the\napplication isnât interested in detailed error information."
        ],
        [
          "pFirstFailed",
          "POINTER TOIEC_BACNET_UNSIGNED",
          "A pointer to a buffer in which to place the sequence number of the first element\nin the pElements list which cannot be added to the property. pFirstFailed may be\n0."
        ]
      ]
    }
  ]
}