{
  "library": "CmpBACnet",
  "title": "BACnetSetClientDeviceFixSubscribeCovTime (Function)",
  "url": "https://content.helpme-codesys.com/en/libs/CmpBACnet/Current/BACnetClientAPI/advanced/BACnetSetClientDeviceFixSubscribeCovTime.html",
  "page_title": "BACnetSetClientDeviceFixSubscribeCovTime (FUN)",
  "text": "Deutsch\nEnglish\nFrançais\nEspañol\nItaliano\nРусский\n日本語\n中文\nMenu\nSearch\nDeutsch\nEnglish\nFrançais\nEspañol\nItaliano\nРусский\n日本語\n中文\nBACnetAsyncTransactionToken (Struct)\nBACnetClientAPI\nBACnetAcknowledgeAlarm (Function)\nBACnetAddListElement (Function)\nBACnetCancelPendingConfirmedRequest (Function)\nBACnetConfPrivateTransfer (Function)\nBACnetConfTextMessage (Function)\nBACnetCreateObject (Function)\nBACnetCreateObjectResult (Struct)\nBACnetDeleteObject (Function)\nBACnetDeviceCommControl (Function)\nBACnetGetAlarmSummary (Function)\nBACnetGetEnrollmentSummary (Function)\nBACnetGetEventInfo (Function)\nBACnetLifeSafetyOperation (Function)\nBACnetReadAllPropertyDataContents (Function)\nBACnetReadFile (Function)\nBACnetReadProperty (Function)\nBACnetReadPropertyMultiple (Function)\nBACnetReadRange (Function)\nBACnetReinitializeDevice (Function)\nBACnetRemoveListElement (Function)\nBACnetSubscribeCOV (Function)\nBACnetSubscribeCOVProperty (Function)\nBACnetUnconfPrivateTransfer (Function)\nBACnetUnconfTextMessage (Function)\nBACnetWhoHas (Function)\nBACnetWhoIs (Function)\nBACnetWriteFile (Function)\nBACnetWriteGroup (Function)\nBACnetWriteProperty (Function)\nBACnetWritePropertyMultiple (Function)\nadvanced\nBACnetBackupBACnetDevice (Function)\nBACnetCloseClientCustomer (Function)\nBACnetGetClientDeviceCommunication (Function)\nBACnetOpenClientCustomer (Function)\nBACnetRegisterClientCommunicationStateCallback (Function)\nBACnetRegisterClientDataPoint (Function)\nBACnetRegisterClientEventNotification (Function)\nBACnetRegisterClientUnsubscribeCompletionCallback (Function)\nBACnetRestartAllClients (Function)\nBACnetRestoreBACnetDevice (Function)\nBACnetSetClientDeviceCommunication (Function)\nBACnetSetClientDeviceFixAddress (Function)\nBACnetSetClientDeviceFixSubscribeCovTime (Function)\nBACnetSetClientGlobalCommTimingParameters (Function)\nBACnetSetClientGlobalMaxDeviceActions (Function)\nBACnetUnregisterClientDataPoint (Function)\nBACnetUnregisterClientEventNotification (Function)\nFile and Project Information\nLibrary Reference\n3SLicense\nLibrary Identification\nLibrary Properties\nCAA Ressource Manager Extern\nLibrary Identification\nLibrary Properties\nCAA Types Extern\nLibrary Identification\nLibrary Properties\nCmpErrors2 Interfaces\nLibrary Identification\nLibrary Properties\nCmpEventMgr\nLibrary Identification\nLibrary Properties\nCmpLog\nLibrary Identification\nLibrary Properties\nCmpSettings\nLibrary Identification\nLibrary Properties\nComponent Manager\nLibrary Identification\nLibrary Properties\nIoStandard\nLibrary Identification\nLibrary Properties\nStandard\nLibrary Identification\nLibrary Properties\nSysMem\nLibrary Identification\nLibrary Properties\nSysTarget\nLibrary Identification\nLibrary Properties\nSysTask\nLibrary Identification\nLibrary Properties\nSysTypes2 Interfaces\nLibrary Identification\nLibrary Properties\nCmpBACnet\nDocs\n»\nBACnetClientAPI\n»\nadvanced\n»\nBACnetSetClientDeviceFixSubscribeCovTime (FUN)\nBACnetSetClientDeviceFixSubscribeCovTime (FUN)\nÂ¶\nFUNCTION BACnetSetClientDeviceFixSubscribeCovTime :\nIEC_BACNET_STATUS\nFunction sets or deletes an fix daily timepoint for sending resubscribes instead of using an configured intervall.\nThis Function sets or deletes an fix daily timepoint for sending resubscribes instead of using an\nconfigured intervall. Main use of this function is to be able to separate resubscribe attempts\nfor devices so that the will not be sent at the same time as this would happen if using the same\nintervall for many registered objects in different devices which could put heavy traffinc on the\nnetwork.\nInOut:\nScope\nName\nType\nComment\nReturn\nBACnetSetClientDeviceFixSubscribeCovTime\nIEC_BACNET_STATUS\nInput\ndevId\nIEC_BACNET_INST_NUMBER\nThe device instance number for which an fixed timepoint for\nsending COV/COVP resubscribe requests shall be set or\ndeleted.\npSubscribeTime\nPOINTER TO\nIEC_BACNET_TIME\nA pointer to an BACnet time structure containing the timepoint for fixed sending of the\nCOV/COVP resubscribe requests. A NULL pointer removes the fix timepoint and reverts using\ngiven intervalls configured with function\nBACnetRegisterClientDataPoint\n.\ntop\nCODESYS Group | We\nsoftware\nAutomation.\nto software\n['sɒftwɛər]\ntransitive verb\n__softwared/softwaring\n: to develop software\n// to software automation: to develop software for automation purposes\nThe CODESYS Group is the manufacturer of CODESYS, the leading hardware-independent\n                                    IEC 61131-3 automation software for developing and engineering controller\n                                    applications.\nCODESYS® is a registered trademark.\nCODESYS GmbH\nA member of the CODESYS Group\nMemminger Straße 151, 87439 Kempten\nGermany\nTel.:\n+49-831-54031-0\ninfo@codesys.com\nLegal Notice\nPrivacy Policy\nLinkedIn\nYoutube\nRSS\nDownloads\nLogin\nCODESYS Store\n© 2022 CODESYS GmbH\n| A member of the CODESYS Group",
  "tables": [
    {
      "headers": [
        "Scope",
        "Name",
        "Type",
        "Comment"
      ],
      "rows": [
        {
          "Scope": "Return",
          "Name": "BACnetSetClientDeviceFixSubscribeCovTime",
          "Type": "IEC_BACNET_STATUS",
          "Comment": ""
        },
        {
          "Scope": "Input",
          "Name": "devId",
          "Type": "IEC_BACNET_INST_NUMBER",
          "Comment": "The device instance number for which an fixed timepoint for\nsending COV/COVP resubscribe requests shall be set or\ndeleted."
        },
        [
          "pSubscribeTime",
          "POINTER TOIEC_BACNET_TIME",
          "A pointer to an BACnet time structure containing the timepoint for fixed sending of the\nCOV/COVP resubscribe requests. A NULL pointer removes the fix timepoint and reverts using\ngiven intervalls configured with functionBACnetRegisterClientDataPoint."
        ]
      ]
    }
  ]
}