{
  "library": "CommFB",
  "title": "ID (Function)",
  "url": "https://content.helpme-codesys.com/en/libs/CommFB/Current/CommFB/DP-Address/ID.html#",
  "page_title": "ID (FUN)",
  "text": "CommFB\nAINFO_TYPE (Union)\nAddressConcept (GVL)\nAddress Concept\nGenerating a CommFB-ID\nProfibus DP\nProfinet IO\nDevice Diagnosis\nAddress Conversion\nAddresses\nADDR_TO_ID (FunctionBlock)\nADDR_TYPE (Union)\nCREATE_ID (FunctionBlock)\nDP_ADDR (Struct)\nDP_DEVICE_ID (Struct)\nID_TO_ADDR (FunctionBlock)\nIO_SYSTEM_TYPE (Enum)\nPN_ADDR (Struct)\nPN_DEVICE_ID (Struct)\nSUBSLOT_ID (Function)\nCNCT (FunctionBlock)\nConstants (GVL)\nDP Address\nADDR (Function)\nID (Function)\nSLOT_ID (Function)\nDP_AINFO (Struct)\nDP_DIAG (Struct)\nErrorCode (Enum)\nErrorCode1_RW (Enum)\nFieldDevice\nPRVREC (FunctionBlock)\nPRVREC_MODE (Enum)\nRCVREC (FunctionBlock)\nRCVREC_MODE (Enum)\nSALARM (FunctionBlock)\nGETIO_PART (FunctionBlock)\nPN_AINFO (Struct)\nRALARM (FunctionBlock)\nRALARM_MODE (Enum)\nRDIAG (FunctionBlock)\nRDREC (FunctionBlock)\nSETIO_PART (FunctionBlock)\nWRREC (FunctionBlock)\nImages\nLibrary Information\nGetLibVersion (Function)\nGetLibVersionNumber (Function)\nIsLibReleased (Function)\nFile and Project Information\nLibrary Reference\nIoDriver Profibus2 Interfaces\nLibrary Identification\nLibrary Properties\nSysMem\nLibrary Identification\nLibrary Properties\nCommFB\nDocs\n»\nCommFB\n»\nDP\nAddress\n»\nID (FUN)\nID (FUN)\nÂ¶\nFUNCTION ID : DWORD\nThis function converts the physical identification of a slot or a DP-slave to a handle which can be used with Communication Function Blocks.\nInOut:\nScope\nName\nType\nInitial\nComment\nReturn\nID\nDWORD\nInput\nEN\nBOOL\nTRUE\nMASTER\nBYTE\nID of the DP system\nSEGMENT\nBYTE\nNumber of the DP segment\nSTATION\nBYTE\nNumber of the DP-slave(station address)\nSLOT\nBYTE\nSlot number",
  "tables": [
    {
      "headers": [
        "Scope",
        "Name",
        "Type",
        "Initial",
        "Comment"
      ],
      "rows": [
        {
          "Scope": "Return",
          "Name": "ID",
          "Type": "DWORD",
          "Initial": "",
          "Comment": ""
        },
        {
          "Scope": "Input",
          "Name": "EN",
          "Type": "BOOL",
          "Initial": "TRUE",
          "Comment": ""
        },
        [
          "MASTER",
          "BYTE",
          "",
          "ID of the DP system"
        ],
        [
          "SEGMENT",
          "BYTE",
          "",
          "Number of the DP segment"
        ],
        [
          "STATION",
          "BYTE",
          "",
          "Number of the DP-slave(station address)"
        ],
        [
          "SLOT",
          "BYTE",
          "",
          "Slot number"
        ]
      ]
    }
  ]
}