{
  "library": "CommFB",
  "title": "WRREC (FunctionBlock)",
  "url": "https://content.helpme-codesys.com/en/libs/CommFB/Current/CommFB/WRREC.html",
  "page_title": "WRREC (FB)",
  "text": "CommFB\nAINFO_TYPE (Union)\nAddressConcept (GVL)\nAddress Concept\nGenerating a CommFB-ID\nProfibus DP\nProfinet IO\nDevice Diagnosis\nAddress Conversion\nAddresses\nADDR_TO_ID (FunctionBlock)\nADDR_TYPE (Union)\nCREATE_ID (FunctionBlock)\nDP_ADDR (Struct)\nDP_DEVICE_ID (Struct)\nID_TO_ADDR (FunctionBlock)\nIO_SYSTEM_TYPE (Enum)\nPN_ADDR (Struct)\nPN_DEVICE_ID (Struct)\nSUBSLOT_ID (Function)\nCNCT (FunctionBlock)\nConstants (GVL)\nDP Address\nADDR (Function)\nID (Function)\nSLOT_ID (Function)\nDP_AINFO (Struct)\nDP_DIAG (Struct)\nErrorCode (Enum)\nErrorCode1_RW (Enum)\nFieldDevice\nPRVREC (FunctionBlock)\nPRVREC_MODE (Enum)\nRCVREC (FunctionBlock)\nRCVREC_MODE (Enum)\nSALARM (FunctionBlock)\nGETIO_PART (FunctionBlock)\nPN_AINFO (Struct)\nRALARM (FunctionBlock)\nRALARM_MODE (Enum)\nRDIAG (FunctionBlock)\nRDREC (FunctionBlock)\nSETIO_PART (FunctionBlock)\nWRREC (FunctionBlock)\nImages\nLibrary Information\nGetLibVersion (Function)\nGetLibVersionNumber (Function)\nIsLibReleased (Function)\nFile and Project Information\nLibrary Reference\nIoDriver Profibus2 Interfaces\nLibrary Identification\nLibrary Properties\nSysMem\nLibrary Identification\nLibrary Properties\nCommFB\nDocs\n»\nCommFB\n»\nWRREC (FB)\nWRREC (FB)\nÂ¶\nFUNCTION_BLOCK WRREC\nWrite Data Record (WRREC)\nThis function block executes an acyclic write of user or system record-data.\nThe ID parameter identifies the slot or subslot of the Field Device the process data record is written to.\nThe INDEX input of the WRREC function block contains an integer which identifies the data record to be written.\nThe data record shall be stored in the variable given at the RECORD parameter.\nThe LEN input contains the length of the data record to be written in byte.\nThe variable given as RECORD parameter shall be at least of LEN byte.\nThe values of the RECORD and LEN parameters shall not be changed as long as the BUSY output is true.\nIf the data record is written successfully, the DONE output indicates that the read data record is written to the Field Device.\nIf an error occurred, the ERROR output indicates an error and the STATUS output contains the error code.\nInOut:\nScope\nName\nType\nComment\nInput\nREQ\nBOOL\nRequest\nID\nDWORD\nIdentifier of a slot / subslot of a Field Device (see:\nAddressConcept\n)\nINDEX\nINT\nIndex of the data record\nLEN\nINT\nLength of the data record\nRECORD\nPOINTER TO BYTE\nData record\nOutput\nDONE\nBOOL\nData record written\nBUSY\nBOOL\nFB is busy\nERROR\nBOOL\nError detected\nSTATUS\nDWORD\nLast detected status",
  "tables": [
    {
      "headers": [
        "Scope",
        "Name",
        "Type",
        "Comment"
      ],
      "rows": [
        {
          "Scope": "Input",
          "Name": "REQ",
          "Type": "BOOL",
          "Comment": "Request"
        },
        [
          "ID",
          "DWORD",
          "Identifier of a slot / subslot of a Field Device (see:AddressConcept)"
        ],
        [
          "INDEX",
          "INT",
          "Index of the data record"
        ],
        [
          "LEN",
          "INT",
          "Length of the data record"
        ],
        [
          "RECORD",
          "POINTER TO BYTE",
          "Data record"
        ],
        {
          "Scope": "Output",
          "Name": "DONE",
          "Type": "BOOL",
          "Comment": "Data record written"
        },
        [
          "BUSY",
          "BOOL",
          "FB is busy"
        ],
        [
          "ERROR",
          "BOOL",
          "Error detected"
        ],
        [
          "STATUS",
          "DWORD",
          "Last detected status"
        ]
      ]
    }
  ]
}