{
  "library": "DNP3",
  "title": "BinaryInput (FunctionBlock)",
  "url": "https://content.helpme-codesys.com/en/libs/DNP3/Current/DNP3/Function-Blocks/Outstation/Points/BinaryInput.html",
  "page_title": "BinaryInput (FB)",
  "text": "DNP3\nDoc\nIntegration of datapoints into the application\nExample\nIntroduction\nCODESYS DNP3 - Components\nOutstation data model and datapoints\nOutstation datapoint - inputs versa configuration\nOutstation datapoint inputs / outputs of type AnyNumber\nOutstation data flow\nMaster functionality\nMaster data flow\nCalling function block instances\nApplication bringup and debugging\nEnums\nCommandRejectReason (Enum)\nDoubleBitState (Enum)\nError (Enum)\nFunction Blocks\nAnyNumberConverter\nAnyNumberToDINT (FunctionBlock)\nAnyNumberToINT (FunctionBlock)\nAnyNumberToLREAL (FunctionBlock)\nAnyNumberToREAL (FunctionBlock)\nAnyNumberToSINT (FunctionBlock)\nAnyNumberToUDINT (FunctionBlock)\nAnyNumberToUINT (FunctionBlock)\nAnyNumberToUSINT (FunctionBlock)\nDINTToAnyNumber (FunctionBlock)\nINTToAnyNumber (FunctionBlock)\nLREALToAnyNumber (FunctionBlock)\nREALToAnyNumber (FunctionBlock)\nSINTToAnyNumber (FunctionBlock)\nUDINTToAnyNumber (FunctionBlock)\nUINTToAnyNumber (FunctionBlock)\nUSINTToAnyNumber (FunctionBlock)\nETHdeviceHelper (FunctionBlock)\nMaster\nAddressQualifier (Enum)\nAnalogInfo (Struct)\nAutoUpdateMode (Enum)\nCROB_Info (Struct)\nCommands\nFreezeTimeDateField (Enum)\nFunctionCode (Enum)\nMaster (FunctionBlock)\nMasterConfiguration (FunctionBlock)\nMasterConfigurationCOM (FunctionBlock)\nMasterConfigurationIP (FunctionBlock)\nMasterLoggingOptions (Enum)\nPointObserver\nTimeSyncType (Enum)\nOutstation\nDNP3OutstationSessionConfigEvents (Struct)\nDNP3OutstationSessionConfigUnsolicitedResponse (Struct)\nEvents\nGroups\nOutstation (FunctionBlock)\nOutstationConfiguration (FunctionBlock)\nOutstationConfigurationCOM (FunctionBlock)\nOutstationConfigurationIP (FunctionBlock)\nOutstationDataModel (FunctionBlock)\nOutstationDataModelExample (FunctionBlock)\nOutstationLoggingOptions (Enum)\nPoints\nFunctions\nAnyNumber\nAnyNumberArithmetic (Function)\nAnyNumberArithmeticOperation (Enum)\nAnyNumberAssign (Function)\nAnyNumberAssignIfNotEqual (Function)\nAnyNumberCheck (Function)\nAnyNumberClipToLimits (Function)\nAnyNumberCompare (Function)\nAnyNumberCompareOperation (Enum)\nAnyNumberConvertFromDINT (Function)\nAnyNumberConvertFromINT (Function)\nAnyNumberConvertFromLREAL (Function)\nAnyNumberConvertFromREAL (Function)\nAnyNumberConvertFromSINT (Function)\nAnyNumberConvertFromUDINT (Function)\nAnyNumberConvertFromUINT (Function)\nAnyNumberConvertFromUSINT (Function)\nAnyNumberConvertToDINT (Function)\nAnyNumberConvertToINT (Function)\nAnyNumberConvertToLREAL (Function)\nAnyNumberConvertToREAL (Function)\nAnyNumberConvertToSINT (Function)\nAnyNumberConvertToUDINT (Function)\nAnyNumberConvertToUINT (Function)\nAnyNumberConvertToUSINT (Function)\nAnyNumberInitToZero (Function)\nAnyNumberIsWithinLimits (Function)\nAnyNumberMaximum (Function)\nAnyNumberMinimum (Function)\nAnyNumberToString (Function)\nAnyNumberTypeEquals (Function)\nAnyNumberTypeToString (Function)\nAnyNumberValueToString (Function)\nAnyNumberZero (Function)\nGetCurrentDateTime (Function)\nGlobalConstants\nConstants (GVL)\nConstantsInternal (GVL)\nInterfaces\nIPoint (Interface)\nGetDescriptionString (Method)\nIdentificationToString (Method)\nPointNum (Property)\nPointTyp (Property)\nToString (Method)\nIPointObserver (Interface)\nEnabled (Property)\nEquals (Method)\nGetError (Method)\nGetErrorId (Method)\nGetSequenceNumber (Method)\nIsModified (Property)\nKey (Property)\nNum (Property)\nToString (Method)\nTyp (Property)\nParameter\nParameter (ParamList)\nTypes\nAnyNumber\nAnyNumber (Struct)\nAnyNumberPointerUnion (Union)\nAnyNumberType (Enum)\nAnyNumberUnion (Union)\nAnyNumberValueUnion (Union)\nCOMParity (Enum)\nCOMStopBits (Enum)\nDNP3_String (Alias)\nLibrary Information\nGetLibVersion (Function)\nGetLibVersionNumber (Function)\nIsLibReleased (Function)\nFile and Project Information\nLibrary Reference\n3SLicense\nLibrary Identification\nLibrary Properties\nCmpApp\nLibrary Identification\nLibrary Properties\nCmpDNP3\nLibrary Identification\nLibrary Properties\nCmpErrors2 Interfaces\nLibrary Identification\nLibrary Properties\nCmpEventMgr\nLibrary Identification\nLibrary Properties\nCmpLog\nLibrary Identification\nLibrary Properties\nComponent Manager\nLibrary Identification\nLibrary Properties\nIoDrvEthernet Interfaces\nLibrary Identification\nLibrary Properties\nIoDrvUtility\nLibrary Identification\nLibrary Properties\nIoStandard\nLibrary Identification\nLibrary Properties\nStandard\nLibrary Identification\nLibrary Properties\nSysCpuHandling\nLibrary Identification\nLibrary Properties\nSysMem\nLibrary Identification\nLibrary Properties\nSysSocket\nLibrary Identification\nLibrary Properties\nSysTask\nLibrary Identification\nLibrary Properties\nSysTimeCore\nLibrary Identification\nLibrary Properties\nSysTimeRtc\nLibrary Identification\nLibrary Properties\nSysTypes2 Interfaces\nLibrary Identification\nLibrary Properties\nUtil\nLibrary Identification\nLibrary Properties\nLibrary Parameter\nDNP3\nDocs\n»\nDNP3\n»\nFunction\nBlocks\n»\nOutstation\n»\nPoints\n»\nBinaryInput (FB)\nBinaryInput (FB)\nÂ¶\nFUNCTION_BLOCK FINAL BinaryInput EXTENDS\nPointWithFlags\nDNP3 datapoint of type Binary Input.\nAn instance of BinaryInput does represent an instance of a datapoint of DNP3 object group 1 âbinary inputsâ.\nInOut:\nScope\nName\nType\nInitial\nComment\nInherited from\nInput\nDescription\nSTRING\nDescription of the datapoint - this is a configuration,\nchanges are ignored after Outstation was enabled.\nPoint\nNumber\nDINT\n-1\nPoint number - this is a configuration, changes are ignored after Outstation was enabled..\nThe point number can be configured if needed to either:\nstart with Point number > 0\nhave gaps in Point numbers\nIf set to -1 (the default) the OutstationDataModel (more precisely the related âGroupâ) takes care to set the Point number internally:\nstarting at 0, if first Point number is not set explicitly.\nincrement by 1\nIn case you set Point number explicitly please keep it consistent:\nPoint numbers need to be >= 0\nPoint numbers need to be ascending\nPoint\nEventClass\nUSINT\nConstants.TMWDEFS_CLASS_MASK_ONE\nThe initial event class - this is a configuration, changes are ignored after Outstation was enabled.\nOperational event class may be changed by a master.\nPoint\nEventMode\nPointEventMode\nPointEventMode.EVENT_MODE_SOE\nThe event mode - this is a configuration, changes are ignored after Outstation was enabled.\nOnly used if the sampling rate is set within the outstation configuration.\nPoint\ntScanPeriod\nTIME\nTIME#0ms\nScan period for datapoint.\nIf tScanPeriod is set to T#0MS, the Group related tScanPeriod or the OutstationDataModel.tScanPeriod is used.\nPoint\nudiLogOptions\nUDINT\nOutstationLoggingOptions.None\nLoggingOptions can be combined using OR.\nPoint\nOutput\nxError\nBOOL\nAn error occured.\nPoint\neErrorID\nError\nThe specific error.\nPoint\nInput\nflags\nBYTE\nConstants.DNPDEFS_DBAS_FLAG_ON_LINE\nFlags used by the point. Can be changed in case a point goes offline or any other error.\nIf set to 0, the variation without flags will be used by DNP3\nPointWithFlags\nEventWithTimeStamp\nBOOL\nTRUE\nEnable / disable if events will be send with / without\ntimestamp - this is a configuration, changes are ignored\nafter Outstation was enabled.\npValue\nPOINTER TO BOOL\nPointer to the current value to use.\nProperties:\nPointNum\n, inherited from\nPoint\nPointTyp\n, inherited from\nPoint\nMethods:\nGetDescriptionString\n, inherited from\nPoint\nIdentificationToString\n, inherited from\nPoint\nToString\n, inherited from\nPointWithFlags",
  "tables": [
    {
      "headers": [
        "Scope",
        "Name",
        "Type",
        "Initial",
        "Comment",
        "Inherited from"
      ],
      "rows": [
        {
          "Scope": "Input",
          "Name": "Description",
          "Type": "STRING",
          "Initial": "",
          "Comment": "Description of the datapoint - this is a configuration,\nchanges are ignored after Outstation was enabled.",
          "Inherited from": "Point"
        },
        [
          "Number",
          "DINT",
          "-1",
          "Point number - this is a configuration, changes are ignored after Outstation was enabled..\nThe point number can be configured if needed to either:start with Point number > 0have gaps in Point numbersIf set to -1 (the default) the OutstationDataModel (more precisely the related âGroupâ) takes care to set the Point number internally:starting at 0, if first Point number is not set explicitly.increment by 1In case you set Point number explicitly please keep it consistent:Point numbers need to be >= 0Point numbers need to be ascending",
          "Point"
        ],
        [
          "EventClass",
          "USINT",
          "Constants.TMWDEFS_CLASS_MASK_ONE",
          "The initial event class - this is a configuration, changes are ignored after Outstation was enabled.\nOperational event class may be changed by a master.",
          "Point"
        ],
        [
          "EventMode",
          "PointEventMode",
          "PointEventMode.EVENT_MODE_SOE",
          "The event mode - this is a configuration, changes are ignored after Outstation was enabled.\nOnly used if the sampling rate is set within the outstation configuration.",
          "Point"
        ],
        [
          "tScanPeriod",
          "TIME",
          "TIME#0ms",
          "Scan period for datapoint.\nIf tScanPeriod is set to T#0MS, the Group related tScanPeriod or the OutstationDataModel.tScanPeriod is used.",
          "Point"
        ],
        [
          "udiLogOptions",
          "UDINT",
          "OutstationLoggingOptions.None",
          "LoggingOptions can be combined using OR.",
          "Point"
        ],
        {
          "Scope": "Output",
          "Name": "xError",
          "Type": "BOOL",
          "Initial": "",
          "Comment": "An error occured.",
          "Inherited from": "Point"
        },
        [
          "eErrorID",
          "Error",
          "",
          "The specific error.",
          "Point"
        ],
        {
          "Scope": "Input",
          "Name": "flags",
          "Type": "BYTE",
          "Initial": "Constants.DNPDEFS_DBAS_FLAG_ON_LINE",
          "Comment": "Flags used by the point. Can be changed in case a point goes offline or any other error.\nIf set to 0, the variation without flags will be used by DNP3",
          "Inherited from": "PointWithFlags"
        },
        [
          "EventWithTimeStamp",
          "BOOL",
          "TRUE",
          "Enable / disable if events will be send with / without\ntimestamp - this is a configuration, changes are ignored\nafter Outstation was enabled.",
          ""
        ],
        [
          "pValue",
          "POINTER TO BOOL",
          "",
          "Pointer to the current value to use.",
          ""
        ]
      ]
    }
  ]
}