{
  "library": "DNP3",
  "title": "SetSessionConfigAspectSizeVarPerPoint (Method)",
  "url": "https://content.helpme-codesys.com/en/libs/DNP3/Current/DNP3/Function-Blocks/Outstation/pou-OutstationConfiguration/SetSessionConfigAspectSizeVarPerPoint.html",
  "page_title": "OutstationConfiguration.SetSessionConfigAspectSizeVarPerPoint (METH)",
  "text": "DNP3\nDoc\nIntegration of datapoints into the application\nExample\nIntroduction\nCODESYS DNP3 - Components\nOutstation data model and datapoints\nOutstation datapoint - inputs versa configuration\nOutstation datapoint inputs / outputs of type AnyNumber\nOutstation data flow\nMaster functionality\nMaster data flow\nCalling function block instances\nApplication bringup and debugging\nEnums\nCommandRejectReason (Enum)\nDoubleBitState (Enum)\nError (Enum)\nFunction Blocks\nAnyNumberConverter\nAnyNumberToDINT (FunctionBlock)\nAnyNumberToINT (FunctionBlock)\nAnyNumberToLREAL (FunctionBlock)\nAnyNumberToREAL (FunctionBlock)\nAnyNumberToSINT (FunctionBlock)\nAnyNumberToUDINT (FunctionBlock)\nAnyNumberToUINT (FunctionBlock)\nAnyNumberToUSINT (FunctionBlock)\nDINTToAnyNumber (FunctionBlock)\nINTToAnyNumber (FunctionBlock)\nLREALToAnyNumber (FunctionBlock)\nREALToAnyNumber (FunctionBlock)\nSINTToAnyNumber (FunctionBlock)\nUDINTToAnyNumber (FunctionBlock)\nUINTToAnyNumber (FunctionBlock)\nUSINTToAnyNumber (FunctionBlock)\nETHdeviceHelper (FunctionBlock)\nMaster\nAddressQualifier (Enum)\nAnalogInfo (Struct)\nAutoUpdateMode (Enum)\nCROB_Info (Struct)\nCommands\nFreezeTimeDateField (Enum)\nFunctionCode (Enum)\nMaster (FunctionBlock)\nMasterConfiguration (FunctionBlock)\nMasterConfigurationCOM (FunctionBlock)\nMasterConfigurationIP (FunctionBlock)\nMasterLoggingOptions (Enum)\nPointObserver\nTimeSyncType (Enum)\nOutstation\nDNP3OutstationSessionConfigEvents (Struct)\nDNP3OutstationSessionConfigUnsolicitedResponse (Struct)\nEvents\nGroups\nOutstation (FunctionBlock)\nOutstationConfiguration (FunctionBlock)\nOutstationConfigurationCOM (FunctionBlock)\nOutstationConfigurationIP (FunctionBlock)\nOutstationDataModel (FunctionBlock)\nOutstationDataModelExample (FunctionBlock)\nOutstationLoggingOptions (Enum)\nPoints\nFunctions\nAnyNumber\nAnyNumberArithmetic (Function)\nAnyNumberArithmeticOperation (Enum)\nAnyNumberAssign (Function)\nAnyNumberAssignIfNotEqual (Function)\nAnyNumberCheck (Function)\nAnyNumberClipToLimits (Function)\nAnyNumberCompare (Function)\nAnyNumberCompareOperation (Enum)\nAnyNumberConvertFromDINT (Function)\nAnyNumberConvertFromINT (Function)\nAnyNumberConvertFromLREAL (Function)\nAnyNumberConvertFromREAL (Function)\nAnyNumberConvertFromSINT (Function)\nAnyNumberConvertFromUDINT (Function)\nAnyNumberConvertFromUINT (Function)\nAnyNumberConvertFromUSINT (Function)\nAnyNumberConvertToDINT (Function)\nAnyNumberConvertToINT (Function)\nAnyNumberConvertToLREAL (Function)\nAnyNumberConvertToREAL (Function)\nAnyNumberConvertToSINT (Function)\nAnyNumberConvertToUDINT (Function)\nAnyNumberConvertToUINT (Function)\nAnyNumberConvertToUSINT (Function)\nAnyNumberInitToZero (Function)\nAnyNumberIsWithinLimits (Function)\nAnyNumberMaximum (Function)\nAnyNumberMinimum (Function)\nAnyNumberToString (Function)\nAnyNumberTypeEquals (Function)\nAnyNumberTypeToString (Function)\nAnyNumberValueToString (Function)\nAnyNumberZero (Function)\nGetCurrentDateTime (Function)\nGlobalConstants\nConstants (GVL)\nConstantsInternal (GVL)\nInterfaces\nIPoint (Interface)\nGetDescriptionString (Method)\nIdentificationToString (Method)\nPointNum (Property)\nPointTyp (Property)\nToString (Method)\nIPointObserver (Interface)\nEnabled (Property)\nEquals (Method)\nGetError (Method)\nGetErrorId (Method)\nGetSequenceNumber (Method)\nIsModified (Property)\nKey (Property)\nNum (Property)\nToString (Method)\nTyp (Property)\nParameter\nParameter (ParamList)\nTypes\nAnyNumber\nAnyNumber (Struct)\nAnyNumberPointerUnion (Union)\nAnyNumberType (Enum)\nAnyNumberUnion (Union)\nAnyNumberValueUnion (Union)\nCOMParity (Enum)\nCOMStopBits (Enum)\nDNP3_String (Alias)\nLibrary Information\nGetLibVersion (Function)\nGetLibVersionNumber (Function)\nIsLibReleased (Function)\nFile and Project Information\nLibrary Reference\n3SLicense\nLibrary Identification\nLibrary Properties\nCmpApp\nLibrary Identification\nLibrary Properties\nCmpDNP3\nLibrary Identification\nLibrary Properties\nCmpErrors2 Interfaces\nLibrary Identification\nLibrary Properties\nCmpEventMgr\nLibrary Identification\nLibrary Properties\nCmpLog\nLibrary Identification\nLibrary Properties\nComponent Manager\nLibrary Identification\nLibrary Properties\nIoDrvEthernet Interfaces\nLibrary Identification\nLibrary Properties\nIoDrvUtility\nLibrary Identification\nLibrary Properties\nIoStandard\nLibrary Identification\nLibrary Properties\nStandard\nLibrary Identification\nLibrary Properties\nSysCpuHandling\nLibrary Identification\nLibrary Properties\nSysMem\nLibrary Identification\nLibrary Properties\nSysSocket\nLibrary Identification\nLibrary Properties\nSysTask\nLibrary Identification\nLibrary Properties\nSysTimeCore\nLibrary Identification\nLibrary Properties\nSysTimeRtc\nLibrary Identification\nLibrary Properties\nSysTypes2 Interfaces\nLibrary Identification\nLibrary Properties\nUtil\nLibrary Identification\nLibrary Properties\nLibrary Parameter\nDNP3\nDocs\n»\nDNP3\n»\nFunction\nBlocks\n»\nOutstation\n»\nOutstationConfiguration\n(FB)\n»\nOutstationConfiguration.SetSessionConfigAspectSizeVarPerPoint (METH)\nOutstationConfiguration.SetSessionConfigAspectSizeVarPerPoint (METH)\nÂ¶\nMETHOD SetSessionConfigAspectSizeVarPerPoint :\nError\nSet optional outstation session configuration aspect - restart delay.\nInOut:\nScope\nName\nType\nInitial\nComment\nReturn\nSetSessionConfigAspectSizeVarPerPoint\nError\nInput\ncounterSizeVarPerPoint\nBOOL\nFALSE\nIf this is TRUE allow per point specification of precision of counter\nand frozen counter points and events.\nThis allows the database to indicate a point value should be sent as a\n16 or 32 bit variation even when read as the other variation as allowed in\nthe new 1815-202x.\nFor example a read from the master of variation 1 32-bit could now result\nin the response using variation 2 to indicate only 16 bit counter precision\n(or the reverse) is to be used for that point. This functionality is an\nextension to the ability to specify per point variation when variation zero\nis requested from the master using the same database interface functionality.\nobj20DefaultVariation, obj21DefaultVariation, obj22DefaultVariation, and/or\nobj23DefaultVariation must each also be set to zero to enable this for running\ncounter, frozen counter and associated event groups.\nanalogInSizeVarPerPoint\nBOOL\nFALSE\nIf this is TRUE allow per point specification of precision of analog\nand frozen analog input points and events.\nThis allows the database to indicate a point value should be sent as a 16 or\n32 bit variation even when read as the other variation as allowed in the\nnew 1815-202x.\nFor example a read from the master of variation 1 32-bit could now result\nin the response using variation 2 to indicate 16 bit analog precision\n(or the reverse) is to be used for that point. This also applies to the\nvariations for Single and Double precision if supported. This functionality\nis an extension to the ability to specify per point variation when variation\nzero is requested from the master using the same database interface functionality.\nobj30DefaultVariation, obj31DefaultVariation, obj32DefaultVariation, and/or\nobj33DefaultVariation must each also be set to zero to enable this for\nanalog input, frozen analog input and associated event groups.\nanalogOutSizeVarPerPoint\nBOOL\nFALSE\nIf this is TRUE allow per point specification of precision of\nanalog output points and events.\nThis allows the database to indicate a point value should be sent as a 16\nor 32 bit variation even when read as the other variation as allowed in\nthe new 1815-202x.\nFor example a read from the master of variation 1 32-bit could now result\nin the response using variation 2 to indicate 16 bit analog precision\n(or the reverse) is to be used for that point. This also applies to the\nvariations for Single and Double precision if supported. This functionality\nis an extension to the ability to specify per point variation when variation\nzero is requested from the master using the same database interface functionality.\nobj40DefaultVariation, obj42DefaultVariation, and/or obj43DefaultVariation must\neach also be set to zero to enable this for analog output status and associated\nevent groups.",
  "tables": [
    {
      "headers": [
        "Scope",
        "Name",
        "Type",
        "Initial",
        "Comment"
      ],
      "rows": [
        {
          "Scope": "Return",
          "Name": "SetSessionConfigAspectSizeVarPerPoint",
          "Type": "Error",
          "Initial": "",
          "Comment": ""
        },
        {
          "Scope": "Input",
          "Name": "counterSizeVarPerPoint",
          "Type": "BOOL",
          "Initial": "FALSE",
          "Comment": "If this is TRUE allow per point specification of precision of counter\nand frozen counter points and events.\nThis allows the database to indicate a point value should be sent as a\n16 or 32 bit variation even when read as the other variation as allowed in\nthe new 1815-202x.\nFor example a read from the master of variation 1 32-bit could now result\nin the response using variation 2 to indicate only 16 bit counter precision\n(or the reverse) is to be used for that point. This functionality is an\nextension to the ability to specify per point variation when variation zero\nis requested from the master using the same database interface functionality.\nobj20DefaultVariation, obj21DefaultVariation, obj22DefaultVariation, and/or\nobj23DefaultVariation must each also be set to zero to enable this for running\ncounter, frozen counter and associated event groups."
        },
        [
          "analogInSizeVarPerPoint",
          "BOOL",
          "FALSE",
          "If this is TRUE allow per point specification of precision of analog\nand frozen analog input points and events.\nThis allows the database to indicate a point value should be sent as a 16 or\n32 bit variation even when read as the other variation as allowed in the\nnew 1815-202x.\nFor example a read from the master of variation 1 32-bit could now result\nin the response using variation 2 to indicate 16 bit analog precision\n(or the reverse) is to be used for that point. This also applies to the\nvariations for Single and Double precision if supported. This functionality\nis an extension to the ability to specify per point variation when variation\nzero is requested from the master using the same database interface functionality.\nobj30DefaultVariation, obj31DefaultVariation, obj32DefaultVariation, and/or\nobj33DefaultVariation must each also be set to zero to enable this for\nanalog input, frozen analog input and associated event groups."
        ],
        [
          "analogOutSizeVarPerPoint",
          "BOOL",
          "FALSE",
          "If this is TRUE allow per point specification of precision of\nanalog output points and events.\nThis allows the database to indicate a point value should be sent as a 16\nor 32 bit variation even when read as the other variation as allowed in\nthe new 1815-202x.\nFor example a read from the master of variation 1 32-bit could now result\nin the response using variation 2 to indicate 16 bit analog precision\n(or the reverse) is to be used for that point. This also applies to the\nvariations for Single and Double precision if supported. This functionality\nis an extension to the ability to specify per point variation when variation\nzero is requested from the master using the same database interface functionality.\nobj40DefaultVariation, obj42DefaultVariation, and/or obj43DefaultVariation must\neach also be set to zero to enable this for analog output status and associated\nevent groups."
        ]
      ]
    }
  ]
}