{
  "library": "MemoryUtils",
  "title": "BitCpy (Function)",
  "url": "https://content.helpme-codesys.com/en/libs/MemoryUtils/Current/MemoryUtils/Functions/BitCpy.html",
  "page_title": "BitCpy (FUN)",
  "text": "Deutsch\nEnglish\nFrançais\nEspañol\nItaliano\nРусский\n日本語\n中文\nMenu\nSearch\nDeutsch\nEnglish\nFrançais\nEspañol\nItaliano\nРусский\n日本語\n中文\nMemoryUtils\nEnums\nByteOrder (Enum)\nERROR (Enum)\nFunctionblocks\nByteBuffer (FunctionBlock)\nAlign2 (Method)\nAlign4 (Method)\nGetByte (Method)\nGetDWord (Method)\nGetDataPointer (Method)\nGetLWord (Method)\nGetNBytes (Method)\nGetNDWords (Method)\nGetNLWords (Method)\nGetNWords (Method)\nGetWord (Method)\nNeedsSwapping (Property)\nPadding (Method)\nPutByte (Method)\nPutDWord (Method)\nPutLWord (Method)\nPutNBytes (Method)\nPutNDWords (Method)\nPutNLWords (Method)\nPutNWords (Method)\nPutWord (Method)\nResetPosition (Method)\nSkip (Method)\nMemoryManager (FunctionBlock)\nPrivate\nPublic\nFunctions\nBitCpy (Function)\nMemCmp (Function)\nMemCpy (Function)\nMemSet (Function)\nSwapping\nMemForceSwap (Function)\nSwap (Function)\nSwapLocalToIntel (Function)\nSwapLocalToMotorola (Function)\nFile and Project Information\nLibrary Reference\nCAA Callback Extern\nLibrary Identification\nLibrary Properties\nCAA Memory Block Manager Extern\nLibrary Identification\nLibrary Properties\nCAA Types Extern\nLibrary Identification\nLibrary Properties\nStandard\nLibrary Identification\nLibrary Properties\nSysCpuHandling\nLibrary Identification\nLibrary Properties\nSysMem\nLibrary Identification\nLibrary Properties\nMemoryUtils\nDocs\n»\nMemoryUtils\n»\nFunctions\n»\nBitCpy (FUN)\nBitCpy (FUN)\nÂ¶\nFUNCTION BitCpy : BOOL\nInOut:\nScope\nName\nType\nComment\nReturn\nBitCpy\nBOOL\nInput\npDest\nPOINTER TO BYTE\nwDstStartBit\nWORD\npSource\nPOINTER TO BYTE\nwSrcStartBit\nWORD\nwSize\nWORD\nSize in bits\ntop\nCODESYS Group | We\nsoftware\nAutomation.\nto software\n['sɒftwɛər]\ntransitive verb\n__softwared/softwaring\n: to develop software\n// to software automation: to develop software for automation purposes\nThe CODESYS Group is the manufacturer of CODESYS, the leading hardware-independent\n                                    IEC 61131-3 automation software for developing and engineering controller\n                                    applications.\nCODESYS® is a registered trademark.\nCODESYS GmbH\nA member of the CODESYS Group\nMemminger Straße 151, 87439 Kempten\nGermany\nTel.:\n+49-831-54031-0\ninfo@codesys.com\nLegal Notice\nPrivacy Policy\nLinkedIn\nYoutube\nRSS\nDownloads\nLogin\nCODESYS Store\n© 2022 CODESYS GmbH\n| A member of the CODESYS Group",
  "tables": [
    {
      "headers": [
        "Scope",
        "Name",
        "Type",
        "Comment"
      ],
      "rows": [
        {
          "Scope": "Return",
          "Name": "BitCpy",
          "Type": "BOOL",
          "Comment": ""
        },
        {
          "Scope": "Input",
          "Name": "pDest",
          "Type": "POINTER TO BYTE",
          "Comment": ""
        },
        [
          "wDstStartBit",
          "WORD",
          ""
        ],
        [
          "pSource",
          "POINTER TO BYTE",
          ""
        ],
        [
          "wSrcStartBit",
          "WORD",
          ""
        ],
        [
          "wSize",
          "WORD",
          "Size in bits"
        ]
      ]
    }
  ]
}