{
  "library": "ModbusFB",
  "title": "ExceptionCodes (Enum)",
  "url": "https://content.helpme-codesys.com/en/libs/ModbusFB/Current/ModbusFB/Enums/ExceptionCodes.html",
  "page_title": "ExceptionCodes (ENUM)",
  "text": "Library Information\nGetLibVersion (Function)\nGetLibVersionNumber (Function)\nIsLibReleased (Function)\nModbusFB\nEnums\nError (Enum)\nExceptionCodes (Enum)\nFunctionCodes (Enum)\nLoggingOptions (Enum)\nPrimaryTables (Enum)\nRtuAscii (Enum)\nSerialSubFunctionCodes (Enum)\nFunction Blocks\nClient\nClient (FunctionBlock)\nClientRequest (FunctionBlock)\nClientRequestMaskWriteRegister (FunctionBlock)\nClientRequestRead (FunctionBlock)\nClientRequestReadBits (FunctionBlock)\nClientRequestReadCoils (FunctionBlock)\nClientRequestReadDiscreteInputs (FunctionBlock)\nClientRequestReadHoldingRegisters (FunctionBlock)\nClientRequestReadInputRegisters (FunctionBlock)\nClientRequestReadRegisters (FunctionBlock)\nClientRequestReadWriteMultipleRegisters (FunctionBlock)\nClientRequestWriteMultiple (FunctionBlock)\nClientRequestWriteMultipleCoils (FunctionBlock)\nClientRequestWriteMultipleRegisters (FunctionBlock)\nClientRequestWriteSingle (FunctionBlock)\nClientRequestWriteSingleCoil (FunctionBlock)\nClientRequestWriteSingleRegister (FunctionBlock)\nClientSerial (FunctionBlock)\nClientTCP (FunctionBlock)\nServer\nExampleDataModel (FunctionBlock)\nServer (FunctionBlock)\nServerSerial (FunctionBlock)\nServerTCP (FunctionBlock)\nUtil\nByteBuffer (FunctionBlock)\nGlobalConstants\nConstants (GVL)\nParameter (ParamList)\nStructs\nRequestData (Struct)\nRequestDataDiagnostics (Struct)\nRequestDataMaskWriteRegister (Struct)\nRequestDataRead (Struct)\nRequestDataReadWriteMultipleRegisters (Struct)\nRequestDataWriteMultiple (Struct)\nRequestDataWriteSingle (Struct)\nRequestUnion (Union)\nSupportedFcs (Struct)\nTableDefinition (Struct)\nTableDefinitions (Struct)\nTableSection (Struct)\nFile and Project Information\nLibrary Reference\n3SLicense\nLibrary Identification\nLibrary Properties\nCmpErrors2 Interfaces\nLibrary Identification\nLibrary Properties\nCmpLog\nLibrary Identification\nLibrary Properties\nCommon Behaviour Model\nLibrary Identification\nLibrary Properties\nComponent Manager\nLibrary Identification\nLibrary Properties\nStandard\nLibrary Identification\nLibrary Properties\nStringUtils\nLibrary Identification\nLibrary Properties\nSysCom\nLibrary Identification\nLibrary Properties\nSysCpuHandling\nLibrary Identification\nLibrary Properties\nSysMem\nLibrary Identification\nLibrary Properties\nSysSocket\nLibrary Identification\nLibrary Properties\nSysTarget\nLibrary Identification\nLibrary Properties\nSysTimeCore\nLibrary Identification\nLibrary Properties\nSysTypes2 Interfaces\nLibrary Identification\nLibrary Properties\nModbusFB\nDocs\n»\nModbusFB\n»\nEnums\n»\nExceptionCodes (ENUM)\nExceptionCodes (ENUM)\nÂ¶\nTYPE ExceptionCodes :\nMODBUS exception codes.\nAttributes:\nqualified_only\nInOut:\nName\nInitial\nComment\nRESPONSE_SUCCESS\n16#0\nEverything OK\nILLEGAL_FUNCTION\n16#1\nThe function code received in the query is not an allowable action for the server (or slave).\nThis may be because the function code is only applicable to newer devices, and was not implemented in the unit selected.\nIt could also indicate that the server (or slave) is in the wrong state to process a request of this type,\nfor example because it is unconfigured and is being asked to return register values.\nILLEGAL_DATA_ADDRESS\n16#2\nThe data address received in the query is not an allowable address for the server (or slave).\nMore specifically, the combination of reference number and transfer length is invalid.\nFor a controller with 100 registers, the PDU addresses the first register as 0, and the last one as 99.\nIf a request is submitted with a starting register address of 96 and a quantity of registers of 4, then this request\nwill successfully operate (address-wise at least) on registers 96, 97, 98, 99.\nIf a request is submitted with a starting register address of 96 and a quantity of registers of 5, then this request\nwill fail with Exception Code 0x02 âIllegal Data Addressâ since it attempts to operate on registers 96, 97, 98, 99 and 100, and there is no register with address 100.\nILLEGAL_DATA_VALUE\n16#3\nThe value to be written is not valid\nSLAVE_DEVICE_FAILURE\n16#4\nUnrecoverable error while performing the request\nACKNOWLEDGE\n16#5\nNotification of a Slave that a lengthy operation being\nstarted\nSLAVE_DEVICE_BUSY\n16#6\nNotification of a Slave that a lengthy operation is in\nprogress\nMEMORY_PARITY_ERROR\n16#8\nSpecial error for function code 20, 21\nGATEWAY_PATH_UNAVAILABLE\n16#A\nSpecial error when using devices behind a gateway (Gateway\nmisconfigured/busy)\nGATEWAY_TARGET_DEVICE_FAILED_TO_RESPOND\n16#B\nSpecial error when using devices behind a gateway (Device\ndoes not respond)",
  "tables": [
    {
      "headers": [
        "Name",
        "Initial",
        "Comment"
      ],
      "rows": [
        {
          "Name": "RESPONSE_SUCCESS",
          "Initial": "16#0",
          "Comment": "Everything OK"
        },
        {
          "Name": "ILLEGAL_FUNCTION",
          "Initial": "16#1",
          "Comment": "The function code received in the query is not an allowable action for the server (or slave).\nThis may be because the function code is only applicable to newer devices, and was not implemented in the unit selected.\nIt could also indicate that the server (or slave) is in the wrong state to process a request of this type,\nfor example because it is unconfigured and is being asked to return register values."
        },
        {
          "Name": "ILLEGAL_DATA_ADDRESS",
          "Initial": "16#2",
          "Comment": "The data address received in the query is not an allowable address for the server (or slave).\nMore specifically, the combination of reference number and transfer length is invalid.\nFor a controller with 100 registers, the PDU addresses the first register as 0, and the last one as 99.\nIf a request is submitted with a starting register address of 96 and a quantity of registers of 4, then this request\nwill successfully operate (address-wise at least) on registers 96, 97, 98, 99.\nIf a request is submitted with a starting register address of 96 and a quantity of registers of 5, then this request\nwill fail with Exception Code 0x02 âIllegal Data Addressâ since it attempts to operate on registers 96, 97, 98, 99 and 100, and there is no register with address 100."
        },
        {
          "Name": "ILLEGAL_DATA_VALUE",
          "Initial": "16#3",
          "Comment": "The value to be written is not valid"
        },
        {
          "Name": "SLAVE_DEVICE_FAILURE",
          "Initial": "16#4",
          "Comment": "Unrecoverable error while performing the request"
        },
        {
          "Name": "ACKNOWLEDGE",
          "Initial": "16#5",
          "Comment": "Notification of a Slave that a lengthy operation being\nstarted"
        },
        {
          "Name": "SLAVE_DEVICE_BUSY",
          "Initial": "16#6",
          "Comment": "Notification of a Slave that a lengthy operation is in\nprogress"
        },
        {
          "Name": "MEMORY_PARITY_ERROR",
          "Initial": "16#8",
          "Comment": "Special error for function code 20, 21"
        },
        {
          "Name": "GATEWAY_PATH_UNAVAILABLE",
          "Initial": "16#A",
          "Comment": "Special error when using devices behind a gateway (Gateway\nmisconfigured/busy)"
        },
        {
          "Name": "GATEWAY_TARGET_DEVICE_FAILED_TO_RESPOND",
          "Initial": "16#B",
          "Comment": "Special error when using devices behind a gateway (Device\ndoes not respond)"
        }
      ]
    }
  ]
}