{
  "library": "MQTT Client SL",
  "title": "SetInitialValue (Method)",
  "url": "https://content.helpme-codesys.com/en/libs/MQTT Client SL/Current/MQTT-Client/Common/Function-Blocks/pou-MQTTClient/SetInitialValue.html",
  "page_title": "MQTTClient.SetInitialValue (METH)",
  "text": "MQTT Client\nCommon\nEnums\nCOMMUNICATION_MODE (Enum)\nFILTER_MODE (Enum)\nMQTT_ERROR (Enum)\nMQTT_QOS (Enum)\nMQTT_VERSION (Enum)\nV5\nFunction Blocks\nMQTTClient (FunctionBlock)\nMQTTPublish (FunctionBlock)\nMQTTSubscribe (FunctionBlock)\nParams\nMQTTParam (ParamList)\nStructs\nMQTTV5\nUTF-8\nConvertUTF16toUTF8 (Function)\nConvertUTF8toUTF16 (Function)\nFile and Project Information\nLibrary Reference\n3SLicense\nLibrary Identification\nLibrary Properties\nCAA FB Factory\nLibrary Identification\nLibrary Properties\nCAA Types Extern\nLibrary Identification\nLibrary Properties\nCmpCrypto\nLibrary Identification\nLibrary Properties\nCmpErrors2 Interfaces\nLibrary Identification\nLibrary Properties\nCmpLog\nLibrary Identification\nLibrary Properties\nCmpSchedule\nLibrary Identification\nLibrary Properties\nCmpX509Cert\nLibrary Identification\nLibrary Properties\nCommon Behaviour Model\nLibrary Identification\nLibrary Properties\nComponent Manager\nLibrary Identification\nLibrary Properties\nElement Collections\nLibrary Identification\nLibrary Properties\nMemoryUtils\nLibrary Identification\nLibrary Properties\nNet Base Services\nLibrary Identification\nLibrary Properties\nStandard\nLibrary Identification\nLibrary Properties\nStringUtils\nLibrary Identification\nLibrary Properties\nSysMem\nLibrary Identification\nLibrary Properties\nSysSocket2\nLibrary Identification\nLibrary Properties\nSysSocket2 Implementation\nLibrary Identification\nLibrary Properties\nSysTime\nLibrary Identification\nLibrary Properties\nSysTypes2 Interfaces\nLibrary Identification\nLibrary Properties\nWeb Socket Client SL\nLibrary Identification\nLibrary Properties\nMQTT Client SL\nDocs\n»\nMQTT\nClient\n»\nCommon\n»\nFunction\nBlocks\n»\nMQTTClient\n(FB)\n»\nMQTTClient.SetInitialValue (METH)\nMQTTClient.SetInitialValue (METH)\nÂ¶\nMETHOD SetInitialValue : BOOL\nInOut:\nScope\nName\nType\nInitial\nReturn\nSetInitialValue\nBOOL\nInput\nitfTLSContext\nNBS.ITLSContext\n0\nitfAsyncProperty\nNBS.IAsyncProperty\n0\nitfTSNContext\nNBS.ITSNContext\n0",
  "tables": [
    {
      "headers": [
        "Scope",
        "Name",
        "Type",
        "Initial"
      ],
      "rows": [
        {
          "Scope": "Return",
          "Name": "SetInitialValue",
          "Type": "BOOL",
          "Initial": ""
        },
        {
          "Scope": "Input",
          "Name": "itfTLSContext",
          "Type": "NBS.ITLSContext",
          "Initial": "0"
        },
        [
          "itfAsyncProperty",
          "NBS.IAsyncProperty",
          "0"
        ],
        [
          "itfTSNContext",
          "NBS.ITSNContext",
          "0"
        ]
      ]
    }
  ]
}