{
  "library": "PLCopen Safety FBs",
  "title": "SF_ESPE (FunctionBlock)",
  "url": "https://content.helpme-codesys.com/en/libs/PLCopen Safety FBs/Current/PLCopenSafetyFBs/Function-Blocks/SF_ESPE.html",
  "page_title": "SF_ESPE (FB)",
  "text": "PLCopenSafetyFBs\nEnums\nFBS_ANTI (Enum)\nFBS_EDM (Enum)\nFBS_ENSWITCH (Enum)\nFBS_ENSWITCH2 (Enum)\nFBS_EQUI (Enum)\nFBS_ESPE (Enum)\nFBS_ESTOP (Enum)\nFBS_GUARD (Enum)\nFBS_GUARDLOCK2 (Enum)\nFBS_MODESEL (Enum)\nFBS_OUTCONTROL (Enum)\nFBS_PSE (Enum)\nFBS_RESBUT (Enum)\nFBS_SAFEREQ (Enum)\nFBS_TESTSEN (Enum)\nFBS_TWOHAND (Enum)\nFunction Blocks\nSF_Antivalent (FunctionBlock)\nSF_EDM (FunctionBlock)\nSF_ESPE (FunctionBlock)\nSF_EmergencyStop (FunctionBlock)\nSF_EnableSwitch (FunctionBlock)\nSF_EnableSwitch_2 (FunctionBlock)\nSF_Equivalent (FunctionBlock)\nSF_Guard (FunctionBlock)\nSF_GuardLocking_2 (FunctionBlock)\nSF_ModeSelector (FunctionBlock)\nSF_OutControl (FunctionBlock)\nSF_PSE (FunctionBlock)\nSF_ResetButton (FunctionBlock)\nSF_SafetyRequest (FunctionBlock)\nSF_TestableSafetySensor (FunctionBlock)\nSF_TwoHandControlTypeII (FunctionBlock)\nSF_TwoHandControlTypeIII (FunctionBlock)\nFile and Project Information\nLibrary Reference\nStandard\nLibrary Identification\nLibrary Properties\nSysTimeCore\nLibrary Identification\nLibrary Properties\nPLCopen Safety FBs\nDocs\n»\nPLCopenSafetyFBs\n»\nFunction\nBlocks\n»\nSF_ESPE (FB)\nSF_ESPE (FB)\nÂ¶\nFUNCTION_BLOCK SF_ESPE\nThis function block is a safety-related function block for monitoring electro-sensitive protective equipment (ESPE).\nInOut:\nScope\nName\nType\nInitial\nComment\nInput\nActivate\nBOOL\nFALSE\nActivation of the FB.\nS_ESPE_In\nBOOL\nFALSE\nSafety demand input. FALSE: ESPE actuated, demand for\nsafety-related response. TRUE: ESPE not actuated, no demand\nfor safety-related response.\nS_StartReset\nBOOL\nFALSE\nStart behaviour of safety FB\nS_AutoReset\nBOOL\nFALSE\nBehaviour on error of safety FB\nReset\nBOOL\nFALSE\nManual reset of FB\nOutput\nReady\nBOOL\nFALSE\nActivation of the FB. TRUE indicates that the FB is\nactivated and the outputs results are valid, FALSE the FB is\nnot active and the program is not executed.\nS_ESPE_Out\nBOOL\nFALSE\nOutput for the safety-related response. FALSE: Safety output\ndisabled. Demand for safety-related response (e.g., reset\nrequired or internal errors active). TRUE: Safety output\nenabled. No demand for safety-related re-sponse\nSafetyDemand\nBOOL\nFALSE\nOutput indicating that the FB is active and the primary\nsafety function is demanded (e.g. related to the safety\nfunctionality).\nResetRequest\nBOOL\nFALSE\nOutput which can be used to signal the operator to press the\nreset functionality to continue.\nError\nBOOL\nFALSE\nError flag\nDiagCode\nWORD\n0\nDiagnostic register",
  "tables": [
    {
      "headers": [
        "Scope",
        "Name",
        "Type",
        "Initial",
        "Comment"
      ],
      "rows": [
        {
          "Scope": "Input",
          "Name": "Activate",
          "Type": "BOOL",
          "Initial": "FALSE",
          "Comment": "Activation of the FB."
        },
        [
          "S_ESPE_In",
          "BOOL",
          "FALSE",
          "Safety demand input. FALSE: ESPE actuated, demand for\nsafety-related response. TRUE: ESPE not actuated, no demand\nfor safety-related response."
        ],
        [
          "S_StartReset",
          "BOOL",
          "FALSE",
          "Start behaviour of safety FB"
        ],
        [
          "S_AutoReset",
          "BOOL",
          "FALSE",
          "Behaviour on error of safety FB"
        ],
        [
          "Reset",
          "BOOL",
          "FALSE",
          "Manual reset of FB"
        ],
        {
          "Scope": "Output",
          "Name": "Ready",
          "Type": "BOOL",
          "Initial": "FALSE",
          "Comment": "Activation of the FB. TRUE indicates that the FB is\nactivated and the outputs results are valid, FALSE the FB is\nnot active and the program is not executed."
        },
        [
          "S_ESPE_Out",
          "BOOL",
          "FALSE",
          "Output for the safety-related response. FALSE: Safety output\ndisabled. Demand for safety-related response (e.g., reset\nrequired or internal errors active). TRUE: Safety output\nenabled. No demand for safety-related re-sponse"
        ],
        [
          "SafetyDemand",
          "BOOL",
          "FALSE",
          "Output indicating that the FB is active and the primary\nsafety function is demanded (e.g. related to the safety\nfunctionality)."
        ],
        [
          "ResetRequest",
          "BOOL",
          "FALSE",
          "Output which can be used to signal the operator to press the\nreset functionality to continue."
        ],
        [
          "Error",
          "BOOL",
          "FALSE",
          "Error flag"
        ],
        [
          "DiagCode",
          "WORD",
          "0",
          "Diagnostic register"
        ]
      ]
    }
  ]
}