{
  "library": "PLCopen Safety FBs",
  "title": "FBS_TESTSEN (Enum)",
  "url": "https://content.helpme-codesys.com/en/libs/PLCopen Safety FBs/Current/PLCopenSafetyFBs/Enums/FBS_TESTSEN.html",
  "page_title": "FBS_TESTSEN (ENUM)",
  "text": "PLCopenSafetyFBs\nEnums\nFBS_ANTI (Enum)\nFBS_EDM (Enum)\nFBS_ENSWITCH (Enum)\nFBS_ENSWITCH2 (Enum)\nFBS_EQUI (Enum)\nFBS_ESPE (Enum)\nFBS_ESTOP (Enum)\nFBS_GUARD (Enum)\nFBS_GUARDLOCK2 (Enum)\nFBS_MODESEL (Enum)\nFBS_OUTCONTROL (Enum)\nFBS_PSE (Enum)\nFBS_RESBUT (Enum)\nFBS_SAFEREQ (Enum)\nFBS_TESTSEN (Enum)\nFBS_TWOHAND (Enum)\nFunction Blocks\nSF_Antivalent (FunctionBlock)\nSF_EDM (FunctionBlock)\nSF_ESPE (FunctionBlock)\nSF_EmergencyStop (FunctionBlock)\nSF_EnableSwitch (FunctionBlock)\nSF_EnableSwitch_2 (FunctionBlock)\nSF_Equivalent (FunctionBlock)\nSF_Guard (FunctionBlock)\nSF_GuardLocking_2 (FunctionBlock)\nSF_ModeSelector (FunctionBlock)\nSF_OutControl (FunctionBlock)\nSF_PSE (FunctionBlock)\nSF_ResetButton (FunctionBlock)\nSF_SafetyRequest (FunctionBlock)\nSF_TestableSafetySensor (FunctionBlock)\nSF_TwoHandControlTypeII (FunctionBlock)\nSF_TwoHandControlTypeIII (FunctionBlock)\nFile and Project Information\nLibrary Reference\nStandard\nLibrary Identification\nLibrary Properties\nSysTimeCore\nLibrary Identification\nLibrary Properties\nPLCopen Safety FBs\nDocs\n»\nPLCopenSafetyFBs\n»\nEnums\n»\nFBS_TESTSEN (ENUM)\nFBS_TESTSEN (ENUM)\nÂ¶\nTYPE FBS_TESTSEN :\nDefinition of SF_TestableSafetySensor function block states and its diagnostic values.\nAttributes:\nqualified_only\nInOut:\nName\nInitial\nComment\nIDLE\n16#0\nThe function block is not active (initial state).\nINIT\n16#8401\nAn activation has been detected by the FB.\nESPE_INTERRUPTED_1\n16#8802\nThe FB has detected a safety demand. The switch has not been\nautomatically tested yet.\nWAIT_FOR_RESET_1\n16#8402\nWait for rising trigger of Reset after state 8802.\nEXT_FUNC_TEST\n16#8002\nThe automatic sensor test was faulty. An external manual sensor test is necessary.\nThe support for the necessary external manual sensor test has been acti-vated at the FB (NoExternalTest = FALSE).\nA negative signal edge at the sensor is required.\nESPE_ESPE_INTERRUPT_EXTTEST\n16#8804\nThe automatic sensor test was faulty. An external manual sensor test is necessary.\nThe support FOR the necessary external manual sensor test has been activated at the FB (NoExternalTest = FALSE). A TRUE signal at the sensor is required\nEND_EXTTEST\n16#8404\nThe automatic sensor test was faulty. An external manual sensor test is necessary. The support for the necessary external manual sensor test has been acti-vated at the FB (NoExternalTest = FALSE).\nThe external manual test is complete. The FB detected a complete sensor switching cycle (external controlled).\nESPE_FREE_NO_TEST\n16#8010\nThe FB has not detected a safety demand. The sensor has not\nbeen tested automatically.\nESPE_INTERRUPTED_2\n16#8806\nThe FB has detected a safety demand. The switch was\nautomatically tested.\nWAIT_FOR_RESET_2\n16#8406\nWait for rising trigger of Reset after state 8812\nTEST_REQUEST\n16#8020\nThe automatic sensor test is active. Test Timer is started first time. The transmitter signal of the sensor is switched off by the FB.\nThe signal of the receiver must follow the signal of the transmitter.\nTEST_ACTIVE\n16#8030\nThe automatic sensor test is active. Test Timer is started second time. The transmitter signal of the sensor is switched on by the FB.\nThe signal of the receiver must follow the signal of the transmitter.\nESPE_FREE_TEST_OK\n16#8000\nThe FB has not detected a safety demand. The sensor was\nautomatically tested.\nERR_PARAMETER\n16#C000\nInvalid value at the TestTime parameter. Values between 0 ms\nand 150 ms are possible.\nERR_RESET_1\n16#C001\nStatic Reset condition detected after FB activation.\nERR_RESET_2\n16#C011\nStatic Reset condition detected in state 8403.\nERR_RESET_3\n16#C021\nStatic Reset condition detected in state Cx10.\nERR_RESET_4\n16#C031\nStatic Reset condition detected in state 8406.\nERR_RESET_5\n16#C041\nStatic Reset condition detected in state C000.\nERR_RESET_6\n16#C051\nStatic Reset condition detected in state 8413.\nERR_TEST_1\n16#C010\nTest time elapsed in state 8020 or 8030. NOT (S_OSSD_IN =\nTRUE AND NoExternalTest = TRUE)\nERR_TEST_2\n16#C410\nTest time elapsed in state 8020 or 8030. S_OSSD_IN = TRUE\nAND NoExternalTest = TRUE",
  "tables": [
    {
      "headers": [
        "Name",
        "Initial",
        "Comment"
      ],
      "rows": [
        {
          "Name": "IDLE",
          "Initial": "16#0",
          "Comment": "The function block is not active (initial state)."
        },
        {
          "Name": "INIT",
          "Initial": "16#8401",
          "Comment": "An activation has been detected by the FB."
        },
        {
          "Name": "ESPE_INTERRUPTED_1",
          "Initial": "16#8802",
          "Comment": "The FB has detected a safety demand. The switch has not been\nautomatically tested yet."
        },
        {
          "Name": "WAIT_FOR_RESET_1",
          "Initial": "16#8402",
          "Comment": "Wait for rising trigger of Reset after state 8802."
        },
        {
          "Name": "EXT_FUNC_TEST",
          "Initial": "16#8002",
          "Comment": "The automatic sensor test was faulty. An external manual sensor test is necessary.\nThe support for the necessary external manual sensor test has been acti-vated at the FB (NoExternalTest = FALSE).\nA negative signal edge at the sensor is required."
        },
        {
          "Name": "ESPE_ESPE_INTERRUPT_EXTTEST",
          "Initial": "16#8804",
          "Comment": "The automatic sensor test was faulty. An external manual sensor test is necessary.\nThe support FOR the necessary external manual sensor test has been activated at the FB (NoExternalTest = FALSE). A TRUE signal at the sensor is required"
        },
        {
          "Name": "END_EXTTEST",
          "Initial": "16#8404",
          "Comment": "The automatic sensor test was faulty. An external manual sensor test is necessary. The support for the necessary external manual sensor test has been acti-vated at the FB (NoExternalTest = FALSE).\nThe external manual test is complete. The FB detected a complete sensor switching cycle (external controlled)."
        },
        {
          "Name": "ESPE_FREE_NO_TEST",
          "Initial": "16#8010",
          "Comment": "The FB has not detected a safety demand. The sensor has not\nbeen tested automatically."
        },
        {
          "Name": "ESPE_INTERRUPTED_2",
          "Initial": "16#8806",
          "Comment": "The FB has detected a safety demand. The switch was\nautomatically tested."
        },
        {
          "Name": "WAIT_FOR_RESET_2",
          "Initial": "16#8406",
          "Comment": "Wait for rising trigger of Reset after state 8812"
        },
        {
          "Name": "TEST_REQUEST",
          "Initial": "16#8020",
          "Comment": "The automatic sensor test is active. Test Timer is started first time. The transmitter signal of the sensor is switched off by the FB.\nThe signal of the receiver must follow the signal of the transmitter."
        },
        {
          "Name": "TEST_ACTIVE",
          "Initial": "16#8030",
          "Comment": "The automatic sensor test is active. Test Timer is started second time. The transmitter signal of the sensor is switched on by the FB.\nThe signal of the receiver must follow the signal of the transmitter."
        },
        {
          "Name": "ESPE_FREE_TEST_OK",
          "Initial": "16#8000",
          "Comment": "The FB has not detected a safety demand. The sensor was\nautomatically tested."
        },
        {
          "Name": "ERR_PARAMETER",
          "Initial": "16#C000",
          "Comment": "Invalid value at the TestTime parameter. Values between 0 ms\nand 150 ms are possible."
        },
        {
          "Name": "ERR_RESET_1",
          "Initial": "16#C001",
          "Comment": "Static Reset condition detected after FB activation."
        },
        {
          "Name": "ERR_RESET_2",
          "Initial": "16#C011",
          "Comment": "Static Reset condition detected in state 8403."
        },
        {
          "Name": "ERR_RESET_3",
          "Initial": "16#C021",
          "Comment": "Static Reset condition detected in state Cx10."
        },
        {
          "Name": "ERR_RESET_4",
          "Initial": "16#C031",
          "Comment": "Static Reset condition detected in state 8406."
        },
        {
          "Name": "ERR_RESET_5",
          "Initial": "16#C041",
          "Comment": "Static Reset condition detected in state C000."
        },
        {
          "Name": "ERR_RESET_6",
          "Initial": "16#C051",
          "Comment": "Static Reset condition detected in state 8413."
        },
        {
          "Name": "ERR_TEST_1",
          "Initial": "16#C010",
          "Comment": "Test time elapsed in state 8020 or 8030. NOT (S_OSSD_IN =\nTRUE AND NoExternalTest = TRUE)"
        },
        {
          "Name": "ERR_TEST_2",
          "Initial": "16#C410",
          "Comment": "Test time elapsed in state 8020 or 8030. S_OSSD_IN = TRUE\nAND NoExternalTest = TRUE"
        }
      ]
    }
  ]
}