{
  "library": "PLCopen Safety FBs",
  "title": "SF_OutControl (FunctionBlock)",
  "url": "https://content.helpme-codesys.com/en/libs/PLCopen Safety FBs/Current/PLCopenSafetyFBs/Function-Blocks/SF_OutControl.html",
  "page_title": "SF_OutControl (FB)",
  "text": "PLCopenSafetyFBs\nEnums\nFBS_ANTI (Enum)\nFBS_EDM (Enum)\nFBS_ENSWITCH (Enum)\nFBS_ENSWITCH2 (Enum)\nFBS_EQUI (Enum)\nFBS_ESPE (Enum)\nFBS_ESTOP (Enum)\nFBS_GUARD (Enum)\nFBS_GUARDLOCK2 (Enum)\nFBS_MODESEL (Enum)\nFBS_OUTCONTROL (Enum)\nFBS_PSE (Enum)\nFBS_RESBUT (Enum)\nFBS_SAFEREQ (Enum)\nFBS_TESTSEN (Enum)\nFBS_TWOHAND (Enum)\nFunction Blocks\nSF_Antivalent (FunctionBlock)\nSF_EDM (FunctionBlock)\nSF_ESPE (FunctionBlock)\nSF_EmergencyStop (FunctionBlock)\nSF_EnableSwitch (FunctionBlock)\nSF_EnableSwitch_2 (FunctionBlock)\nSF_Equivalent (FunctionBlock)\nSF_Guard (FunctionBlock)\nSF_GuardLocking_2 (FunctionBlock)\nSF_ModeSelector (FunctionBlock)\nSF_OutControl (FunctionBlock)\nSF_PSE (FunctionBlock)\nSF_ResetButton (FunctionBlock)\nSF_SafetyRequest (FunctionBlock)\nSF_TestableSafetySensor (FunctionBlock)\nSF_TwoHandControlTypeII (FunctionBlock)\nSF_TwoHandControlTypeIII (FunctionBlock)\nFile and Project Information\nLibrary Reference\nStandard\nLibrary Identification\nLibrary Properties\nSysTimeCore\nLibrary Identification\nLibrary Properties\nPLCopen Safety FBs\nDocs\n»\nPLCopenSafetyFBs\n»\nFunction\nBlocks\n»\nSF_OutControl (FB)\nSF_OutControl (FB)\nÂ¶\nFUNCTION_BLOCK SF_OutControl\nControl of a safety output with a signal from the functional application and a safety signal with optional startup inhib-its.\nFunction block according to PLCopen, Technical Committee 5: Safety Software (Technical Specification), Part 1: Concepts and Function Blocks, Version 2.01 (2020-2)\nInOut:\nScope\nName\nType\nInitial\nComment\nInput\nActivate\nBOOL\nFALSE\nActivation of the FB.\nS_SafeControl\nBOOL\nFALSE\nControl signal of the preceding safety FB. FALSE: The\npreceding safety FBâs are in safe state, TRUE: The preceding\nsafety FBâs enable safety control.\nProcessControl\nBOOL\nFALSE\nControl signal from the functional application. FALSE:\nRequest to set S_OutControl to FALSE, TRUE: Request to set\nS_OutControl to TRUE.\nStaticControl\nBOOL\nFALSE\nOptional conditions for process control. FALSE: Dynamic\nchange at ProcessControl, TRUE: No dynamic change at\nProcessControl.\nS_StartReset\nBOOL\nFALSE\nStart behaviour of safety FB\nS_AutoReset\nBOOL\nFALSE\nBehaviour on error of safety FB\nReset\nBOOL\nFALSE\nManual reset of FB\nOutput\nReady\nBOOL\nFALSE\nActivation of the FB. TRUE indicates that the FB is\nactivated and the outputs results are valid, FALSE the FB is\nnot active and the program is not executed.\nS_OutControl\nBOOL\nFALSE\nControls connected actuators. FALSE: Disable connected\nactuators, TRUE: Enable connected actuators.\nSafetyDemand\nBOOL\nFALSE\nOutput indicating that the FB is active and the primary\nsafety function is demanded (e.g. related to the safety\nfunctionality).\nResetRequest\nBOOL\nFALSE\nOutput which can be used to signal the operator to press the\nreset functionality to continue.\nError\nBOOL\nFALSE\nError flag\nDiagCode\nWORD\n0\nDiagnostic register",
  "tables": [
    {
      "headers": [
        "Scope",
        "Name",
        "Type",
        "Initial",
        "Comment"
      ],
      "rows": [
        {
          "Scope": "Input",
          "Name": "Activate",
          "Type": "BOOL",
          "Initial": "FALSE",
          "Comment": "Activation of the FB."
        },
        [
          "S_SafeControl",
          "BOOL",
          "FALSE",
          "Control signal of the preceding safety FB. FALSE: The\npreceding safety FBâs are in safe state, TRUE: The preceding\nsafety FBâs enable safety control."
        ],
        [
          "ProcessControl",
          "BOOL",
          "FALSE",
          "Control signal from the functional application. FALSE:\nRequest to set S_OutControl to FALSE, TRUE: Request to set\nS_OutControl to TRUE."
        ],
        [
          "StaticControl",
          "BOOL",
          "FALSE",
          "Optional conditions for process control. FALSE: Dynamic\nchange at ProcessControl, TRUE: No dynamic change at\nProcessControl."
        ],
        [
          "S_StartReset",
          "BOOL",
          "FALSE",
          "Start behaviour of safety FB"
        ],
        [
          "S_AutoReset",
          "BOOL",
          "FALSE",
          "Behaviour on error of safety FB"
        ],
        [
          "Reset",
          "BOOL",
          "FALSE",
          "Manual reset of FB"
        ],
        {
          "Scope": "Output",
          "Name": "Ready",
          "Type": "BOOL",
          "Initial": "FALSE",
          "Comment": "Activation of the FB. TRUE indicates that the FB is\nactivated and the outputs results are valid, FALSE the FB is\nnot active and the program is not executed."
        },
        [
          "S_OutControl",
          "BOOL",
          "FALSE",
          "Controls connected actuators. FALSE: Disable connected\nactuators, TRUE: Enable connected actuators."
        ],
        [
          "SafetyDemand",
          "BOOL",
          "FALSE",
          "Output indicating that the FB is active and the primary\nsafety function is demanded (e.g. related to the safety\nfunctionality)."
        ],
        [
          "ResetRequest",
          "BOOL",
          "FALSE",
          "Output which can be used to signal the operator to press the\nreset functionality to continue."
        ],
        [
          "Error",
          "BOOL",
          "FALSE",
          "Error flag"
        ],
        [
          "DiagCode",
          "WORD",
          "0",
          "Diagnostic register"
        ]
      ]
    }
  ]
}