{
  "library": "PLCopen Safety FBs",
  "title": "FBS_ENSWITCH (Enum)",
  "url": "https://content.helpme-codesys.com/en/libs/PLCopen Safety FBs/Current/PLCopenSafetyFBs/Enums/FBS_ENSWITCH.html",
  "page_title": "FBS_ENSWITCH (ENUM)",
  "text": "PLCopenSafetyFBs\nEnums\nFBS_ANTI (Enum)\nFBS_EDM (Enum)\nFBS_ENSWITCH (Enum)\nFBS_ENSWITCH2 (Enum)\nFBS_EQUI (Enum)\nFBS_ESPE (Enum)\nFBS_ESTOP (Enum)\nFBS_GUARD (Enum)\nFBS_GUARDLOCK2 (Enum)\nFBS_MODESEL (Enum)\nFBS_OUTCONTROL (Enum)\nFBS_PSE (Enum)\nFBS_RESBUT (Enum)\nFBS_SAFEREQ (Enum)\nFBS_TESTSEN (Enum)\nFBS_TWOHAND (Enum)\nFunction Blocks\nSF_Antivalent (FunctionBlock)\nSF_EDM (FunctionBlock)\nSF_ESPE (FunctionBlock)\nSF_EmergencyStop (FunctionBlock)\nSF_EnableSwitch (FunctionBlock)\nSF_EnableSwitch_2 (FunctionBlock)\nSF_Equivalent (FunctionBlock)\nSF_Guard (FunctionBlock)\nSF_GuardLocking_2 (FunctionBlock)\nSF_ModeSelector (FunctionBlock)\nSF_OutControl (FunctionBlock)\nSF_PSE (FunctionBlock)\nSF_ResetButton (FunctionBlock)\nSF_SafetyRequest (FunctionBlock)\nSF_TestableSafetySensor (FunctionBlock)\nSF_TwoHandControlTypeII (FunctionBlock)\nSF_TwoHandControlTypeIII (FunctionBlock)\nFile and Project Information\nLibrary Reference\nStandard\nLibrary Identification\nLibrary Properties\nSysTimeCore\nLibrary Identification\nLibrary Properties\nPLCopen Safety FBs\nDocs\n»\nPLCopenSafetyFBs\n»\nEnums\n»\nFBS_ENSWITCH (ENUM)\nFBS_ENSWITCH (ENUM)\nÂ¶\nTYPE FBS_ENSWITCH :\nDefinition of SF_EnableSwitch_2 function block states and its diagnostic values.\nAttributes:\nqualified_only\nInOut:\nName\nInitial\nComment\nIDLE\n16#0\nThe function block is not active (initial state).\nBASIC_OPMODE\n16#8002\nSafe operation mode is not active.\nSAFE_OPMODE\n16#8004\nSafe operation mode is active.\nPOSITION_1\n16#8802\nSafe operation mode is active and the enable switch is in\nposition 1.\nPOSITION_3\n16#8804\nSafe operation mode is active and the enable switch is in\nposition 3.\nPOSITION_2\n16#8000\nSafe operation mode is active and the enable switch is in\nposition 2.\nERR_OPERATION_1\n16#C010\nEnable switch not in position 1 during activation of\nS_SafetyActive.\nERR_OPERATION_2\n16#C020\nEnable switch in position 1 after C010.\nERR_OPERATION_3\n16#C030\nEnable switch in position 2 after position 3.\nERR_OPERATION_4\n16#C040\nEnable switch not in position 2 after C030.\nERR_RESET_1\n16#C001\nStatic Reset signal detected in state C020.\nERR_RESET_2\n16#C011\nStatic Reset signal detected in state C040.",
  "tables": [
    {
      "headers": [
        "Name",
        "Initial",
        "Comment"
      ],
      "rows": [
        {
          "Name": "IDLE",
          "Initial": "16#0",
          "Comment": "The function block is not active (initial state)."
        },
        {
          "Name": "BASIC_OPMODE",
          "Initial": "16#8002",
          "Comment": "Safe operation mode is not active."
        },
        {
          "Name": "SAFE_OPMODE",
          "Initial": "16#8004",
          "Comment": "Safe operation mode is active."
        },
        {
          "Name": "POSITION_1",
          "Initial": "16#8802",
          "Comment": "Safe operation mode is active and the enable switch is in\nposition 1."
        },
        {
          "Name": "POSITION_3",
          "Initial": "16#8804",
          "Comment": "Safe operation mode is active and the enable switch is in\nposition 3."
        },
        {
          "Name": "POSITION_2",
          "Initial": "16#8000",
          "Comment": "Safe operation mode is active and the enable switch is in\nposition 2."
        },
        {
          "Name": "ERR_OPERATION_1",
          "Initial": "16#C010",
          "Comment": "Enable switch not in position 1 during activation of\nS_SafetyActive."
        },
        {
          "Name": "ERR_OPERATION_2",
          "Initial": "16#C020",
          "Comment": "Enable switch in position 1 after C010."
        },
        {
          "Name": "ERR_OPERATION_3",
          "Initial": "16#C030",
          "Comment": "Enable switch in position 2 after position 3."
        },
        {
          "Name": "ERR_OPERATION_4",
          "Initial": "16#C040",
          "Comment": "Enable switch not in position 2 after C030."
        },
        {
          "Name": "ERR_RESET_1",
          "Initial": "16#C001",
          "Comment": "Static Reset signal detected in state C020."
        },
        {
          "Name": "ERR_RESET_2",
          "Initial": "16#C011",
          "Comment": "Static Reset signal detected in state C040."
        }
      ]
    }
  ]
}