{
  "library": "SM3_Robotics",
  "title": "SMC_GroupWait (FunctionBlock)",
  "url": "https://content.helpme-codesys.com/en/libs/SM3_Robotics/Current/SM3_Robotics/POUs/Movement/SMC_GroupWait.html",
  "page_title": "SMC_GroupWait (FB)",
  "text": "Library Information\nGetLibVersion (Function)\nGetLibVersionNumber (Function)\nGetVersion (Function)\nIsLibReleased (Function)\nSM3_Robotics\nBasic types\nIDENT_IN_GROUP_REF_SM3 (Alias)\nMC_CIRC_PATHCHOICE (Enum)\nMC_COORD_REF (Struct)\nMC_EXECUTION_MODE (Enum)\nMC_TRANSITION_MODE (Enum)\nSMC_AXIS_GROUP_COMPATIBILITY_OPTIONS (Struct)\nSMC_AXIS_GROUP_CONTINUE_DATA (FunctionBlock)\nSMC_AXIS_GROUP_STATE (Enum)\nSMC_CIRC_MODE (Enum)\nSMC_DYN_LIMITS (Alias)\nSMC_IDynamicCS (Interface)\nSMC_ORIENTATION_MODE (Enum)\nSMC_POS_REF (Union)\nSMC_PTP_MOVEMENT_TYPE (Enum)\nSMC_READ_TOOL_MODE (Enum)\nPOUs\nAdditional\nSMC_AxisDistanceAxes (Enum)\nSMC_AxisDistanceSubMode (Enum)\nSMC_AxisDistanceTransition (FunctionBlock)\nSMC_AxisDistanceTransitionParam (Function)\nSMC_CornerDistance (FunctionBlock)\nSMC_CornerDistanceTransitionParam (Function)\nSMC_StartVelocity (FunctionBlock)\nSMC_StartVelocityAxes (Enum)\nSMC_StartVelocityTransitionParam (Function)\nSMC_StartupAxisGroup (FunctionBlock)\nAdministrative/Configuration\nAxisGroup\nComputation\nCoordinate systems\nDynamics\nKinematics\nTrigger\nAxisGroup\nAXIS_GROUP_REF_SM3 (FunctionBlock)\nHelpers\nMovements\nDiagnostics\nMC_GroupReadActualAcceleration (FunctionBlock)\nMC_GroupReadActualPosition (FunctionBlock)\nMC_GroupReadActualVelocity (FunctionBlock)\nMC_GroupReadConfiguration (FunctionBlock)\nMC_GroupReadError (FunctionBlock)\nMC_GroupReadStatus (FunctionBlock)\nMC_ReadCoordinateTransform (FunctionBlock)\nMC_ReadKinTransform (FunctionBlock)\nSMC_GroupAddOffset (FunctionBlock)\nSMC_GroupAdditionalAxesTargetPositions (FunctionBlock)\nSMC_GroupConvertPosition (FunctionBlock)\nSMC_GroupGetContinuePosition (FunctionBlock)\nSMC_GroupGetContinueToolOffset (FunctionBlock)\nSMC_GroupReadPathAcceleration (FunctionBlock)\nSMC_GroupReadPathDynamics (FunctionBlock)\nSMC_GroupReadPathVelocity (FunctionBlock)\nSMC_GroupReadPlanningStatistics (FunctionBlock)\nSMC_GroupReadPositionInMovement (FunctionBlock)\nSMC_GroupReadRemainingTrajectoryDuration (FunctionBlock)\nSMC_GroupReadSetAcceleration (FunctionBlock)\nSMC_GroupReadSetJerk (FunctionBlock)\nSMC_GroupReadSetPosition (FunctionBlock)\nSMC_GroupReadSetVelocity (FunctionBlock)\nSMC_GroupTargetPosition (FunctionBlock)\nSMC_ReadKinTransformForAxis (FunctionBlock)\nMovement\nAdditionalAxes\nGroupInterrupt\nMC_GroupContinue (FunctionBlock)\nMC_GroupHalt (FunctionBlock)\nMC_GroupInterrupt (FunctionBlock)\nMC_GroupStop (FunctionBlock)\nMC_MoveCircularAbsolute (FunctionBlock)\nMC_MoveCircularRelative (FunctionBlock)\nMC_MoveDirectAbsolute (FunctionBlock)\nMC_MoveDirectRelative (FunctionBlock)\nMC_MoveLinearAbsolute (FunctionBlock)\nMC_MoveLinearRelative (FunctionBlock)\nSMC_GroupEnableResumeAfterError (FunctionBlock)\nSMC_GroupJog (FunctionBlock)\nSMC_GroupJog2 (FunctionBlock)\nSMC_GroupUpdateContinueData (FunctionBlock)\nSMC_GroupWait (FunctionBlock)\nSMC_MoveAdditionalAxes (FunctionBlock)\ninternal\nDivers\nKernel_CP\nFile and Project Information\nLibrary Reference\n3SLicense\nLibrary Identification\nLibrary Properties\nCmpApp\nLibrary Identification\nLibrary Properties\nCmpIecTask\nLibrary Identification\nLibrary Properties\nCmpLog\nLibrary Identification\nLibrary Properties\nFloatingPointUtils\nLibrary Identification\nLibrary Properties\nSM3_Basic\nLibrary Identification\nLibrary Properties\nLibrary Parameter\nSM3_CPKernelDefaults\nLibrary Identification\nLibrary Properties\nLibrary Parameter\nSM3_CommonPublic\nLibrary Identification\nLibrary Properties\nSM3_Dynamics\nLibrary Identification\nLibrary Properties\nSM3_Error\nLibrary Identification\nLibrary Properties\nSM3_RBase\nLibrary Identification\nLibrary Properties\nSM3_RCP\nLibrary Identification\nLibrary Properties\nSM3_RError\nLibrary Identification\nLibrary Properties\nSM3_Ramps\nLibrary Identification\nLibrary Properties\nSM3_Shared\nLibrary Identification\nLibrary Properties\nSM3_StringUtils\nLibrary Identification\nLibrary Properties\nSM3_TrajectoryGeneration\nLibrary Identification\nLibrary Properties\nSM3_Transformation\nLibrary Identification\nLibrary Properties\nStandard\nLibrary Identification\nLibrary Properties\nSysMem\nLibrary Identification\nLibrary Properties\nSysTarget\nLibrary Identification\nLibrary Properties\nSysTime\nLibrary Identification\nLibrary Properties\nSysTypes2 Interfaces\nLibrary Identification\nLibrary Properties\nSM3_Robotics\nDocs\n»\nSM3_Robotics\n»\nPOUs\n»\nMovement\n»\nSMC_GroupWait (FB)\nSMC_GroupWait (FB)\nÂ¶\nFUNCTION_BLOCK FINAL SMC_GroupWait\nProgrammed waiting on the path.\nSMC_GroupWait\nbehaves like a buffered movement command, leading\nto a wait for a given time between two movements.\nIt is not possible to blend into or from waiting.\nThe waiting time starts right after the previously commanded\nmovement has finished.\nThe waiting time between the two surrounding movements will be\nexactly the configured time.\nIf a waiting command follows a tracking movement, the axis group will\ntrack the endpoint of the preceding movement for the specified time.\nIf the axes are not in standstill, but not controlled by the axis group,\nand waiting is commanded, the axis group will report the error\nSMC_AXIS_GROUP_IDLE_WAIT_AXES_MOVING\n.\nAs set-values are updated once per bus cycle, waiting times different from\na multiple of the bus cycle time will just appear as a smoother start-up\nof the subsequent movement.\nNote\nBuffered movements always start at the beginning of a task cycle.\nThis means that there is an implicit wait of at most one task cycle\nbetween any two consecutive buffered movements.  The duration of this\nimplicit wait can be reduced by\nSMC_GroupWait\nwith a shorter wait\ntime.\nInOut:\nScope\nName\nType\nInitial\nComment\nInout\nAxisGroup\nAXIS_GROUP_REF_SM3\nReference to a group of axes\nInput\nExecute\nBOOL\nStart the action at rising edge\nWaitTime\nLREAL\nThe time to wait on the path, in seconds.\nMay not be negative.\nName\nSTRING\nâSMC_GroupWaitâ\nThe name of the movement.\nOutput\nDone\nBOOL\nStandstill has been reached\nBusy\nBOOL\nThe FB is not finished\nActive\nBOOL\nIndicates that the FB has control on the axis\nCommandAborted\nBOOL\nCommand is aborted by another command\nCommandAccepted\nBOOL\nThe command has been accepted by the axis group.\nIf the output becomes\nTRUE\n, the function block instance can be used to\ncommand the next movement with a new rising edge on\nExecute\n.\nWhile the output is\nFALSE\n, keep calling the function block without\na new rising edge of\nExecute\n.\nThe output is reset to\nFALSE\non a falling edge of\nExecute\n.\nError\nBOOL\nSignals that an error has occurred within the function block\nErrorID\nSMC_ERROR\nError identification\nMovementId\nSMC_Movement_Id\nThe unique identifier of the movement.  Valid if\nCommandAccepted\nor\nDone\nis\nTRUE\n.",
  "tables": [
    {
      "headers": [
        "Scope",
        "Name",
        "Type",
        "Initial",
        "Comment"
      ],
      "rows": [
        {
          "Scope": "Inout",
          "Name": "AxisGroup",
          "Type": "AXIS_GROUP_REF_SM3",
          "Initial": "",
          "Comment": "Reference to a group of axes"
        },
        {
          "Scope": "Input",
          "Name": "Execute",
          "Type": "BOOL",
          "Initial": "",
          "Comment": "Start the action at rising edge"
        },
        [
          "WaitTime",
          "LREAL",
          "",
          "The time to wait on the path, in seconds.\nMay not be negative."
        ],
        [
          "Name",
          "STRING",
          "âSMC_GroupWaitâ",
          "The name of the movement."
        ],
        {
          "Scope": "Output",
          "Name": "Done",
          "Type": "BOOL",
          "Initial": "",
          "Comment": "Standstill has been reached"
        },
        [
          "Busy",
          "BOOL",
          "",
          "The FB is not finished"
        ],
        [
          "Active",
          "BOOL",
          "",
          "Indicates that the FB has control on the axis"
        ],
        [
          "CommandAborted",
          "BOOL",
          "",
          "Command is aborted by another command"
        ],
        [
          "CommandAccepted",
          "BOOL",
          "",
          "The command has been accepted by the axis group.\nIf the output becomesTRUE, the function block instance can be used to\ncommand the next movement with a new rising edge onExecute.\nWhile the output isFALSE, keep calling the function block without\na new rising edge ofExecute.\nThe output is reset toFALSEon a falling edge ofExecute."
        ],
        [
          "Error",
          "BOOL",
          "",
          "Signals that an error has occurred within the function block"
        ],
        [
          "ErrorID",
          "SMC_ERROR",
          "",
          "Error identification"
        ],
        [
          "MovementId",
          "SMC_Movement_Id",
          "",
          "The unique identifier of the movement.  Valid ifCommandAcceptedorDoneisTRUE."
        ]
      ]
    }
  ]
}