{
  "library": "SM3_Robotics",
  "title": "MC_GroupReadStatus (FunctionBlock)",
  "url": "https://content.helpme-codesys.com/en/libs/SM3_Robotics/Current/SM3_Robotics/POUs/Diagnostics/MC_GroupReadStatus.html",
  "page_title": "MC_GroupReadStatus (FB)",
  "text": "Library Information\nGetLibVersion (Function)\nGetLibVersionNumber (Function)\nGetVersion (Function)\nIsLibReleased (Function)\nSM3_Robotics\nBasic types\nIDENT_IN_GROUP_REF_SM3 (Alias)\nMC_CIRC_PATHCHOICE (Enum)\nMC_COORD_REF (Struct)\nMC_EXECUTION_MODE (Enum)\nMC_TRANSITION_MODE (Enum)\nSMC_AXIS_GROUP_COMPATIBILITY_OPTIONS (Struct)\nSMC_AXIS_GROUP_CONTINUE_DATA (FunctionBlock)\nSMC_AXIS_GROUP_STATE (Enum)\nSMC_CIRC_MODE (Enum)\nSMC_DYN_LIMITS (Alias)\nSMC_IDynamicCS (Interface)\nSMC_ORIENTATION_MODE (Enum)\nSMC_POS_REF (Union)\nSMC_PTP_MOVEMENT_TYPE (Enum)\nSMC_READ_TOOL_MODE (Enum)\nPOUs\nAdditional\nSMC_AxisDistanceAxes (Enum)\nSMC_AxisDistanceSubMode (Enum)\nSMC_AxisDistanceTransition (FunctionBlock)\nSMC_AxisDistanceTransitionParam (Function)\nSMC_CornerDistance (FunctionBlock)\nSMC_CornerDistanceTransitionParam (Function)\nSMC_StartVelocity (FunctionBlock)\nSMC_StartVelocityAxes (Enum)\nSMC_StartVelocityTransitionParam (Function)\nSMC_StartupAxisGroup (FunctionBlock)\nAdministrative/Configuration\nAxisGroup\nComputation\nCoordinate systems\nDynamics\nKinematics\nTrigger\nAxisGroup\nAXIS_GROUP_REF_SM3 (FunctionBlock)\nHelpers\nMovements\nDiagnostics\nMC_GroupReadActualAcceleration (FunctionBlock)\nMC_GroupReadActualPosition (FunctionBlock)\nMC_GroupReadActualVelocity (FunctionBlock)\nMC_GroupReadConfiguration (FunctionBlock)\nMC_GroupReadError (FunctionBlock)\nMC_GroupReadStatus (FunctionBlock)\nMC_ReadCoordinateTransform (FunctionBlock)\nMC_ReadKinTransform (FunctionBlock)\nSMC_GroupAddOffset (FunctionBlock)\nSMC_GroupAdditionalAxesTargetPositions (FunctionBlock)\nSMC_GroupConvertPosition (FunctionBlock)\nSMC_GroupGetContinuePosition (FunctionBlock)\nSMC_GroupGetContinueToolOffset (FunctionBlock)\nSMC_GroupReadPathAcceleration (FunctionBlock)\nSMC_GroupReadPathDynamics (FunctionBlock)\nSMC_GroupReadPathVelocity (FunctionBlock)\nSMC_GroupReadPlanningStatistics (FunctionBlock)\nSMC_GroupReadPositionInMovement (FunctionBlock)\nSMC_GroupReadRemainingTrajectoryDuration (FunctionBlock)\nSMC_GroupReadSetAcceleration (FunctionBlock)\nSMC_GroupReadSetJerk (FunctionBlock)\nSMC_GroupReadSetPosition (FunctionBlock)\nSMC_GroupReadSetVelocity (FunctionBlock)\nSMC_GroupTargetPosition (FunctionBlock)\nSMC_ReadKinTransformForAxis (FunctionBlock)\nMovement\nAdditionalAxes\nGroupInterrupt\nMC_GroupContinue (FunctionBlock)\nMC_GroupHalt (FunctionBlock)\nMC_GroupInterrupt (FunctionBlock)\nMC_GroupStop (FunctionBlock)\nMC_MoveCircularAbsolute (FunctionBlock)\nMC_MoveCircularRelative (FunctionBlock)\nMC_MoveDirectAbsolute (FunctionBlock)\nMC_MoveDirectRelative (FunctionBlock)\nMC_MoveLinearAbsolute (FunctionBlock)\nMC_MoveLinearRelative (FunctionBlock)\nSMC_GroupEnableResumeAfterError (FunctionBlock)\nSMC_GroupJog (FunctionBlock)\nSMC_GroupJog2 (FunctionBlock)\nSMC_GroupUpdateContinueData (FunctionBlock)\nSMC_GroupWait (FunctionBlock)\nSMC_MoveAdditionalAxes (FunctionBlock)\ninternal\nDivers\nKernel_CP\nFile and Project Information\nLibrary Reference\n3SLicense\nLibrary Identification\nLibrary Properties\nCmpApp\nLibrary Identification\nLibrary Properties\nCmpIecTask\nLibrary Identification\nLibrary Properties\nCmpLog\nLibrary Identification\nLibrary Properties\nFloatingPointUtils\nLibrary Identification\nLibrary Properties\nSM3_Basic\nLibrary Identification\nLibrary Properties\nLibrary Parameter\nSM3_CPKernelDefaults\nLibrary Identification\nLibrary Properties\nLibrary Parameter\nSM3_CommonPublic\nLibrary Identification\nLibrary Properties\nSM3_Dynamics\nLibrary Identification\nLibrary Properties\nSM3_Error\nLibrary Identification\nLibrary Properties\nSM3_RBase\nLibrary Identification\nLibrary Properties\nSM3_RCP\nLibrary Identification\nLibrary Properties\nSM3_RError\nLibrary Identification\nLibrary Properties\nSM3_Ramps\nLibrary Identification\nLibrary Properties\nSM3_Shared\nLibrary Identification\nLibrary Properties\nSM3_StringUtils\nLibrary Identification\nLibrary Properties\nSM3_TrajectoryGeneration\nLibrary Identification\nLibrary Properties\nSM3_Transformation\nLibrary Identification\nLibrary Properties\nStandard\nLibrary Identification\nLibrary Properties\nSysMem\nLibrary Identification\nLibrary Properties\nSysTarget\nLibrary Identification\nLibrary Properties\nSysTime\nLibrary Identification\nLibrary Properties\nSysTypes2 Interfaces\nLibrary Identification\nLibrary Properties\nSM3_Robotics\nDocs\n»\nSM3_Robotics\n»\nPOUs\n»\nDiagnostics\n»\nMC_GroupReadStatus (FB)\nMC_GroupReadStatus (FB)\nÂ¶\nFUNCTION_BLOCK MC_GroupReadStatus\nThis function block returns the status of an axis group.\nInOut:\nScope\nName\nType\nComment\nInout\nAxisGroup\nAXIS_GROUP_REF_SM3\nReference to a group of axes\nInput\nEnable\nBOOL\nGet the status of the axis group continuously while enabled\nOutput\nValid\nBOOL\nTRUE\nif valid outputs are available\nBusy\nBOOL\nThe FB is not finished\nError\nBOOL\nSignals that an error has occurred within the function block\nErrorID\nSMC_ERROR\nError identification\nGroupMoving\nBOOL\nSee\nSMC_Axis_Group_State\nGroupHoming\nBOOL\nSee\nSMC_Axis_Group_State\nGroupErrorStop\nBOOL\nSee\nSMC_Axis_Group_State\nGroupStandby\nBOOL\nSee\nSMC_Axis_Group_State\nGroupStopping\nBOOL\nSee\nSMC_Axis_Group_State\nGroupDisabled\nBOOL\nSee\nSMC_Axis_Group_State\nTrackingDynamicCS\nBOOL\nIf the active movement is commanded using a dynamic coordination system,\nE.g. with\nMC_TrackConveyorBelt\nor\nMC_TrackRotaryTable\n.\nInSync\nBOOL\nIndicates whether the axis group follows the programmed path exactly.\nIf FALSE, the axis group is following the path within the configured\ntolerance.  See\nSMC_GroupSetPathTolerance\n.\nActiveMovementId\nSMC_Movement_Id\nThe identifier of the active movement.  An Id of 0 means\nthat no movement is active.\nDuring blending between two movements, the second movement becomes\nactive as soon as blending starts.\nWhen aborting, the aborting movements becomes active immediately\nafter it has been accepted.\nSee\nFirstReferencedMovementId\nfor additional information.\nActiveMovementName\nSTRING\nThe name of the active movement.\nFirstReferencedMovementId\nSMC_Movement_Id\nThe identifier of the first (i.e. oldest) movement which is still\nbeing referenced by an ongoing movement.\nAn Id of 0 means that no movement is active.\nTo test whether the axis group is fully tracked in to a dynamic\ncoordinate system (or fully tracked out), the condition\nFirstReferencedMovementId = ActiveMovementId can be used.\nLastAcceptedMovementId\nSMC_Movement_Id\nThe identifier of the movement that was last accepted.  An Id of 0 means\nthat no movement has been accepted yet.\nPositionLag\nLREAL\nThe magnitude of the position lag (in position units).  The position lag\nis the deviation of the position of the axis group from the programmed\ntrajectory.\nOrientationLag\nLREAL\nThe magnitude of the orientation lag (in angular degrees).  The orientation\nlag is the deviation of the orientation of the axis group from the programmed\ntrajectory.\nCurrentPlanningForecast\nLREAL\nThe current planning forecast in seconds.  Will be between 0 and the\nfPlanningForecastDuration\nconfigured using\nSMC_TuneCPKernel\n.  While the axis group is moving, should be\nexactly the\nfPlanningForecastDuration\n.  Limited to the remaining trajectory duration\nwhile the axis group is stopping.\nCurrentSyncBufferDuration\nLREAL\nThe current duration of the synchronisation buffer between fieldbus and planning task\nin seconds.  Will be between 0 and the\nfSyncBufferDuration\nconfigured using\nSMC_TuneCPKernel\n.\nThis value must be > 0 while the axis group is moving.  Otherwise, the error\nSMC_CP_QUEUE_UNDERRUN will be reported.",
  "tables": [
    {
      "headers": [
        "Scope",
        "Name",
        "Type",
        "Comment"
      ],
      "rows": [
        {
          "Scope": "Inout",
          "Name": "AxisGroup",
          "Type": "AXIS_GROUP_REF_SM3",
          "Comment": "Reference to a group of axes"
        },
        {
          "Scope": "Input",
          "Name": "Enable",
          "Type": "BOOL",
          "Comment": "Get the status of the axis group continuously while enabled"
        },
        {
          "Scope": "Output",
          "Name": "Valid",
          "Type": "BOOL",
          "Comment": "TRUEif valid outputs are available"
        },
        [
          "Busy",
          "BOOL",
          "The FB is not finished"
        ],
        [
          "Error",
          "BOOL",
          "Signals that an error has occurred within the function block"
        ],
        [
          "ErrorID",
          "SMC_ERROR",
          "Error identification"
        ],
        [
          "GroupMoving",
          "BOOL",
          "SeeSMC_Axis_Group_State"
        ],
        [
          "GroupHoming",
          "BOOL",
          "SeeSMC_Axis_Group_State"
        ],
        [
          "GroupErrorStop",
          "BOOL",
          "SeeSMC_Axis_Group_State"
        ],
        [
          "GroupStandby",
          "BOOL",
          "SeeSMC_Axis_Group_State"
        ],
        [
          "GroupStopping",
          "BOOL",
          "SeeSMC_Axis_Group_State"
        ],
        [
          "GroupDisabled",
          "BOOL",
          "SeeSMC_Axis_Group_State"
        ],
        [
          "TrackingDynamicCS",
          "BOOL",
          "If the active movement is commanded using a dynamic coordination system,\nE.g. withMC_TrackConveyorBeltorMC_TrackRotaryTable."
        ],
        [
          "InSync",
          "BOOL",
          "Indicates whether the axis group follows the programmed path exactly.\nIf FALSE, the axis group is following the path within the configured\ntolerance.  SeeSMC_GroupSetPathTolerance."
        ],
        [
          "ActiveMovementId",
          "SMC_Movement_Id",
          "The identifier of the active movement.  An Id of 0 means\nthat no movement is active.\nDuring blending between two movements, the second movement becomes\nactive as soon as blending starts.\nWhen aborting, the aborting movements becomes active immediately\nafter it has been accepted.\nSeeFirstReferencedMovementIdfor additional information."
        ],
        [
          "ActiveMovementName",
          "STRING",
          "The name of the active movement."
        ],
        [
          "FirstReferencedMovementId",
          "SMC_Movement_Id",
          "The identifier of the first (i.e. oldest) movement which is still\nbeing referenced by an ongoing movement.\nAn Id of 0 means that no movement is active.\nTo test whether the axis group is fully tracked in to a dynamic\ncoordinate system (or fully tracked out), the condition\nFirstReferencedMovementId = ActiveMovementId can be used."
        ],
        [
          "LastAcceptedMovementId",
          "SMC_Movement_Id",
          "The identifier of the movement that was last accepted.  An Id of 0 means\nthat no movement has been accepted yet."
        ],
        [
          "PositionLag",
          "LREAL",
          "The magnitude of the position lag (in position units).  The position lag\nis the deviation of the position of the axis group from the programmed\ntrajectory."
        ],
        [
          "OrientationLag",
          "LREAL",
          "The magnitude of the orientation lag (in angular degrees).  The orientation\nlag is the deviation of the orientation of the axis group from the programmed\ntrajectory."
        ],
        [
          "CurrentPlanningForecast",
          "LREAL",
          "The current planning forecast in seconds.  Will be between 0 and thefPlanningForecastDurationconfigured usingSMC_TuneCPKernel.  While the axis group is moving, should be\nexactly thefPlanningForecastDuration.  Limited to the remaining trajectory duration\nwhile the axis group is stopping."
        ],
        [
          "CurrentSyncBufferDuration",
          "LREAL",
          "The current duration of the synchronisation buffer between fieldbus and planning task\nin seconds.  Will be between 0 and thefSyncBufferDurationconfigured usingSMC_TuneCPKernel.\nThis value must be > 0 while the axis group is moving.  Otherwise, the error\nSMC_CP_QUEUE_UNDERRUN will be reported."
        ]
      ]
    }
  ]
}