{
  "library": "SM3_CNC",
  "title": "SMC_ToolCorr (FunctionBlock)",
  "url": "https://content.helpme-codesys.com/en/libs/SM3_CNC/Current/SM_CNC_POUs/SoftMotion-CNC/SoftMotion-Function-Blocks/SMC_ToolCorr.html",
  "page_title": "SMC_ToolCorr (FB)",
  "text": "GlobalTextList (GlobalTextList)\nImagePool_cnc_sm3 (ImagePool)\nImages\nLibrary Information\nGetLibVersion (Function)\nGetLibVersionNumber (Function)\nIsLibReleased (Function)\nProjektinformationen\nGetBooleanProperty (Function)\nGetCompany (Function)\nGetNumberProperty (Function)\nGetTextProperty (Function)\nGetTextProperty2 (Function)\nGetTitle (Function)\nGetVersion (Function)\nGetVersionProperty (Function)\nSM3_CNC_GetVersion (Function)\nSMC_CNC_LibParams (ParamList)\nSM_CNC_Data types\nFile\nSMC_SINGLEVAR (Struct)\nSMC_TOKENTYPE (Enum)\nSMC_VARLIST (Struct)\nSMC_VARTYPE (Enum)\nSoftMotion CNC\nSMC_ABC_SLOPES_AT_STOP (Enum)\nSMC_ABC_SLOPES_NO_STOP (Enum)\nSMC_ADDAXIS (Enum)\nSMC_AL_STATUS (Enum)\nSMC_CNC_REF (FunctionBlock)\nSMC_DEC_STATUS (Enum)\nSMC_DIRECTION (Enum)\nSMC_GAddress (Alias)\nSMC_GCODEVIEWER_DATA (Struct)\nSMC_GCODE_TEXT (Struct)\nSMC_GCODE_WORD (Struct)\nSMC_GCodeObjectId (Struct)\nSMC_GEOINFO (Struct)\nSMC_GWord (Struct)\nSMC_INT_STATUS (Enum)\nSMC_INT_VELMODE (Enum)\nSMC_LINE_3D (Struct)\nSMC_MOVTYP (Enum)\nSMC_M_PARAMETERS (Struct)\nSMC_OBJECTSPLITTERMODE (Enum)\nSMC_ORI_CONVENTION (Enum)\nSMC_OUTQUEUE (FunctionBlock)\nbFull (Property)\nSMC_PLANE_H (Struct)\nSMC_POSINFO (Struct)\nSMC_SEGMENT (Struct)\nSMC_SEGMENTTYPE (Enum)\nSMC_SMOOTHBSPLINE_MODE (Enum)\nSMC_SMOOTHPATHADDAXMODE (Enum)\nSMC_SMOOTHPATHMODE (Enum)\nSMC_Seg (Struct)\nSMC_TC_STATUS (Enum)\nSMC_TOOLCORRMODE (Enum)\nSMC_VECTOR6D (Struct)\nSM_CNC_POUs\nFile\nReadNCFile\nSMC_ReadNCFile (FunctionBlock)\nStream\nToken\nSMC_ReadNCQueue (FunctionBlock)\nCloseFile (Action)\nhelp functions\nSMC_StringBuffer (FunctionBlock)\nNC2\nGSentence\nSMC_GExpToken_Iterator (FunctionBlock)\nSMC_GJUMP_COMMAND (Enum)\nSMC_GJUMP_TARGET (Union)\nSMC_GSentence (Struct)\nSMC_GSentenceQueue (FunctionBlock)\nSMC_GSentence_DynCall (Struct)\nSMC_GSentence_GWords (Struct)\nSMC_GSentence_GWords_Create (Function)\nSMC_GSentence_Iterator (FunctionBlock)\nSMC_GSentence_Let (Struct)\nSMC_GSentence_SubCall (Struct)\nSMC_GSentence_SubRet (Struct)\nSMC_GSentence_Type (Enum)\nSMC_GSentence_Union (Union)\nSMC_GVarDecl (Struct)\nSMC_GVar_Type (Enum)\nSMC_GWord_Iterator (FunctionBlock)\nSMC_NC_CopySentence (Function)\nSMC_NC_CopySentenceChecked (Function)\nGSentenceJumpBuffer\nSMC_GSentenceJumpBuffer (FunctionBlock)\nInterpreter\nCallstack\nSMC_NCInterpreter (FunctionBlock)\nParser\nExpressions\nSMC_NCTokenParser (FunctionBlock)\nSMC_NC_SourcePosition (Struct)\nSymbolTable\nReadNCFile2\nSMC_IGSentenceModifier (Interface)\nSMC_INCLookup (Interface)\nSMC_ITokenModifier (Interface)\nSMC_NCLookupFile (FunctionBlock)\nSMC_NCNavigator (FunctionBlock)\nSMC_NC_CanProcessTokens (Function)\nSMC_NC_FindProgramFile (Function)\nSMC_NC_PrependDefaults (FunctionBlock)\nSMC_NC_TokenQueue_Completed (Function)\nSMC_ReadNCFile2 (FunctionBlock)\nSMC_ReadNCFromStream (FunctionBlock)\nSoftMotion CNC\nCoordinate Transformations\nSMC_CoordinateTransformation3D (FunctionBlock)\nSMC_DetermineCuboidBearing (FunctionBlock)\nSMC_InvCoordinateTransformation3D (FunctionBlock)\nSMC_TeachCoordinateSystem (FunctionBlock)\nSMC_UnitVectorToRPY (FunctionBlock)\nDirect Axis Control\nSMC_ControlAxisByPos (FunctionBlock)\nSMC_ControlAxisByPosVel (FunctionBlock)\nSMC_ControlAxisByVel (FunctionBlock)\nGCode Viewer\nSMC_GCodeViewer (FunctionBlock)\nGeoInfo Help Functions\nSMC_AdaptHelpMarks (Function)\nSMC_CalcEndPnt (Function)\nSMC_CalcLengthGeo (Function)\nSMC_CalcStartPnt (Function)\nSMC_CutEnd (Function)\nSMC_CutStart (Function)\nSMC_GeoinfoInit (Function)\nSMC_GetAccVec (Function)\nSMC_GetAddAxValue (Function)\nSMC_GetClosestPnt (Function)\nSMC_GetLengthOfPrefix (Function)\nSMC_GetPnt (Function)\nSMC_GetPntPI (Function)\nSMC_GetTanVec (Function)\nSMC_GetTanVec3D (Function)\nSMC_InvertDirection (Function)\nSMC_RampInCorr (Function)\nSMC_RampOutCorr (Function)\nSMC_RecalculateHelpMarks (Function)\nSMC_SingleCorr (Function)\nOutQueue Functions\nSMC_AppendObj (Function)\nSMC_DeleteObj (Function)\nSMC_GetCount (Function)\nSMC_GetHistoryCount (Function)\nSMC_GetLastObj (Function)\nSMC_GetObj (Function)\nSMC_GetObjFromEnd (Function)\nSMC_GetObjFromHistory (Function)\nSMC_OutQueueInit (Function)\nSMC_OutQueueIsSyncing (Function)\nSMC_OutQueue_IsFull (Function)\nSMC_RestoreQueue (Function)\nSMC_SetObj (Function)\nSMC_SetQueueCapacity (Function)\nPosinfo Functions\nSMC_PosInfo_Trf_Inverse (Function)\nSMC_PosInfo_Trf_Mult (Function)\nQueue manipulation\nSMC_QueueSetReservedEntries (FunctionBlock)\nSMC_RotateQueue2D (FunctionBlock)\nSMC_ScaleQueue3D (FunctionBlock)\nSMC_TranslateQueue3D (FunctionBlock)\nSoftMotion Function Blocks\nBlockSearch\nDecoderBuffer\nInterpolator_Help_Functions\nM_Functions\nNCDecoder_Help_Functions\nSMC_AddGCodeState (Struct)\nSMC_AvoidLoop (FunctionBlock)\nSMC_CheckForLimits (FunctionBlock)\nSMC_CheckVelocities (FunctionBlock)\nSMC_ExtendedVelocityChecks (FunctionBlock)\nSMC_Interpolator (FunctionBlock)\nSMC_Interpolator2Dir (FunctionBlock)\nSMC_Interpolator2Dir_SlowTask (FunctionBlock)\nSMC_LimitCircularVelocity (FunctionBlock)\nSMC_LimitDynamics (FunctionBlock)\nSMC_NCDecoder (FunctionBlock)\nSMC_ObjectSplitter (FunctionBlock)\nSMC_ReadAdditionalIpoState (FunctionBlock)\nSMC_RecomputeABCSlopes (FunctionBlock)\nSMC_ReduceVelEndAtCorner (FunctionBlock)\nSMC_RoundPath (FunctionBlock)\nSMC_SegmentAnalyzer (FunctionBlock)\nSMC_SetInterpreterStartPosition (FunctionBlock)\nSMC_SmoothAddAxes (FunctionBlock)\nSMC_SmoothBSpline (FunctionBlock)\nSMC_SmoothMerge (FunctionBlock)\nSMC_SmoothPath (FunctionBlock)\nSMC_ToolCorr (FunctionBlock)\nSMC_ToolLengthCorr (FunctionBlock)\nSMC_ToolRadiusCorr (FunctionBlock)\nSMC_XInterpolator (FunctionBlock)\nSM_Trafo_Data types\nSMC_ArticulatedRobot_6DOF_J0_State (Enum)\nSMC_ArticulatedRobot_6DOF_J1_State (Enum)\nSMC_ArticulatedRobot_6DOF_J4_State (Enum)\nSMC_TrafoConfig_4AxisPalletizer (Struct)\nSMC_TrafoConfig_ArticulatedRobot_6DOF (Struct)\nSMC_TrafoResult_4AxisPalletizer (Enum)\nSMC_TrafoResult_ArticulatedRobot_6DOF (Enum)\nSMC_VECTORDIR (Enum)\nSM_Trafo_POUs\nForward and inverse transformation\nSMC_TRAFOV_\nSoftMotion Transformations\nGantry systems\nParallel Systems\nRobot Kinematiks\nScara System\nWrapper\nadditional FBs\nVisu_Templates\nFile\nCNC\nSM_CNC_Visualizations\nFBs\nCNC\nDirect Axis Control\nTranslation & Rotation & Scaling\nhelp visu\nSM_Trafo_Visualizations\nTrafo templates\nGantry\nParallel\nRobot\nScara\nVisu_Templates_New\nFramed Visu Helpers\nTextListForCombobox_MC_DIRECTION (TextList)\nTextListForCombobox_SMC_ABC_SLOPES_AT_STOP (TextList)\nTextListForCombobox_SMC_ABC_SLOPES_NO_STOP (TextList)\nTextListForCombobox_SMC_AL_STATUS (TextList)\nTextListForCombobox_SMC_DEC_STATUS (TextList)\nTextListForCombobox_SMC_DIRECTION (TextList)\nTextListForCombobox_SMC_ERROR (TextList)\nTextListForCombobox_SMC_INT_STATUS (TextList)\nTextListForCombobox_SMC_INT_VELMODE (TextList)\nTextListForCombobox_SMC_ORI_CONVENTION (TextList)\nTextListForCombobox_SMC_SMOOTHBSPLINE_MODE (TextList)\nTextListForCombobox_SMC_SMOOTHPATHADDAXMODE (TextList)\nTextListForCombobox_SMC_SMOOTHPATHMODE (TextList)\nTextListForCombobox_SMC_TC_STATUS (TextList)\nTextListForCombobox_SMC_TOOLCORRMODE (TextList)\nFile and Project Information\nLibrary Reference\n3SLicense\nLibrary Identification\nLibrary Properties\nBase Interfaces\nLibrary Identification\nLibrary Properties\nCmpLog\nLibrary Identification\nLibrary Properties\nFloatingPointUtils\nLibrary Identification\nLibrary Properties\nMatrix\nLibrary Identification\nLibrary Properties\nSM3_Basic\nLibrary Identification\nLibrary Properties\nLibrary Parameter\nSM3_RBase\nLibrary Identification\nLibrary Properties\nSM3_Shared\nLibrary Identification\nLibrary Properties\nSM3_Transformation\nLibrary Identification\nLibrary Properties\nStandard\nLibrary Identification\nLibrary Properties\nSysFile\nLibrary Identification\nLibrary Properties\nSysMem\nLibrary Identification\nLibrary Properties\nSysTarget\nLibrary Identification\nLibrary Properties\nSysTypes2 Interfaces\nLibrary Identification\nLibrary Properties\nVisuElem3DPath\nLibrary Identification\nLibrary Properties\nLibrary Parameter\nVisuElemCamDisplayer\nLibrary Identification\nLibrary Properties\nLibrary Parameter\nVisuElemMeter\nLibrary Identification\nLibrary Properties\nVisuElemTextEditor\nLibrary Identification\nLibrary Properties\nVisuElemTrace\nLibrary Identification\nLibrary Properties\nVisuElems\nLibrary Identification\nLibrary Properties\nVisuElemsAlarm\nLibrary Identification\nLibrary Properties\nVisuElemsDateTime\nLibrary Identification\nLibrary Properties\nVisuElemsSpecialControls\nLibrary Identification\nLibrary Properties\nVisuElemsWinControls\nLibrary Identification\nLibrary Properties\nVisuInputs\nLibrary Identification\nLibrary Properties\nVisuNativeControl\nLibrary Identification\nLibrary Properties\nSM3_CNC\nDocs\n»\nSM_CNC_POUs\n»\nSoftMotion\nCNC\n»\nSoftMotion\nFunction\nBlocks\n»\nSMC_ToolCorr (FB)\nSMC_ToolCorr (FB)\nÂ¶\nFUNCTION_BLOCK SMC_ToolCorr\nThis function block is replaced by\nSMC_ToolRadiusCorr\n.\nSMC_ToolCorr\ncreates a shifted path.\nIn the shifted path each point has a defined distance to\nthe original point (tool radius correction).\nA typical application is the milling of a programmed contour with a\nmilling drill of a certain diameter. In order to compensate the radius of the\ndrill, the milling drill must follow a shifted path.\nNote\nThe shifted path may contain self-intersections or loops\nThat would mean that the desired contour would be destroyed\nduring passing the shifted path. (See the example below.)\nTo avoid such intersections, use\nSMC_AvoidLoop\n.\nProceeding of SMC_ToolCorr\nAll SMC_GEOINFO objects found in the Input\nSMC_OUTQUEUE\nstructure\nwill be checked one after the other.\nIf Bit1 (Bit2) of the variable\nIntern_Mark\nis set in one of these objects,\nthen starting from there â in direction of motion - the path will be\nshifted to the left (right) by the currently set tool radius.\nIn order to get a continuous path the input\neMode\nhave to set\non one the desired mode:\nTC_RAMP_IN\n: this mode is used to ramp into the offset path,\nwhich means that the start position stays unchanged, but the\nend position is offset. All further objects are offset as well until the\ntool radius correction is switched off by setting Bit0 of\nIntern_Mark\n.\nThen, the start position of the object is still offset, but the\nend position is the original one.\nTC_BLIND_POS\n: this mode is used for insetting a positioning object\n(SMC_GEOINFO.iMoveType = 100), resp. if such a positioning object is\nalready preceding the object. It will be shifted directly to the\nstart point of the shifted path. Each further object will then be\noffset as well, until Bit0 of\nIntern_Mark\ngets set, what will stop\nthe tool radius correction. A further positioning object will be\ninserted.\nSMC_NCDecoder\nwill set these bits in reaction on the instructions G41/G42/G40.\nIn other words: The tool radius correction will be done for all objects\nlocated between the instructions G41 and G40 resp. G42 and G40.\nExample 1: Simple tool correction\nG-Code:\nN0 G0 X10 Y-10 F10 E100 E-100\nN1 G41 D10\nN2 G1 X20 Y-10\nN2 G1 X30 Y-10\nCNC path without tool correction:\nCNC path with tool correction, eMode=TC_BLIND_POS:\nExample 2: Tool correction with eMode=TC_BLIND_POS\nG-Code\nN000 G41 D1 (WRK an)\nN010 G00 X3 F100 E1000 E-1000\nN020 G01 X5 Y10\nN030 G01 X7 Y10\nN040 G01 X10 Y0\nN050 G00 X20\nN060 G40 (WRK off)\nIn the example above the element in sentence N010 ramps in the shifted path.\nThe element in sentence N050 is used for ramping out. The following figure shows\nthe CNC path with tool correction and\neMode=TC_BLIND_POS\n:\nIt is highly recommended, that the first and last element in the parenthesis is\na positioning element (G0). If this is not the case, the first move is to the\noriginal starting point of the object, and the next move is to the offset start point.\nExample 3: Tool correction with eMode=TC_RAMP_IN\nG-Code\n% G-code RampIn and Rampout in radius correction\nN0 G0 X10.0 Y-15.0 F10.0 E100 E-100.0\nN1 G41 D10.0\nN2 G1 X20.0 Y-15.0 (RampIn)\nN3 G1 X30.0 Y-15\nN4 G40\nN5 G1 X40.0 Y-15.0 (RampOut)\nCondition for RampIn and RampOut is a linear movement (G1 in sentence N1 and sentence N5).\nThe following figure shows the CNC path with radius correction\neMode=TC_RAMP_IN\n:\nExample 4: Tool correction with eMode=TC_RAMP_IN\nG-Code\nN000 G41 D3 (WRK an)\nN010 G01 X3 Y10 F100 E1000 E-1000\nN020 G01 X7 Y10\nN030 G01 X10 Y0\nN040 G40 (WRK off)\nN050 G01 X20\nIn the example above the element in sentence N010 ramps in the shifted path. The\nelement in sentence N050 is used for ramping out.\nNote the first element inside the G41/G40 parenthesis is used for ramping in and\nthe next is used for ramping out and must be a line (G01).\nExample 5: Milling a contour with a milling drill moved in Z-direction\nG-Code\n(First section)\nN000 G41 D1 (WRK on) F100 E1000 E-1000\nN010 G00 X3\nN020 G01 Z10\nN030 G01 X5 Y10 (Beginning of the milling contour)\nN040 G01 X7 Y10\nN050 G01 X10 Y0 (End of the milling contour)\nN060 G01 Z0\nN070 G40 (WRK off)\nN080 G00 X20\n(Second section)\nN080 G42 D1 (WRK on)\nN090 G00 X23\nN100 G01 Z10\nN110 G01 X25 Y10\nN120 G01 X27 Y10\nN130 G01 X30 Y0\nN140 G01 Z0\nN150 G40 (WRK off)\nN160 G00 X40\nThe example above shows the using of the tool radius correction (WRK) together\nwith the cutter positioning in Z-direction. The mode is set to\nBLIND_POS\n.\nThe first element in the G41/G42-G40 parenthesis is to be a positioning to the\nstart point of the contour. The next step is the positioning of the shaping tool\nin Z. Then the contour starts. At last the Z-axis is positioned off the workpiece\nand the tool radius correction is turned off. The second section of the example\nshows a tool radius correction in another direction. The following figure shows\nthe milling CNC path along the Z-axis:\nInOut:\nScope\nName\nType\nInitial\nComment\nInput\nbExecute\nBOOL\nStarts on rising edge.\nbAbort\nBOOL\nIf\nTRUE\n, the current processing of this function block\nis aborted\nbAppend\nBOOL\nAs long as this input remains\nFALSE\n, the DataOutQueue will be\ncleared at each reset.\nAs long as it remains\nTRUE\n, newly incoming data will be written\nto the end of the DataOutQueue.\npoqDataIn\nPOINTER TO\nSMC_OUTQUEUE\nThe input path queue.\ndToolRadius\nLREAL\nThis variable contains the value, which â added to the current ToolRadius\nof the\nSMC_GEOINFO\nobject â  will determine the tool radius by which\nthe path is to be shifted (see above). This value can be modified online.\nThus it is possible to predefine the value offline\n(by the\nSMC_GEOINFO\nstructure) and to modulate it online.\nNote that a tool radius correction that gets initiated during a shift\nof the block will cause the abort of the path correction and therefore\nshould be avoided! But it is possible to do the radius correction\nduring a reset or within a phase guaranteeing that the module is not\ncurrently shifting a block (\nStatus\n=\nTC_ORIG\n). Default-Value: 0.\nnSizeOutQueue\nUDINT\nThis variable contains the size of the data buffer, the list of\nSMC_GEOINFO\nstructure objects will be written to.\nThis buffer must be at least five times as big as a\nSMC_GEOINFO\nstructure\nitself. Otherwise,\nSMC_NCDecoder\nwill not execute any actions at all.\nIts size may be predefined, but may be modified later only during a reset.\nIt is recommended to create the buffer as described by the example below.\nExampleBuf:\nArray[1..50]\nof\nSMC_GeoInfo\n.\nThe correct buffer size will then be retrieved by use of the\noperator\nsizeof(ExampleBuf)\n.\npbyBufferOutQueue\nPOINTER TO ARRAY [0..0]\nOF SMC_GEOINFO\nThis input must point to the first byte of the memory area that is\nallocated for the\nSMC_OUTQUEUE\nstructure.\nThis area must be at least as big as defined in\nnSizeOutQueue\n.\nTypically the allocation of the memory buffer is done in the declaration\npart of the IEC-program by defining an array of\nSMC_GEOINFO\n(for example\nBUF:\nARRAY[1..50]\nOF\nSMC_GEOINFO;\nfor a buffer that can store 50 path elements).\nThe value may be predefined, but may be modified later on\nonly during a reset.\neMode\nSMC_TOOLCORRMODE\nTC_RAMP_IN\nMode that defines the transition between offset and non-\noffset path.\nOutput\nbDone\nBOOL\nThis variable is be set to\nTRUE\nas soon as the input path\nhas been processed completely.\nThe function block does not perform any further actions\nuntil it gets a reset.\nbBusy\nBOOL\nTRUE\n, while execution of function block is not finished\nbError\nBOOL\nSignals, that an error has occurred within the function\nblock\nwErrorID\nSMC_ERROR\nError identification\npoqDataOut\nPOINTER TO\nSMC_OUTQUEUE\nThis variable points to the\nSMC_OUTQUEUE\nstructure that manages\nthe decoded\nSMC_GEOINFO\nobjects.\niStatus\nSMC_TC_STATUS\nTC_ORIG\nShows the current status of the module.\nTC_ORIG\n(0): No tool radius correction at the object.\nTC_RIGHT\n(1): Shift objects to the right.\nTC_LEFT\n(2): Shift objects to the left.\nTC_END\n(4): Processing of the objects is terminated.\nStructure:\nSMC_DoBeforeLeave (Action)\nSMC_ToolCorrInit (Action)",
  "tables": [
    {
      "headers": [
        "Scope",
        "Name",
        "Type",
        "Initial",
        "Comment"
      ],
      "rows": [
        {
          "Scope": "Input",
          "Name": "bExecute",
          "Type": "BOOL",
          "Initial": "",
          "Comment": "Starts on rising edge."
        },
        [
          "bAbort",
          "BOOL",
          "",
          "IfTRUE, the current processing of this function block\nis aborted"
        ],
        [
          "bAppend",
          "BOOL",
          "",
          "As long as this input remainsFALSE, the DataOutQueue will be\ncleared at each reset.\nAs long as it remainsTRUE, newly incoming data will be written\nto the end of the DataOutQueue."
        ],
        [
          "poqDataIn",
          "POINTER TOSMC_OUTQUEUE",
          "",
          "The input path queue."
        ],
        [
          "dToolRadius",
          "LREAL",
          "",
          "This variable contains the value, which â added to the current ToolRadius\nof theSMC_GEOINFOobject â  will determine the tool radius by which\nthe path is to be shifted (see above). This value can be modified online.\nThus it is possible to predefine the value offline\n(by theSMC_GEOINFOstructure) and to modulate it online.\nNote that a tool radius correction that gets initiated during a shift\nof the block will cause the abort of the path correction and therefore\nshould be avoided! But it is possible to do the radius correction\nduring a reset or within a phase guaranteeing that the module is not\ncurrently shifting a block (Status=TC_ORIG). Default-Value: 0."
        ],
        [
          "nSizeOutQueue",
          "UDINT",
          "",
          "This variable contains the size of the data buffer, the list ofSMC_GEOINFOstructure objects will be written to.\nThis buffer must be at least five times as big as aSMC_GEOINFOstructure\nitself. Otherwise,SMC_NCDecoderwill not execute any actions at all.\nIts size may be predefined, but may be modified later only during a reset.\nIt is recommended to create the buffer as described by the example below.ExampleBuf:Array[1..50]ofSMC_GeoInfo.The correct buffer size will then be retrieved by use of the\noperatorsizeof(ExampleBuf)."
        ],
        [
          "pbyBufferOutQueue",
          "POINTER TO ARRAY [0..0]\nOF SMC_GEOINFO",
          "",
          "This input must point to the first byte of the memory area that is\nallocated for theSMC_OUTQUEUEstructure.\nThis area must be at least as big as defined innSizeOutQueue.\nTypically the allocation of the memory buffer is done in the declaration\npart of the IEC-program by defining an array ofSMC_GEOINFO(for exampleBUF:ARRAY[1..50]OFSMC_GEOINFO;for a buffer that can store 50 path elements).\nThe value may be predefined, but may be modified later on\nonly during a reset."
        ],
        [
          "eMode",
          "SMC_TOOLCORRMODE",
          "TC_RAMP_IN",
          "Mode that defines the transition between offset and non-\noffset path."
        ],
        {
          "Scope": "Output",
          "Name": "bDone",
          "Type": "BOOL",
          "Initial": "",
          "Comment": "This variable is be set toTRUEas soon as the input path\nhas been processed completely.\nThe function block does not perform any further actions\nuntil it gets a reset."
        },
        [
          "bBusy",
          "BOOL",
          "",
          "TRUE, while execution of function block is not finished"
        ],
        [
          "bError",
          "BOOL",
          "",
          "Signals, that an error has occurred within the function\nblock"
        ],
        [
          "wErrorID",
          "SMC_ERROR",
          "",
          "Error identification"
        ],
        [
          "poqDataOut",
          "POINTER TOSMC_OUTQUEUE",
          "",
          "This variable points to theSMC_OUTQUEUEstructure that manages\nthe decodedSMC_GEOINFOobjects."
        ],
        [
          "iStatus",
          "SMC_TC_STATUS",
          "TC_ORIG",
          "Shows the current status of the module.TC_ORIG(0): No tool radius correction at the object.TC_RIGHT(1): Shift objects to the right.TC_LEFT(2): Shift objects to the left.TC_END(4): Processing of the objects is terminated."
        ]
      ]
    }
  ]
}