{
  "library": "SM3_Robotics",
  "title": "SMC_GroupJog (FunctionBlock)",
  "url": "https://content.helpme-codesys.com/en/libs/SM3_Robotics/Current/SM3_Robotics/POUs/Movement/SMC_GroupJog.html",
  "page_title": "SMC_GroupJog (FB)",
  "text": "Library Information\nGetLibVersion (Function)\nGetLibVersionNumber (Function)\nGetVersion (Function)\nIsLibReleased (Function)\nSM3_Robotics\nBasic types\nIDENT_IN_GROUP_REF_SM3 (Alias)\nMC_CIRC_PATHCHOICE (Enum)\nMC_COORD_REF (Struct)\nMC_EXECUTION_MODE (Enum)\nMC_TRANSITION_MODE (Enum)\nSMC_AXIS_GROUP_COMPATIBILITY_OPTIONS (Struct)\nSMC_AXIS_GROUP_CONTINUE_DATA (FunctionBlock)\nSMC_AXIS_GROUP_STATE (Enum)\nSMC_CIRC_MODE (Enum)\nSMC_DYN_LIMITS (Alias)\nSMC_IDynamicCS (Interface)\nSMC_ORIENTATION_MODE (Enum)\nSMC_POS_REF (Union)\nSMC_PTP_MOVEMENT_TYPE (Enum)\nSMC_READ_TOOL_MODE (Enum)\nPOUs\nAdditional\nSMC_AxisDistanceAxes (Enum)\nSMC_AxisDistanceSubMode (Enum)\nSMC_AxisDistanceTransition (FunctionBlock)\nSMC_AxisDistanceTransitionParam (Function)\nSMC_CornerDistance (FunctionBlock)\nSMC_CornerDistanceTransitionParam (Function)\nSMC_StartVelocity (FunctionBlock)\nSMC_StartVelocityAxes (Enum)\nSMC_StartVelocityTransitionParam (Function)\nSMC_StartupAxisGroup (FunctionBlock)\nAdministrative/Configuration\nAxisGroup\nComputation\nCoordinate systems\nDynamics\nKinematics\nTrigger\nAxisGroup\nAXIS_GROUP_REF_SM3 (FunctionBlock)\nHelpers\nMovements\nDiagnostics\nMC_GroupReadActualAcceleration (FunctionBlock)\nMC_GroupReadActualPosition (FunctionBlock)\nMC_GroupReadActualVelocity (FunctionBlock)\nMC_GroupReadConfiguration (FunctionBlock)\nMC_GroupReadError (FunctionBlock)\nMC_GroupReadStatus (FunctionBlock)\nMC_ReadCoordinateTransform (FunctionBlock)\nMC_ReadKinTransform (FunctionBlock)\nSMC_GroupAddOffset (FunctionBlock)\nSMC_GroupAdditionalAxesTargetPositions (FunctionBlock)\nSMC_GroupConvertPosition (FunctionBlock)\nSMC_GroupGetContinuePosition (FunctionBlock)\nSMC_GroupGetContinueToolOffset (FunctionBlock)\nSMC_GroupReadPathAcceleration (FunctionBlock)\nSMC_GroupReadPathDynamics (FunctionBlock)\nSMC_GroupReadPathVelocity (FunctionBlock)\nSMC_GroupReadPlanningStatistics (FunctionBlock)\nSMC_GroupReadPositionInMovement (FunctionBlock)\nSMC_GroupReadRemainingTrajectoryDuration (FunctionBlock)\nSMC_GroupReadSetAcceleration (FunctionBlock)\nSMC_GroupReadSetJerk (FunctionBlock)\nSMC_GroupReadSetPosition (FunctionBlock)\nSMC_GroupReadSetVelocity (FunctionBlock)\nSMC_GroupTargetPosition (FunctionBlock)\nSMC_ReadKinTransformForAxis (FunctionBlock)\nMovement\nAdditionalAxes\nGroupInterrupt\nMC_GroupContinue (FunctionBlock)\nMC_GroupHalt (FunctionBlock)\nMC_GroupInterrupt (FunctionBlock)\nMC_GroupStop (FunctionBlock)\nMC_MoveCircularAbsolute (FunctionBlock)\nMC_MoveCircularRelative (FunctionBlock)\nMC_MoveDirectAbsolute (FunctionBlock)\nMC_MoveDirectRelative (FunctionBlock)\nMC_MoveLinearAbsolute (FunctionBlock)\nMC_MoveLinearRelative (FunctionBlock)\nSMC_GroupEnableResumeAfterError (FunctionBlock)\nSMC_GroupJog (FunctionBlock)\nSMC_GroupJog2 (FunctionBlock)\nSMC_GroupUpdateContinueData (FunctionBlock)\nSMC_GroupWait (FunctionBlock)\nSMC_MoveAdditionalAxes (FunctionBlock)\ninternal\nDivers\nKernel_CP\nFile and Project Information\nLibrary Reference\n3SLicense\nLibrary Identification\nLibrary Properties\nCmpApp\nLibrary Identification\nLibrary Properties\nCmpIecTask\nLibrary Identification\nLibrary Properties\nCmpLog\nLibrary Identification\nLibrary Properties\nFloatingPointUtils\nLibrary Identification\nLibrary Properties\nSM3_Basic\nLibrary Identification\nLibrary Properties\nLibrary Parameter\nSM3_CPKernelDefaults\nLibrary Identification\nLibrary Properties\nLibrary Parameter\nSM3_CommonPublic\nLibrary Identification\nLibrary Properties\nSM3_Dynamics\nLibrary Identification\nLibrary Properties\nSM3_Error\nLibrary Identification\nLibrary Properties\nSM3_RBase\nLibrary Identification\nLibrary Properties\nSM3_RCP\nLibrary Identification\nLibrary Properties\nSM3_RError\nLibrary Identification\nLibrary Properties\nSM3_Ramps\nLibrary Identification\nLibrary Properties\nSM3_Shared\nLibrary Identification\nLibrary Properties\nSM3_StringUtils\nLibrary Identification\nLibrary Properties\nSM3_TrajectoryGeneration\nLibrary Identification\nLibrary Properties\nSM3_Transformation\nLibrary Identification\nLibrary Properties\nStandard\nLibrary Identification\nLibrary Properties\nSysMem\nLibrary Identification\nLibrary Properties\nSysTarget\nLibrary Identification\nLibrary Properties\nSysTime\nLibrary Identification\nLibrary Properties\nSysTypes2 Interfaces\nLibrary Identification\nLibrary Properties\nSM3_Robotics\nDocs\n»\nSM3_Robotics\n»\nPOUs\n»\nMovement\n»\nSMC_GroupJog (FB)\nSMC_GroupJog (FB)\nÂ¶\nFUNCTION_BLOCK SMC_GroupJog\nThis function block has been deprecated.\nPlease donât use it in new projects. See\nSMC_GroupJog2\nfor the\nrecommended way to jog an axis group.\nWarning\nWith SoftMotion version 4.11.0.0, the support for input ABC_as_ACS has\nbeen dropped.  Please change to\nSMC_GroupJog2\nif this feature is\nrequired.\nActivates coordinated jogging of the axis group.\nWhen this function block is active, the axis group tracks\nthe position (and orientation) given by the axes connected to\nthe inputs AxisX, AxisY, AxisZ, AxisA, AxisB, and AxisC.\nInitially, a movement to the current position of the\naxes is commanded.  Once this movement is done, the output\nInitialPositionReached\nis TRUE.\nThe position of the axes is interpreted in the coordinate system\ndefined by input\nCoordSystem\n.  To jog in machine coordinates,\nfor example, use MCS here.\nSince the position is followed via tracking, one of the product\ncoordinate systems is used for this purpose.  This can be\nconfigured in input\nCoordSystemPCS\n.  Note that this coordinate\nsystem of the axis group is changed.\nTo perform cartesian jogging, the function blocks\nMC_Jog\nor\nSMC_Inch\ncan be used on the axes given as inputs to this\nfunction block.  It is recommended to call the movement function blocks\nof the virtual axes _before_ SMC_GroupJog.\nBefore restarting this FB without changing CoordSystemPCS,\nyou have to command an additional movement, like\nMC_GroupHalt\n.\nOtherwise, error SMC_AXIS_GROUP_PCS_STILL_IN_USE is returned.\nCompared to\nSMC_GroupJog2\n, this function block has several disadvantages:\nThe input ABC_as_ACS is no longer supported (since SoftMotion 4.11.0.0).\nIt requires virtual axes for all jogged coordinates.\nIf the robot cannot follow the configured jogging velocity,\njogging may leave the straight-line path, or move the TCP temporarily\neven if only the orientation is being jogged.\nA path override commanded with\nMC_GroupSetOverride\ndoes not affect\n(cartesian) jogging.\nInOut:\nScope\nName\nType\nInitial\nComment\nInout\nAxisGroup\nAXIS_GROUP_REF_SM3\nReference to a group of axes\nInput\nExecute\nBOOL\nStart the action at the rising edge\nCoordSystem\nSMC_COORD_SYSTEM\nThe coordinate system in which the axis group is jogged.\nCoordSystemPCS\nSMC_COORD_SYSTEM\nThe coordinate system used internally for the jogging.\nMust be a PCS.  This coordinate system is changed\nusing\nSMC_SetDynCoordTransformEx\n.\nVelFactor\nLREAL\n1\nThe maximum velocity of each axis is multiplied by this\nfactor, which must be in the range ]0, 1].\nAccFactor\nLREAL\n1\nThe maximum acceleration of each axis is multiplied by this\nfactor, which must be in the range ]0, 1].\nJerkFactor\nLREAL\n1\nThe maximum jerk of each axis is multiplied by this factor,\nwhich must be in the range ]0, 1].\nAxisX\nIAxisRef\nThe axis controlling the x-coordinate of the configured coordinate\nsystem or the first axis of the axis group in case of ACS.\nAxisY\nIAxisRef\nThe axis controlling the y-coordinate of the configured coordinate\nsystem or the second axis of the axis group in case of ACS. Set to 0 if not\napplicable.\nAxisZ\nIAxisRef\nThe axis controlling the z-coordinate of the configured coordinate\nsystem or the third axis of the axis group in case of ACS. Set to 0 if not\napplicable.\nAxisA\nIAxisRef\nThis axis controls\nthe fourth axis of the axis group, if the coordinate system is ACS or\nthe rotation around the x-axis of the configured cartesian coordinate\nsystem otherwise.\nSet to 0 if not applicable.\nAxisB\nIAxisRef\nThis axis controls\nthe fifth axis of the axis group, if the coordinate system is ACS or\nthe rotation around the y-axis of the configured cartesian coordinate\nsystem otherwise.\nSet to 0 if not applicable.\nAxisC\nIAxisRef\nThis axis controls\nthe sixth axis of the axis group, if the coordinate system is ACS or\nthe rotation around the z-axis of the configured cartesian coordinate\nsystem otherwise.\nSet to 0 if not applicable.\nABC_as_ACS\nBOOL\nThis input is no longer supported.\nOutput\nBusy\nBOOL\nThe FB is not finished\nInitialPositionReached\nBOOL\nThe position given by AxisX, â¦, AxisC has been reached initially, after the\nrising edge of Execute.\nCommandAborted\nBOOL\nCommand is aborted by another command\nError\nBOOL\nSignals that an error has occurred within the function block\nErrorID\nSMC_ERROR\nError identification",
  "tables": [
    {
      "headers": [
        "Scope",
        "Name",
        "Type",
        "Initial",
        "Comment"
      ],
      "rows": [
        {
          "Scope": "Inout",
          "Name": "AxisGroup",
          "Type": "AXIS_GROUP_REF_SM3",
          "Initial": "",
          "Comment": "Reference to a group of axes"
        },
        {
          "Scope": "Input",
          "Name": "Execute",
          "Type": "BOOL",
          "Initial": "",
          "Comment": "Start the action at the rising edge"
        },
        [
          "CoordSystem",
          "SMC_COORD_SYSTEM",
          "",
          "The coordinate system in which the axis group is jogged."
        ],
        [
          "CoordSystemPCS",
          "SMC_COORD_SYSTEM",
          "",
          "The coordinate system used internally for the jogging.\nMust be a PCS.  This coordinate system is changed\nusingSMC_SetDynCoordTransformEx."
        ],
        [
          "VelFactor",
          "LREAL",
          "1",
          "The maximum velocity of each axis is multiplied by this\nfactor, which must be in the range ]0, 1]."
        ],
        [
          "AccFactor",
          "LREAL",
          "1",
          "The maximum acceleration of each axis is multiplied by this\nfactor, which must be in the range ]0, 1]."
        ],
        [
          "JerkFactor",
          "LREAL",
          "1",
          "The maximum jerk of each axis is multiplied by this factor,\nwhich must be in the range ]0, 1]."
        ],
        [
          "AxisX",
          "IAxisRef",
          "",
          "The axis controlling the x-coordinate of the configured coordinate\nsystem or the first axis of the axis group in case of ACS."
        ],
        [
          "AxisY",
          "IAxisRef",
          "",
          "The axis controlling the y-coordinate of the configured coordinate\nsystem or the second axis of the axis group in case of ACS. Set to 0 if not\napplicable."
        ],
        [
          "AxisZ",
          "IAxisRef",
          "",
          "The axis controlling the z-coordinate of the configured coordinate\nsystem or the third axis of the axis group in case of ACS. Set to 0 if not\napplicable."
        ],
        [
          "AxisA",
          "IAxisRef",
          "",
          "This axis controlsthe fourth axis of the axis group, if the coordinate system is ACS orthe rotation around the x-axis of the configured cartesian coordinate\nsystem otherwise.Set to 0 if not applicable."
        ],
        [
          "AxisB",
          "IAxisRef",
          "",
          "This axis controlsthe fifth axis of the axis group, if the coordinate system is ACS orthe rotation around the y-axis of the configured cartesian coordinate\nsystem otherwise.Set to 0 if not applicable."
        ],
        [
          "AxisC",
          "IAxisRef",
          "",
          "This axis controlsthe sixth axis of the axis group, if the coordinate system is ACS orthe rotation around the z-axis of the configured cartesian coordinate\nsystem otherwise.Set to 0 if not applicable."
        ],
        [
          "ABC_as_ACS",
          "BOOL",
          "",
          "This input is no longer supported."
        ],
        {
          "Scope": "Output",
          "Name": "Busy",
          "Type": "BOOL",
          "Initial": "",
          "Comment": "The FB is not finished"
        },
        [
          "InitialPositionReached",
          "BOOL",
          "",
          "The position given by AxisX, â¦, AxisC has been reached initially, after the\nrising edge of Execute."
        ],
        [
          "CommandAborted",
          "BOOL",
          "",
          "Command is aborted by another command"
        ],
        [
          "Error",
          "BOOL",
          "",
          "Signals that an error has occurred within the function block"
        ],
        [
          "ErrorID",
          "SMC_ERROR",
          "",
          "Error identification"
        ]
      ]
    }
  ]
}