{
  "library": "SM3_Dynamics",
  "title": "DynLoad (Struct)",
  "url": "https://content.helpme-codesys.com/en/libs/SM3_Dynamics/Current/SM3_Dynamics/ISMDynamics/DynLoad.html",
  "page_title": "DynLoad (STRUCT)",
  "text": "Library Information\nGetLibVersion (Function)\nGetLibVersionNumber (Function)\nIsLibReleased (Function)\nSM3_Dynamics\nISMDynamics\nDynLoad (Struct)\nDynSpatialInertia (Struct)\nDynUnits (Struct)\nDynamicsParams (Struct)\nISMDynamics (Interface)\nAxesStateToTorque (Method)\nFile and Project Information\nLibrary Reference\nSM3_Error\nLibrary Identification\nLibrary Properties\nSM3_Math\nLibrary Identification\nLibrary Properties\nSM3_RBase\nLibrary Identification\nLibrary Properties\nSM3_Dynamics\nDocs\n»\nSM3_Dynamics\n»\nISMDynamics\n»\nDynLoad (STRUCT)\nDynLoad (STRUCT)\nÂ¶\nTYPE DynLoad : STRUCT\nA load that is attached to the end effector.\nInOut:\nName\nType\nInitial\nComment\nName\nSTRING\nâLoadâ\nInertia\nDynSpatialInertia\nThe inertia of the load defined in the center of mass frame.\nCenterOfMassFrame\nSM3M.SMC_Frame\nSM3M.SMC_FRAME_IDENTITY\nThe center of mass frame of the load relative to the machines flange.\n[vT.dX] = [vT.dY] = [vT.dZ] = u",
  "tables": [
    {
      "headers": [
        "Name",
        "Type",
        "Initial",
        "Comment"
      ],
      "rows": [
        {
          "Name": "Name",
          "Type": "STRING",
          "Initial": "âLoadâ",
          "Comment": ""
        },
        {
          "Name": "Inertia",
          "Type": "DynSpatialInertia",
          "Initial": "",
          "Comment": "The inertia of the load defined in the center of mass frame."
        },
        {
          "Name": "CenterOfMassFrame",
          "Type": "SM3M.SMC_Frame",
          "Initial": "SM3M.SMC_FRAME_IDENTITY",
          "Comment": "The center of mass frame of the load relative to the machines flange.\n[vT.dX] = [vT.dY] = [vT.dZ] = u"
        }
      ]
    }
  ]
}