{
  "library": "SML_Basic",
  "title": "MC_ReadParameter_SML (FunctionBlock)",
  "url": "https://content.helpme-codesys.com/en/libs/SML_Basic/Current/PLCopen/MC_ReadParameter_SML.html",
  "page_title": "MC_ReadParameter_SML (FB)",
  "text": "Additional\nSML_ChangeAxisConfig (FunctionBlock)\nSML_ReinitDrive (FunctionBlock)\nSML_SetOpmode (FunctionBlock)\nSML_StartupDrive (FunctionBlock)\nBase\nAxis_REF_SML (FunctionBlock)\nConfig\nReadStandardConfigParameters (Method)\nReinitAxis (Method)\nError\nSML_ClearFBError (Function)\nSML_ErrorText (Function)\nSML_Language (Enum)\nSML_AXIS_STATE (Enum)\nSML_Constants (GVL)\nSML_ERROR (Enum)\nSML_FBError (Struct)\nSML_Globals (GVL)\nSML_MOVEMENTTYPE (Enum)\nSML_OPMODE (Enum)\nSML_Ramptype (Enum)\nGlobalTextList (GlobalTextList)\nLibrary Information\nGetLibVersion (Function)\nGetLibVersionNumber (Function)\nIsLibReleased (Function)\nPLCopen\nMC_Halt_SML (FunctionBlock)\nMC_Home_SML (FunctionBlock)\nMC_MoveAbsolute_SML (FunctionBlock)\nMC_MoveRelative_SML (FunctionBlock)\nMC_MoveVelocity_SML (FunctionBlock)\nMC_Power_SML (FunctionBlock)\nMC_ReadBoolParameter_SML (FunctionBlock)\nMC_ReadParameter_SML (FunctionBlock)\nMC_ReadStatus_SML (FunctionBlock)\nMC_Reset_SML (FunctionBlock)\nMC_Stop_SML (FunctionBlock)\nMC_WriteBoolParameter_SML (FunctionBlock)\nMC_WriteParameter_SML (FunctionBlock)\nVisu_Templates\nHelpers\nTextListForCombobox_SML_MOVEMENTTYPE (TextList)\nTextListForCombobox_SML_OPMODE (TextList)\nStartupDrive\nFile and Project Information\nLibrary Reference\n3SLicense\nLibrary Identification\nLibrary Properties\nCmpApp\nLibrary Identification\nLibrary Properties\nCmpErrors2 Interfaces\nLibrary Identification\nLibrary Properties\nCmpLog\nLibrary Identification\nLibrary Properties\nCmpSchedule\nLibrary Identification\nLibrary Properties\nComponent Manager\nLibrary Identification\nLibrary Properties\nIoStandard\nLibrary Identification\nLibrary Properties\nSM3_Math\nLibrary Identification\nLibrary Properties\nSM3_Shared\nLibrary Identification\nLibrary Properties\nSM3_StringUtils\nLibrary Identification\nLibrary Properties\nStandard\nLibrary Identification\nLibrary Properties\nSysCpuHandling\nLibrary Identification\nLibrary Properties\nSysMem\nLibrary Identification\nLibrary Properties\nSysTarget\nLibrary Identification\nLibrary Properties\nSysTypes2 Interfaces\nLibrary Identification\nLibrary Properties\nVisuElem3DPath\nLibrary Identification\nLibrary Properties\nLibrary Parameter\nVisuElemCamDisplayer\nLibrary Identification\nLibrary Properties\nLibrary Parameter\nVisuElemMeter\nLibrary Identification\nLibrary Properties\nVisuElemTextEditor\nLibrary Identification\nLibrary Properties\nVisuElemTrace\nLibrary Identification\nLibrary Properties\nVisuElems\nLibrary Identification\nLibrary Properties\nVisuElemsAlarm\nLibrary Identification\nLibrary Properties\nVisuElemsDateTime\nLibrary Identification\nLibrary Properties\nVisuElemsSpecialControls\nLibrary Identification\nLibrary Properties\nVisuElemsWinControls\nLibrary Identification\nLibrary Properties\nVisuInputs\nLibrary Identification\nLibrary Properties\nVisuNativeControl\nLibrary Identification\nLibrary Properties\nSML_Basic\nDocs\n»\nPLCopen\n»\nMC_ReadParameter_SML (FB)\nMC_ReadParameter_SML (FB)\nÂ¶\nFUNCTION_BLOCK FINAL MC_ReadParameter_SML\nReads the value of a SoftMotion or axis specific parameter.\nFor the list of all SoftMotion parameter numbers see\nAxis_REF_SML\n.\nThe value of parameters is converted to\nLREAL\n.\nTo read an axis specific parameter, the axis specific parameter number must be negated.\nFor CANOpen based parameter, the axis specific parameter number is built from the\nobject number 16#ABCD (2 Bytes) and the subindex 16#EF (1 Byte): 16#ABCDEF.\nExample: read object 16#6070, subindex 0: ParameterNumber:= -16#607000.\nNote\nAxis specific parameters are interpreted as unsigned values and converted\nto\nLREAL\n.\nInOut:\nScope\nName\nType\nComment\nInout\nAxis\nAXIS_REF_SML\nReference to the axis\nInput\nEnable\nBOOL\nGet value is updated continuously while enabled\nParameterNumber\nDINT\nNumber of the parameter\nOutput\nValid\nBOOL\nThe value is valid\nBusy\nBOOL\nThe FB is not finished and new output values are to be\nexpected\nError\nBOOL\nAn error occurred\nErrorID\nSML_ERROR\nThe error number\nValue\nLREAL\nThe value of the parameter, converted to\nLREAL",
  "tables": [
    {
      "headers": [
        "Scope",
        "Name",
        "Type",
        "Comment"
      ],
      "rows": [
        {
          "Scope": "Inout",
          "Name": "Axis",
          "Type": "AXIS_REF_SML",
          "Comment": "Reference to the axis"
        },
        {
          "Scope": "Input",
          "Name": "Enable",
          "Type": "BOOL",
          "Comment": "Get value is updated continuously while enabled"
        },
        [
          "ParameterNumber",
          "DINT",
          "Number of the parameter"
        ],
        {
          "Scope": "Output",
          "Name": "Valid",
          "Type": "BOOL",
          "Comment": "The value is valid"
        },
        [
          "Busy",
          "BOOL",
          "The FB is not finished and new output values are to be\nexpected"
        ],
        [
          "Error",
          "BOOL",
          "An error occurred"
        ],
        [
          "ErrorID",
          "SML_ERROR",
          "The error number"
        ],
        [
          "Value",
          "LREAL",
          "The value of the parameter, converted toLREAL"
        ]
      ]
    }
  ]
}