{
  "library": "SML_Basic",
  "title": "MC_Halt_SML (FunctionBlock)",
  "url": "https://content.helpme-codesys.com/en/libs/SML_Basic/Current/PLCopen/MC_Halt_SML.html",
  "page_title": "MC_Halt_SML (FB)",
  "text": "Additional\nSML_ChangeAxisConfig (FunctionBlock)\nSML_ReinitDrive (FunctionBlock)\nSML_SetOpmode (FunctionBlock)\nSML_StartupDrive (FunctionBlock)\nBase\nAxis_REF_SML (FunctionBlock)\nConfig\nReadStandardConfigParameters (Method)\nReinitAxis (Method)\nError\nSML_ClearFBError (Function)\nSML_ErrorText (Function)\nSML_Language (Enum)\nSML_AXIS_STATE (Enum)\nSML_Constants (GVL)\nSML_ERROR (Enum)\nSML_FBError (Struct)\nSML_Globals (GVL)\nSML_MOVEMENTTYPE (Enum)\nSML_OPMODE (Enum)\nSML_Ramptype (Enum)\nGlobalTextList (GlobalTextList)\nLibrary Information\nGetLibVersion (Function)\nGetLibVersionNumber (Function)\nIsLibReleased (Function)\nPLCopen\nMC_Halt_SML (FunctionBlock)\nMC_Home_SML (FunctionBlock)\nMC_MoveAbsolute_SML (FunctionBlock)\nMC_MoveRelative_SML (FunctionBlock)\nMC_MoveVelocity_SML (FunctionBlock)\nMC_Power_SML (FunctionBlock)\nMC_ReadBoolParameter_SML (FunctionBlock)\nMC_ReadParameter_SML (FunctionBlock)\nMC_ReadStatus_SML (FunctionBlock)\nMC_Reset_SML (FunctionBlock)\nMC_Stop_SML (FunctionBlock)\nMC_WriteBoolParameter_SML (FunctionBlock)\nMC_WriteParameter_SML (FunctionBlock)\nVisu_Templates\nHelpers\nTextListForCombobox_SML_MOVEMENTTYPE (TextList)\nTextListForCombobox_SML_OPMODE (TextList)\nStartupDrive\nFile and Project Information\nLibrary Reference\n3SLicense\nLibrary Identification\nLibrary Properties\nCmpApp\nLibrary Identification\nLibrary Properties\nCmpErrors2 Interfaces\nLibrary Identification\nLibrary Properties\nCmpLog\nLibrary Identification\nLibrary Properties\nCmpSchedule\nLibrary Identification\nLibrary Properties\nComponent Manager\nLibrary Identification\nLibrary Properties\nIoStandard\nLibrary Identification\nLibrary Properties\nSM3_Math\nLibrary Identification\nLibrary Properties\nSM3_Shared\nLibrary Identification\nLibrary Properties\nSM3_StringUtils\nLibrary Identification\nLibrary Properties\nStandard\nLibrary Identification\nLibrary Properties\nSysCpuHandling\nLibrary Identification\nLibrary Properties\nSysMem\nLibrary Identification\nLibrary Properties\nSysTarget\nLibrary Identification\nLibrary Properties\nSysTypes2 Interfaces\nLibrary Identification\nLibrary Properties\nVisuElem3DPath\nLibrary Identification\nLibrary Properties\nLibrary Parameter\nVisuElemCamDisplayer\nLibrary Identification\nLibrary Properties\nLibrary Parameter\nVisuElemMeter\nLibrary Identification\nLibrary Properties\nVisuElemTextEditor\nLibrary Identification\nLibrary Properties\nVisuElemTrace\nLibrary Identification\nLibrary Properties\nVisuElems\nLibrary Identification\nLibrary Properties\nVisuElemsAlarm\nLibrary Identification\nLibrary Properties\nVisuElemsDateTime\nLibrary Identification\nLibrary Properties\nVisuElemsSpecialControls\nLibrary Identification\nLibrary Properties\nVisuElemsWinControls\nLibrary Identification\nLibrary Properties\nVisuInputs\nLibrary Identification\nLibrary Properties\nVisuNativeControl\nLibrary Identification\nLibrary Properties\nSML_Basic\nDocs\n»\nPLCopen\n»\nMC_Halt_SML (FB)\nMC_Halt_SML (FB)\nÂ¶\nFUNCTION_BLOCK FINAL MC_Halt_SML\nCommands a controlled motion stop.\nThe axis is moved to the state\nDiscreteMotion\n, until the velocity is zero.\nWhen the output\nDone\nis set, the state is transferred to\nStandstill\n.\nNote\nMC_Halt_SML\nis used to stop the axis under normal operation conditions.\nIt is possible to start another motion command during deceleration of the axis,\nwhich will abort\nMC_Halt_SML\nand will be executed immediately.\nThe example below shows the behavior in combination with\nMC_MoveVelocity_SML\n.\nA rotating axis is ramped down with Function Block\nMC_Halt_SML\nAnother motion command overrides the\nMC_Halt_SML\ncommand.\nMC_Halt_SML\nallows this, in contrast to\nMC_Stop_SML\n.\nThe axis can accelerate again without reaching\nStandstill\n.\nInOut:\nScope\nName\nType\nComment\nInout\nAxis\nAxis_REF_SML\nReference to the axis\nInput\nExecute\nBOOL\nRising edeg: The halt is started\nDeceleration\nLREAL\nValue of the deceleration (decreasing energy of the motor)\n[u/sÂ²]\nOutput\nDone\nBOOL\nBecomes true as soon as the axis has reached velocity zero\nBusy\nBOOL\nTRUE\nas long as\nMC_Halt_SML\nis operating, reset when\nvelocity is zero\nCommandAborted\nBOOL\nCommanded motion was interrupted by any motion FB acting on\nthe same axis\nError\nBOOL\nSignals that an error has occured\nErrorID\nSML_ERROR\nError number",
  "tables": [
    {
      "headers": [
        "Scope",
        "Name",
        "Type",
        "Comment"
      ],
      "rows": [
        {
          "Scope": "Inout",
          "Name": "Axis",
          "Type": "Axis_REF_SML",
          "Comment": "Reference to the axis"
        },
        {
          "Scope": "Input",
          "Name": "Execute",
          "Type": "BOOL",
          "Comment": "Rising edeg: The halt is started"
        },
        [
          "Deceleration",
          "LREAL",
          "Value of the deceleration (decreasing energy of the motor)\n[u/sÂ²]"
        ],
        {
          "Scope": "Output",
          "Name": "Done",
          "Type": "BOOL",
          "Comment": "Becomes true as soon as the axis has reached velocity zero"
        },
        [
          "Busy",
          "BOOL",
          "TRUEas long asMC_Halt_SMLis operating, reset when\nvelocity is zero"
        ],
        [
          "CommandAborted",
          "BOOL",
          "Commanded motion was interrupted by any motion FB acting on\nthe same axis"
        ],
        [
          "Error",
          "BOOL",
          "Signals that an error has occured"
        ],
        [
          "ErrorID",
          "SML_ERROR",
          "Error number"
        ]
      ]
    }
  ]
}