{
  "library": "Standard",
  "title": "DELETE (Function)",
  "url": "https://content.helpme-codesys.com/en/libs/Standard/Current/String-Functions/DELETE.html",
  "page_title": "DELETE (FUN)",
  "text": "Deutsch\nEnglish\nFrançais\nEspañol\nItaliano\nРусский\n日本語\n中文\nMenu\nSearch\nDeutsch\nEnglish\nFrançais\nEspañol\nItaliano\nРусский\n日本語\n中文\nBistable Function Blocks\nRS (FunctionBlock)\nSR (FunctionBlock)\nCounter\nCTD (FunctionBlock)\nCTU (FunctionBlock)\nCTUD (FunctionBlock)\nMiscellaneous\nRTC (FunctionBlock)\nString Functions\nCONCAT (Function)\nDELETE (Function)\nFIND (Function)\nINSERT (Function)\nLEFT (Function)\nLEN (Function)\nMID (Function)\nREPLACE (Function)\nRIGHT (Function)\nTimer\nTOF (FunctionBlock)\nTON (FunctionBlock)\nTP (FunctionBlock)\nTrigger\nF_TRIG (FunctionBlock)\nR_TRIG (FunctionBlock)\nFile and Project Information\nLibrary Reference\nStandard\nDocs\n»\nString\nFunctions\n»\nDELETE (FUN)\nDELETE (FUN)\nÂ¶\nFUNCTION DELETE : STRING(255)\nDeletes a number of characters from a string\nDELETE\n(STR,\nLEN,\nPOS)\nmeans: Delete\nLEN\ncharacters from\nSTR\n, beginning with the character in the\nPOS\nposition.\nPOS\n=\n0\nor\nPOS\n=\n1\n, are both addressing the first character.\nNote\nThe current implementation is unfortunately not correct for the case\nPos=0\n. The implementation cannot be changed for compatibility reasons.\nIf\nPos=0\nis used, the parameter\nLEN\nis internally reduced by one!\nIt is generally recommended to use values in the range specified by IEC 61131-3. The smallest value for\nPos\nis specified there as\n1\n.\n(* Example declaration *)\nVarSTRING1\n:\nSTRING\n;\n(* Example in ST , result is 'SUSI' *)\nVarSTRING1\n:=\nDELETE\n(\n'SUXYSI'\n,\n2\n,\n3\n);\nInOut:\nScope\nName\nType\nComment\nReturn\nDELETE\nSTRING(255)\nString remaining after deletion\nInput\nSTR\nSTRING(255)\nString to be modfied\nLEN\nINT\nLength of the partial string to be deleted, number of\ncharacters\nPOS\nINT\nPosition in\nSTR\nafter which the deletion starts. Counted from left,\nstarting with 1\ntop\nCODESYS Group | We\nsoftware\nAutomation.\nto software\n['sɒftwɛər]\ntransitive verb\n__softwared/softwaring\n: to develop software\n// to software automation: to develop software for automation purposes\nThe CODESYS Group is the manufacturer of CODESYS, the leading hardware-independent\n                                    IEC 61131-3 automation software for developing and engineering controller\n                                    applications.\nCODESYS® is a registered trademark.\nCODESYS GmbH\nA member of the CODESYS Group\nMemminger Straße 151, 87439 Kempten\nGermany\nTel.:\n+49-831-54031-0\ninfo@codesys.com\nLegal Notice\nPrivacy Policy\nLinkedIn\nYoutube\nRSS\nDownloads\nLogin\nCODESYS Store\n© 2022 CODESYS GmbH\n| A member of the CODESYS Group",
  "tables": [
    {
      "headers": [
        "Scope",
        "Name",
        "Type",
        "Comment"
      ],
      "rows": [
        {
          "Scope": "Return",
          "Name": "DELETE",
          "Type": "STRING(255)",
          "Comment": "String remaining after deletion"
        },
        {
          "Scope": "Input",
          "Name": "STR",
          "Type": "STRING(255)",
          "Comment": "String to be modfied"
        },
        [
          "LEN",
          "INT",
          "Length of the partial string to be deleted, number of\ncharacters"
        ],
        [
          "POS",
          "INT",
          "Position inSTRafter which the deletion starts. Counted from left,\nstarting with 1"
        ]
      ]
    }
  ]
}