{
  "library": "Standard64",
  "title": "WINSERT (Function)",
  "url": "https://content.helpme-codesys.com/en/libs/Standard64/Current/String-Functions/WINSERT.html",
  "page_title": "WINSERT (FUN)",
  "text": "Deutsch\nEnglish\nFrançais\nEspañol\nItaliano\nРусский\n日本語\n中文\nMenu\nSearch\nDeutsch\nEnglish\nFrançais\nEspañol\nItaliano\nРусский\n日本語\n中文\nAtomic Read-Write Functions\nAtomicReadLInt (Function)\nAtomicReadLReal (Function)\nAtomicReadLTime (Function)\nAtomicReadLWord (Function)\nAtomicReadULInt (Function)\nAtomicWriteLInt (Function)\nAtomicWriteLReal (Function)\nAtomicWriteLTime (Function)\nAtomicWriteLWord (Function)\nAtomicWriteULInt (Function)\nCounter\nLCTD (FunctionBlock)\nLCTU (FunctionBlock)\nLCTUD (FunctionBlock)\nString Functions\nWCONCAT (Function)\nWDELETE (Function)\nWFIND (Function)\nWINSERT (Function)\nWLEFT (Function)\nWLEN (Function)\nWMID (Function)\nWREPLACE (Function)\nWRIGHT (Function)\nTimer\nLTOF (FunctionBlock)\nLTON (FunctionBlock)\nLTP (FunctionBlock)\nFile and Project Information\nLibrary Reference\nStandard64\nDocs\n»\nString\nFunctions\n»\nWINSERT (FUN)\nWINSERT (FUN)\nÂ¶\nFUNCTION WINSERT : WSTRING(255)\nInsert STR2 into STR1 after\nthe POS-th wcharacter position.\nPOS = 0 inserts before the first wcharacter.\nPOS = 1 inserts after the first wcharacter.\nInOut:\nScope\nName\nType\nReturn\nWINSERT\nWSTRING(255)\nInput\nSTR1\nWSTRING(255)\nSTR2\nWSTRING(255)\nPOS\nINT\ntop\nCODESYS Group | We\nsoftware\nAutomation.\nto software\n['sɒftwɛər]\ntransitive verb\n__softwared/softwaring\n: to develop software\n// to software automation: to develop software for automation purposes\nThe CODESYS Group is the manufacturer of CODESYS, the leading hardware-independent\n                                    IEC 61131-3 automation software for developing and engineering controller\n                                    applications.\nCODESYS® is a registered trademark.\nCODESYS GmbH\nA member of the CODESYS Group\nMemminger Straße 151, 87439 Kempten\nGermany\nTel.:\n+49-831-54031-0\ninfo@codesys.com\nLegal Notice\nPrivacy Policy\nLinkedIn\nYoutube\nRSS\nDownloads\nLogin\nCODESYS Store\n© 2022 CODESYS GmbH\n| A member of the CODESYS Group",
  "tables": [
    {
      "headers": [
        "Scope",
        "Name",
        "Type"
      ],
      "rows": [
        {
          "Scope": "Return",
          "Name": "WINSERT",
          "Type": "WSTRING(255)"
        },
        {
          "Scope": "Input",
          "Name": "STR1",
          "Type": "WSTRING(255)"
        },
        [
          "STR2",
          "WSTRING(255)"
        ],
        [
          "POS",
          "INT"
        ]
      ]
    }
  ]
}