{
  "library": "String Builder",
  "title": "WriteMemSegment (Method)",
  "url": "https://content.helpme-codesys.com/en/libs/String Builder/Current/Builder/Function-Blocks/pou-_Builder/IBuilder/WriteMemSegment.html",
  "page_title": "_Builder.WriteMemSegment (METH)",
  "text": "Builder\nAliases\nConstants (GVL)\nEnums\nENCODING (Alias)\nERROR (Alias)\nSTATS (Alias)\nFunction Blocks\nRange (Alias)\n_RangePool (Alias)\nInterfaces\nIBuilder (Folder)\nICharmap (Alias)\nIString (Alias)\nIStringRepresentation (Folder)\nTypes\nRUNE (Alias)\nFunction Blocks\n_Builder (FunctionBlock)\nIBuilder\nIStringRepresentation\nSetInitialValue (Method)\nFunctions\nCreateRange (Function)\nCreateRangePool (Function)\nLibrary Information\nGetLibVersion (Function)\nGetLibVersionNumber (Function)\nIsLibReleased (Function)\nFile and Project Information\nLibrary Reference\nImmutable String Segments\nLibrary Identification\nLibrary Properties\nMemory Block Manager\nLibrary Identification\nLibrary Properties\nString Builder Base\nLibrary Identification\nLibrary Properties\nString Conversions\nLibrary Identification\nLibrary Properties\nSysMem\nLibrary Identification\nLibrary Properties\nUTF-16 Encoding Support\nLibrary Identification\nLibrary Properties\nUTF-8 Encoding Support\nLibrary Identification\nLibrary Properties\nString Builder\nDocs\n»\nBuilder\n»\nFunction\nBlocks\n»\n_Builder\n(FB)\n»\nIBuilder\n»\n_Builder.WriteMemSegment (METH)\n_Builder.WriteMemSegment (METH)\nÂ¶\nMETHOD FINAL WriteMemSegment : UDINT\nWrites the memory to one or more segments in the buffer.\nIt returns the number of bytes written.\nInOut:\nScope\nName\nType\nInitial\nComment\nReturn\nWriteMemSegment\nUDINT\nInput\npbyMemory\nPOINTER TO BYTE\nEntry pointer for memory\nudiSize\nUDINT\nSize of memory in byte\neEncoding\nENCODING\nENCODING.UTF8\nEncoding type\nOutput\neErrorID\nERROR\nCheck error message for better diagnostics",
  "tables": [
    {
      "headers": [
        "Scope",
        "Name",
        "Type",
        "Initial",
        "Comment"
      ],
      "rows": [
        {
          "Scope": "Return",
          "Name": "WriteMemSegment",
          "Type": "UDINT",
          "Initial": "",
          "Comment": ""
        },
        {
          "Scope": "Input",
          "Name": "pbyMemory",
          "Type": "POINTER TO BYTE",
          "Initial": "",
          "Comment": "Entry pointer for memory"
        },
        [
          "udiSize",
          "UDINT",
          "",
          "Size of memory in byte"
        ],
        [
          "eEncoding",
          "ENCODING",
          "ENCODING.UTF8",
          "Encoding type"
        ],
        {
          "Scope": "Output",
          "Name": "eErrorID",
          "Type": "ERROR",
          "Initial": "",
          "Comment": "Check error message for better diagnostics"
        }
      ]
    }
  ]
}