{
  "library": "String Segments",
  "title": "GetSegment (Method)",
  "url": "https://content.helpme-codesys.com/en/libs/String Segments/Current/Strings/Functionblocks/pou-_UTF8String/IString/GetSegment.html",
  "page_title": "_UTF8String.GetSegment (METH)",
  "text": "Library Information\nGetLibVersion (Function)\nGetLibVersionNumber (Function)\nIsLibReleased (Function)\nStrings\nAliases\nConstants (GVL)\nIDisposable (Alias)\nRUNE (Alias)\nEnums\nERROR (Enum)\nFunctionblocks\nRange (FunctionBlock)\nIRange\nSetInitialValue (Method)\nUTF8Literal (FunctionBlock)\nSetInitialValue (Method)\n_RangePool (FunctionBlock)\nProtected\n_StringPool (FunctionBlock)\nIStringPool\nSetInitialValue (Method)\n_UTF8String (FunctionBlock)\nIString\nIStringRepresentation\nFunctions\nCompare (Function)\nCopy (Function)\nCreateRangePool (Function)\nCreateString (Function)\nCreateStringPool (Function)\nIsASCIIString (Function)\nIsValidString (Function)\nLen (Function)\nReset (Function)\nRuneCount (Function)\nSetSegment (Function)\nInterfaces\nIRange (Interface)\nGetNextRune (Method)\nReset (Method)\nUngetLastRune (Method)\nIRangePool (Interface)\nGetPoolStatus (Method)\nGetRange (Method)\nIRangeProvider (Interface)\nGetRange (Method)\nIString (Interface)\nGetSegment (Method)\nIsASCII (Method)\nIsValid (Method)\nLen (Method)\nIStringPool (Interface)\nGetPoolConfig (Method)\nGetString (Method)\nIStringRepresentation (Interface)\nLen (Method)\nToIString (Method)\nStructs\nCONFIG (Struct)\nSTATUS (Struct)\nFile and Project Information\nLibrary Reference\nMemory Block Manager\nLibrary Identification\nLibrary Properties\nSysMem\nLibrary Identification\nLibrary Properties\nUTF-8 Encoding Support\nLibrary Identification\nLibrary Properties\nString Segments\nDocs\n»\nStrings\n»\nFunctionblocks\n»\n_UTF8String\n(FB)\n»\nIString\n»\n_UTF8String.GetSegment (METH)\n_UTF8String.GetSegment (METH)\nÂ¶\nMETHOD FINAL GetSegment : POINTER TO BYTE\nThis method returns the memory segment of string instance\nReturn value POINTER TO BYTE is the pointer to the first byte of the memory\nInOut:\nScope\nName\nType\nComment\nReturn\nGetSegment\nPOINTER TO BYTE\nOutput\nudiSize\nUDINT\nSize of the memory in bytes\nudiLength\nUDINT\nNumber of bytes currently allocated to the string data\nxASCII\nBOOL\nAll characters are in the ASCII range\neErrorID\nERROR",
  "tables": [
    {
      "headers": [
        "Scope",
        "Name",
        "Type",
        "Comment"
      ],
      "rows": [
        {
          "Scope": "Return",
          "Name": "GetSegment",
          "Type": "POINTER TO BYTE",
          "Comment": ""
        },
        {
          "Scope": "Output",
          "Name": "udiSize",
          "Type": "UDINT",
          "Comment": "Size of the memory in bytes"
        },
        [
          "udiLength",
          "UDINT",
          "Number of bytes currently allocated to the string data"
        ],
        [
          "xASCII",
          "BOOL",
          "All characters are in the ASCII range"
        ],
        [
          "eErrorID",
          "ERROR",
          ""
        ]
      ]
    }
  ]
}