{
  "library": "String Segments",
  "title": "GetString (Method)",
  "url": "https://content.helpme-codesys.com/en/libs/String Segments/Current/Strings/Functionblocks/pou-_StringPool/IStringPool/GetString.html",
  "page_title": "_StringPool.GetString (METH)",
  "text": "Library Information\nGetLibVersion (Function)\nGetLibVersionNumber (Function)\nIsLibReleased (Function)\nStrings\nAliases\nConstants (GVL)\nIDisposable (Alias)\nRUNE (Alias)\nEnums\nERROR (Enum)\nFunctionblocks\nRange (FunctionBlock)\nIRange\nSetInitialValue (Method)\nUTF8Literal (FunctionBlock)\nSetInitialValue (Method)\n_RangePool (FunctionBlock)\nProtected\n_StringPool (FunctionBlock)\nIStringPool\nSetInitialValue (Method)\n_UTF8String (FunctionBlock)\nIString\nIStringRepresentation\nFunctions\nCompare (Function)\nCopy (Function)\nCreateRangePool (Function)\nCreateString (Function)\nCreateStringPool (Function)\nIsASCIIString (Function)\nIsValidString (Function)\nLen (Function)\nReset (Function)\nRuneCount (Function)\nSetSegment (Function)\nInterfaces\nIRange (Interface)\nGetNextRune (Method)\nReset (Method)\nUngetLastRune (Method)\nIRangePool (Interface)\nGetPoolStatus (Method)\nGetRange (Method)\nIRangeProvider (Interface)\nGetRange (Method)\nIString (Interface)\nGetSegment (Method)\nIsASCII (Method)\nIsValid (Method)\nLen (Method)\nIStringPool (Interface)\nGetPoolConfig (Method)\nGetString (Method)\nIStringRepresentation (Interface)\nLen (Method)\nToIString (Method)\nStructs\nCONFIG (Struct)\nSTATUS (Struct)\nFile and Project Information\nLibrary Reference\nMemory Block Manager\nLibrary Identification\nLibrary Properties\nSysMem\nLibrary Identification\nLibrary Properties\nUTF-8 Encoding Support\nLibrary Identification\nLibrary Properties\nString Segments\nDocs\n»\nStrings\n»\nFunctionblocks\n»\n_StringPool\n(FB)\n»\nIStringPool\n»\n_StringPool.GetString (METH)\n_StringPool.GetString (METH)\nÂ¶\nMETHOD GetString :\nIString\nReturns a\nIString\ninstance out of this\nStringPool\nInOut:\nScope\nName\nType\nInitial\nComment\nReturn\nGetString\nIString\nInput\npsValue\nPOINTER TO BYTE\n0\noptional address of a utf-8 encoded, zero terminated byte\narray (string), used as inital value\nOutput\nudiSize\nUDINT\neErrorID\nERROR",
  "tables": [
    {
      "headers": [
        "Scope",
        "Name",
        "Type",
        "Initial",
        "Comment"
      ],
      "rows": [
        {
          "Scope": "Return",
          "Name": "GetString",
          "Type": "IString",
          "Initial": "",
          "Comment": ""
        },
        {
          "Scope": "Input",
          "Name": "psValue",
          "Type": "POINTER TO BYTE",
          "Initial": "0",
          "Comment": "optional address of a utf-8 encoded, zero terminated byte\narray (string), used as inital value"
        },
        {
          "Scope": "Output",
          "Name": "udiSize",
          "Type": "UDINT",
          "Initial": "",
          "Comment": ""
        },
        [
          "eErrorID",
          "ERROR",
          "",
          ""
        ]
      ]
    }
  ]
}