{
  "library": "String Builder Base",
  "title": "CreateRangePool (Function)",
  "url": "https://content.helpme-codesys.com/en/libs/String Builder Base/Current/BuilderBase/Functions/CreateRangePool.html",
  "page_title": "CreateRangePool (FUN)",
  "text": "BuilderBase\nAliases\nConstants (GVL)\nIStringRepresentation (Alias)\nRUNE (Alias)\nEnums\nENCODING (Enum)\nERROR (Enum)\nFunction Blocks\nRange (FunctionBlock)\nIRange\nSetInitialValue (Method)\nFunctions\nCreateRange (Function)\nCreateRangePool (Function)\nInterfaces\nIBuilder (Interface)\nGetBuilderStats (Method)\nReset (Method)\nSegments\nWriteIString (Method)\nWriteMemSegment (Method)\nWriteRune (Method)\nWriteString (Method)\nWriteWString (Method)\nICharmap (Interface)\nDecode (Method)\nEncode (Method)\nInternals\n_RangePool (FunctionBlock)\nProtected\nStructs\nSTATS (Struct)\nLibrary Information\nGetLibVersion (Function)\nGetLibVersionNumber (Function)\nIsLibReleased (Function)\nFile and Project Information\nLibrary Reference\nMemory Block Manager\nLibrary Identification\nLibrary Properties\nString Segments\nLibrary Identification\nLibrary Properties\nUTF-8 Encoding Support\nLibrary Identification\nLibrary Properties\nString Builder Base\nDocs\n»\nBuilderBase\n»\nFunctions\n»\nCreateRangePool (FUN)\nCreateRangePool (FUN)\nÂ¶\nFUNCTION CreateRangePool : STR.IRangePool\nCreates a pool for\n|IRange|\ninstances in the specified memory space\nInOut:\nScope\nName\nType\nInitial\nReturn\nCreateRangePool\nSTR.IRangePool\nInput\npbyPool\nPOINTER TO BYTE\nudiPoolSize\nUDINT\nusiExtensionFactor\nUSINT\n0\nOutput\neErrorID\nSTR.ERROR",
  "tables": [
    {
      "headers": [
        "Scope",
        "Name",
        "Type",
        "Initial"
      ],
      "rows": [
        {
          "Scope": "Return",
          "Name": "CreateRangePool",
          "Type": "STR.IRangePool",
          "Initial": ""
        },
        {
          "Scope": "Input",
          "Name": "pbyPool",
          "Type": "POINTER TO BYTE",
          "Initial": ""
        },
        [
          "udiPoolSize",
          "UDINT",
          ""
        ],
        [
          "usiExtensionFactor",
          "USINT",
          "0"
        ],
        {
          "Scope": "Output",
          "Name": "eErrorID",
          "Type": "STR.ERROR",
          "Initial": ""
        }
      ]
    }
  ]
}