{
  "library": "String Builder Base",
  "title": "GetFirstSegment (Method)",
  "url": "https://content.helpme-codesys.com/en/libs/String Builder Base/Current/BuilderBase/Interfaces/pou-IBuilder/Segments/GetFirstSegment.html",
  "page_title": "IBuilder.GetFirstSegment (METH)",
  "text": "BuilderBase\nAliases\nConstants (GVL)\nIStringRepresentation (Alias)\nRUNE (Alias)\nEnums\nENCODING (Enum)\nERROR (Enum)\nFunction Blocks\nRange (FunctionBlock)\nIRange\nSetInitialValue (Method)\nFunctions\nCreateRange (Function)\nCreateRangePool (Function)\nInterfaces\nIBuilder (Interface)\nGetBuilderStats (Method)\nReset (Method)\nSegments\nWriteIString (Method)\nWriteMemSegment (Method)\nWriteRune (Method)\nWriteString (Method)\nWriteWString (Method)\nICharmap (Interface)\nDecode (Method)\nEncode (Method)\nInternals\n_RangePool (FunctionBlock)\nProtected\nStructs\nSTATS (Struct)\nLibrary Information\nGetLibVersion (Function)\nGetLibVersionNumber (Function)\nIsLibReleased (Function)\nFile and Project Information\nLibrary Reference\nMemory Block Manager\nLibrary Identification\nLibrary Properties\nString Segments\nLibrary Identification\nLibrary Properties\nUTF-8 Encoding Support\nLibrary Identification\nLibrary Properties\nString Builder Base\nDocs\n»\nBuilderBase\n»\nInterfaces\n»\nIBuilder\n(ITF)\n»\nSegments\n»\nIBuilder.GetFirstSegment (METH)\nIBuilder.GetFirstSegment (METH)\nÂ¶\nMETHOD GetFirstSegment : POINTER TO BYTE\nInOut:\nScope\nName\nType\nReturn\nGetFirstSegment\nPOINTER TO BYTE\nOutput\nudiSize\nUDINT\neErrorID\nERROR",
  "tables": [
    {
      "headers": [
        "Scope",
        "Name",
        "Type"
      ],
      "rows": [
        {
          "Scope": "Return",
          "Name": "GetFirstSegment",
          "Type": "POINTER TO BYTE"
        },
        {
          "Scope": "Output",
          "Name": "udiSize",
          "Type": "UDINT"
        },
        [
          "eErrorID",
          "ERROR"
        ]
      ]
    }
  ]
}