{
  "library": "String Segments",
  "title": "Constants (GVL)",
  "url": "https://content.helpme-codesys.com/en/libs/String Segments/Current/Strings/Aliases/Constants.html",
  "page_title": "Constants (GVL)",
  "text": "Library Information\nGetLibVersion (Function)\nGetLibVersionNumber (Function)\nIsLibReleased (Function)\nStrings\nAliases\nConstants (GVL)\nIDisposable (Alias)\nRUNE (Alias)\nEnums\nERROR (Enum)\nFunctionblocks\nRange (FunctionBlock)\nIRange\nSetInitialValue (Method)\nUTF8Literal (FunctionBlock)\nSetInitialValue (Method)\n_RangePool (FunctionBlock)\nProtected\n_StringPool (FunctionBlock)\nIStringPool\nSetInitialValue (Method)\n_UTF8String (FunctionBlock)\nIString\nIStringRepresentation\nFunctions\nCompare (Function)\nCopy (Function)\nCreateRangePool (Function)\nCreateString (Function)\nCreateStringPool (Function)\nIsASCIIString (Function)\nIsValidString (Function)\nLen (Function)\nReset (Function)\nRuneCount (Function)\nSetSegment (Function)\nInterfaces\nIRange (Interface)\nGetNextRune (Method)\nReset (Method)\nUngetLastRune (Method)\nIRangePool (Interface)\nGetPoolStatus (Method)\nGetRange (Method)\nIRangeProvider (Interface)\nGetRange (Method)\nIString (Interface)\nGetSegment (Method)\nIsASCII (Method)\nIsValid (Method)\nLen (Method)\nIStringPool (Interface)\nGetPoolConfig (Method)\nGetString (Method)\nIStringRepresentation (Interface)\nLen (Method)\nToIString (Method)\nStructs\nCONFIG (Struct)\nSTATUS (Struct)\nFile and Project Information\nLibrary Reference\nMemory Block Manager\nLibrary Identification\nLibrary Properties\nSysMem\nLibrary Identification\nLibrary Properties\nUTF-8 Encoding Support\nLibrary Identification\nLibrary Properties\nString Segments\nDocs\n»\nStrings\n»\nAliases\n»\nConstants (GVL)\nConstants (GVL)\nÂ¶\nInOut:\nScope\nName\nType\nInitial\nComment\nConstant\nc_diRuneError\nRUNE\nUTF8.c_diRuneError\nThe âerrorâ Rune or âUnicode replacement characterâ\nc_diMaxRune\nDINT\nUTF8.c_diMaxRune\nc_liMinIndex\nLINT\n-4294967295\nc_liMaxIndex\nLINT\n4294967294",
  "tables": [
    {
      "headers": [
        "Scope",
        "Name",
        "Type",
        "Initial",
        "Comment"
      ],
      "rows": [
        {
          "Scope": "Constant",
          "Name": "c_diRuneError",
          "Type": "RUNE",
          "Initial": "UTF8.c_diRuneError",
          "Comment": "The âerrorâ Rune or âUnicode replacement characterâ"
        },
        [
          "c_diMaxRune",
          "DINT",
          "UTF8.c_diMaxRune",
          ""
        ],
        [
          "c_liMinIndex",
          "LINT",
          "-4294967295",
          ""
        ],
        [
          "c_liMaxIndex",
          "LINT",
          "4294967294",
          ""
        ]
      ]
    }
  ]
}