{
  "library": "String Builder Base",
  "title": "WriteString (Method)",
  "url": "https://content.helpme-codesys.com/en/libs/String Builder Base/Current/BuilderBase/Interfaces/pou-IBuilder/WriteString.html",
  "page_title": "IBuilder.WriteString (METH)",
  "text": "BuilderBase\nAliases\nConstants (GVL)\nIStringRepresentation (Alias)\nRUNE (Alias)\nEnums\nENCODING (Enum)\nERROR (Enum)\nFunction Blocks\nRange (FunctionBlock)\nIRange\nSetInitialValue (Method)\nFunctions\nCreateRange (Function)\nCreateRangePool (Function)\nInterfaces\nIBuilder (Interface)\nGetBuilderStats (Method)\nReset (Method)\nSegments\nWriteIString (Method)\nWriteMemSegment (Method)\nWriteRune (Method)\nWriteString (Method)\nWriteWString (Method)\nICharmap (Interface)\nDecode (Method)\nEncode (Method)\nInternals\n_RangePool (FunctionBlock)\nProtected\nStructs\nSTATS (Struct)\nLibrary Information\nGetLibVersion (Function)\nGetLibVersionNumber (Function)\nIsLibReleased (Function)\nFile and Project Information\nLibrary Reference\nMemory Block Manager\nLibrary Identification\nLibrary Properties\nString Segments\nLibrary Identification\nLibrary Properties\nUTF-8 Encoding Support\nLibrary Identification\nLibrary Properties\nString Builder Base\nDocs\n»\nBuilderBase\n»\nInterfaces\n»\nIBuilder\n(ITF)\n»\nIBuilder.WriteString (METH)\nIBuilder.WriteString (METH)\nÂ¶\nMETHOD WriteString : UDINT\nAppends the contents of\nsValue\nto the buffer.\nIt returns the number of bytes written.\nInOut:\nScope\nName\nType\nInitial\nComment\nReturn\nWriteString\nUDINT\nInout Const\nsValue\nSTRING(255)\nInput\nitfCharmap\nICharmap\n0\nDefault: Windows-1252\nOutput\neErrorID\nERROR",
  "tables": [
    {
      "headers": [
        "Scope",
        "Name",
        "Type",
        "Initial",
        "Comment"
      ],
      "rows": [
        {
          "Scope": "Return",
          "Name": "WriteString",
          "Type": "UDINT",
          "Initial": "",
          "Comment": ""
        },
        {
          "Scope": "Inout Const",
          "Name": "sValue",
          "Type": "STRING(255)",
          "Initial": "",
          "Comment": ""
        },
        {
          "Scope": "Input",
          "Name": "itfCharmap",
          "Type": "ICharmap",
          "Initial": "0",
          "Comment": "Default: Windows-1252"
        },
        {
          "Scope": "Output",
          "Name": "eErrorID",
          "Type": "ERROR",
          "Initial": "",
          "Comment": ""
        }
      ]
    }
  ]
}