{
  "library": "String Functions",
  "title": "LEN (Function)",
  "url": "https://content.helpme-codesys.com/en/libs/String Functions/Current/StrFunc/Functions/LEN.html",
  "page_title": "LEN (FUN)",
  "text": "Library Information\nGetLibVersion (Function)\nGetLibVersionNumber (Function)\nIsLibReleased (Function)\nStrFunc\nAliases\nIString (Alias)\nEnums\nERROR (Enum)\nFunctions\nCONCAT (Function)\nCOUNT (Function)\nDELETE (Function)\nFIND (Function)\nINSERT (Function)\nLEFT (Function)\nLEN (Function)\nMID (Function)\nREPLACE (Function)\nRIGHT (Function)\nFile and Project Information\nLibrary Reference\nString Segments\nLibrary Identification\nLibrary Properties\nSysMem\nLibrary Identification\nLibrary Properties\nUTF-8 Encoding Support\nLibrary Identification\nLibrary Properties\nString Functions\nDocs\n»\nStrFunc\n»\nFunctions\n»\nLEN (FUN)\nLEN (FUN)\nÂ¶\nFUNCTION LEN : UDINT\nReturns the number of\nbytes\nof a string\nSee function\nCOUNT\nfor calculating the number of runes\nInOut:\nScope\nName\nType\nComment\nReturn\nLEN\nUDINT\nInput\nitfString\nIString\nString to be analyzed\nOutput\neErrorID\nERROR",
  "tables": [
    {
      "headers": [
        "Scope",
        "Name",
        "Type",
        "Comment"
      ],
      "rows": [
        {
          "Scope": "Return",
          "Name": "LEN",
          "Type": "UDINT",
          "Comment": ""
        },
        {
          "Scope": "Input",
          "Name": "itfString",
          "Type": "IString",
          "Comment": "String to be analyzed"
        },
        {
          "Scope": "Output",
          "Name": "eErrorID",
          "Type": "ERROR",
          "Comment": ""
        }
      ]
    }
  ]
}