{
  "library": "String Functions",
  "title": "CONCAT (Function)",
  "url": "https://content.helpme-codesys.com/en/libs/String Functions/Current/StrFunc/Functions/CONCAT.html",
  "page_title": "CONCAT (FUN)",
  "text": "Library Information\nGetLibVersion (Function)\nGetLibVersionNumber (Function)\nIsLibReleased (Function)\nStrFunc\nAliases\nIString (Alias)\nEnums\nERROR (Enum)\nFunctions\nCONCAT (Function)\nCOUNT (Function)\nDELETE (Function)\nFIND (Function)\nINSERT (Function)\nLEFT (Function)\nLEN (Function)\nMID (Function)\nREPLACE (Function)\nRIGHT (Function)\nFile and Project Information\nLibrary Reference\nString Segments\nLibrary Identification\nLibrary Properties\nSysMem\nLibrary Identification\nLibrary Properties\nUTF-8 Encoding Support\nLibrary Identification\nLibrary Properties\nString Functions\nDocs\n»\nStrFunc\n»\nFunctions\n»\nCONCAT (FUN)\nCONCAT (FUN)\nÂ¶\nFUNCTION CONCAT :\nIString\nConcatenates two strings\n| See:\nSBD.IBuilder\n| The multiple nesting of CONCAT calls can often be replaced much faster via multiple calls to IBuilder.WriteIString.\nInOut:\nScope\nName\nType\nComment\nReturn\nCONCAT\nIString\nInput\nitfHead\nIString\nThe first part of the new string\nitfTail\nIString\nThe second part of the new string\nitfResource\nIString\nThe resource that this function is working on. It will\ncontain the result after the function call and will also be\nreturned by this function so it can be used in nested calls.\nOutput\neErrorID\nERROR",
  "tables": [
    {
      "headers": [
        "Scope",
        "Name",
        "Type",
        "Comment"
      ],
      "rows": [
        {
          "Scope": "Return",
          "Name": "CONCAT",
          "Type": "IString",
          "Comment": ""
        },
        {
          "Scope": "Input",
          "Name": "itfHead",
          "Type": "IString",
          "Comment": "The first part of the new string"
        },
        [
          "itfTail",
          "IString",
          "The second part of the new string"
        ],
        [
          "itfResource",
          "IString",
          "The resource that this function is working on. It will\ncontain the result after the function call and will also be\nreturned by this function so it can be used in nested calls."
        ],
        {
          "Scope": "Output",
          "Name": "eErrorID",
          "Type": "ERROR",
          "Comment": ""
        }
      ]
    }
  ]
}