{
  "library": "String Segments",
  "title": "CreateStringPool (Function)",
  "url": "https://content.helpme-codesys.com/en/libs/String Segments/Current/Strings/Functions/CreateStringPool.html",
  "page_title": "CreateStringPool (FUN)",
  "text": "Library Information\nGetLibVersion (Function)\nGetLibVersionNumber (Function)\nIsLibReleased (Function)\nStrings\nAliases\nConstants (GVL)\nIDisposable (Alias)\nRUNE (Alias)\nEnums\nERROR (Enum)\nFunctionblocks\nRange (FunctionBlock)\nIRange\nSetInitialValue (Method)\nUTF8Literal (FunctionBlock)\nSetInitialValue (Method)\n_RangePool (FunctionBlock)\nProtected\n_StringPool (FunctionBlock)\nIStringPool\nSetInitialValue (Method)\n_UTF8String (FunctionBlock)\nIString\nIStringRepresentation\nFunctions\nCompare (Function)\nCopy (Function)\nCreateRangePool (Function)\nCreateString (Function)\nCreateStringPool (Function)\nIsASCIIString (Function)\nIsValidString (Function)\nLen (Function)\nReset (Function)\nRuneCount (Function)\nSetSegment (Function)\nInterfaces\nIRange (Interface)\nGetNextRune (Method)\nReset (Method)\nUngetLastRune (Method)\nIRangePool (Interface)\nGetPoolStatus (Method)\nGetRange (Method)\nIRangeProvider (Interface)\nGetRange (Method)\nIString (Interface)\nGetSegment (Method)\nIsASCII (Method)\nIsValid (Method)\nLen (Method)\nIStringPool (Interface)\nGetPoolConfig (Method)\nGetString (Method)\nIStringRepresentation (Interface)\nLen (Method)\nToIString (Method)\nStructs\nCONFIG (Struct)\nSTATUS (Struct)\nFile and Project Information\nLibrary Reference\nMemory Block Manager\nLibrary Identification\nLibrary Properties\nSysMem\nLibrary Identification\nLibrary Properties\nUTF-8 Encoding Support\nLibrary Identification\nLibrary Properties\nString Segments\nDocs\n»\nStrings\n»\nFunctions\n»\nCreateStringPool (FUN)\nCreateStringPool (FUN)\nÂ¶\nFUNCTION CreateStringPool :\nIStringPool\nCreates a pool for\nIString\ninstances in the specified memory space\nThe size of the strings is specified via\nudiStringSize\nExample for a\n_StringPool\ninstance\nwith\na\ncapacity\nof\n10\n``IString\ninstances with a size of minimal 80 bytes each:\naxwMemory\n:\nARRAY\n[0..209]\nOF\n__XWORD\n;\nfbStringPool\n:\nSTR._StringPool\n:=\n(\nudiStringSize\n:=\n80\n,\npbyPool\n:=\nADR\n(\naxwMemory\n),\nudiPoolSize\n:=\nSIZEOF\n(\naxwMemory\n));\nstPoolConfig\n:\nSTR.CONFIG\n:=\nfbStringPool.GetPoolConfig\n();\n// -> udiStringSize = 87 | udiCapacity = 10\nPlease take a look to the function blocks in the Library âGeneric String Baseâ\nYou can use the\nGSB.StringPool\nfunction block, which performs this task in a much more convenient way\nInOut:\nScope\nName\nType\nInitial\nComment\nReturn\nCreateStringPool\nIStringPool\nInput\nudiStringSize\nUDINT\npbyPool\nPOINTER TO BYTE\nPointer to the first byte of the memory.\nThis address should aligned to a\n__XWORD\nboundary!\nudiPoolSize\nUDINT\nSize of the allocated memory for the range.\nThis size must not be smaller than\nSIZEOF(STR._StringPool)\n, because it includes an instance of\n_StringPool(FB)\nusiExtensionFactor\nUSINT\n0\nOptional extension factor of the\nIStringPool\ninstance\nOutput\neErrorID\nERROR",
  "tables": [
    {
      "headers": [
        "Scope",
        "Name",
        "Type",
        "Initial",
        "Comment"
      ],
      "rows": [
        {
          "Scope": "Return",
          "Name": "CreateStringPool",
          "Type": "IStringPool",
          "Initial": "",
          "Comment": ""
        },
        {
          "Scope": "Input",
          "Name": "udiStringSize",
          "Type": "UDINT",
          "Initial": "",
          "Comment": ""
        },
        [
          "pbyPool",
          "POINTER TO BYTE",
          "",
          "Pointer to the first byte of the memory.This address should aligned to a__XWORDboundary!"
        ],
        [
          "udiPoolSize",
          "UDINT",
          "",
          "Size of the allocated memory for the range.This size must not be smaller thanSIZEOF(STR._StringPool), because it includes an instance of_StringPool(FB)"
        ],
        [
          "usiExtensionFactor",
          "USINT",
          "0",
          "Optional extension factor of theIStringPoolinstance"
        ],
        {
          "Scope": "Output",
          "Name": "eErrorID",
          "Type": "ERROR",
          "Initial": "",
          "Comment": ""
        }
      ]
    }
  ]
}