{
  "library": "String Segments",
  "title": "ToIString (Method)",
  "url": "https://content.helpme-codesys.com/en/libs/String Segments/Current/Strings/Functionblocks/pou-_UTF8String/IStringRepresentation/ToIString.html",
  "page_title": "_UTF8String.ToIString (METH)",
  "text": "Library Information\nGetLibVersion (Function)\nGetLibVersionNumber (Function)\nIsLibReleased (Function)\nStrings\nAliases\nConstants (GVL)\nIDisposable (Alias)\nRUNE (Alias)\nEnums\nERROR (Enum)\nFunctionblocks\nRange (FunctionBlock)\nIRange\nSetInitialValue (Method)\nUTF8Literal (FunctionBlock)\nSetInitialValue (Method)\n_RangePool (FunctionBlock)\nProtected\n_StringPool (FunctionBlock)\nIStringPool\nSetInitialValue (Method)\n_UTF8String (FunctionBlock)\nIString\nIStringRepresentation\nFunctions\nCompare (Function)\nCopy (Function)\nCreateRangePool (Function)\nCreateString (Function)\nCreateStringPool (Function)\nIsASCIIString (Function)\nIsValidString (Function)\nLen (Function)\nReset (Function)\nRuneCount (Function)\nSetSegment (Function)\nInterfaces\nIRange (Interface)\nGetNextRune (Method)\nReset (Method)\nUngetLastRune (Method)\nIRangePool (Interface)\nGetPoolStatus (Method)\nGetRange (Method)\nIRangeProvider (Interface)\nGetRange (Method)\nIString (Interface)\nGetSegment (Method)\nIsASCII (Method)\nIsValid (Method)\nLen (Method)\nIStringPool (Interface)\nGetPoolConfig (Method)\nGetString (Method)\nIStringRepresentation (Interface)\nLen (Method)\nToIString (Method)\nStructs\nCONFIG (Struct)\nSTATUS (Struct)\nFile and Project Information\nLibrary Reference\nMemory Block Manager\nLibrary Identification\nLibrary Properties\nSysMem\nLibrary Identification\nLibrary Properties\nUTF-8 Encoding Support\nLibrary Identification\nLibrary Properties\nString Segments\nDocs\n»\nStrings\n»\nFunctionblocks\n»\n_UTF8String\n(FB)\n»\nIStringRepresentation\n»\n_UTF8String.ToIString (METH)\n_UTF8String.ToIString (METH)\nÂ¶\nMETHOD FINAL ToIString :\nIString\nReturns the string representation\nInOut:\nScope\nName\nType\nInitial\nComment\nReturn\nToIString\nIString\nInput\nitfString\nIString\nDefines the output target\nliStart\nLINT\n0\nDefines the rune index from which the content is output\n0 => first rune, -1 => last rune\n[c_liMinIndex\n<=\nliStart\n<=\nc_liMaxIndex]\nliEnd\nLINT\n-1\nDefines the rune index up to which the content is output\n0 => first rune, -1 => last rune\n[c_liMinIndex\n<=\nliEnd\n<=\nc_liMaxIndex]\nOutput\neErrorID\nERROR",
  "tables": [
    {
      "headers": [
        "Scope",
        "Name",
        "Type",
        "Initial",
        "Comment"
      ],
      "rows": [
        {
          "Scope": "Return",
          "Name": "ToIString",
          "Type": "IString",
          "Initial": "",
          "Comment": ""
        },
        {
          "Scope": "Input",
          "Name": "itfString",
          "Type": "IString",
          "Initial": "",
          "Comment": "Defines the output target"
        },
        [
          "liStart",
          "LINT",
          "0",
          "Defines the rune index from which the content is output0 => first rune, -1 => last rune[c_liMinIndex<=liStart<=c_liMaxIndex]"
        ],
        [
          "liEnd",
          "LINT",
          "-1",
          "Defines the rune index up to which the content is output0 => first rune, -1 => last rune[c_liMinIndex<=liEnd<=c_liMaxIndex]"
        ],
        {
          "Scope": "Output",
          "Name": "eErrorID",
          "Type": "ERROR",
          "Initial": "",
          "Comment": ""
        }
      ]
    }
  ]
}