{
  "library": "String Segments",
  "title": "NewRange (Method)",
  "url": "https://content.helpme-codesys.com/en/libs/String Segments/Current/Strings/Functionblocks/pou-_RangePool/Protected/NewRange.html",
  "page_title": "_RangePool.NewRange (METH)",
  "text": "Library Information\nGetLibVersion (Function)\nGetLibVersionNumber (Function)\nIsLibReleased (Function)\nStrings\nAliases\nConstants (GVL)\nIDisposable (Alias)\nRUNE (Alias)\nEnums\nERROR (Enum)\nFunctionblocks\nRange (FunctionBlock)\nIRange\nSetInitialValue (Method)\nUTF8Literal (FunctionBlock)\nSetInitialValue (Method)\n_RangePool (FunctionBlock)\nProtected\n_StringPool (FunctionBlock)\nIStringPool\nSetInitialValue (Method)\n_UTF8String (FunctionBlock)\nIString\nIStringRepresentation\nFunctions\nCompare (Function)\nCopy (Function)\nCreateRangePool (Function)\nCreateString (Function)\nCreateStringPool (Function)\nIsASCIIString (Function)\nIsValidString (Function)\nLen (Function)\nReset (Function)\nRuneCount (Function)\nSetSegment (Function)\nInterfaces\nIRange (Interface)\nGetNextRune (Method)\nReset (Method)\nUngetLastRune (Method)\nIRangePool (Interface)\nGetPoolStatus (Method)\nGetRange (Method)\nIRangeProvider (Interface)\nGetRange (Method)\nIString (Interface)\nGetSegment (Method)\nIsASCII (Method)\nIsValid (Method)\nLen (Method)\nIStringPool (Interface)\nGetPoolConfig (Method)\nGetString (Method)\nIStringRepresentation (Interface)\nLen (Method)\nToIString (Method)\nStructs\nCONFIG (Struct)\nSTATUS (Struct)\nFile and Project Information\nLibrary Reference\nMemory Block Manager\nLibrary Identification\nLibrary Properties\nSysMem\nLibrary Identification\nLibrary Properties\nUTF-8 Encoding Support\nLibrary Identification\nLibrary Properties\nString Segments\nDocs\n»\nStrings\n»\nFunctionblocks\n»\n_RangePool\n(FB)\n»\nProtected\n»\n_RangePool.NewRange (METH)\n_RangePool.NewRange (METH)\nÂ¶\nMETHOD FINAL PROTECTED NewRange :\nIRange\nInOut:\nScope\nName\nType\nReturn\nNewRange\nIRange\nInput\nitfStrRep\nIStringRepresentation\npbyMemory\nPOINTER TO BYTE\nudiMemSize\nUDINT\nOutput\neErrorID\nERROR",
  "tables": [
    {
      "headers": [
        "Scope",
        "Name",
        "Type"
      ],
      "rows": [
        {
          "Scope": "Return",
          "Name": "NewRange",
          "Type": "IRange"
        },
        {
          "Scope": "Input",
          "Name": "itfStrRep",
          "Type": "IStringRepresentation"
        },
        [
          "pbyMemory",
          "POINTER TO BYTE"
        ],
        [
          "udiMemSize",
          "UDINT"
        ],
        {
          "Scope": "Output",
          "Name": "eErrorID",
          "Type": "ERROR"
        }
      ]
    }
  ]
}