{
  "library": "SysDir",
  "title": "SysDirCopy (Function)",
  "url": "https://content.helpme-codesys.com/en/libs/SysDir/Current/SysDirCopy.html",
  "page_title": "SysDirCopy (FUN)",
  "text": "Deutsch\nEnglish\nFrançais\nEspañol\nItaliano\nРусский\n日本語\n中文\nMenu\nSearch\nDeutsch\nEnglish\nFrançais\nEspañol\nItaliano\nРусский\n日本語\n中文\nDirFileTime (Struct)\nDirInfo (Struct)\nDirInfoFlags (GVL)\nSysDirClose (Function)\nSysDirCopy (Function)\nSysDirCreate (Function)\nSysDirCreate2 (Function)\nSysDirDelete (Function)\nSysDirDelete2 (Function)\nSysDirGetCurrent (Function)\nSysDirOpen (Function)\nSysDirRead (Function)\nSysDirRename (Function)\nSysDirSetCurrent (Function)\nFile and Project Information\nLibrary Reference\nCmpErrors2 Interfaces\nLibrary Identification\nLibrary Properties\nSysTypes2 Interfaces\nLibrary Identification\nLibrary Properties\nSysDir\nDocs\n»\nSysDirCopy (FUN)\nSysDirCopy (FUN)\nÂ¶\nFUNCTION SysDirCopy : RTS_IEC_RESULT\nCopies the contents of szSourceDir to szDestDir.\nNonexisting destination path will be created.\nDepending of the parameters, all subdirectories and its content will be copied too, and existing files will be overwritten.\nNOTE: Empty direcories will be copied if xRecursive is TRUE.\nInOut:\nScope\nName\nType\nComment\nReturn\nSysDirCopy\nRTS_IEC_RESULT\nReturns the runtime system error code (see\nCmpErrors_Itf.library)\nInput\nszDestDir\nREFERENCE TO STRING\nName of destination directory\nszSourceDir\nREFERENCE TO STRING\nName of source directory\nxRecursive\nBOOL\nTRUE: all subdirectories and their contents are copied,\nFALSE: subdirectories are omitted\nxOverwrite\nBOOL\nTRUE: existing files are overwritten, FALSE: existing files\nare left untouched\ntop\nCODESYS Group | We\nsoftware\nAutomation.\nto software\n['sɒftwɛər]\ntransitive verb\n__softwared/softwaring\n: to develop software\n// to software automation: to develop software for automation purposes\nThe CODESYS Group is the manufacturer of CODESYS, the leading hardware-independent\n                                    IEC 61131-3 automation software for developing and engineering controller\n                                    applications.\nCODESYS® is a registered trademark.\nCODESYS GmbH\nA member of the CODESYS Group\nMemminger Straße 151, 87439 Kempten\nGermany\nTel.:\n+49-831-54031-0\ninfo@codesys.com\nLegal Notice\nPrivacy Policy\nLinkedIn\nYoutube\nRSS\nDownloads\nLogin\nCODESYS Store\n© 2022 CODESYS GmbH\n| A member of the CODESYS Group",
  "tables": [
    {
      "headers": [
        "Scope",
        "Name",
        "Type",
        "Comment"
      ],
      "rows": [
        {
          "Scope": "Return",
          "Name": "SysDirCopy",
          "Type": "RTS_IEC_RESULT",
          "Comment": "Returns the runtime system error code (see\nCmpErrors_Itf.library)"
        },
        {
          "Scope": "Input",
          "Name": "szDestDir",
          "Type": "REFERENCE TO STRING",
          "Comment": "Name of destination directory"
        },
        [
          "szSourceDir",
          "REFERENCE TO STRING",
          "Name of source directory"
        ],
        [
          "xRecursive",
          "BOOL",
          "TRUE: all subdirectories and their contents are copied,\nFALSE: subdirectories are omitted"
        ],
        [
          "xOverwrite",
          "BOOL",
          "TRUE: existing files are overwritten, FALSE: existing files\nare left untouched"
        ]
      ]
    }
  ]
}