{
  "library": "SysFile",
  "title": "SysFileSetPos (Function)",
  "url": "https://content.helpme-codesys.com/en/libs/SysFile/Current/SysFileSetPos.html",
  "page_title": "SysFileSetPos (FUN)",
  "text": "Deutsch\nEnglish\nFrançais\nEspañol\nItaliano\nРусский\n日本語\n中文\nMenu\nSearch\nDeutsch\nEnglish\nFrançais\nEspañol\nItaliano\nРусский\n日本語\n中文\nACCESS_MODE (Enum)\nSYS_FILETIME (Struct)\nSYS_FILE_STATUS (Enum)\nSysFileClose (Function)\nSysFileCopy (Function)\nSysFileDelete (Function)\nSysFileDeleteByHandle (Function)\nSysFileEOF (Function)\nSysFileFlush (Function)\nSysFileGetName (Function)\nSysFileGetName2 (Function)\nSysFileGetPath (Function)\nSysFileGetPos (Function)\nSysFileGetSize (Function)\nSysFileGetSizeByHandle (Function)\nSysFileGetStatus (Function)\nSysFileGetStatus2 (Function)\nSysFileGetTime (Function)\nSysFileOpen (Function)\nSysFileRead (Function)\nSysFileRename (Function)\nSysFileSetPos (Function)\nSysFileTruncate (Function)\nSysFileWrite (Function)\nFile and Project Information\nLibrary Reference\nSysTypes2 Interfaces\nLibrary Identification\nLibrary Properties\nSysFile\nDocs\n»\nSysFileSetPos (FUN)\nSysFileSetPos (FUN)\nÂ¶\nFUNCTION SysFileSetPos : RTS_IEC_RESULT\nSet the file pointer to the specified position\nInOut:\nScope\nName\nType\nComment\nReturn\nSysFileSetPos\nRTS_IEC_RESULT\nReturns the runtime system error code (see\nCmpErrors.library)\nInput\nhFile\nRTS_IEC_HANDLE\nHandle of the file\nulOffset\n__XWORD\nOffset to set from the beginning of the file\ntop\nCODESYS Group | We\nsoftware\nAutomation.\nto software\n['sɒftwɛər]\ntransitive verb\n__softwared/softwaring\n: to develop software\n// to software automation: to develop software for automation purposes\nThe CODESYS Group is the manufacturer of CODESYS, the leading hardware-independent\n                                    IEC 61131-3 automation software for developing and engineering controller\n                                    applications.\nCODESYS® is a registered trademark.\nCODESYS GmbH\nA member of the CODESYS Group\nMemminger Straße 151, 87439 Kempten\nGermany\nTel.:\n+49-831-54031-0\ninfo@codesys.com\nLegal Notice\nPrivacy Policy\nLinkedIn\nYoutube\nRSS\nDownloads\nLogin\nCODESYS Store\n© 2022 CODESYS GmbH\n| A member of the CODESYS Group",
  "tables": [
    {
      "headers": [
        "Scope",
        "Name",
        "Type",
        "Comment"
      ],
      "rows": [
        {
          "Scope": "Return",
          "Name": "SysFileSetPos",
          "Type": "RTS_IEC_RESULT",
          "Comment": "Returns the runtime system error code (see\nCmpErrors.library)"
        },
        {
          "Scope": "Input",
          "Name": "hFile",
          "Type": "RTS_IEC_HANDLE",
          "Comment": "Handle of the file"
        },
        [
          "ulOffset",
          "__XWORD",
          "Offset to set from the beginning of the file"
        ]
      ]
    }
  ]
}