{
  "library": "SysFile",
  "title": "SysFileEOF (Function)",
  "url": "https://content.helpme-codesys.com/en/libs/SysFile/Current/SysFileEOF.html",
  "page_title": "SysFileEOF (FUN)",
  "text": "Deutsch\nEnglish\nFrançais\nEspañol\nItaliano\nРусский\n日本語\n中文\nMenu\nSearch\nDeutsch\nEnglish\nFrançais\nEspañol\nItaliano\nРусский\n日本語\n中文\nACCESS_MODE (Enum)\nSYS_FILETIME (Struct)\nSYS_FILE_STATUS (Enum)\nSysFileClose (Function)\nSysFileCopy (Function)\nSysFileDelete (Function)\nSysFileDeleteByHandle (Function)\nSysFileEOF (Function)\nSysFileFlush (Function)\nSysFileGetName (Function)\nSysFileGetName2 (Function)\nSysFileGetPath (Function)\nSysFileGetPos (Function)\nSysFileGetSize (Function)\nSysFileGetSizeByHandle (Function)\nSysFileGetStatus (Function)\nSysFileGetStatus2 (Function)\nSysFileGetTime (Function)\nSysFileOpen (Function)\nSysFileRead (Function)\nSysFileRename (Function)\nSysFileSetPos (Function)\nSysFileTruncate (Function)\nSysFileWrite (Function)\nFile and Project Information\nLibrary Reference\nSysTypes2 Interfaces\nLibrary Identification\nLibrary Properties\nSysFile\nDocs\n»\nSysFileEOF (FUN)\nSysFileEOF (FUN)\nÂ¶\nFUNCTION SysFileEOF : RTS_IEC_RESULT\nCheck, if end of file is reached\nNote\nEnd of file is only checked after a read operation with SysFileRead! But after a SysFileWrite or SysFileSetPos call, the function\nreturns ERR_FAILED (no end of file)!\nInOut:\nScope\nName\nType\nComment\nReturn\nSysFileEOF\nRTS_IEC_RESULT\nReturns the runtime system error code (see CmpErrors.library):\nERR_OK: End of file reached at reading beyond the end of the file\nERR_FAILED: No end of file reached\nERR_PARAMETER: hFile is invalid\nInput\nhFile\nRTS_IEC_HANDLE\nHandle of the file\ntop\nCODESYS Group | We\nsoftware\nAutomation.\nto software\n['sɒftwɛər]\ntransitive verb\n__softwared/softwaring\n: to develop software\n// to software automation: to develop software for automation purposes\nThe CODESYS Group is the manufacturer of CODESYS, the leading hardware-independent\n                                    IEC 61131-3 automation software for developing and engineering controller\n                                    applications.\nCODESYS® is a registered trademark.\nCODESYS GmbH\nA member of the CODESYS Group\nMemminger Straße 151, 87439 Kempten\nGermany\nTel.:\n+49-831-54031-0\ninfo@codesys.com\nLegal Notice\nPrivacy Policy\nLinkedIn\nYoutube\nRSS\nDownloads\nLogin\nCODESYS Store\n© 2022 CODESYS GmbH\n| A member of the CODESYS Group",
  "tables": [
    {
      "headers": [
        "Scope",
        "Name",
        "Type",
        "Comment"
      ],
      "rows": [
        {
          "Scope": "Return",
          "Name": "SysFileEOF",
          "Type": "RTS_IEC_RESULT",
          "Comment": "Returns the runtime system error code (see CmpErrors.library):ERR_OK: End of file reached at reading beyond the end of the fileERR_FAILED: No end of file reachedERR_PARAMETER: hFile is invalid"
        },
        {
          "Scope": "Input",
          "Name": "hFile",
          "Type": "RTS_IEC_HANDLE",
          "Comment": "Handle of the file"
        }
      ]
    }
  ]
}