{
  "library": "Util",
  "title": "BCD_TO_INT (Function)",
  "url": "https://content.helpme-codesys.com/en/libs/Util/Current/BCD-Conversions/BCD_TO_INT.html",
  "page_title": "BCD_TO_INT (FUN)",
  "text": "Analog Monitors\nHYSTERESIS (FunctionBlock)\nLIMITALARM (FunctionBlock)\nBCD Conversions\nBCD_TO_BYTE (Function)\nBCD_TO_DWORD (Function)\nBCD_TO_INT (Function)\nBCD_TO_WORD (Function)\nBYTE_TO_BCD (Function)\nDWORD_TO_BCD (Function)\nINT_TO_BCD (Function)\nWORD_TO_BCD (Function)\nBit/Byte Functions\nBIT_AS_BYTE (FunctionBlock)\nBIT_AS_DWORD (FunctionBlock)\nBIT_AS_WORD (FunctionBlock)\nBYTE_AS_BIT (FunctionBlock)\nDWORD_AS_BIT (FunctionBlock)\nEXTRACT (Function)\nGETBIT (Function)\nPACK (Function)\nPUTBIT (Function)\nSETBIT (Function)\nSWITCHBIT (Function)\nUNPACK (FunctionBlock)\nWORD_AS_BIT (FunctionBlock)\nConstants\nTextBlockSize (ParamList)\nController\nPD (FunctionBlock)\nPID\n(FB)\nTemperature control with PID and LIMIT\nPID_FIXCYCLE (FunctionBlock)\nDatatypes\nGEN_MODE (Enum)\nPOINT (Struct)\nPT_SIZE (Struct)\nEncoding\nBASE64 (Function)\nFunction Manipulators\nCHARCURVE (FunctionBlock)\nRAMP_INT (FunctionBlock)\nRAMP_REAL (FunctionBlock)\nGray Conversions\nBYTE_TO_GRAY (Function)\nDWORD_TO_GRAY (Function)\nGRAY_TO_BYTE (Function)\nGRAY_TO_DWORD (Function)\nGRAY_TO_WORD (Function)\nWORD_TO_GRAY (Function)\nHEX/ASCII Functions\nBYTE_TO_HEXinASCII (Function)\nHEXinASCII_TO_BYTE (Function)\nWORD_AS_STRING (Function)\nLibrary Information\nGetLibVersion (Function)\nGetLibVersionNumber (Function)\nIsLibReleased (Function)\nMathematical Functions\nDERIVATIVE (FunctionBlock)\nINTEGRAL (FunctionBlock)\nLIN_TRAFO (FunctionBlock)\nROTATION_DIFFERENCE (FunctionBlock)\nSTATISTICS_INT (FunctionBlock)\nSTATISTICS_REAL (FunctionBlock)\nVARIANCE (FunctionBlock)\nSignals\nBLINK (FunctionBlock)\nFREQ_MEASURE (FunctionBlock)\nGEN (FunctionBlock)\nTimerSwitch\nEnums\nERROR (Enum)\nPERIOD (Enum)\nWEEKDAY (Enum)\nFunctionBlocks\nDateTimeProvider (FunctionBlock)\nGetDateTime (Method)\nTimerSwitch (FunctionBlock)\nIDateTimeProvider\nFunctions\nCombineDateTime (Function)\nDateTimeFromWeek (Function)\nDayOfWeek (Function)\nGetDateTime (Function)\nGetLocalDateTime (Function)\nGetTimeStampsDifference (Function)\nIsLeapYear (Function)\nJoinDateTime (Function)\nLocalDateTime (Function)\nSeparateDateTime (Function)\nSplitDateTime (Function)\nWeekOfYear (Function)\nGlobalConstants\nDAY_FLAGS (GVL)\nTSW (GVL)\nInterfaces\nIDateTimeProvider (Interface)\nGetDateTime (Method)\nStructs\nDateTime (Struct)\nSchedule (Struct)\nSegment (Struct)\nTimeZone (Struct)\nTypes\nDAY (Alias)\nDAYS (Alias)\nHOUR (Alias)\nMILLISECOND (Alias)\nMINUTE (Alias)\nMONTH (Alias)\nSECOND (Alias)\nTZ_NAME (Alias)\nWEEK (Alias)\nYEAR (Alias)\nFile and Project Information\nLibrary Reference\nCmpErrors2 Interfaces\nLibrary Identification\nLibrary Properties\nStandard\nLibrary Identification\nLibrary Properties\nSysMem\nLibrary Identification\nLibrary Properties\nSysTimeRtc\nLibrary Identification\nLibrary Properties\nSysTypes2 Interfaces\nLibrary Identification\nLibrary Properties\nUtil\nDocs\n»\nBCD\nConversions\n»\nBCD_TO_INT (FUN)\nBCD_TO_INT (FUN)\nÂ¶\nFUNCTION BCD_TO_INT : INT\nConverts one byte in BCD format into an INT value\nExample in ST:\ni\n:=\nBCD_TO_INT\n(\n73\n);\n(* Result is 49 *)\nk\n:=\nBCD_TO_INT\n(\n151\n);\n(* Result is 97 *)\nl\n:=\nBCD_TO_INT\n(\n15\n);\n(* Output -1, because it is not in BCD format *)\nInOut:\nScope\nName\nType\nComment\nReturn\nBCD_TO_INT\nINT\nValue as INT for the input\nB\nInput\nB\nBYTE\nValue in BCD code. If the value is not in the BCD format,\nthen the output is -1.",
  "tables": [
    {
      "headers": [
        "Scope",
        "Name",
        "Type",
        "Comment"
      ],
      "rows": [
        {
          "Scope": "Return",
          "Name": "BCD_TO_INT",
          "Type": "INT",
          "Comment": "Value as INT for the inputB"
        },
        {
          "Scope": "Input",
          "Name": "B",
          "Type": "BYTE",
          "Comment": "Value in BCD code. If the value is not in the BCD format,\nthen the output is -1."
        }
      ]
    }
  ]
}