{
  "library": "Util",
  "title": "GEN (FunctionBlock)",
  "url": "https://content.helpme-codesys.com/en/libs/Util/Current/Signals/GEN.html",
  "page_title": "GEN (FB)",
  "text": "Analog Monitors\nHYSTERESIS (FunctionBlock)\nLIMITALARM (FunctionBlock)\nBCD Conversions\nBCD_TO_BYTE (Function)\nBCD_TO_DWORD (Function)\nBCD_TO_INT (Function)\nBCD_TO_WORD (Function)\nBYTE_TO_BCD (Function)\nDWORD_TO_BCD (Function)\nINT_TO_BCD (Function)\nWORD_TO_BCD (Function)\nBit/Byte Functions\nBIT_AS_BYTE (FunctionBlock)\nBIT_AS_DWORD (FunctionBlock)\nBIT_AS_WORD (FunctionBlock)\nBYTE_AS_BIT (FunctionBlock)\nDWORD_AS_BIT (FunctionBlock)\nEXTRACT (Function)\nGETBIT (Function)\nPACK (Function)\nPUTBIT (Function)\nSETBIT (Function)\nSWITCHBIT (Function)\nUNPACK (FunctionBlock)\nWORD_AS_BIT (FunctionBlock)\nConstants\nTextBlockSize (ParamList)\nController\nPD (FunctionBlock)\nPID\n(FB)\nTemperature control with PID and LIMIT\nPID_FIXCYCLE (FunctionBlock)\nDatatypes\nGEN_MODE (Enum)\nPOINT (Struct)\nPT_SIZE (Struct)\nEncoding\nBASE64 (Function)\nFunction Manipulators\nCHARCURVE (FunctionBlock)\nRAMP_INT (FunctionBlock)\nRAMP_REAL (FunctionBlock)\nGray Conversions\nBYTE_TO_GRAY (Function)\nDWORD_TO_GRAY (Function)\nGRAY_TO_BYTE (Function)\nGRAY_TO_DWORD (Function)\nGRAY_TO_WORD (Function)\nWORD_TO_GRAY (Function)\nHEX/ASCII Functions\nBYTE_TO_HEXinASCII (Function)\nHEXinASCII_TO_BYTE (Function)\nWORD_AS_STRING (Function)\nLibrary Information\nGetLibVersion (Function)\nGetLibVersionNumber (Function)\nIsLibReleased (Function)\nMathematical Functions\nDERIVATIVE (FunctionBlock)\nINTEGRAL (FunctionBlock)\nLIN_TRAFO (FunctionBlock)\nROTATION_DIFFERENCE (FunctionBlock)\nSTATISTICS_INT (FunctionBlock)\nSTATISTICS_REAL (FunctionBlock)\nVARIANCE (FunctionBlock)\nSignals\nBLINK (FunctionBlock)\nFREQ_MEASURE (FunctionBlock)\nGEN (FunctionBlock)\nTimerSwitch\nEnums\nERROR (Enum)\nPERIOD (Enum)\nWEEKDAY (Enum)\nFunctionBlocks\nDateTimeProvider (FunctionBlock)\nGetDateTime (Method)\nTimerSwitch (FunctionBlock)\nIDateTimeProvider\nFunctions\nCombineDateTime (Function)\nDateTimeFromWeek (Function)\nDayOfWeek (Function)\nGetDateTime (Function)\nGetLocalDateTime (Function)\nGetTimeStampsDifference (Function)\nIsLeapYear (Function)\nJoinDateTime (Function)\nLocalDateTime (Function)\nSeparateDateTime (Function)\nSplitDateTime (Function)\nWeekOfYear (Function)\nGlobalConstants\nDAY_FLAGS (GVL)\nTSW (GVL)\nInterfaces\nIDateTimeProvider (Interface)\nGetDateTime (Method)\nStructs\nDateTime (Struct)\nSchedule (Struct)\nSegment (Struct)\nTimeZone (Struct)\nTypes\nDAY (Alias)\nDAYS (Alias)\nHOUR (Alias)\nMILLISECOND (Alias)\nMINUTE (Alias)\nMONTH (Alias)\nSECOND (Alias)\nTZ_NAME (Alias)\nWEEK (Alias)\nYEAR (Alias)\nFile and Project Information\nLibrary Reference\nCmpErrors2 Interfaces\nLibrary Identification\nLibrary Properties\nStandard\nLibrary Identification\nLibrary Properties\nSysMem\nLibrary Identification\nLibrary Properties\nSysTimeRtc\nLibrary Identification\nLibrary Properties\nSysTypes2 Interfaces\nLibrary Identification\nLibrary Properties\nUtil\nDocs\n»\nSignals\n»\nGEN (FB)\nGEN (FB)\nÂ¶\nFUNCTION_BLOCK GEN\nGenerates periodic functions of different, given types\nThe generation may be done relative to a specific time base or a given call-count base (\nBASE\n).\nAn example set of available types of periodic functions are shown in the following image.\nInOut:\nScope\nName\nType\nInitial\nComment\nInput\nMODE\nGEN_MODE\nTypes available:\nTRIANGLE\n: Triangular from -\nAMPLITUDE\nto +\nAMPLITUDE\nTRIANGLE_POS\n: Triangular from 0 to +\nAMPLITUDE\nSAWTOOTH_RISE\n: Sawtooth increasing from -\nAMPLITUDE\nto +\nAMPLITUDE\nSAWTOOTH_FALL\n: Sawtooth decreasing from +\nAMPLITUDE\nto -\nAMPLITUDE\nRECTANGLE\n: Rectangular switching from  -\nAMPLITUDE\nto +\nAMPLITUDE\nSINE\n: Sine\nCOSINE\n: Cosine\nBASE\nBOOL\nFALSE\n: Period referring to call (\nCYCLES\n)\nTRUE\n: Period referring to time (\nPERIOD\n)\nPERIOD\nTIME\nTIME#1s0ms\nPeriod time, only relevant if\nBASE\n=\nTRUE\nCYCLES\nINT\n1000\nNumber of calls per period, only relevant if\nBASE\n=\nFALSE\nAMPLITUDE\nINT\nAmplitud of the function to be generated\nRESET\nBOOL\nTRUE\n: Sets\nOUT\nto zero\nOutput\nOUT\nINT\nGenerated function value",
  "tables": [
    {
      "headers": [
        "Scope",
        "Name",
        "Type",
        "Initial",
        "Comment"
      ],
      "rows": [
        {
          "Scope": "Input",
          "Name": "MODE",
          "Type": "GEN_MODE",
          "Initial": "",
          "Comment": "Types available:TRIANGLE: Triangular from -AMPLITUDEto +AMPLITUDETRIANGLE_POS: Triangular from 0 to +AMPLITUDESAWTOOTH_RISE: Sawtooth increasing from -AMPLITUDEto +AMPLITUDESAWTOOTH_FALL: Sawtooth decreasing from +AMPLITUDEto -AMPLITUDERECTANGLE: Rectangular switching from  -AMPLITUDEto +AMPLITUDESINE: SineCOSINE: Cosine"
        },
        [
          "BASE",
          "BOOL",
          "",
          "FALSE: Period referring to call (CYCLES)TRUE: Period referring to time (PERIOD)"
        ],
        [
          "PERIOD",
          "TIME",
          "TIME#1s0ms",
          "Period time, only relevant ifBASE=TRUE"
        ],
        [
          "CYCLES",
          "INT",
          "1000",
          "Number of calls per period, only relevant ifBASE=FALSE"
        ],
        [
          "AMPLITUDE",
          "INT",
          "",
          "Amplitud of the function to be generated"
        ],
        [
          "RESET",
          "BOOL",
          "",
          "TRUE: SetsOUTto zero"
        ],
        {
          "Scope": "Output",
          "Name": "OUT",
          "Type": "INT",
          "Initial": "",
          "Comment": "Generated function value"
        }
      ]
    }
  ]
}