{
  "library": "SysDir",
  "title": "SysDirClose (Function)",
  "url": "https://content.helpme-codesys.com/en/libs/SysDir/Current/SysDirClose.html",
  "page_title": "SysDirClose (FUN)",
  "text": "Deutsch\nEnglish\nFrançais\nEspañol\nItaliano\nРусский\n日本語\n中文\nMenu\nSearch\nDeutsch\nEnglish\nFrançais\nEspañol\nItaliano\nРусский\n日本語\n中文\nDirFileTime (Struct)\nDirInfo (Struct)\nDirInfoFlags (GVL)\nSysDirClose (Function)\nSysDirCopy (Function)\nSysDirCreate (Function)\nSysDirCreate2 (Function)\nSysDirDelete (Function)\nSysDirDelete2 (Function)\nSysDirGetCurrent (Function)\nSysDirOpen (Function)\nSysDirRead (Function)\nSysDirRename (Function)\nSysDirSetCurrent (Function)\nFile and Project Information\nLibrary Reference\nCmpErrors2 Interfaces\nLibrary Identification\nLibrary Properties\nSysTypes2 Interfaces\nLibrary Identification\nLibrary Properties\nSysDir\nDocs\n»\nSysDirClose (FUN)\nSysDirClose (FUN)\nÂ¶\nFUNCTION SysDirClose : RTS_IEC_RESULT\nClose an open directory\nInOut:\nScope\nName\nType\nComment\nReturn\nSysDirClose\nRTS_IEC_RESULT\nReturns the runtime system error code (see\nCmpErrors_Itf.library)\nInput\nhDir\nRTS_IEC_HANDLE\nHandle to directory opened with SysDirOpen\ntop\nCODESYS Group | We\nsoftware\nAutomation.\nto software\n['sɒftwɛər]\ntransitive verb\n__softwared/softwaring\n: to develop software\n// to software automation: to develop software for automation purposes\nThe CODESYS Group is the manufacturer of CODESYS, the leading hardware-independent\n                                    IEC 61131-3 automation software for developing and engineering controller\n                                    applications.\nCODESYS® is a registered trademark.\nCODESYS GmbH\nA member of the CODESYS Group\nMemminger Straße 151, 87439 Kempten\nGermany\nTel.:\n+49-831-54031-0\ninfo@codesys.com\nLegal Notice\nPrivacy Policy\nLinkedIn\nYoutube\nRSS\nDownloads\nLogin\nCODESYS Store\n© 2022 CODESYS GmbH\n| A member of the CODESYS Group",
  "tables": [
    {
      "headers": [
        "Scope",
        "Name",
        "Type",
        "Comment"
      ],
      "rows": [
        {
          "Scope": "Return",
          "Name": "SysDirClose",
          "Type": "RTS_IEC_RESULT",
          "Comment": "Returns the runtime system error code (see\nCmpErrors_Itf.library)"
        },
        {
          "Scope": "Input",
          "Name": "hDir",
          "Type": "RTS_IEC_HANDLE",
          "Comment": "Handle to directory opened with SysDirOpen"
        }
      ]
    }
  ]
}