{
  "library": "AC_ModuleBase",
  "title": "AC_Visu_Base (FunctionBlock)",
  "url": "https://content.helpme-codesys.com/en/libs/AC_ModuleBase/Current/GenVisu/AC_Visu_Base.html",
  "page_title": "AC_Visu_Base (FB)",
  "text": "AC_Module\nBaseInstance (FunctionBlock)\nComAddress (Property)\nFB_EXIT (Method)\nInit (Method)\nInitParametersDone (Property)\nInstanceName (Property)\nMain (Method)\nOnAfterOnlineChange (Method)\nOnBeforeOnlineChange (Method)\nSetBaseIdentification (Method)\nCopyStr (Function)\nIBaseInstance (Interface)\nComAddress (Property)\nInit (Method)\nInstanceName (Property)\nMain (Method)\nOnAfterOnlineChange (Method)\nOnBeforeOnlineChange (Method)\nIBaseInstance2 (Interface)\nInitParametersDone (Property)\nIEnvironmentExtender (Interface)\nGetID (Property)\nIModule (Interface)\nErrorHandling\nClearErrors (Method)\nFirstErrorInstance (Property)\nFirstErrorNumber (Property)\nGetErrorMessage (Method)\nGetFirstErrorMessage (Method)\nGetLastErrorMessage (Method)\nLastErrorInstance (Property)\nLastErrorNumber (Property)\nIdentification\nEnvironment (Property)\nHandle (Property)\nModuleInfo (Property)\nStandardCalls\nCallPrioHighEnd (Method)\nCallPrioHighStart (Method)\nCallPrioLowEnd (Method)\nCallPrioLowStart (Method)\nCallPrioMediumEnd (Method)\nCallPrioMediumStart (Method)\nIModuleTree (Interface)\nGetFirstChild (Method)\nGetFirstToplevelInstance (Method)\nGetParent (Method)\nNextSibling (Method)\nPrevSibling (Method)\nMEnv (Struct)\nModule (FunctionBlock)\nErrorHandling\nClearErrors (Method)\nFirstErrorInstance (Property)\nFirstErrorNumber (Property)\nGetErrorMessage (Method)\nGetFirstErrorMessage (Method)\nGetLastErrorMessage (Method)\nLastErrorInstance (Property)\nLastErrorNumber (Property)\nReportError (Method)\nIdentification\nEnvironment (Property)\nHandle (Property)\nModuleInfo (Property)\nSetIdentification (Method)\nInit (Method)\nMain (Method)\nOnAfterOnlineChange (Method)\nOnBeforeOnlineChange (Method)\nStandardCalls\nCallPrioHighEnd (Method)\nCallPrioHighStart (Method)\nCallPrioLowEnd (Method)\nCallPrioLowStart (Method)\nCallPrioMediumEnd (Method)\nCallPrioMediumStart (Method)\nModuleHandle (Alias)\nModuleInfo (FunctionBlock)\nModuleType (Property)\nProxyInstance (FunctionBlock)\nLocalComAddress (Property)\nMain (Method)\nSetProxyIdentification (Method)\nTreeNavigation\nAncestorRange (FunctionBlock)\nFirst (Property)\nInit (Method)\nIsEmpty (Property)\nPopFirst (Method)\nDepthFirstRange (FunctionBlock)\nFirst (Property)\nInit (Method)\nIsEmpty (Property)\nPopFirst (Method)\nGetAncestorRange (Function)\nGetChildRange (Function)\nGetDepthFirstRange (Function)\nGetInstancePath (Function)\nGetLastChild (Function)\nGetLastInRange (Function)\nGetLastSibling (Function)\nGetNextModule (Function)\nGetPrevModule (Function)\nGetToplevelInstance (Function)\nGetToplevelRange (Function)\nIModuleRangeForward (Interface)\nFirst (Property)\nIsEmpty (Property)\nPopFirst (Method)\nSiblingRange (FunctionBlock)\nFirst (Property)\nInit (Method)\nIsEmpty (Property)\nPopFirst (Method)\nAC_RMP_ReliableMessageProtocol\nAC_RMP_FBCommunication\nIRMPFBCommunication (Interface)\nCyclicCall (Method)\nInitializeCommunicationFBConnections (Method)\nInitializeCommunicationParameters (Method)\nInitializeReceiveBuffers (Method)\nInitializeSendBuffers (Method)\nReceiveComAdress (Property)\nReceiveCounter (Property)\nSendCounter (Property)\nSendToComAdress (Property)\nRMPVarData (Struct)\nIRMPService (Interface)\nIsMessageSent (Method)\nLocalAppID (Property)\nQueueSendMessage (Method)\nReceive (Method)\nIRmpService2 (Interface)\nGetIsActionOngoing (Method)\nSetIsActionOngoing (Method)\nIRmpService3 (Interface)\nGetComFBForComAddress (Method)\nRMPBufferedMessage (Struct)\nRMPConnection (FunctionBlock)\nActivate (Method)\nActiveIndexInQueue (Property)\nCheckConnectivity (Method)\nDeactivate (Method)\nIsActive (Property)\nIsUp (Property)\nRMPExchangeData (Struct)\nRMPMessageBuffer (FunctionBlock)\nAddMessage (Method)\nClearExpiredMessages (Method)\nDelete (Method)\nEnlargeExpirationTime (Method)\nExistsMessageWithHandle (Method)\nGetMessage (Method)\nGetMessageForReceiver (Method)\nGetMessageToApplication (Method)\nLock (Method)\nUnlock (Method)\nRMPSendMessage (FunctionBlock)\nCyclicAction (Method)\nResetAction (Method)\nStartAction (Method)\nRMPService (FunctionBlock)\nCyclic\nCyclicCall (Method)\nGetComFBForComAddress (Method)\nGetIsActionOngoing (Method)\nLocalAppID (Property)\nReceive\nReceive (Method)\nSend\nIsMessageSent (Method)\nQueueSendMessage (Method)\nSetIsActionOngoing (Method)\nRMP_GVL (GVL)\nRMP_GVL_CONST (GVL)\nGenVisu\nAC_Visu_Base (FunctionBlock)\nBack (Method)\nChangeFrame (Method)\nClearHistory (Method)\nForward (Method)\nGetModuleFrameIndex (Method)\nUp (Method)\nprotected\nGetAncestor (Method)\nOnFrameIndexChanged (Method)\nGVL_Visu (GVL)\nGenVisu_Toplevel_Template\nGetCurrentDisplayedModuleInstance (Function)\nIModuleVisuClientListener (Interface)\nClientCreated (Method)\nClientDestroyed (Method)\nOnClientCreatedOrDestroyed (Function)\nOnClientCreatedOrDestroyed_2 (Function)\nToplevel_Vertical_Template\nIP_Toplevel_Template (ImagePool)\nGlobalTextList (GlobalTextList)\nLibrary Information\nGetLibVersion (Function)\nGetLibVersionNumber (Function)\nIsLibReleased (Function)\nFile and Project Information\nLibrary Reference\nAC_Persistence\nLibrary Identification\nLibrary Properties\nLibrary Parameter\nCAA Types Extern\nLibrary Identification\nLibrary Properties\nCmpIecTask\nLibrary Identification\nLibrary Properties\nCmpLog\nLibrary Identification\nLibrary Properties\nCommon Behaviour Model\nLibrary Identification\nLibrary Properties\nComponent Manager\nLibrary Identification\nLibrary Properties\nIoStandard\nLibrary Identification\nLibrary Properties\nStandard\nLibrary Identification\nLibrary Properties\nSysCpuHandling\nLibrary Identification\nLibrary Properties\nSysTypes2 Interfaces\nLibrary Identification\nLibrary Properties\nVisuElem3DPath\nLibrary Identification\nLibrary Properties\nLibrary Parameter\nVisuElemCamDisplayer\nLibrary Identification\nLibrary Properties\nLibrary Parameter\nVisuElemMeter\nLibrary Identification\nLibrary Properties\nVisuElemTextEditor\nLibrary Identification\nLibrary Properties\nVisuElemTrace\nLibrary Identification\nLibrary Properties\nVisuElemXYChart\nLibrary Identification\nLibrary Properties\nVisuElems\nLibrary Identification\nLibrary Properties\nVisuElemsAlarm\nLibrary Identification\nLibrary Properties\nVisuElemsDateTime\nLibrary Identification\nLibrary Properties\nVisuElemsSpecialControls\nLibrary Identification\nLibrary Properties\nVisuElemsWinControls\nLibrary Identification\nLibrary Properties\nVisuNativeControl\nLibrary Identification\nLibrary Properties\nAC_ModuleBase\nDocs\n»\nGenVisu\n»\nAC_Visu_Base (FB)\nAC_Visu_Base (FB)\nÂ¶\nFUNCTION_BLOCK ABSTRACT AC_Visu_Base\nThis function block implements the logic of the visualizations\ngenerated by GenVisu.\nSpecific information about the ancestor visualization and custom\nbehavior on frame changes is provided by extending this FB and\nimplementing the methods GetAncestor() and OnFrameChanged().\nThis FB must be called cyclically, preferably at the end of the\nvisu task.\nInputs\nIf uiFrameIdx is set to a value different from uiCurFrameIdx,\nthe frame is changed in the next cycle\nIf xUp, xBack, or xFwd is set, the corresponding navigation is\nperformed in the next cycle.\nIf xâ¦Pressed is set or reset, the output state (iâ¦State) is set\naccordingly.\nNote\n: At the end of each cycle, xUp, xBack, and xFwd are set to\nFALSE and uiFrameIdx is set to uiCurFrameIdx.\nOutputs\nThe output variable uiCurFrameIdx controls which visualization is\ndisplayed in the main frame of the toplevel visualization.\nThe output variables stAddr controls the content of the address bar.\nThe output variables iâ¦State control whether the respective\nnavigation buttons are pressed or disabled.\nAdditional functions created during generation\nDuring generation this function block gets attached a method\nGetModuleFrameIndex, which allows to get the index of the page\nvisu in the main frame, which belongs to certain module\nBy this it is possible to arbitrallily change pages visus\nand i.e. jump from one page visu to a completelly different on\ndepending on some own IEC logic.\nInOut:\nScope\nName\nType\nInitial\nComment\nInput\nuiFrameIdx\nUINT\n0\nThe new frame index to change to\nxUp\nBOOL\nFALSE\nWhether Up() should be called\nxBack\nBOOL\nFALSE\nWhether Back() should be called\nxFwd\nBOOL\nFALSE\nWhether Forward() should be called\nxUpPressed\nBOOL\nFALSE\nWhether the Up button is currently pressed\nxBackPressed\nBOOL\nFALSE\nWhether the Back button is currently pressed\nxFwdPressed\nBOOL\nFALSE\nWhether the Forward button is currently pressed\nOutput\nuiCurFrameIdx\nUINT\n0\nThe current frame index\nstAddr\nSTRING\nââ\nThe current âmodule addressâ displayed in the visu\niUpState\nINT\n0\n0: neutral, 1: pressed, 2: disabled\niBackState\nINT\n0\n0: neutral, 1: pressed, 2: disabled\niFwdState\nINT\n0\n0: neutral, 1: pressed, 2: disabled\nMethods:\nBack\nChangeFrame\nClearHistory\nForward\nGetModuleFrameIndex\nUp\nGetAncestor\nOnFrameIndexChanged\nStructure:\nBack (Method)\nChangeFrame (Method)\nClearHistory (Method)\nForward (Method)\nGetModuleFrameIndex (Method)\nUp (Method)\nprotected\nGetAncestor (Method)\nOnFrameIndexChanged (Method)",
  "tables": [
    {
      "headers": [
        "Scope",
        "Name",
        "Type",
        "Initial",
        "Comment"
      ],
      "rows": [
        {
          "Scope": "Input",
          "Name": "uiFrameIdx",
          "Type": "UINT",
          "Initial": "0",
          "Comment": "The new frame index to change to"
        },
        [
          "xUp",
          "BOOL",
          "FALSE",
          "Whether Up() should be called"
        ],
        [
          "xBack",
          "BOOL",
          "FALSE",
          "Whether Back() should be called"
        ],
        [
          "xFwd",
          "BOOL",
          "FALSE",
          "Whether Forward() should be called"
        ],
        [
          "xUpPressed",
          "BOOL",
          "FALSE",
          "Whether the Up button is currently pressed"
        ],
        [
          "xBackPressed",
          "BOOL",
          "FALSE",
          "Whether the Back button is currently pressed"
        ],
        [
          "xFwdPressed",
          "BOOL",
          "FALSE",
          "Whether the Forward button is currently pressed"
        ],
        {
          "Scope": "Output",
          "Name": "uiCurFrameIdx",
          "Type": "UINT",
          "Initial": "0",
          "Comment": "The current frame index"
        },
        [
          "stAddr",
          "STRING",
          "ââ",
          "The current âmodule addressâ displayed in the visu"
        ],
        [
          "iUpState",
          "INT",
          "0",
          "0: neutral, 1: pressed, 2: disabled"
        ],
        [
          "iBackState",
          "INT",
          "0",
          "0: neutral, 1: pressed, 2: disabled"
        ],
        [
          "iFwdState",
          "INT",
          "0",
          "0: neutral, 1: pressed, 2: disabled"
        ]
      ]
    }
  ]
}