{
  "library": "IoStandard",
  "title": "private_iomgr_memcpy (Function)",
  "url": "https://content.helpme-codesys.com/en/libs/IoStandard/Current/Config-Access-Help-Functions-internal/private/private_iomgr_memcpy.html",
  "page_title": "private_iomgr_memcpy (FUN)",
  "text": "Deutsch\nEnglish\nFrançais\nEspañol\nItaliano\nРусский\n日本語\n中文\nMenu\nSearch\nDeutsch\nEnglish\nFrançais\nEspañol\nItaliano\nРусский\n日本語\n中文\nConfig Access Help Functions (internal)\nConfigGetConnector (Function)\nConfigGetFirstChild (Function)\nConfigGetFirstConnector (Function)\nConfigGetNextChild (Function)\nConfigGetNextConnector (Function)\nConfigGetParameter (Function)\nConfigGetParameterLength (Function)\nConfigGetParameterValueByte (Function)\nConfigGetParameterValueDword (Function)\nConfigGetParameterValuePointer (Function)\nConfigGetParameterValueWord (Function)\nprivate\nprivate_iomgr_memcpy (Function)\nFile and Project Information\nLibrary Reference\nBase Interfaces\nLibrary Identification\nLibrary Properties\nCmpErrors2 Interfaces\nLibrary Identification\nLibrary Properties\nCmpIoMgr Implementation\nLibrary Identification\nLibrary Properties\nCmpIoMgr Interfaces\nLibrary Identification\nLibrary Properties\nSysTypes2 Interfaces\nLibrary Identification\nLibrary Properties\nIoStandard\nDocs\n»\nConfig\nAccess\nHelp\nFunctions\n(internal)\n»\nprivate\n»\nprivate_iomgr_memcpy (FUN)\nprivate_iomgr_memcpy (FUN)\nÂ¶\nFUNCTION private_iomgr_memcpy : INT\nInOut:\nScope\nName\nType\nReturn\nprivate_iomgr_memcpy\nINT\nInput\npSrc\nPOINTER TO BYTE\npDst\nPOINTER TO BYTE\niSize\nINT\ntop\nCODESYS Group | We\nsoftware\nAutomation.\nto software\n['sɒftwɛər]\ntransitive verb\n__softwared/softwaring\n: to develop software\n// to software automation: to develop software for automation purposes\nThe CODESYS Group is the manufacturer of CODESYS, the leading hardware-independent\n                                    IEC 61131-3 automation software for developing and engineering controller\n                                    applications.\nCODESYS® is a registered trademark.\nCODESYS GmbH\nA member of the CODESYS Group\nMemminger Straße 151, 87439 Kempten\nGermany\nTel.:\n+49-831-54031-0\ninfo@codesys.com\nLegal Notice\nPrivacy Policy\nLinkedIn\nYoutube\nRSS\nDownloads\nLogin\nCODESYS Store\n© 2022 CODESYS GmbH\n| A member of the CODESYS Group",
  "tables": [
    {
      "headers": [
        "Scope",
        "Name",
        "Type"
      ],
      "rows": [
        {
          "Scope": "Return",
          "Name": "private_iomgr_memcpy",
          "Type": "INT"
        },
        {
          "Scope": "Input",
          "Name": "pSrc",
          "Type": "POINTER TO BYTE"
        },
        [
          "pDst",
          "POINTER TO BYTE"
        ],
        [
          "iSize",
          "INT"
        ]
      ]
    }
  ]
}