{
  "library": "CommFB",
  "title": "ADDR (Function)",
  "url": "https://content.helpme-codesys.com/en/libs/CommFB/Current/CommFB/DP-Address/ADDR.html#",
  "page_title": "ADDR (FUN)",
  "text": "CommFB\nAINFO_TYPE (Union)\nAddressConcept (GVL)\nAddress Concept\nGenerating a CommFB-ID\nProfibus DP\nProfinet IO\nDevice Diagnosis\nAddress Conversion\nAddresses\nADDR_TO_ID (FunctionBlock)\nADDR_TYPE (Union)\nCREATE_ID (FunctionBlock)\nDP_ADDR (Struct)\nDP_DEVICE_ID (Struct)\nID_TO_ADDR (FunctionBlock)\nIO_SYSTEM_TYPE (Enum)\nPN_ADDR (Struct)\nPN_DEVICE_ID (Struct)\nSUBSLOT_ID (Function)\nCNCT (FunctionBlock)\nConstants (GVL)\nDP Address\nADDR (Function)\nID (Function)\nSLOT_ID (Function)\nDP_AINFO (Struct)\nDP_DIAG (Struct)\nErrorCode (Enum)\nErrorCode1_RW (Enum)\nFieldDevice\nPRVREC (FunctionBlock)\nPRVREC_MODE (Enum)\nRCVREC (FunctionBlock)\nRCVREC_MODE (Enum)\nSALARM (FunctionBlock)\nGETIO_PART (FunctionBlock)\nPN_AINFO (Struct)\nRALARM (FunctionBlock)\nRALARM_MODE (Enum)\nRDIAG (FunctionBlock)\nRDREC (FunctionBlock)\nSETIO_PART (FunctionBlock)\nWRREC (FunctionBlock)\nImages\nLibrary Information\nGetLibVersion (Function)\nGetLibVersionNumber (Function)\nIsLibReleased (Function)\nFile and Project Information\nLibrary Reference\nIoDriver Profibus2 Interfaces\nLibrary Identification\nLibrary Properties\nSysMem\nLibrary Identification\nLibrary Properties\nCommFB\nDocs\n»\nCommFB\n»\nDP\nAddress\n»\nADDR (FUN)\nADDR (FUN)\nÂ¶\nFUNCTION ADDR : DWORD\nThis function converts a handle which addresses a slot or a DP-slave into its physical address.\nInOut:\nScope\nName\nType\nInitial\nComment\nReturn\nADDR\nDWORD\nInput\nEN\nBOOL\nTRUE\nID\nDWORD\nSlot or device handle\nOutput\nENO\nBOOL",
  "tables": [
    {
      "headers": [
        "Scope",
        "Name",
        "Type",
        "Initial",
        "Comment"
      ],
      "rows": [
        {
          "Scope": "Return",
          "Name": "ADDR",
          "Type": "DWORD",
          "Initial": "",
          "Comment": ""
        },
        {
          "Scope": "Input",
          "Name": "EN",
          "Type": "BOOL",
          "Initial": "TRUE",
          "Comment": ""
        },
        [
          "ID",
          "DWORD",
          "",
          "Slot or device handle"
        ],
        {
          "Scope": "Output",
          "Name": "ENO",
          "Type": "BOOL",
          "Initial": "",
          "Comment": ""
        }
      ]
    }
  ]
}