{
  "library": "CommFB",
  "title": "Constants (GVL)",
  "url": "https://content.helpme-codesys.com/en/libs/CommFB/Current/CommFB/Constants.html",
  "page_title": "Constants (GVL)",
  "text": "CommFB\nAINFO_TYPE (Union)\nAddressConcept (GVL)\nAddress Concept\nGenerating a CommFB-ID\nProfibus DP\nProfinet IO\nDevice Diagnosis\nAddress Conversion\nAddresses\nADDR_TO_ID (FunctionBlock)\nADDR_TYPE (Union)\nCREATE_ID (FunctionBlock)\nDP_ADDR (Struct)\nDP_DEVICE_ID (Struct)\nID_TO_ADDR (FunctionBlock)\nIO_SYSTEM_TYPE (Enum)\nPN_ADDR (Struct)\nPN_DEVICE_ID (Struct)\nSUBSLOT_ID (Function)\nCNCT (FunctionBlock)\nConstants (GVL)\nDP Address\nADDR (Function)\nID (Function)\nSLOT_ID (Function)\nDP_AINFO (Struct)\nDP_DIAG (Struct)\nErrorCode (Enum)\nErrorCode1_RW (Enum)\nFieldDevice\nPRVREC (FunctionBlock)\nPRVREC_MODE (Enum)\nRCVREC (FunctionBlock)\nRCVREC_MODE (Enum)\nSALARM (FunctionBlock)\nGETIO_PART (FunctionBlock)\nPN_AINFO (Struct)\nRALARM (FunctionBlock)\nRALARM_MODE (Enum)\nRDIAG (FunctionBlock)\nRDREC (FunctionBlock)\nSETIO_PART (FunctionBlock)\nWRREC (FunctionBlock)\nImages\nLibrary Information\nGetLibVersion (Function)\nGetLibVersionNumber (Function)\nIsLibReleased (Function)\nFile and Project Information\nLibrary Reference\nIoDriver Profibus2 Interfaces\nLibrary Identification\nLibrary Properties\nSysMem\nLibrary Identification\nLibrary Properties\nCommFB\nDocs\n»\nCommFB\n»\nConstants (GVL)\nConstants (GVL)\nÂ¶\nAttributes:\nqualified_only\nInOut:\nScope\nName\nType\nInitial\nConstant\nINVALID_ID\nUDINT\n16#FFFFFFFF\nMAX_PN_ALARM_DATA\nUDINT\n198",
  "tables": [
    {
      "headers": [
        "Scope",
        "Name",
        "Type",
        "Initial"
      ],
      "rows": [
        {
          "Scope": "Constant",
          "Name": "INVALID_ID",
          "Type": "UDINT",
          "Initial": "16#FFFFFFFF"
        },
        [
          "MAX_PN_ALARM_DATA",
          "UDINT",
          "198"
        ]
      ]
    }
  ]
}