{
  "library": "CommFB",
  "title": "RALARM (FunctionBlock)",
  "url": "https://content.helpme-codesys.com/en/libs/CommFB/Current/CommFB/RALARM.html",
  "page_title": "RALARM (FB)",
  "text": "CommFB\nAINFO_TYPE (Union)\nAddressConcept (GVL)\nAddress Concept\nGenerating a CommFB-ID\nProfibus DP\nProfinet IO\nDevice Diagnosis\nAddress Conversion\nAddresses\nADDR_TO_ID (FunctionBlock)\nADDR_TYPE (Union)\nCREATE_ID (FunctionBlock)\nDP_ADDR (Struct)\nDP_DEVICE_ID (Struct)\nID_TO_ADDR (FunctionBlock)\nIO_SYSTEM_TYPE (Enum)\nPN_ADDR (Struct)\nPN_DEVICE_ID (Struct)\nSUBSLOT_ID (Function)\nCNCT (FunctionBlock)\nConstants (GVL)\nDP Address\nADDR (Function)\nID (Function)\nSLOT_ID (Function)\nDP_AINFO (Struct)\nDP_DIAG (Struct)\nErrorCode (Enum)\nErrorCode1_RW (Enum)\nFieldDevice\nPRVREC (FunctionBlock)\nPRVREC_MODE (Enum)\nRCVREC (FunctionBlock)\nRCVREC_MODE (Enum)\nSALARM (FunctionBlock)\nGETIO_PART (FunctionBlock)\nPN_AINFO (Struct)\nRALARM (FunctionBlock)\nRALARM_MODE (Enum)\nRDIAG (FunctionBlock)\nRDREC (FunctionBlock)\nSETIO_PART (FunctionBlock)\nWRREC (FunctionBlock)\nImages\nLibrary Information\nGetLibVersion (Function)\nGetLibVersionNumber (Function)\nIsLibReleased (Function)\nFile and Project Information\nLibrary Reference\nIoDriver Profibus2 Interfaces\nLibrary Identification\nLibrary Properties\nSysMem\nLibrary Identification\nLibrary Properties\nCommFB\nDocs\n»\nCommFB\n»\nRALARM (FB)\nRALARM (FB)\nÂ¶\nFUNCTION_BLOCK RALARM\nThe RALARM function block is used to receive alarm information of alarms from a PROFIBUS DP or a PROFINET IO subsystem.\nCode-Example: receive Alarm\nPROGRAM\nPLC_PRG\nVAR\nralarm\n:\nCommFB.RALARM\n;\nalarm\n:\nCommFB.AINFO_TYPE\n;\nconvertID\n:\nCommFB.ID_TO_ADDR\n;\naddr\n:\nCommFB.ADDR_TYPE\n;\nmessage\n:\nSTRING\n;\nEND_VAR\nralarm.EN\n:=\nTRUE\n;\nralarm.MODE\n:=\nCommFB.RALARM_MODE.ALL_ALARMS\n;\n// receive all alarms from all devices connected to the controller\nralarm.F_ID\n:=\nPN_Controller.MasterID\n;\n// Filter ID, if MODE = ALL_ALARMS use MasterID here, else the ID of a slot/subslot\nralarm\n(\nainfo\n:=\nalarm\n);\nWHILE\n(\nralarm.NEW\n)\nDO\nconvertID\n(\nEN\n:=\nTRUE\n,\nID\n:=\nralarm.ID\n,\nADDR\n:=\naddr\n);\nIF\n(\nconvertID.ENO\n)\nTHEN\nIF\n(\naddr.SYSTEM\n=\nCommFB.IO_SYSTEM_TYPE.PROFINET_IO\n)\nTHEN\nmessage\n:=\n'Station '\n;\nmessage\n:=\nconcat\n(\nmessage\n,\naddr.PN.D.STATIONNAME\n);\nmessage\n:=\nconcat\n(\nmessage\n,\n' (Slot = '\n);\nmessage\n:=\nconcat\n(\nmessage\n,\nTO_STRING\n(\naddr.PN.SLOT\n));\nmessage\n:=\nconcat\n(\nmessage\n,\n') sends an alarm !'\n);\n//Log Alarm to PLC-Logger\nCmpLog.LogAdd2\n(\nCmpLog.LogConstants.LOG_STD_LOGGER\n,\n555\n,\nCmpLog.LogClass.LOG_WARNING\n,\n0\n,\n0\n,\nmessage\n);\nEND_IF\nEND_IF\nralarm\n(\nainfo\n:=\nalarm\n);\n// exec-again\nEND_WHILE\nInOut:\nScope\nName\nType\nComment\nInput\nEN\nBOOL\nEnable\nMODE\nINT\nFunction specifier, see RALARM_MODE enum\nF_ID\nDWORD\nSlot / subslot identification to filter the alarms to receive.\n| If MODE = RALARM_MODE.ALL_ALARMS user MasterID\nOutput\nENO\nBOOL\nFunction enabled, no error\nNEW\nBOOL\nNew alarm received\nSTATUS\nDWORD\nHost Controller interface status\nID\nDWORD\nIdentifier of the slot / subslot the alarm is received from\n(see:\nAddressConcept\n)\nLEN\nINT\nLength of the received data record\nInout\nAINFO\nAINFO_TYPE\nAlarm data that has been received",
  "tables": [
    {
      "headers": [
        "Scope",
        "Name",
        "Type",
        "Comment"
      ],
      "rows": [
        {
          "Scope": "Input",
          "Name": "EN",
          "Type": "BOOL",
          "Comment": "Enable"
        },
        [
          "MODE",
          "INT",
          "Function specifier, see RALARM_MODE enum"
        ],
        [
          "F_ID",
          "DWORD",
          "Slot / subslot identification to filter the alarms to receive.\n| If MODE = RALARM_MODE.ALL_ALARMS user MasterID"
        ],
        {
          "Scope": "Output",
          "Name": "ENO",
          "Type": "BOOL",
          "Comment": "Function enabled, no error"
        },
        [
          "NEW",
          "BOOL",
          "New alarm received"
        ],
        [
          "STATUS",
          "DWORD",
          "Host Controller interface status"
        ],
        [
          "ID",
          "DWORD",
          "Identifier of the slot / subslot the alarm is received from\n(see:AddressConcept)"
        ],
        [
          "LEN",
          "INT",
          "Length of the received data record"
        ],
        {
          "Scope": "Inout",
          "Name": "AINFO",
          "Type": "AINFO_TYPE",
          "Comment": "Alarm data that has been received"
        }
      ]
    }
  ]
}