{
  "library": "CommFB",
  "title": "SUBSLOT_ID (Function)",
  "url": "https://content.helpme-codesys.com/en/libs/CommFB/Current/CommFB/Addresses/SUBSLOT_ID.html",
  "page_title": "SUBSLOT_ID (FUN)",
  "text": "CommFB\nAINFO_TYPE (Union)\nAddressConcept (GVL)\nAddress Concept\nGenerating a CommFB-ID\nProfibus DP\nProfinet IO\nDevice Diagnosis\nAddress Conversion\nAddresses\nADDR_TO_ID (FunctionBlock)\nADDR_TYPE (Union)\nCREATE_ID (FunctionBlock)\nDP_ADDR (Struct)\nDP_DEVICE_ID (Struct)\nID_TO_ADDR (FunctionBlock)\nIO_SYSTEM_TYPE (Enum)\nPN_ADDR (Struct)\nPN_DEVICE_ID (Struct)\nSUBSLOT_ID (Function)\nCNCT (FunctionBlock)\nConstants (GVL)\nDP Address\nADDR (Function)\nID (Function)\nSLOT_ID (Function)\nDP_AINFO (Struct)\nDP_DIAG (Struct)\nErrorCode (Enum)\nErrorCode1_RW (Enum)\nFieldDevice\nPRVREC (FunctionBlock)\nPRVREC_MODE (Enum)\nRCVREC (FunctionBlock)\nRCVREC_MODE (Enum)\nSALARM (FunctionBlock)\nGETIO_PART (FunctionBlock)\nPN_AINFO (Struct)\nRALARM (FunctionBlock)\nRALARM_MODE (Enum)\nRDIAG (FunctionBlock)\nRDREC (FunctionBlock)\nSETIO_PART (FunctionBlock)\nWRREC (FunctionBlock)\nImages\nLibrary Information\nGetLibVersion (Function)\nGetLibVersionNumber (Function)\nIsLibReleased (Function)\nFile and Project Information\nLibrary Reference\nIoDriver Profibus2 Interfaces\nLibrary Identification\nLibrary Properties\nSysMem\nLibrary Identification\nLibrary Properties\nCommFB\nDocs\n»\nCommFB\n»\nAddresses\n»\nSUBSLOT_ID (FUN)\nSUBSLOT_ID (FUN)\nÂ¶\nFUNCTION SUBSLOT_ID : DWORD\nReturns the ID of a subslot.\nInOut:\nScope\nName\nType\nInitial\nComment\nReturn\nSUBSLOT_ID\nDWORD\nInput\nEN\nBOOL\nTRUE\nOptional\nID\nDWORD\nHandle to a PN-slave or a subslot\nSLOT\nUINT\nSlot number\nSUBSLOT\nUINT\nSubslot number. Use 0 for Profibus DP\nOutput\nENO\nBOOL\nTRUE: Subslot ID found; FALSE: The requested Subslot could\nnot be found.",
  "tables": [
    {
      "headers": [
        "Scope",
        "Name",
        "Type",
        "Initial",
        "Comment"
      ],
      "rows": [
        {
          "Scope": "Return",
          "Name": "SUBSLOT_ID",
          "Type": "DWORD",
          "Initial": "",
          "Comment": ""
        },
        {
          "Scope": "Input",
          "Name": "EN",
          "Type": "BOOL",
          "Initial": "TRUE",
          "Comment": "Optional"
        },
        [
          "ID",
          "DWORD",
          "",
          "Handle to a PN-slave or a subslot"
        ],
        [
          "SLOT",
          "UINT",
          "",
          "Slot number"
        ],
        [
          "SUBSLOT",
          "UINT",
          "",
          "Subslot number. Use 0 for Profibus DP"
        ],
        {
          "Scope": "Output",
          "Name": "ENO",
          "Type": "BOOL",
          "Initial": "",
          "Comment": "TRUE: Subslot ID found; FALSE: The requested Subslot could\nnot be found."
        }
      ]
    }
  ]
}