{
  "library": "Standard",
  "title": "R_TRIG (FunctionBlock)",
  "url": "https://content.helpme-codesys.com/en/libs/Standard/Current/Trigger/R_TRIG.html",
  "page_title": "R_TRIG (FB)",
  "text": "Deutsch\nEnglish\nFrançais\nEspañol\nItaliano\nРусский\n日本語\n中文\nMenu\nSearch\nDeutsch\nEnglish\nFrançais\nEspañol\nItaliano\nРусский\n日本語\n中文\nBistable Function Blocks\nRS (FunctionBlock)\nSR (FunctionBlock)\nCounter\nCTD (FunctionBlock)\nCTU (FunctionBlock)\nCTUD (FunctionBlock)\nMiscellaneous\nRTC (FunctionBlock)\nString Functions\nCONCAT (Function)\nDELETE (Function)\nFIND (Function)\nINSERT (Function)\nLEFT (Function)\nLEN (Function)\nMID (Function)\nREPLACE (Function)\nRIGHT (Function)\nTimer\nTOF (FunctionBlock)\nTON (FunctionBlock)\nTP (FunctionBlock)\nTrigger\nF_TRIG (FunctionBlock)\nR_TRIG (FunctionBlock)\nFile and Project Information\nLibrary Reference\nStandard\nDocs\n»\nTrigger\n»\nR_TRIG (FB)\nR_TRIG (FB)\nÂ¶\nFUNCTION_BLOCK R_TRIG\nDetects a rising edge of a boolean signal\n(* Example declaration *)\nRTRIGInst\n:\nR_TRIG\n;\n(* Example in ST *)\nRTRIGInst\n(\nCLK\n:=\nVarBOOL1\n);\nVarBOOL2\n:=\nRTRIGInst.Q\n;\nInOut:\nScope\nName\nType\nComment\nInput\nCLK\nBOOL\nBoolean signal to be checked\nOutput\nQ\nBOOL\nTRUE\n: Rising edge detected\ntop\nCODESYS Group | We\nsoftware\nAutomation.\nto software\n['sɒftwɛər]\ntransitive verb\n__softwared/softwaring\n: to develop software\n// to software automation: to develop software for automation purposes\nThe CODESYS Group is the manufacturer of CODESYS, the leading hardware-independent\n                                    IEC 61131-3 automation software for developing and engineering controller\n                                    applications.\nCODESYS® is a registered trademark.\nCODESYS GmbH\nA member of the CODESYS Group\nMemminger Straße 151, 87439 Kempten\nGermany\nTel.:\n+49-831-54031-0\ninfo@codesys.com\nLegal Notice\nPrivacy Policy\nLinkedIn\nYoutube\nRSS\nDownloads\nLogin\nCODESYS Store\n© 2022 CODESYS GmbH\n| A member of the CODESYS Group",
  "tables": [
    {
      "headers": [
        "Scope",
        "Name",
        "Type",
        "Comment"
      ],
      "rows": [
        {
          "Scope": "Input",
          "Name": "CLK",
          "Type": "BOOL",
          "Comment": "Boolean signal to be checked"
        },
        {
          "Scope": "Output",
          "Name": "Q",
          "Type": "BOOL",
          "Comment": "TRUE: Rising edge detected"
        }
      ]
    }
  ]
}