{
  "library": "Standard",
  "title": "SR (FunctionBlock)",
  "url": "https://content.helpme-codesys.com/en/libs/Standard/Current/Bistable-Function-Blocks/SR.html",
  "page_title": "SR (FB)",
  "text": "Deutsch\nEnglish\nFrançais\nEspañol\nItaliano\nРусский\n日本語\n中文\nMenu\nSearch\nDeutsch\nEnglish\nFrançais\nEspañol\nItaliano\nРусский\n日本語\n中文\nBistable Function Blocks\nRS (FunctionBlock)\nSR (FunctionBlock)\nCounter\nCTD (FunctionBlock)\nCTU (FunctionBlock)\nCTUD (FunctionBlock)\nMiscellaneous\nRTC (FunctionBlock)\nString Functions\nCONCAT (Function)\nDELETE (Function)\nFIND (Function)\nINSERT (Function)\nLEFT (Function)\nLEN (Function)\nMID (Function)\nREPLACE (Function)\nRIGHT (Function)\nTimer\nTOF (FunctionBlock)\nTON (FunctionBlock)\nTP (FunctionBlock)\nTrigger\nF_TRIG (FunctionBlock)\nR_TRIG (FunctionBlock)\nFile and Project Information\nLibrary Reference\nStandard\nDocs\n»\nBistable\nFunction\nBlocks\n»\nSR (FB)\nSR (FB)\nÂ¶\nFUNCTION_BLOCK SR\nRealizes a bistable set-dominat latch\n(* Example declaration *)\nSRInst\n:\nSR\n;\n(* Example in ST *)\nSRInst\n(\nSET1\n:=\nVarBOOL1\n,\nRESET\n:=\nVarBOOL2\n);\nVarBOOL3\n:=\nSRInst.Q1\n;\nInOut:\nScope\nName\nType\nComment\nInput\nSET1\nBOOL\nRising edge: Set\nQ1\nto\nTRUE\n(dominant)\nRESET\nBOOL\nRising edge: Reset\nQ1\nto\nFALSE\nOutput\nQ1\nBOOL\nOutput value\ntop\nCODESYS Group | We\nsoftware\nAutomation.\nto software\n['sɒftwɛər]\ntransitive verb\n__softwared/softwaring\n: to develop software\n// to software automation: to develop software for automation purposes\nThe CODESYS Group is the manufacturer of CODESYS, the leading hardware-independent\n                                    IEC 61131-3 automation software for developing and engineering controller\n                                    applications.\nCODESYS® is a registered trademark.\nCODESYS GmbH\nA member of the CODESYS Group\nMemminger Straße 151, 87439 Kempten\nGermany\nTel.:\n+49-831-54031-0\ninfo@codesys.com\nLegal Notice\nPrivacy Policy\nLinkedIn\nYoutube\nRSS\nDownloads\nLogin\nCODESYS Store\n© 2022 CODESYS GmbH\n| A member of the CODESYS Group",
  "tables": [
    {
      "headers": [
        "Scope",
        "Name",
        "Type",
        "Comment"
      ],
      "rows": [
        {
          "Scope": "Input",
          "Name": "SET1",
          "Type": "BOOL",
          "Comment": "Rising edge: SetQ1toTRUE(dominant)"
        },
        [
          "RESET",
          "BOOL",
          "Rising edge: ResetQ1toFALSE"
        ],
        {
          "Scope": "Output",
          "Name": "Q1",
          "Type": "BOOL",
          "Comment": "Output value"
        }
      ]
    }
  ]
}