{
  "library": "String Segments",
  "title": "_StringPool (FunctionBlock)",
  "url": "https://content.helpme-codesys.com/en/libs/String Segments/Current/Strings/Functionblocks/_StringPool.html",
  "page_title": "_StringPool (FB)",
  "text": "Library Information\nGetLibVersion (Function)\nGetLibVersionNumber (Function)\nIsLibReleased (Function)\nStrings\nAliases\nConstants (GVL)\nIDisposable (Alias)\nRUNE (Alias)\nEnums\nERROR (Enum)\nFunctionblocks\nRange (FunctionBlock)\nIRange\nSetInitialValue (Method)\nUTF8Literal (FunctionBlock)\nSetInitialValue (Method)\n_RangePool (FunctionBlock)\nProtected\n_StringPool (FunctionBlock)\nIStringPool\nSetInitialValue (Method)\n_UTF8String (FunctionBlock)\nIString\nIStringRepresentation\nFunctions\nCompare (Function)\nCopy (Function)\nCreateRangePool (Function)\nCreateString (Function)\nCreateStringPool (Function)\nIsASCIIString (Function)\nIsValidString (Function)\nLen (Function)\nReset (Function)\nRuneCount (Function)\nSetSegment (Function)\nInterfaces\nIRange (Interface)\nGetNextRune (Method)\nReset (Method)\nUngetLastRune (Method)\nIRangePool (Interface)\nGetPoolStatus (Method)\nGetRange (Method)\nIRangeProvider (Interface)\nGetRange (Method)\nIString (Interface)\nGetSegment (Method)\nIsASCII (Method)\nIsValid (Method)\nLen (Method)\nIStringPool (Interface)\nGetPoolConfig (Method)\nGetString (Method)\nIStringRepresentation (Interface)\nLen (Method)\nToIString (Method)\nStructs\nCONFIG (Struct)\nSTATUS (Struct)\nFile and Project Information\nLibrary Reference\nMemory Block Manager\nLibrary Identification\nLibrary Properties\nSysMem\nLibrary Identification\nLibrary Properties\nUTF-8 Encoding Support\nLibrary Identification\nLibrary Properties\nString Segments\nDocs\n»\nStrings\n»\nFunctionblocks\n»\n_StringPool (FB)\n_StringPool (FB)\nÂ¶\nFUNCTION_BLOCK FINAL _StringPool EXTENDS MBM.Disposable IMPLEMENTS\nIStringPool\nProvides a pool of\nIString\ninstances.\nUse the\nGetString\nmethod to get a new instance.\nExample for a\n``\n_StringPool instance with a capacity of 10 IString instances with a size of minimal 80 bytes each:\naxwMemory\n:\nARRAY\n[0..209]\nOF\n__XWORD\n;\nfbStringPool\n:\nSTR._StringPool\n:=\n(\nudiStringSize\n:=\n80\n,\npbyPool\n:=\nADR\n(\naxwMemory\n),\nudiPoolSize\n:=\nSIZEOF\n(\naxwMemory\n));\nstPoolConfig\n:\nSTR.CONFIG\n:=\nfbStringPool.GetPoolConfig\n();\n// -> udiStringSize = 87 | udiCapacity = 10\nPlease take a look to the function blocks in the Library âGeneric String Baseâ\nYou can use the\nGSB.StringPool\nfunction block, which performs the same task in a much more convenient way\nInOut:\nScope\nName\nType\nInitial\nInput Const\nudiStringSize\nUDINT\n16#FFFFFFFF\nudiInitialCapacity\nUDINT\n5\npbyPool\nPOINTER TO BYTE\nudiPoolSize\nUDINT\nusiExtensionFactor\nUSINT\nMethods:\nSetInitialValue\nGetPoolConfig\nGetString\nStructure:\nIStringPool\nGetPoolConfig (Method)\nGetString (Method)\nSetInitialValue (Method)",
  "tables": [
    {
      "headers": [
        "Scope",
        "Name",
        "Type",
        "Initial"
      ],
      "rows": [
        {
          "Scope": "Input Const",
          "Name": "udiStringSize",
          "Type": "UDINT",
          "Initial": "16#FFFFFFFF"
        },
        [
          "udiInitialCapacity",
          "UDINT",
          "5"
        ],
        [
          "pbyPool",
          "POINTER TO BYTE",
          ""
        ],
        [
          "udiPoolSize",
          "UDINT",
          ""
        ],
        [
          "usiExtensionFactor",
          "USINT",
          ""
        ]
      ]
    }
  ]
}