{
  "library": "String Segments",
  "title": "CreateRangePool (Function)",
  "url": "https://content.helpme-codesys.com/en/libs/String Segments/Current/Strings/Functions/CreateRangePool.html",
  "page_title": "CreateRangePool (FUN)",
  "text": "Library Information\nGetLibVersion (Function)\nGetLibVersionNumber (Function)\nIsLibReleased (Function)\nStrings\nAliases\nConstants (GVL)\nIDisposable (Alias)\nRUNE (Alias)\nEnums\nERROR (Enum)\nFunctionblocks\nRange (FunctionBlock)\nIRange\nSetInitialValue (Method)\nUTF8Literal (FunctionBlock)\nSetInitialValue (Method)\n_RangePool (FunctionBlock)\nProtected\n_StringPool (FunctionBlock)\nIStringPool\nSetInitialValue (Method)\n_UTF8String (FunctionBlock)\nIString\nIStringRepresentation\nFunctions\nCompare (Function)\nCopy (Function)\nCreateRangePool (Function)\nCreateString (Function)\nCreateStringPool (Function)\nIsASCIIString (Function)\nIsValidString (Function)\nLen (Function)\nReset (Function)\nRuneCount (Function)\nSetSegment (Function)\nInterfaces\nIRange (Interface)\nGetNextRune (Method)\nReset (Method)\nUngetLastRune (Method)\nIRangePool (Interface)\nGetPoolStatus (Method)\nGetRange (Method)\nIRangeProvider (Interface)\nGetRange (Method)\nIString (Interface)\nGetSegment (Method)\nIsASCII (Method)\nIsValid (Method)\nLen (Method)\nIStringPool (Interface)\nGetPoolConfig (Method)\nGetString (Method)\nIStringRepresentation (Interface)\nLen (Method)\nToIString (Method)\nStructs\nCONFIG (Struct)\nSTATUS (Struct)\nFile and Project Information\nLibrary Reference\nMemory Block Manager\nLibrary Identification\nLibrary Properties\nSysMem\nLibrary Identification\nLibrary Properties\nUTF-8 Encoding Support\nLibrary Identification\nLibrary Properties\nString Segments\nDocs\n»\nStrings\n»\nFunctions\n»\nCreateRangePool (FUN)\nCreateRangePool (FUN)\nÂ¶\nFUNCTION CreateRangePool :\nIRangePool\nCreates a pool for\nIRange\ninstances in the specified memory space\nInOut:\nScope\nName\nType\nInitial\nComment\nReturn\nCreateRangePool\nIRangePool\nInput\npbyPool\nPOINTER TO BYTE\nPointer to the first byte of the memory.\nThis address should aligned to a\n__XWORD\nboundary!\nudiPoolSize\nUDINT\nSize of the allocated memory for the range pool.\nThis size must not be smaller than\nSIZEOF(_RangePool)\n, because it includes an instance of\n_RangePool(FB)\nusiExtensionFactor\nUSINT\n0\nOptional extension factor of the\nIRangePool\ninstance\nOutput\neErrorID\nERROR",
  "tables": [
    {
      "headers": [
        "Scope",
        "Name",
        "Type",
        "Initial",
        "Comment"
      ],
      "rows": [
        {
          "Scope": "Return",
          "Name": "CreateRangePool",
          "Type": "IRangePool",
          "Initial": "",
          "Comment": ""
        },
        {
          "Scope": "Input",
          "Name": "pbyPool",
          "Type": "POINTER TO BYTE",
          "Initial": "",
          "Comment": "Pointer to the first byte of the memory.This address should aligned to a__XWORDboundary!"
        },
        [
          "udiPoolSize",
          "UDINT",
          "",
          "Size of the allocated memory for the range pool.This size must not be smaller thanSIZEOF(_RangePool), because it includes an instance of_RangePool(FB)"
        ],
        [
          "usiExtensionFactor",
          "USINT",
          "0",
          "Optional extension factor of theIRangePoolinstance"
        ],
        {
          "Scope": "Output",
          "Name": "eErrorID",
          "Type": "ERROR",
          "Initial": "",
          "Comment": ""
        }
      ]
    }
  ]
}