{
  "library": "Util",
  "title": "BASE64 (Function)",
  "url": "https://content.helpme-codesys.com/en/libs/Util/Current/Encoding/BASE64.html",
  "page_title": "BASE64 (FUN)",
  "text": "Analog Monitors\nHYSTERESIS (FunctionBlock)\nLIMITALARM (FunctionBlock)\nBCD Conversions\nBCD_TO_BYTE (Function)\nBCD_TO_DWORD (Function)\nBCD_TO_INT (Function)\nBCD_TO_WORD (Function)\nBYTE_TO_BCD (Function)\nDWORD_TO_BCD (Function)\nINT_TO_BCD (Function)\nWORD_TO_BCD (Function)\nBit/Byte Functions\nBIT_AS_BYTE (FunctionBlock)\nBIT_AS_DWORD (FunctionBlock)\nBIT_AS_WORD (FunctionBlock)\nBYTE_AS_BIT (FunctionBlock)\nDWORD_AS_BIT (FunctionBlock)\nEXTRACT (Function)\nGETBIT (Function)\nPACK (Function)\nPUTBIT (Function)\nSETBIT (Function)\nSWITCHBIT (Function)\nUNPACK (FunctionBlock)\nWORD_AS_BIT (FunctionBlock)\nConstants\nTextBlockSize (ParamList)\nController\nPD (FunctionBlock)\nPID\n(FB)\nTemperature control with PID and LIMIT\nPID_FIXCYCLE (FunctionBlock)\nDatatypes\nGEN_MODE (Enum)\nPOINT (Struct)\nPT_SIZE (Struct)\nEncoding\nBASE64 (Function)\nFunction Manipulators\nCHARCURVE (FunctionBlock)\nRAMP_INT (FunctionBlock)\nRAMP_REAL (FunctionBlock)\nGray Conversions\nBYTE_TO_GRAY (Function)\nDWORD_TO_GRAY (Function)\nGRAY_TO_BYTE (Function)\nGRAY_TO_DWORD (Function)\nGRAY_TO_WORD (Function)\nWORD_TO_GRAY (Function)\nHEX/ASCII Functions\nBYTE_TO_HEXinASCII (Function)\nHEXinASCII_TO_BYTE (Function)\nWORD_AS_STRING (Function)\nLibrary Information\nGetLibVersion (Function)\nGetLibVersionNumber (Function)\nIsLibReleased (Function)\nMathematical Functions\nDERIVATIVE (FunctionBlock)\nINTEGRAL (FunctionBlock)\nLIN_TRAFO (FunctionBlock)\nROTATION_DIFFERENCE (FunctionBlock)\nSTATISTICS_INT (FunctionBlock)\nSTATISTICS_REAL (FunctionBlock)\nVARIANCE (FunctionBlock)\nSignals\nBLINK (FunctionBlock)\nFREQ_MEASURE (FunctionBlock)\nGEN (FunctionBlock)\nTimerSwitch\nEnums\nERROR (Enum)\nPERIOD (Enum)\nWEEKDAY (Enum)\nFunctionBlocks\nDateTimeProvider (FunctionBlock)\nGetDateTime (Method)\nTimerSwitch (FunctionBlock)\nIDateTimeProvider\nFunctions\nCombineDateTime (Function)\nDateTimeFromWeek (Function)\nDayOfWeek (Function)\nGetDateTime (Function)\nGetLocalDateTime (Function)\nGetTimeStampsDifference (Function)\nIsLeapYear (Function)\nJoinDateTime (Function)\nLocalDateTime (Function)\nSeparateDateTime (Function)\nSplitDateTime (Function)\nWeekOfYear (Function)\nGlobalConstants\nDAY_FLAGS (GVL)\nTSW (GVL)\nInterfaces\nIDateTimeProvider (Interface)\nGetDateTime (Method)\nStructs\nDateTime (Struct)\nSchedule (Struct)\nSegment (Struct)\nTimeZone (Struct)\nTypes\nDAY (Alias)\nDAYS (Alias)\nHOUR (Alias)\nMILLISECOND (Alias)\nMINUTE (Alias)\nMONTH (Alias)\nSECOND (Alias)\nTZ_NAME (Alias)\nWEEK (Alias)\nYEAR (Alias)\nFile and Project Information\nLibrary Reference\nCmpErrors2 Interfaces\nLibrary Identification\nLibrary Properties\nStandard\nLibrary Identification\nLibrary Properties\nSysMem\nLibrary Identification\nLibrary Properties\nSysTimeRtc\nLibrary Identification\nLibrary Properties\nSysTypes2 Interfaces\nLibrary Identification\nLibrary Properties\nUtil\nDocs\n»\nEncoding\n»\nBASE64 (FUN)\nBASE64 (FUN)\nÂ¶\nFUNCTION BASE64 :\nPT_SIZE\nencodes 8 bit binary data into ASCII data\nA text block (string, binary, array of bytes) will be base64 encoded. The maximum of the block is set in the\nTextBlockSize\nparameter.\nThis size can be changed but must be divisible by 3.\nIf the text block is only a part of a text and followed by more text, the size must be\nTextBlockSize.iBlockSize\nand\nthe\nisLastBlock\nvariable must be set to\nFALSE\n. If a text is not followed by another block, the specific length\nof it must be used and\nisLastBlock\nhas to be set to\nTRUE\n, as shown in the following example. The reason is\nthree 8-bit letters will become four 6-bit letters. If only two 8-Bit letters are remaining at the end, the encoded text is\nfilled with â=â. This must only be at the end of a text.\nExample:\nStringToConvert\n:\nPT_SIZE\n;\nEncodedString\n:\nPT_SIZE\n;\nbyError\n:\nBYTE\n;\nsText\n:\nSTRING\n:=\n'This is a test string.'\n;\nStringToConvert.uiSize\n:=\nLEN\n(\nsText\n);\n(* When another block follows, use the size TextBlockSize.iBlockSize\nand set isLastBlock to FALSE. *)\nStringToConvert.pString\n:=\nADR\n(\nsText\n);\nEncodedString\n:=\nBase64\n(\nTextToEncode\n:=\nStringToConvert\n,\nisLastBlock\n:=\nTRUE\n,\npbyError\n:=\nADR\n(\nbyError\n));\nInOut:\nScope\nName\nType\nComment\nReturn\nBASE64\nPT_SIZE\nA structure with a pointer to the text and its size\n(comprising the terminating character)\nInput\nTextToEncode\nPT_SIZE\nThe text block which should be encoded\nisLastBlock\nBOOL\nTRUE\n: The current text block is the end of a text\nFALSE\n: The current text block is just a small text\npbyError\nPOINTER TO BYTE\n0: No error\n1: Text block is too long\n2: Not divisible through 3\n4: Empty string",
  "tables": [
    {
      "headers": [
        "Scope",
        "Name",
        "Type",
        "Comment"
      ],
      "rows": [
        {
          "Scope": "Return",
          "Name": "BASE64",
          "Type": "PT_SIZE",
          "Comment": "A structure with a pointer to the text and its size\n(comprising the terminating character)"
        },
        {
          "Scope": "Input",
          "Name": "TextToEncode",
          "Type": "PT_SIZE",
          "Comment": "The text block which should be encoded"
        },
        [
          "isLastBlock",
          "BOOL",
          "TRUE: The current text block is the end of a textFALSE: The current text block is just a small text"
        ],
        [
          "pbyError",
          "POINTER TO BYTE",
          "0: No error1: Text block is too long2: Not divisible through 34: Empty string"
        ]
      ]
    }
  ]
}