{
  "library": "Util",
  "title": "BIT_AS_DWORD (FunctionBlock)",
  "url": "https://content.helpme-codesys.com/en/libs/Util/Current/BitByte-Functions/BIT_AS_DWORD.html",
  "page_title": "BIT_AS_DWORD (FB)",
  "text": "Analog Monitors\nHYSTERESIS (FunctionBlock)\nLIMITALARM (FunctionBlock)\nBCD Conversions\nBCD_TO_BYTE (Function)\nBCD_TO_DWORD (Function)\nBCD_TO_INT (Function)\nBCD_TO_WORD (Function)\nBYTE_TO_BCD (Function)\nDWORD_TO_BCD (Function)\nINT_TO_BCD (Function)\nWORD_TO_BCD (Function)\nBit/Byte Functions\nBIT_AS_BYTE (FunctionBlock)\nBIT_AS_DWORD (FunctionBlock)\nBIT_AS_WORD (FunctionBlock)\nBYTE_AS_BIT (FunctionBlock)\nDWORD_AS_BIT (FunctionBlock)\nEXTRACT (Function)\nGETBIT (Function)\nPACK (Function)\nPUTBIT (Function)\nSETBIT (Function)\nSWITCHBIT (Function)\nUNPACK (FunctionBlock)\nWORD_AS_BIT (FunctionBlock)\nConstants\nTextBlockSize (ParamList)\nController\nPD (FunctionBlock)\nPID\n(FB)\nTemperature control with PID and LIMIT\nPID_FIXCYCLE (FunctionBlock)\nDatatypes\nGEN_MODE (Enum)\nPOINT (Struct)\nPT_SIZE (Struct)\nEncoding\nBASE64 (Function)\nFunction Manipulators\nCHARCURVE (FunctionBlock)\nRAMP_INT (FunctionBlock)\nRAMP_REAL (FunctionBlock)\nGray Conversions\nBYTE_TO_GRAY (Function)\nDWORD_TO_GRAY (Function)\nGRAY_TO_BYTE (Function)\nGRAY_TO_DWORD (Function)\nGRAY_TO_WORD (Function)\nWORD_TO_GRAY (Function)\nHEX/ASCII Functions\nBYTE_TO_HEXinASCII (Function)\nHEXinASCII_TO_BYTE (Function)\nWORD_AS_STRING (Function)\nLibrary Information\nGetLibVersion (Function)\nGetLibVersionNumber (Function)\nIsLibReleased (Function)\nMathematical Functions\nDERIVATIVE (FunctionBlock)\nINTEGRAL (FunctionBlock)\nLIN_TRAFO (FunctionBlock)\nROTATION_DIFFERENCE (FunctionBlock)\nSTATISTICS_INT (FunctionBlock)\nSTATISTICS_REAL (FunctionBlock)\nVARIANCE (FunctionBlock)\nSignals\nBLINK (FunctionBlock)\nFREQ_MEASURE (FunctionBlock)\nGEN (FunctionBlock)\nTimerSwitch\nEnums\nERROR (Enum)\nPERIOD (Enum)\nWEEKDAY (Enum)\nFunctionBlocks\nDateTimeProvider (FunctionBlock)\nGetDateTime (Method)\nTimerSwitch (FunctionBlock)\nIDateTimeProvider\nFunctions\nCombineDateTime (Function)\nDateTimeFromWeek (Function)\nDayOfWeek (Function)\nGetDateTime (Function)\nGetLocalDateTime (Function)\nGetTimeStampsDifference (Function)\nIsLeapYear (Function)\nJoinDateTime (Function)\nLocalDateTime (Function)\nSeparateDateTime (Function)\nSplitDateTime (Function)\nWeekOfYear (Function)\nGlobalConstants\nDAY_FLAGS (GVL)\nTSW (GVL)\nInterfaces\nIDateTimeProvider (Interface)\nGetDateTime (Method)\nStructs\nDateTime (Struct)\nSchedule (Struct)\nSegment (Struct)\nTimeZone (Struct)\nTypes\nDAY (Alias)\nDAYS (Alias)\nHOUR (Alias)\nMILLISECOND (Alias)\nMINUTE (Alias)\nMONTH (Alias)\nSECOND (Alias)\nTZ_NAME (Alias)\nWEEK (Alias)\nYEAR (Alias)\nFile and Project Information\nLibrary Reference\nCmpErrors2 Interfaces\nLibrary Identification\nLibrary Properties\nStandard\nLibrary Identification\nLibrary Properties\nSysMem\nLibrary Identification\nLibrary Properties\nSysTimeRtc\nLibrary Identification\nLibrary Properties\nSysTypes2 Interfaces\nLibrary Identification\nLibrary Properties\nUtil\nDocs\n»\nBit/Byte\nFunctions\n»\nBIT_AS_DWORD (FB)\nBIT_AS_DWORD (FB)\nÂ¶\nFUNCTION_BLOCK BIT_AS_DWORD\nConverts 32 input values of data type BOOL into an output value of the data type DWORD\nInOut:\nScope\nName\nType\nComment\nInput\nB00\nBOOL\nInput bit 0\nB01\nBOOL\nInput bit 1\nB02\nBOOL\nInput bit 2\nB03\nBOOL\nInput bit 3\nB04\nBOOL\nInput bit 4\nB05\nBOOL\nInput bit 5\nB06\nBOOL\nInput bit 6\nB07\nBOOL\nInput bit 7\nB08\nBOOL\nInput bit 8\nB09\nBOOL\nInput bit 9\nB10\nBOOL\nInput bit 10\nB11\nBOOL\nInput bit 11\nB12\nBOOL\nInput bit 12\nB13\nBOOL\nInput bit 13\nB14\nBOOL\nInput bit 14\nB15\nBOOL\nInput bit 15\nB16\nBOOL\nInput bit 16\nB17\nBOOL\nInput bit 17\nB18\nBOOL\nInput bit 18\nB19\nBOOL\nInput bit 19\nB20\nBOOL\nInput bit 20\nB21\nBOOL\nInput bit 21\nB22\nBOOL\nInput bit 22\nB23\nBOOL\nInput bit 23\nB24\nBOOL\nInput bit 24\nB25\nBOOL\nInput bit 25\nB26\nBOOL\nInput bit 26\nB27\nBOOL\nInput bit 27\nB28\nBOOL\nInput bit 28\nB29\nBOOL\nInput bit 29\nB30\nBOOL\nInput bit 30\nB31\nBOOL\nInput bit 31\nOutput\nX\nDWORD\nOutput value",
  "tables": [
    {
      "headers": [
        "Scope",
        "Name",
        "Type",
        "Comment"
      ],
      "rows": [
        {
          "Scope": "Input",
          "Name": "B00",
          "Type": "BOOL",
          "Comment": "Input bit 0"
        },
        [
          "B01",
          "BOOL",
          "Input bit 1"
        ],
        [
          "B02",
          "BOOL",
          "Input bit 2"
        ],
        [
          "B03",
          "BOOL",
          "Input bit 3"
        ],
        [
          "B04",
          "BOOL",
          "Input bit 4"
        ],
        [
          "B05",
          "BOOL",
          "Input bit 5"
        ],
        [
          "B06",
          "BOOL",
          "Input bit 6"
        ],
        [
          "B07",
          "BOOL",
          "Input bit 7"
        ],
        [
          "B08",
          "BOOL",
          "Input bit 8"
        ],
        [
          "B09",
          "BOOL",
          "Input bit 9"
        ],
        [
          "B10",
          "BOOL",
          "Input bit 10"
        ],
        [
          "B11",
          "BOOL",
          "Input bit 11"
        ],
        [
          "B12",
          "BOOL",
          "Input bit 12"
        ],
        [
          "B13",
          "BOOL",
          "Input bit 13"
        ],
        [
          "B14",
          "BOOL",
          "Input bit 14"
        ],
        [
          "B15",
          "BOOL",
          "Input bit 15"
        ],
        [
          "B16",
          "BOOL",
          "Input bit 16"
        ],
        [
          "B17",
          "BOOL",
          "Input bit 17"
        ],
        [
          "B18",
          "BOOL",
          "Input bit 18"
        ],
        [
          "B19",
          "BOOL",
          "Input bit 19"
        ],
        [
          "B20",
          "BOOL",
          "Input bit 20"
        ],
        [
          "B21",
          "BOOL",
          "Input bit 21"
        ],
        [
          "B22",
          "BOOL",
          "Input bit 22"
        ],
        [
          "B23",
          "BOOL",
          "Input bit 23"
        ],
        [
          "B24",
          "BOOL",
          "Input bit 24"
        ],
        [
          "B25",
          "BOOL",
          "Input bit 25"
        ],
        [
          "B26",
          "BOOL",
          "Input bit 26"
        ],
        [
          "B27",
          "BOOL",
          "Input bit 27"
        ],
        [
          "B28",
          "BOOL",
          "Input bit 28"
        ],
        [
          "B29",
          "BOOL",
          "Input bit 29"
        ],
        [
          "B30",
          "BOOL",
          "Input bit 30"
        ],
        [
          "B31",
          "BOOL",
          "Input bit 31"
        ],
        {
          "Scope": "Output",
          "Name": "X",
          "Type": "DWORD",
          "Comment": "Output value"
        }
      ]
    }
  ]
}