{
  "library": "Util",
  "title": "LIN_TRAFO (FunctionBlock)",
  "url": "https://content.helpme-codesys.com/en/libs/Util/Current/Mathematical-Functions/LIN_TRAFO.html",
  "page_title": "LIN_TRAFO (FB)",
  "text": "Analog Monitors\nHYSTERESIS (FunctionBlock)\nLIMITALARM (FunctionBlock)\nBCD Conversions\nBCD_TO_BYTE (Function)\nBCD_TO_DWORD (Function)\nBCD_TO_INT (Function)\nBCD_TO_WORD (Function)\nBYTE_TO_BCD (Function)\nDWORD_TO_BCD (Function)\nINT_TO_BCD (Function)\nWORD_TO_BCD (Function)\nBit/Byte Functions\nBIT_AS_BYTE (FunctionBlock)\nBIT_AS_DWORD (FunctionBlock)\nBIT_AS_WORD (FunctionBlock)\nBYTE_AS_BIT (FunctionBlock)\nDWORD_AS_BIT (FunctionBlock)\nEXTRACT (Function)\nGETBIT (Function)\nPACK (Function)\nPUTBIT (Function)\nSETBIT (Function)\nSWITCHBIT (Function)\nUNPACK (FunctionBlock)\nWORD_AS_BIT (FunctionBlock)\nConstants\nTextBlockSize (ParamList)\nController\nPD (FunctionBlock)\nPID\n(FB)\nTemperature control with PID and LIMIT\nPID_FIXCYCLE (FunctionBlock)\nDatatypes\nGEN_MODE (Enum)\nPOINT (Struct)\nPT_SIZE (Struct)\nEncoding\nBASE64 (Function)\nFunction Manipulators\nCHARCURVE (FunctionBlock)\nRAMP_INT (FunctionBlock)\nRAMP_REAL (FunctionBlock)\nGray Conversions\nBYTE_TO_GRAY (Function)\nDWORD_TO_GRAY (Function)\nGRAY_TO_BYTE (Function)\nGRAY_TO_DWORD (Function)\nGRAY_TO_WORD (Function)\nWORD_TO_GRAY (Function)\nHEX/ASCII Functions\nBYTE_TO_HEXinASCII (Function)\nHEXinASCII_TO_BYTE (Function)\nWORD_AS_STRING (Function)\nLibrary Information\nGetLibVersion (Function)\nGetLibVersionNumber (Function)\nIsLibReleased (Function)\nMathematical Functions\nDERIVATIVE (FunctionBlock)\nINTEGRAL (FunctionBlock)\nLIN_TRAFO (FunctionBlock)\nROTATION_DIFFERENCE (FunctionBlock)\nSTATISTICS_INT (FunctionBlock)\nSTATISTICS_REAL (FunctionBlock)\nVARIANCE (FunctionBlock)\nSignals\nBLINK (FunctionBlock)\nFREQ_MEASURE (FunctionBlock)\nGEN (FunctionBlock)\nTimerSwitch\nEnums\nERROR (Enum)\nPERIOD (Enum)\nWEEKDAY (Enum)\nFunctionBlocks\nDateTimeProvider (FunctionBlock)\nGetDateTime (Method)\nTimerSwitch (FunctionBlock)\nIDateTimeProvider\nFunctions\nCombineDateTime (Function)\nDateTimeFromWeek (Function)\nDayOfWeek (Function)\nGetDateTime (Function)\nGetLocalDateTime (Function)\nGetTimeStampsDifference (Function)\nIsLeapYear (Function)\nJoinDateTime (Function)\nLocalDateTime (Function)\nSeparateDateTime (Function)\nSplitDateTime (Function)\nWeekOfYear (Function)\nGlobalConstants\nDAY_FLAGS (GVL)\nTSW (GVL)\nInterfaces\nIDateTimeProvider (Interface)\nGetDateTime (Method)\nStructs\nDateTime (Struct)\nSchedule (Struct)\nSegment (Struct)\nTimeZone (Struct)\nTypes\nDAY (Alias)\nDAYS (Alias)\nHOUR (Alias)\nMILLISECOND (Alias)\nMINUTE (Alias)\nMONTH (Alias)\nSECOND (Alias)\nTZ_NAME (Alias)\nWEEK (Alias)\nYEAR (Alias)\nFile and Project Information\nLibrary Reference\nCmpErrors2 Interfaces\nLibrary Identification\nLibrary Properties\nStandard\nLibrary Identification\nLibrary Properties\nSysMem\nLibrary Identification\nLibrary Properties\nSysTimeRtc\nLibrary Identification\nLibrary Properties\nSysTypes2 Interfaces\nLibrary Identification\nLibrary Properties\nUtil\nDocs\n»\nMathematical\nFunctions\n»\nLIN_TRAFO (FB)\nLIN_TRAFO (FB)\nÂ¶\nFUNCTION_BLOCK LIN_TRAFO\nPerforms a linear transformation\nThe transformation is performed by using the minimum and maximum values\nof the inputs for a linear approximation of the output value.\nApplication example:\nA temperature sensor provides Volt-values (input\nIN\n). These are to be converted to temperature\nvalues in degree centigrade (output\nOUT\n). The input (Volt) values range is defined by the\nlimits\nIN_MIN=0\nand\nIN_MAX=10\n. The output(degree centigrade) value range is defined by the\nlimits\nOUT_MIN=-20\nand\nOUT_MAX=40\n.\nThus for an input of 5 Volt a temperature of 10 degree centigrade will result.\nInOut:\nScope\nName\nType\nComment\nInput\nIN\nREAL\nInput value\nIN_MIN\nREAL\nMinimum input value\nIN_MAX\nREAL\nMaximum input value\nOUT_MIN\nREAL\nCorresponding minimum output value\nOUT_MAX\nREAL\nCorresponding maximum output value\nOutput\nOUT\nREAL\nOutput value\nERROR\nBOOL\nTRUE\n:\nIN_MIN\n=\nIN_MAX\nor\nIN\nout of input range",
  "tables": [
    {
      "headers": [
        "Scope",
        "Name",
        "Type",
        "Comment"
      ],
      "rows": [
        {
          "Scope": "Input",
          "Name": "IN",
          "Type": "REAL",
          "Comment": "Input value"
        },
        [
          "IN_MIN",
          "REAL",
          "Minimum input value"
        ],
        [
          "IN_MAX",
          "REAL",
          "Maximum input value"
        ],
        [
          "OUT_MIN",
          "REAL",
          "Corresponding minimum output value"
        ],
        [
          "OUT_MAX",
          "REAL",
          "Corresponding maximum output value"
        ],
        {
          "Scope": "Output",
          "Name": "OUT",
          "Type": "REAL",
          "Comment": "Output value"
        },
        [
          "ERROR",
          "BOOL",
          "TRUE:IN_MIN=IN_MAXorINout of input range"
        ]
      ]
    }
  ]
}