{
  "library": "Util",
  "title": "PUTBIT (Function)",
  "url": "https://content.helpme-codesys.com/en/libs/Util/Current/BitByte-Functions/PUTBIT.html",
  "page_title": "PUTBIT (FUN)",
  "text": "Analog Monitors\nHYSTERESIS (FunctionBlock)\nLIMITALARM (FunctionBlock)\nBCD Conversions\nBCD_TO_BYTE (Function)\nBCD_TO_DWORD (Function)\nBCD_TO_INT (Function)\nBCD_TO_WORD (Function)\nBYTE_TO_BCD (Function)\nDWORD_TO_BCD (Function)\nINT_TO_BCD (Function)\nWORD_TO_BCD (Function)\nBit/Byte Functions\nBIT_AS_BYTE (FunctionBlock)\nBIT_AS_DWORD (FunctionBlock)\nBIT_AS_WORD (FunctionBlock)\nBYTE_AS_BIT (FunctionBlock)\nDWORD_AS_BIT (FunctionBlock)\nEXTRACT (Function)\nGETBIT (Function)\nPACK (Function)\nPUTBIT (Function)\nSETBIT (Function)\nSWITCHBIT (Function)\nUNPACK (FunctionBlock)\nWORD_AS_BIT (FunctionBlock)\nConstants\nTextBlockSize (ParamList)\nController\nPD (FunctionBlock)\nPID\n(FB)\nTemperature control with PID and LIMIT\nPID_FIXCYCLE (FunctionBlock)\nDatatypes\nGEN_MODE (Enum)\nPOINT (Struct)\nPT_SIZE (Struct)\nEncoding\nBASE64 (Function)\nFunction Manipulators\nCHARCURVE (FunctionBlock)\nRAMP_INT (FunctionBlock)\nRAMP_REAL (FunctionBlock)\nGray Conversions\nBYTE_TO_GRAY (Function)\nDWORD_TO_GRAY (Function)\nGRAY_TO_BYTE (Function)\nGRAY_TO_DWORD (Function)\nGRAY_TO_WORD (Function)\nWORD_TO_GRAY (Function)\nHEX/ASCII Functions\nBYTE_TO_HEXinASCII (Function)\nHEXinASCII_TO_BYTE (Function)\nWORD_AS_STRING (Function)\nLibrary Information\nGetLibVersion (Function)\nGetLibVersionNumber (Function)\nIsLibReleased (Function)\nMathematical Functions\nDERIVATIVE (FunctionBlock)\nINTEGRAL (FunctionBlock)\nLIN_TRAFO (FunctionBlock)\nROTATION_DIFFERENCE (FunctionBlock)\nSTATISTICS_INT (FunctionBlock)\nSTATISTICS_REAL (FunctionBlock)\nVARIANCE (FunctionBlock)\nSignals\nBLINK (FunctionBlock)\nFREQ_MEASURE (FunctionBlock)\nGEN (FunctionBlock)\nTimerSwitch\nEnums\nERROR (Enum)\nPERIOD (Enum)\nWEEKDAY (Enum)\nFunctionBlocks\nDateTimeProvider (FunctionBlock)\nGetDateTime (Method)\nTimerSwitch (FunctionBlock)\nIDateTimeProvider\nFunctions\nCombineDateTime (Function)\nDateTimeFromWeek (Function)\nDayOfWeek (Function)\nGetDateTime (Function)\nGetLocalDateTime (Function)\nGetTimeStampsDifference (Function)\nIsLeapYear (Function)\nJoinDateTime (Function)\nLocalDateTime (Function)\nSeparateDateTime (Function)\nSplitDateTime (Function)\nWeekOfYear (Function)\nGlobalConstants\nDAY_FLAGS (GVL)\nTSW (GVL)\nInterfaces\nIDateTimeProvider (Interface)\nGetDateTime (Method)\nStructs\nDateTime (Struct)\nSchedule (Struct)\nSegment (Struct)\nTimeZone (Struct)\nTypes\nDAY (Alias)\nDAYS (Alias)\nHOUR (Alias)\nMILLISECOND (Alias)\nMINUTE (Alias)\nMONTH (Alias)\nSECOND (Alias)\nTZ_NAME (Alias)\nWEEK (Alias)\nYEAR (Alias)\nFile and Project Information\nLibrary Reference\nCmpErrors2 Interfaces\nLibrary Identification\nLibrary Properties\nStandard\nLibrary Identification\nLibrary Properties\nSysMem\nLibrary Identification\nLibrary Properties\nSysTimeRtc\nLibrary Identification\nLibrary Properties\nSysTypes2 Interfaces\nLibrary Identification\nLibrary Properties\nUtil\nDocs\n»\nBit/Byte\nFunctions\n»\nPUTBIT (FUN)\nPUTBIT (FUN)\nÂ¶\nFUNCTION PUTBIT : DWORD\nSets a bit of a DWORD value\nExample in ST:\nvar1\n:=\n38\n;\n(* binÃ¤r 100110 *)\nvar2\n:=\nPUTBIT\n(\nA\n,\n4\n,\nTRUE\n);\n(* Result: 54 = 2#110110 *)\nvar3\n:=\nPUTBIT\n(\nA\n,\n1\n,\nFALSE\n);\n(* Result: 36 = 2#100100 *)\nInOut:\nScope\nName\nType\nComment\nReturn\nPUTBIT\nDWORD\nValue with the changed bit\nInput\nX\nDWORD\nValue to be manipulated\nN\nBYTE\nPosition of the bit to be changed, starting with 0\nB\nBOOL\nValue of specified bit",
  "tables": [
    {
      "headers": [
        "Scope",
        "Name",
        "Type",
        "Comment"
      ],
      "rows": [
        {
          "Scope": "Return",
          "Name": "PUTBIT",
          "Type": "DWORD",
          "Comment": "Value with the changed bit"
        },
        {
          "Scope": "Input",
          "Name": "X",
          "Type": "DWORD",
          "Comment": "Value to be manipulated"
        },
        [
          "N",
          "BYTE",
          "Position of the bit to be changed, starting with 0"
        ],
        [
          "B",
          "BOOL",
          "Value of specified bit"
        ]
      ]
    }
  ]
}