{
  "library": "Util",
  "title": "RAMP_REAL (FunctionBlock)",
  "url": "https://content.helpme-codesys.com/en/libs/Util/Current/Function-Manipulators/RAMP_REAL.html",
  "page_title": "RAMP_REAL (FB)",
  "text": "Analog Monitors\nHYSTERESIS (FunctionBlock)\nLIMITALARM (FunctionBlock)\nBCD Conversions\nBCD_TO_BYTE (Function)\nBCD_TO_DWORD (Function)\nBCD_TO_INT (Function)\nBCD_TO_WORD (Function)\nBYTE_TO_BCD (Function)\nDWORD_TO_BCD (Function)\nINT_TO_BCD (Function)\nWORD_TO_BCD (Function)\nBit/Byte Functions\nBIT_AS_BYTE (FunctionBlock)\nBIT_AS_DWORD (FunctionBlock)\nBIT_AS_WORD (FunctionBlock)\nBYTE_AS_BIT (FunctionBlock)\nDWORD_AS_BIT (FunctionBlock)\nEXTRACT (Function)\nGETBIT (Function)\nPACK (Function)\nPUTBIT (Function)\nSETBIT (Function)\nSWITCHBIT (Function)\nUNPACK (FunctionBlock)\nWORD_AS_BIT (FunctionBlock)\nConstants\nTextBlockSize (ParamList)\nController\nPD (FunctionBlock)\nPID\n(FB)\nTemperature control with PID and LIMIT\nPID_FIXCYCLE (FunctionBlock)\nDatatypes\nGEN_MODE (Enum)\nPOINT (Struct)\nPT_SIZE (Struct)\nEncoding\nBASE64 (Function)\nFunction Manipulators\nCHARCURVE (FunctionBlock)\nRAMP_INT (FunctionBlock)\nRAMP_REAL (FunctionBlock)\nGray Conversions\nBYTE_TO_GRAY (Function)\nDWORD_TO_GRAY (Function)\nGRAY_TO_BYTE (Function)\nGRAY_TO_DWORD (Function)\nGRAY_TO_WORD (Function)\nWORD_TO_GRAY (Function)\nHEX/ASCII Functions\nBYTE_TO_HEXinASCII (Function)\nHEXinASCII_TO_BYTE (Function)\nWORD_AS_STRING (Function)\nLibrary Information\nGetLibVersion (Function)\nGetLibVersionNumber (Function)\nIsLibReleased (Function)\nMathematical Functions\nDERIVATIVE (FunctionBlock)\nINTEGRAL (FunctionBlock)\nLIN_TRAFO (FunctionBlock)\nROTATION_DIFFERENCE (FunctionBlock)\nSTATISTICS_INT (FunctionBlock)\nSTATISTICS_REAL (FunctionBlock)\nVARIANCE (FunctionBlock)\nSignals\nBLINK (FunctionBlock)\nFREQ_MEASURE (FunctionBlock)\nGEN (FunctionBlock)\nTimerSwitch\nEnums\nERROR (Enum)\nPERIOD (Enum)\nWEEKDAY (Enum)\nFunctionBlocks\nDateTimeProvider (FunctionBlock)\nGetDateTime (Method)\nTimerSwitch (FunctionBlock)\nIDateTimeProvider\nFunctions\nCombineDateTime (Function)\nDateTimeFromWeek (Function)\nDayOfWeek (Function)\nGetDateTime (Function)\nGetLocalDateTime (Function)\nGetTimeStampsDifference (Function)\nIsLeapYear (Function)\nJoinDateTime (Function)\nLocalDateTime (Function)\nSeparateDateTime (Function)\nSplitDateTime (Function)\nWeekOfYear (Function)\nGlobalConstants\nDAY_FLAGS (GVL)\nTSW (GVL)\nInterfaces\nIDateTimeProvider (Interface)\nGetDateTime (Method)\nStructs\nDateTime (Struct)\nSchedule (Struct)\nSegment (Struct)\nTimeZone (Struct)\nTypes\nDAY (Alias)\nDAYS (Alias)\nHOUR (Alias)\nMILLISECOND (Alias)\nMINUTE (Alias)\nMONTH (Alias)\nSECOND (Alias)\nTZ_NAME (Alias)\nWEEK (Alias)\nYEAR (Alias)\nFile and Project Information\nLibrary Reference\nCmpErrors2 Interfaces\nLibrary Identification\nLibrary Properties\nStandard\nLibrary Identification\nLibrary Properties\nSysMem\nLibrary Identification\nLibrary Properties\nSysTimeRtc\nLibrary Identification\nLibrary Properties\nSysTypes2 Interfaces\nLibrary Identification\nLibrary Properties\nUtil\nDocs\n»\nFunction\nManipulators\n»\nRAMP_REAL (FB)\nRAMP_REAL (FB)\nÂ¶\nFUNCTION_BLOCK RAMP_REAL\nLimits the slope of a value to a certain value\nThe function block is similar to\nRAMP_INT\nwith the difference that the inputs\nIN\n,\nASCEND\n,\nDESCEND\nand the output\nOUT\nare of the type\nREAL\n.\nRAMP_REAL\ntakes more computing time but calculates more precisely than\nRAMP_INT\n.\nNote\nA reset of the function block (\nRESET\n=\nTRUE\n) stops the calculation and the last output value\nOUT\nis maintained.\nSo if afterwards the ramp gets restarted by\nRESET\n=\nFALSE\n, it will start with this last output value!\nInOut:\nScope\nName\nType\nComment\nInput\nIN\nREAL\nInput value\nASCEND\nREAL\nMaximum positive slope\nDESCEND\nREAL\nMaximum negative slope (non-negative!)\nTIMEBASE\nTIME\nReference for\nASCEND/DESCEND\n:\nt#0s\n:\nASCEND/DESCEND\ndefined per call\nElse :\nASCEND/DESCEND\ndefined per specified time\nRESET\nBOOL\nResets the function block\nOutput\nOUT\nREAL\nFnction value with limited slope",
  "tables": [
    {
      "headers": [
        "Scope",
        "Name",
        "Type",
        "Comment"
      ],
      "rows": [
        {
          "Scope": "Input",
          "Name": "IN",
          "Type": "REAL",
          "Comment": "Input value"
        },
        [
          "ASCEND",
          "REAL",
          "Maximum positive slope"
        ],
        [
          "DESCEND",
          "REAL",
          "Maximum negative slope (non-negative!)"
        ],
        [
          "TIMEBASE",
          "TIME",
          "Reference forASCEND/DESCEND:t#0s:ASCEND/DESCENDdefined per callElse :ASCEND/DESCENDdefined per specified time"
        ],
        [
          "RESET",
          "BOOL",
          "Resets the function block"
        ],
        {
          "Scope": "Output",
          "Name": "OUT",
          "Type": "REAL",
          "Comment": "Fnction value with limited slope"
        }
      ]
    }
  ]
}