{
  "library": "Util",
  "title": "UNPACK (FunctionBlock)",
  "url": "https://content.helpme-codesys.com/en/libs/Util/Current/BitByte-Functions/UNPACK.html",
  "page_title": "UNPACK (FB)",
  "text": "Analog Monitors\nHYSTERESIS (FunctionBlock)\nLIMITALARM (FunctionBlock)\nBCD Conversions\nBCD_TO_BYTE (Function)\nBCD_TO_DWORD (Function)\nBCD_TO_INT (Function)\nBCD_TO_WORD (Function)\nBYTE_TO_BCD (Function)\nDWORD_TO_BCD (Function)\nINT_TO_BCD (Function)\nWORD_TO_BCD (Function)\nBit/Byte Functions\nBIT_AS_BYTE (FunctionBlock)\nBIT_AS_DWORD (FunctionBlock)\nBIT_AS_WORD (FunctionBlock)\nBYTE_AS_BIT (FunctionBlock)\nDWORD_AS_BIT (FunctionBlock)\nEXTRACT (Function)\nGETBIT (Function)\nPACK (Function)\nPUTBIT (Function)\nSETBIT (Function)\nSWITCHBIT (Function)\nUNPACK (FunctionBlock)\nWORD_AS_BIT (FunctionBlock)\nConstants\nTextBlockSize (ParamList)\nController\nPD (FunctionBlock)\nPID\n(FB)\nTemperature control with PID and LIMIT\nPID_FIXCYCLE (FunctionBlock)\nDatatypes\nGEN_MODE (Enum)\nPOINT (Struct)\nPT_SIZE (Struct)\nEncoding\nBASE64 (Function)\nFunction Manipulators\nCHARCURVE (FunctionBlock)\nRAMP_INT (FunctionBlock)\nRAMP_REAL (FunctionBlock)\nGray Conversions\nBYTE_TO_GRAY (Function)\nDWORD_TO_GRAY (Function)\nGRAY_TO_BYTE (Function)\nGRAY_TO_DWORD (Function)\nGRAY_TO_WORD (Function)\nWORD_TO_GRAY (Function)\nHEX/ASCII Functions\nBYTE_TO_HEXinASCII (Function)\nHEXinASCII_TO_BYTE (Function)\nWORD_AS_STRING (Function)\nLibrary Information\nGetLibVersion (Function)\nGetLibVersionNumber (Function)\nIsLibReleased (Function)\nMathematical Functions\nDERIVATIVE (FunctionBlock)\nINTEGRAL (FunctionBlock)\nLIN_TRAFO (FunctionBlock)\nROTATION_DIFFERENCE (FunctionBlock)\nSTATISTICS_INT (FunctionBlock)\nSTATISTICS_REAL (FunctionBlock)\nVARIANCE (FunctionBlock)\nSignals\nBLINK (FunctionBlock)\nFREQ_MEASURE (FunctionBlock)\nGEN (FunctionBlock)\nTimerSwitch\nEnums\nERROR (Enum)\nPERIOD (Enum)\nWEEKDAY (Enum)\nFunctionBlocks\nDateTimeProvider (FunctionBlock)\nGetDateTime (Method)\nTimerSwitch (FunctionBlock)\nIDateTimeProvider\nFunctions\nCombineDateTime (Function)\nDateTimeFromWeek (Function)\nDayOfWeek (Function)\nGetDateTime (Function)\nGetLocalDateTime (Function)\nGetTimeStampsDifference (Function)\nIsLeapYear (Function)\nJoinDateTime (Function)\nLocalDateTime (Function)\nSeparateDateTime (Function)\nSplitDateTime (Function)\nWeekOfYear (Function)\nGlobalConstants\nDAY_FLAGS (GVL)\nTSW (GVL)\nInterfaces\nIDateTimeProvider (Interface)\nGetDateTime (Method)\nStructs\nDateTime (Struct)\nSchedule (Struct)\nSegment (Struct)\nTimeZone (Struct)\nTypes\nDAY (Alias)\nDAYS (Alias)\nHOUR (Alias)\nMILLISECOND (Alias)\nMINUTE (Alias)\nMONTH (Alias)\nSECOND (Alias)\nTZ_NAME (Alias)\nWEEK (Alias)\nYEAR (Alias)\nFile and Project Information\nLibrary Reference\nCmpErrors2 Interfaces\nLibrary Identification\nLibrary Properties\nStandard\nLibrary Identification\nLibrary Properties\nSysMem\nLibrary Identification\nLibrary Properties\nSysTimeRtc\nLibrary Identification\nLibrary Properties\nSysTypes2 Interfaces\nLibrary Identification\nLibrary Properties\nUtil\nDocs\n»\nBit/Byte\nFunctions\n»\nUNPACK (FB)\nUNPACK (FB)\nÂ¶\nFUNCTION_BLOCK UNPACK\nConverts a byte into 8 bits\nInOut:\nScope\nName\nType\nComment\nInput\nB\nBYTE\nInput value\nOutput\nB0\nBOOL\nOutput bit 0\nB1\nBOOL\nOutput bit 1\nB2\nBOOL\nOutput bit 2\nB3\nBOOL\nOutput bit 3\nB4\nBOOL\nOutput bit 4\nB5\nBOOL\nOutput bit 5\nB6\nBOOL\nOutput bit 6\nB7\nBOOL\nOutput bit 7",
  "tables": [
    {
      "headers": [
        "Scope",
        "Name",
        "Type",
        "Comment"
      ],
      "rows": [
        {
          "Scope": "Input",
          "Name": "B",
          "Type": "BYTE",
          "Comment": "Input value"
        },
        {
          "Scope": "Output",
          "Name": "B0",
          "Type": "BOOL",
          "Comment": "Output bit 0"
        },
        [
          "B1",
          "BOOL",
          "Output bit 1"
        ],
        [
          "B2",
          "BOOL",
          "Output bit 2"
        ],
        [
          "B3",
          "BOOL",
          "Output bit 3"
        ],
        [
          "B4",
          "BOOL",
          "Output bit 4"
        ],
        [
          "B5",
          "BOOL",
          "Output bit 5"
        ],
        [
          "B6",
          "BOOL",
          "Output bit 6"
        ],
        [
          "B7",
          "BOOL",
          "Output bit 7"
        ]
      ]
    }
  ]
}