{
  "library": "SysFile",
  "title": "SysFileFlush (Function)",
  "url": "https://content.helpme-codesys.com/en/libs/SysFile/Current/SysFileFlush.html",
  "page_title": "SysFileFlush (FUN)",
  "text": "Deutsch\nEnglish\nFrançais\nEspañol\nItaliano\nРусский\n日本語\n中文\nMenu\nSearch\nDeutsch\nEnglish\nFrançais\nEspañol\nItaliano\nРусский\n日本語\n中文\nACCESS_MODE (Enum)\nSYS_FILETIME (Struct)\nSYS_FILE_STATUS (Enum)\nSysFileClose (Function)\nSysFileCopy (Function)\nSysFileDelete (Function)\nSysFileDeleteByHandle (Function)\nSysFileEOF (Function)\nSysFileFlush (Function)\nSysFileGetName (Function)\nSysFileGetName2 (Function)\nSysFileGetPath (Function)\nSysFileGetPos (Function)\nSysFileGetSize (Function)\nSysFileGetSizeByHandle (Function)\nSysFileGetStatus (Function)\nSysFileGetStatus2 (Function)\nSysFileGetTime (Function)\nSysFileOpen (Function)\nSysFileRead (Function)\nSysFileRename (Function)\nSysFileSetPos (Function)\nSysFileTruncate (Function)\nSysFileWrite (Function)\nFile and Project Information\nLibrary Reference\nSysTypes2 Interfaces\nLibrary Identification\nLibrary Properties\nSysFile\nDocs\n»\nSysFileFlush (FUN)\nSysFileFlush (FUN)\nÂ¶\nFUNCTION SysFileFlush : RTS_IEC_RESULT\nFlush the file cache and write into the file\nInOut:\nScope\nName\nType\nComment\nReturn\nSysFileFlush\nRTS_IEC_RESULT\nReturns the runtime system error code (see CmpErrors_Itfs.library):\nERR_OK: Succeeded flushing the file\nERR_FAILED: Error occurred during file flush\nERR_NOTIMPLEMENTED: File flush is not implemented\nERR_NOT_SUPPORTED: File flush not available on the target\nInput\nhFile\nRTS_IEC_HANDLE\nHandle of the file\ntop\nCODESYS Group | We\nsoftware\nAutomation.\nto software\n['sɒftwɛər]\ntransitive verb\n__softwared/softwaring\n: to develop software\n// to software automation: to develop software for automation purposes\nThe CODESYS Group is the manufacturer of CODESYS, the leading hardware-independent\n                                    IEC 61131-3 automation software for developing and engineering controller\n                                    applications.\nCODESYS® is a registered trademark.\nCODESYS GmbH\nA member of the CODESYS Group\nMemminger Straße 151, 87439 Kempten\nGermany\nTel.:\n+49-831-54031-0\ninfo@codesys.com\nLegal Notice\nPrivacy Policy\nLinkedIn\nYoutube\nRSS\nDownloads\nLogin\nCODESYS Store\n© 2022 CODESYS GmbH\n| A member of the CODESYS Group",
  "tables": [
    {
      "headers": [
        "Scope",
        "Name",
        "Type",
        "Comment"
      ],
      "rows": [
        {
          "Scope": "Return",
          "Name": "SysFileFlush",
          "Type": "RTS_IEC_RESULT",
          "Comment": "Returns the runtime system error code (see CmpErrors_Itfs.library):ERR_OK: Succeeded flushing the fileERR_FAILED: Error occurred during file flushERR_NOTIMPLEMENTED: File flush is not implementedERR_NOT_SUPPORTED: File flush not available on the target"
        },
        {
          "Scope": "Input",
          "Name": "hFile",
          "Type": "RTS_IEC_HANDLE",
          "Comment": "Handle of the file"
        }
      ]
    }
  ]
}