{
  "library": "String Builder",
  "title": "CreateRangePool (Function)",
  "url": "https://content.helpme-codesys.com/en/libs/String Builder/Current/Builder/Functions/CreateRangePool.html",
  "page_title": "CreateRangePool (FUN)",
  "text": "Builder\nAliases\nConstants (GVL)\nEnums\nENCODING (Alias)\nERROR (Alias)\nSTATS (Alias)\nFunction Blocks\nRange (Alias)\n_RangePool (Alias)\nInterfaces\nIBuilder (Folder)\nICharmap (Alias)\nIString (Alias)\nIStringRepresentation (Folder)\nTypes\nRUNE (Alias)\nFunction Blocks\n_Builder (FunctionBlock)\nIBuilder\nIStringRepresentation\nSetInitialValue (Method)\nFunctions\nCreateRange (Function)\nCreateRangePool (Function)\nLibrary Information\nGetLibVersion (Function)\nGetLibVersionNumber (Function)\nIsLibReleased (Function)\nFile and Project Information\nLibrary Reference\nImmutable String Segments\nLibrary Identification\nLibrary Properties\nMemory Block Manager\nLibrary Identification\nLibrary Properties\nString Builder Base\nLibrary Identification\nLibrary Properties\nString Conversions\nLibrary Identification\nLibrary Properties\nSysMem\nLibrary Identification\nLibrary Properties\nUTF-16 Encoding Support\nLibrary Identification\nLibrary Properties\nUTF-8 Encoding Support\nLibrary Identification\nLibrary Properties\nString Builder\nDocs\n»\nBuilder\n»\nFunctions\n»\nCreateRangePool (FUN)\nCreateRangePool (FUN)\nÂ¶\nFUNCTION CreateRangePool : STR.IRangePool\nCreates a pool for\nIRange\ninstances in the specified memory space\nInOut:\nScope\nName\nType\nInitial\nReturn\nCreateRangePool\nSTR.IRangePool\nInput\npbyPool\nPOINTER TO BYTE\nudiPoolSize\nUDINT\nusiExtensionFactor\nUSINT\n0\nOutput\neErrorID\nSTR.ERROR",
  "tables": [
    {
      "headers": [
        "Scope",
        "Name",
        "Type",
        "Initial"
      ],
      "rows": [
        {
          "Scope": "Return",
          "Name": "CreateRangePool",
          "Type": "STR.IRangePool",
          "Initial": ""
        },
        {
          "Scope": "Input",
          "Name": "pbyPool",
          "Type": "POINTER TO BYTE",
          "Initial": ""
        },
        [
          "udiPoolSize",
          "UDINT",
          ""
        ],
        [
          "usiExtensionFactor",
          "USINT",
          "0"
        ],
        {
          "Scope": "Output",
          "Name": "eErrorID",
          "Type": "STR.ERROR",
          "Initial": ""
        }
      ]
    }
  ]
}