{
  "library": "String Builder",
  "title": "CreateRange (Function)",
  "url": "https://content.helpme-codesys.com/en/libs/String Builder/Current/Builder/Functions/CreateRange.html",
  "page_title": "CreateRange (FUN)",
  "text": "Builder\nAliases\nConstants (GVL)\nEnums\nENCODING (Alias)\nERROR (Alias)\nSTATS (Alias)\nFunction Blocks\nRange (Alias)\n_RangePool (Alias)\nInterfaces\nIBuilder (Folder)\nICharmap (Alias)\nIString (Alias)\nIStringRepresentation (Folder)\nTypes\nRUNE (Alias)\nFunction Blocks\n_Builder (FunctionBlock)\nIBuilder\nIStringRepresentation\nSetInitialValue (Method)\nFunctions\nCreateRange (Function)\nCreateRangePool (Function)\nLibrary Information\nGetLibVersion (Function)\nGetLibVersionNumber (Function)\nIsLibReleased (Function)\nFile and Project Information\nLibrary Reference\nImmutable String Segments\nLibrary Identification\nLibrary Properties\nMemory Block Manager\nLibrary Identification\nLibrary Properties\nString Builder Base\nLibrary Identification\nLibrary Properties\nString Conversions\nLibrary Identification\nLibrary Properties\nSysMem\nLibrary Identification\nLibrary Properties\nUTF-16 Encoding Support\nLibrary Identification\nLibrary Properties\nUTF-8 Encoding Support\nLibrary Identification\nLibrary Properties\nString Builder\nDocs\n»\nBuilder\n»\nFunctions\n»\nCreateRange (FUN)\nCreateRange (FUN)\nÂ¶\nFUNCTION CreateRange : STR.IRange\nReturns a\nSTR.IRange\ninstance placed in the memory area given by the parameters\nInOut:\nScope\nName\nType\nReturn\nCreateRange\nSTR.IRange\nInput\npbyMemory\nPOINTER TO BYTE\nudiMemSize\nUDINT\nOutput\neErrorID\nSTR.ERROR",
  "tables": [
    {
      "headers": [
        "Scope",
        "Name",
        "Type"
      ],
      "rows": [
        {
          "Scope": "Return",
          "Name": "CreateRange",
          "Type": "STR.IRange"
        },
        {
          "Scope": "Input",
          "Name": "pbyMemory",
          "Type": "POINTER TO BYTE"
        },
        [
          "udiMemSize",
          "UDINT"
        ],
        {
          "Scope": "Output",
          "Name": "eErrorID",
          "Type": "STR.ERROR"
        }
      ]
    }
  ]
}