{
  "library": "String Builder",
  "title": "Len (Method)",
  "url": "https://content.helpme-codesys.com/en/libs/String Builder/Current/Builder/Function-Blocks/pou-_Builder/IStringRepresentation/Len.html",
  "page_title": "_Builder.Len (METH)",
  "text": "Builder\nAliases\nConstants (GVL)\nEnums\nENCODING (Alias)\nERROR (Alias)\nSTATS (Alias)\nFunction Blocks\nRange (Alias)\n_RangePool (Alias)\nInterfaces\nIBuilder (Folder)\nICharmap (Alias)\nIString (Alias)\nIStringRepresentation (Folder)\nTypes\nRUNE (Alias)\nFunction Blocks\n_Builder (FunctionBlock)\nIBuilder\nIStringRepresentation\nSetInitialValue (Method)\nFunctions\nCreateRange (Function)\nCreateRangePool (Function)\nLibrary Information\nGetLibVersion (Function)\nGetLibVersionNumber (Function)\nIsLibReleased (Function)\nFile and Project Information\nLibrary Reference\nImmutable String Segments\nLibrary Identification\nLibrary Properties\nMemory Block Manager\nLibrary Identification\nLibrary Properties\nString Builder Base\nLibrary Identification\nLibrary Properties\nString Conversions\nLibrary Identification\nLibrary Properties\nSysMem\nLibrary Identification\nLibrary Properties\nUTF-16 Encoding Support\nLibrary Identification\nLibrary Properties\nUTF-8 Encoding Support\nLibrary Identification\nLibrary Properties\nString Builder\nDocs\n»\nBuilder\n»\nFunction\nBlocks\n»\n_Builder\n(FB)\n»\nIStringRepresentation\n»\n_Builder.Len (METH)\n_Builder.Len (METH)\nÂ¶\nMETHOD FINAL Len : UDINT\nReturns the number of accumulated bytes\nInOut:\nScope\nName\nType\nComment\nReturn\nLen\nUDINT\nOutput\neErrorID\nSTR.ERROR\nCheck error message for better diagnostics",
  "tables": [
    {
      "headers": [
        "Scope",
        "Name",
        "Type",
        "Comment"
      ],
      "rows": [
        {
          "Scope": "Return",
          "Name": "Len",
          "Type": "UDINT",
          "Comment": ""
        },
        {
          "Scope": "Output",
          "Name": "eErrorID",
          "Type": "STR.ERROR",
          "Comment": "Check error message for better diagnostics"
        }
      ]
    }
  ]
}