{
  "library": "DNP3",
  "title": "AnyNumber (Struct)",
  "url": "https://content.helpme-codesys.com/en/libs/DNP3/Current/DNP3/Types/AnyNumber/AnyNumber.html#",
  "page_title": "AnyNumber (STRUCT)",
  "text": "DNP3\nDoc\nIntegration of datapoints into the application\nExample\nIntroduction\nCODESYS DNP3 - Components\nOutstation data model and datapoints\nOutstation datapoint - inputs versa configuration\nOutstation datapoint inputs / outputs of type AnyNumber\nOutstation data flow\nMaster functionality\nMaster data flow\nCalling function block instances\nApplication bringup and debugging\nEnums\nCommandRejectReason (Enum)\nDoubleBitState (Enum)\nError (Enum)\nFunction Blocks\nAnyNumberConverter\nAnyNumberToDINT (FunctionBlock)\nAnyNumberToINT (FunctionBlock)\nAnyNumberToLREAL (FunctionBlock)\nAnyNumberToREAL (FunctionBlock)\nAnyNumberToSINT (FunctionBlock)\nAnyNumberToUDINT (FunctionBlock)\nAnyNumberToUINT (FunctionBlock)\nAnyNumberToUSINT (FunctionBlock)\nDINTToAnyNumber (FunctionBlock)\nINTToAnyNumber (FunctionBlock)\nLREALToAnyNumber (FunctionBlock)\nREALToAnyNumber (FunctionBlock)\nSINTToAnyNumber (FunctionBlock)\nUDINTToAnyNumber (FunctionBlock)\nUINTToAnyNumber (FunctionBlock)\nUSINTToAnyNumber (FunctionBlock)\nETHdeviceHelper (FunctionBlock)\nMaster\nAddressQualifier (Enum)\nAnalogInfo (Struct)\nAutoUpdateMode (Enum)\nCROB_Info (Struct)\nCommands\nFreezeTimeDateField (Enum)\nFunctionCode (Enum)\nMaster (FunctionBlock)\nMasterConfiguration (FunctionBlock)\nMasterConfigurationCOM (FunctionBlock)\nMasterConfigurationIP (FunctionBlock)\nMasterLoggingOptions (Enum)\nPointObserver\nTimeSyncType (Enum)\nOutstation\nDNP3OutstationSessionConfigEvents (Struct)\nDNP3OutstationSessionConfigUnsolicitedResponse (Struct)\nEvents\nGroups\nOutstation (FunctionBlock)\nOutstationConfiguration (FunctionBlock)\nOutstationConfigurationCOM (FunctionBlock)\nOutstationConfigurationIP (FunctionBlock)\nOutstationDataModel (FunctionBlock)\nOutstationDataModelExample (FunctionBlock)\nOutstationLoggingOptions (Enum)\nPoints\nFunctions\nAnyNumber\nAnyNumberArithmetic (Function)\nAnyNumberArithmeticOperation (Enum)\nAnyNumberAssign (Function)\nAnyNumberAssignIfNotEqual (Function)\nAnyNumberCheck (Function)\nAnyNumberClipToLimits (Function)\nAnyNumberCompare (Function)\nAnyNumberCompareOperation (Enum)\nAnyNumberConvertFromDINT (Function)\nAnyNumberConvertFromINT (Function)\nAnyNumberConvertFromLREAL (Function)\nAnyNumberConvertFromREAL (Function)\nAnyNumberConvertFromSINT (Function)\nAnyNumberConvertFromUDINT (Function)\nAnyNumberConvertFromUINT (Function)\nAnyNumberConvertFromUSINT (Function)\nAnyNumberConvertToDINT (Function)\nAnyNumberConvertToINT (Function)\nAnyNumberConvertToLREAL (Function)\nAnyNumberConvertToREAL (Function)\nAnyNumberConvertToSINT (Function)\nAnyNumberConvertToUDINT (Function)\nAnyNumberConvertToUINT (Function)\nAnyNumberConvertToUSINT (Function)\nAnyNumberInitToZero (Function)\nAnyNumberIsWithinLimits (Function)\nAnyNumberMaximum (Function)\nAnyNumberMinimum (Function)\nAnyNumberToString (Function)\nAnyNumberTypeEquals (Function)\nAnyNumberTypeToString (Function)\nAnyNumberValueToString (Function)\nAnyNumberZero (Function)\nGetCurrentDateTime (Function)\nGlobalConstants\nConstants (GVL)\nConstantsInternal (GVL)\nInterfaces\nIPoint (Interface)\nGetDescriptionString (Method)\nIdentificationToString (Method)\nPointNum (Property)\nPointTyp (Property)\nToString (Method)\nIPointObserver (Interface)\nEnabled (Property)\nEquals (Method)\nGetError (Method)\nGetErrorId (Method)\nGetSequenceNumber (Method)\nIsModified (Property)\nKey (Property)\nNum (Property)\nToString (Method)\nTyp (Property)\nParameter\nParameter (ParamList)\nTypes\nAnyNumber\nAnyNumber (Struct)\nAnyNumberPointerUnion (Union)\nAnyNumberType (Enum)\nAnyNumberUnion (Union)\nAnyNumberValueUnion (Union)\nCOMParity (Enum)\nCOMStopBits (Enum)\nDNP3_String (Alias)\nLibrary Information\nGetLibVersion (Function)\nGetLibVersionNumber (Function)\nIsLibReleased (Function)\nFile and Project Information\nLibrary Reference\n3SLicense\nLibrary Identification\nLibrary Properties\nCmpApp\nLibrary Identification\nLibrary Properties\nCmpDNP3\nLibrary Identification\nLibrary Properties\nCmpErrors2 Interfaces\nLibrary Identification\nLibrary Properties\nCmpEventMgr\nLibrary Identification\nLibrary Properties\nCmpLog\nLibrary Identification\nLibrary Properties\nComponent Manager\nLibrary Identification\nLibrary Properties\nIoDrvEthernet Interfaces\nLibrary Identification\nLibrary Properties\nIoDrvUtility\nLibrary Identification\nLibrary Properties\nIoStandard\nLibrary Identification\nLibrary Properties\nStandard\nLibrary Identification\nLibrary Properties\nSysCpuHandling\nLibrary Identification\nLibrary Properties\nSysMem\nLibrary Identification\nLibrary Properties\nSysSocket\nLibrary Identification\nLibrary Properties\nSysTask\nLibrary Identification\nLibrary Properties\nSysTimeCore\nLibrary Identification\nLibrary Properties\nSysTimeRtc\nLibrary Identification\nLibrary Properties\nSysTypes2 Interfaces\nLibrary Identification\nLibrary Properties\nUtil\nLibrary Identification\nLibrary Properties\nLibrary Parameter\nDNP3\nDocs\n»\nDNP3\n»\nTypes\n»\nAnyNumber\n»\nAnyNumber (STRUCT)\nAnyNumber (STRUCT)\nÂ¶\nTYPE AnyNumber : STRUCT\nAnyNumber represents a numeric value either as value or POINTER TO value with variable base type.\nSupported base types:\nSINT (8bit -128 .. 127)\nUSINT (8bit 0 .. 255)\nINT (16bit -32768 .. 32767)\nUINT (16bit 0 .. 65535)\nDINT (32bit -2147483648 .. 2147483647)\nUDINT (32bit 0 .. 4294967295)\nREAL (32bit float)\nDOUBLE (64bit float)\nThe base type is initialized to AnyNumberType.TYPE_NONE, which will be detected as invalid base type on read operations,\nso ensure to set the base type properly.\nUsing the POINTER TO value representation requires the POINTER TO value <> 0 (set u.p.p* according to baseType).\nThe POINTER TO value is initialized to 0, which will be detected as invalid on read / write operations,\nso ensure to set the POINTER TO value properly.\nThere are functions to support certain operations using AnyNumber:\ncompare base type - see\n|AnyNumberBaseTypeEquals|\ncheck for consistency - see\nAnyNumberCheck\ncompare - see\nAnyNumberCompare\nassigment - see\nAnyNumberAssign\narithmetic - see\nAnyNumberArithmetic\nInitialization of AnyNumber is a bit eloquent, but no matter of this simple:\nExample:\n/// AnyNumber base type REAL with value representation\nany1_REAL_value : DNP3.AnyNumber := (\nbaseType:=DNP3.AnyNumberType.TYPE_REAL, /// init the base type\nu:=(val:=(valREAL:=42)) /// init the value\n);\n/// AnyNumber base type REAL with POINTER TO value representation\n/// The value to point to â¦\nany2_value : REAL;\n/// Now the AnyNumber pointing to any2_value\nany2_REAL_POINTER_TO_value : DNP3.AnyNumber := (\nbaseType:=DNP3.AnyNumberType.TYPE_REAL, /// init the base type\nisPtr:=TRUE, /// select POINTER TO value representation\nu:=(p:=(pREAL:=ADR(any2_value))) /// init the POINTER TO\n);\nInOut:\nName\nType\nInitial\nComment\nbaseType\nAnyNumberType\nAnyNumberType.TYPE_NONE\nBase type\nisPtr\nBOOL\nFALSE\nisPtr = TRUE=>represents a POINTER TO value\nu\nAnyNumberUnion\nData holding either the value or POINTER TO value according to baseType.\nFor value representation access u.val.val*\nFor POINTER TO value representation access u.p.p* according to baseType.",
  "tables": [
    {
      "headers": [
        "Name",
        "Type",
        "Initial",
        "Comment"
      ],
      "rows": [
        {
          "Name": "baseType",
          "Type": "AnyNumberType",
          "Initial": "AnyNumberType.TYPE_NONE",
          "Comment": "Base type"
        },
        {
          "Name": "isPtr",
          "Type": "BOOL",
          "Initial": "FALSE",
          "Comment": "isPtr = TRUE=>represents a POINTER TO value"
        },
        {
          "Name": "u",
          "Type": "AnyNumberUnion",
          "Initial": "",
          "Comment": "Data holding either the value or POINTER TO value according to baseType.\nFor value representation access u.val.val*\nFor POINTER TO value representation access u.p.p* according to baseType."
        }
      ]
    }
  ]
}