{
  "library": "CmpBACnet",
  "title": "BACnetReadFile (Function)",
  "url": "https://content.helpme-codesys.com/en/libs/CmpBACnet/Current/BACnetClientAPI/BACnetReadFile.html",
  "page_title": "BACnetReadFile (FUN)",
  "text": "Deutsch\nEnglish\nFrançais\nEspañol\nItaliano\nРусский\n日本語\n中文\nMenu\nSearch\nDeutsch\nEnglish\nFrançais\nEspañol\nItaliano\nРусский\n日本語\n中文\nBACnetAsyncTransactionToken (Struct)\nBACnetClientAPI\nBACnetAcknowledgeAlarm (Function)\nBACnetAddListElement (Function)\nBACnetCancelPendingConfirmedRequest (Function)\nBACnetConfPrivateTransfer (Function)\nBACnetConfTextMessage (Function)\nBACnetCreateObject (Function)\nBACnetCreateObjectResult (Struct)\nBACnetDeleteObject (Function)\nBACnetDeviceCommControl (Function)\nBACnetGetAlarmSummary (Function)\nBACnetGetEnrollmentSummary (Function)\nBACnetGetEventInfo (Function)\nBACnetLifeSafetyOperation (Function)\nBACnetReadAllPropertyDataContents (Function)\nBACnetReadFile (Function)\nBACnetReadProperty (Function)\nBACnetReadPropertyMultiple (Function)\nBACnetReadRange (Function)\nBACnetReinitializeDevice (Function)\nBACnetRemoveListElement (Function)\nBACnetSubscribeCOV (Function)\nBACnetSubscribeCOVProperty (Function)\nBACnetUnconfPrivateTransfer (Function)\nBACnetUnconfTextMessage (Function)\nBACnetWhoHas (Function)\nBACnetWhoIs (Function)\nBACnetWriteFile (Function)\nBACnetWriteGroup (Function)\nBACnetWriteProperty (Function)\nBACnetWritePropertyMultiple (Function)\nadvanced\nBACnetBackupBACnetDevice (Function)\nBACnetCloseClientCustomer (Function)\nBACnetGetClientDeviceCommunication (Function)\nBACnetOpenClientCustomer (Function)\nBACnetRegisterClientCommunicationStateCallback (Function)\nBACnetRegisterClientDataPoint (Function)\nBACnetRegisterClientEventNotification (Function)\nBACnetRegisterClientUnsubscribeCompletionCallback (Function)\nBACnetRestartAllClients (Function)\nBACnetRestoreBACnetDevice (Function)\nBACnetSetClientDeviceCommunication (Function)\nBACnetSetClientDeviceFixAddress (Function)\nBACnetSetClientDeviceFixSubscribeCovTime (Function)\nBACnetSetClientGlobalCommTimingParameters (Function)\nBACnetSetClientGlobalMaxDeviceActions (Function)\nBACnetUnregisterClientDataPoint (Function)\nBACnetUnregisterClientEventNotification (Function)\nFile and Project Information\nLibrary Reference\n3SLicense\nLibrary Identification\nLibrary Properties\nCAA Ressource Manager Extern\nLibrary Identification\nLibrary Properties\nCAA Types Extern\nLibrary Identification\nLibrary Properties\nCmpErrors2 Interfaces\nLibrary Identification\nLibrary Properties\nCmpEventMgr\nLibrary Identification\nLibrary Properties\nCmpLog\nLibrary Identification\nLibrary Properties\nCmpSettings\nLibrary Identification\nLibrary Properties\nComponent Manager\nLibrary Identification\nLibrary Properties\nIoStandard\nLibrary Identification\nLibrary Properties\nStandard\nLibrary Identification\nLibrary Properties\nSysMem\nLibrary Identification\nLibrary Properties\nSysTarget\nLibrary Identification\nLibrary Properties\nSysTask\nLibrary Identification\nLibrary Properties\nSysTypes2 Interfaces\nLibrary Identification\nLibrary Properties\nCmpBACnet\nDocs\n»\nBACnetClientAPI\n»\nBACnetReadFile (FUN)\nBACnetReadFile (FUN)\nÂ¶\nFUNCTION BACnetReadFile :\nIEC_BACNET_STATUS\nSends an AtomicReadFile request.\nSends a request to read the contents of the specified file beginning from the\nspecified position. The file may be accessed as records or as a stream of octets\nthat is defined by the contents of File_Access_Method property of the File object.\nSince the present version of this API does not support a default processing of this\nservice, the user application has to include a Hook procedure to process it. This\nroutine may control APDU properties like APDU length, segmentation, and timeout for\nboth request and response. This routine can execute asynchronously, i.e. this routine\nwill return to the caller before the BACnet reply comes so that the applications can\nkeep running. In this case the response information will be received by the thread\nwhich is responsible for receiving asynchronous responses. An optional\nBACNET_READ_FILE_COMPLETE_CB routine, which is provided by the BACnet application,\nshall be used to process this information. If a number of asynchronous requests are\nsent, the responses shall be queued and identified by the transaction handles. If\napplication does not supply the BACNET_READ_FILE_COMPLETE_CB routine; then the\nBACnetReadFile routine sends a request and waits for reply.\nAsynchron call, which fills pResult with the call result in an asynchronus manner. As soon as pResultStatus\nis\nIEC_BACNET_STATUS.BACNET_STATUS_OK\nthe data in pResult is valid.\nInOut:\nScope\nName\nType\nComment\nReturn\nBACnetReadFile\nIEC_BACNET_STATUS\nA status indicating if the operation worked.\nInput\npSourceAddress\nPOINTER TO\nIEC_BACNET_ADDRESS\nIf the BACnet application has only one device constructed and installed, this can\nbe 0. In this case the MAC address of this device will be used. Otherwise this\nshall be the MAC address returned on device object construction.\npDestinationAddress\nPOINTER TO\nIEC_BACNET_ADDRESS\nThis is the MAC address of the device to which the request\nshould be sent.\npReadInfo\nPOINTER TO\nIEC_BACNET_READ_FILE_INFO\nA pointer to hold the request information data structure. This data structure\ncontains the objectID, File Access Type (\nIEC_BACNET_FILE_ACCESS_TYPE.FILE_ACCESS_STREAM\nor\nIEC_BACNET_FILE_ACCESS_TYPE.FILE_ACCESS_RECORD\n) and Read File Range information.\npAPDUParams\nPOINTER TO\nIEC_BACNET_APDU_PROPERTIES\nA pointer to the APDU-Properties structure which sets APDU properties for this\ntransaction only. This does not change global defaults or settings for the application\nAPDU Properties. This argument may be 0. In this case APDU properties  are used\nwhich were specified in the device object properties of the applications device which\nsends the request.\npResult\nPOINTER TO\nIEC_BACNET_READ_FILE_RESULT\nA pointer to a buffer to hold the response data if successful reading (datatype\nIEC_BACNET_READ_FILE_RESULT\n). This pointer may be 0 if the asynchron call is used.\nIn this case the memory for the response is allocated by the API and the application is\nresponsible to release it with a call to\nBACnetFreeStackAllocatedMemory\nif the\nbuffer is no longer needed.\npTransactionToken\nPOINTER TO\nBACnetAsyncTransactionToken\nTransaction token of the asynchronous call - see\nBACnetAsyncTransactionToken\n.\npError\nPOINTER TO\nIEC_BACNET_ERROR\nA pointer to a structure to hold BACnet Error information. pError may be 0 if the\napplication isnât interested in detailed error information.\ntop\nCODESYS Group | We\nsoftware\nAutomation.\nto software\n['sɒftwɛər]\ntransitive verb\n__softwared/softwaring\n: to develop software\n// to software automation: to develop software for automation purposes\nThe CODESYS Group is the manufacturer of CODESYS, the leading hardware-independent\n                                    IEC 61131-3 automation software for developing and engineering controller\n                                    applications.\nCODESYS® is a registered trademark.\nCODESYS GmbH\nA member of the CODESYS Group\nMemminger Straße 151, 87439 Kempten\nGermany\nTel.:\n+49-831-54031-0\ninfo@codesys.com\nLegal Notice\nPrivacy Policy\nLinkedIn\nYoutube\nRSS\nDownloads\nLogin\nCODESYS Store\n© 2022 CODESYS GmbH\n| A member of the CODESYS Group",
  "tables": [
    {
      "headers": [
        "Scope",
        "Name",
        "Type",
        "Comment"
      ],
      "rows": [
        {
          "Scope": "Return",
          "Name": "BACnetReadFile",
          "Type": "IEC_BACNET_STATUS",
          "Comment": "A status indicating if the operation worked."
        },
        {
          "Scope": "Input",
          "Name": "pSourceAddress",
          "Type": "POINTER TOIEC_BACNET_ADDRESS",
          "Comment": "If the BACnet application has only one device constructed and installed, this can\nbe 0. In this case the MAC address of this device will be used. Otherwise this\nshall be the MAC address returned on device object construction."
        },
        [
          "pDestinationAddress",
          "POINTER TOIEC_BACNET_ADDRESS",
          "This is the MAC address of the device to which the request\nshould be sent."
        ],
        [
          "pReadInfo",
          "POINTER TOIEC_BACNET_READ_FILE_INFO",
          "A pointer to hold the request information data structure. This data structure\ncontains the objectID, File Access Type (IEC_BACNET_FILE_ACCESS_TYPE.FILE_ACCESS_STREAMorIEC_BACNET_FILE_ACCESS_TYPE.FILE_ACCESS_RECORD) and Read File Range information."
        ],
        [
          "pAPDUParams",
          "POINTER TOIEC_BACNET_APDU_PROPERTIES",
          "A pointer to the APDU-Properties structure which sets APDU properties for this\ntransaction only. This does not change global defaults or settings for the application\nAPDU Properties. This argument may be 0. In this case APDU properties  are used\nwhich were specified in the device object properties of the applications device which\nsends the request."
        ],
        [
          "pResult",
          "POINTER TOIEC_BACNET_READ_FILE_RESULT",
          "A pointer to a buffer to hold the response data if successful reading (datatypeIEC_BACNET_READ_FILE_RESULT). This pointer may be 0 if the asynchron call is used.\nIn this case the memory for the response is allocated by the API and the application is\nresponsible to release it with a call toBACnetFreeStackAllocatedMemoryif the\nbuffer is no longer needed."
        ],
        [
          "pTransactionToken",
          "POINTER TOBACnetAsyncTransactionToken",
          "Transaction token of the asynchronous call - seeBACnetAsyncTransactionToken."
        ],
        [
          "pError",
          "POINTER TOIEC_BACNET_ERROR",
          "A pointer to a structure to hold BACnet Error information. pError may be 0 if the\napplication isnât interested in detailed error information."
        ]
      ]
    }
  ]
}