{
  "library": "CmpBACnet",
  "title": "BACnetUnregisterClientEventNotification (Function)",
  "url": "https://content.helpme-codesys.com/en/libs/CmpBACnet/Current/BACnetClientAPI/advanced/BACnetUnregisterClientEventNotification.html",
  "page_title": "BACnetUnregisterClientEventNotification (FUN)",
  "text": "Deutsch\nEnglish\nFrançais\nEspañol\nItaliano\nРусский\n日本語\n中文\nMenu\nSearch\nDeutsch\nEnglish\nFrançais\nEspañol\nItaliano\nРусский\n日本語\n中文\nBACnetAsyncTransactionToken (Struct)\nBACnetClientAPI\nBACnetAcknowledgeAlarm (Function)\nBACnetAddListElement (Function)\nBACnetCancelPendingConfirmedRequest (Function)\nBACnetConfPrivateTransfer (Function)\nBACnetConfTextMessage (Function)\nBACnetCreateObject (Function)\nBACnetCreateObjectResult (Struct)\nBACnetDeleteObject (Function)\nBACnetDeviceCommControl (Function)\nBACnetGetAlarmSummary (Function)\nBACnetGetEnrollmentSummary (Function)\nBACnetGetEventInfo (Function)\nBACnetLifeSafetyOperation (Function)\nBACnetReadAllPropertyDataContents (Function)\nBACnetReadFile (Function)\nBACnetReadProperty (Function)\nBACnetReadPropertyMultiple (Function)\nBACnetReadRange (Function)\nBACnetReinitializeDevice (Function)\nBACnetRemoveListElement (Function)\nBACnetSubscribeCOV (Function)\nBACnetSubscribeCOVProperty (Function)\nBACnetUnconfPrivateTransfer (Function)\nBACnetUnconfTextMessage (Function)\nBACnetWhoHas (Function)\nBACnetWhoIs (Function)\nBACnetWriteFile (Function)\nBACnetWriteGroup (Function)\nBACnetWriteProperty (Function)\nBACnetWritePropertyMultiple (Function)\nadvanced\nBACnetBackupBACnetDevice (Function)\nBACnetCloseClientCustomer (Function)\nBACnetGetClientDeviceCommunication (Function)\nBACnetOpenClientCustomer (Function)\nBACnetRegisterClientCommunicationStateCallback (Function)\nBACnetRegisterClientDataPoint (Function)\nBACnetRegisterClientEventNotification (Function)\nBACnetRegisterClientUnsubscribeCompletionCallback (Function)\nBACnetRestartAllClients (Function)\nBACnetRestoreBACnetDevice (Function)\nBACnetSetClientDeviceCommunication (Function)\nBACnetSetClientDeviceFixAddress (Function)\nBACnetSetClientDeviceFixSubscribeCovTime (Function)\nBACnetSetClientGlobalCommTimingParameters (Function)\nBACnetSetClientGlobalMaxDeviceActions (Function)\nBACnetUnregisterClientDataPoint (Function)\nBACnetUnregisterClientEventNotification (Function)\nFile and Project Information\nLibrary Reference\n3SLicense\nLibrary Identification\nLibrary Properties\nCAA Ressource Manager Extern\nLibrary Identification\nLibrary Properties\nCAA Types Extern\nLibrary Identification\nLibrary Properties\nCmpErrors2 Interfaces\nLibrary Identification\nLibrary Properties\nCmpEventMgr\nLibrary Identification\nLibrary Properties\nCmpLog\nLibrary Identification\nLibrary Properties\nCmpSettings\nLibrary Identification\nLibrary Properties\nComponent Manager\nLibrary Identification\nLibrary Properties\nIoStandard\nLibrary Identification\nLibrary Properties\nStandard\nLibrary Identification\nLibrary Properties\nSysMem\nLibrary Identification\nLibrary Properties\nSysTarget\nLibrary Identification\nLibrary Properties\nSysTask\nLibrary Identification\nLibrary Properties\nSysTypes2 Interfaces\nLibrary Identification\nLibrary Properties\nCmpBACnet\nDocs\n»\nBACnetClientAPI\n»\nadvanced\n»\nBACnetUnregisterClientEventNotification (FUN)\nBACnetUnregisterClientEventNotification (FUN)\nÂ¶\nFUNCTION BACnetUnregisterClientEventNotification :\nIEC_BACNET_STATUS\nReleases an device notification class reference from event acquisation.\nThe user application can remove device notification class references from event\nacquisation which it doesnât need anymore. If the user application has registered an\ncallback for unsubscribe completion, it will get notified about the successful or\nunsuccessful unsubscription asynchronously.\nReturns\nBACNET_STATUS_BUSY: if unsubscription is pending. The registered unsubscribe-complete\ncallback will be called on completion\nBACNET_STATUS_OK:   unsubscription completed. The registered unsubscribe-complete\ncallback WILL NOT BE CALLED\nOTHER:              some other failure in given parameters has been detected\nInOut:\nScope\nName\nType\nComment\nReturn\nBACnetUnregisterClientEventNotification\nIEC_BACNET_STATUS\nInput\nhCustomer\nIEC_BACNET_HANDLE\nAn handle to an created advanced BACnet client customer created by\nBACnetOpenClientCustomer\n.\ndevId\nIEC_BACNET_INST_NUMBER\nThe device instance number from the remote or local device from which the events or\nalarms shall NOT be acquired anymore.\nnotifClass\nIEC_BACNET_INST_NUMBER\nThe notification class object instance number from the remote or local device from\nwhich the events or alarms shall NOT be acquired anymore.\ntop\nCODESYS Group | We\nsoftware\nAutomation.\nto software\n['sɒftwɛər]\ntransitive verb\n__softwared/softwaring\n: to develop software\n// to software automation: to develop software for automation purposes\nThe CODESYS Group is the manufacturer of CODESYS, the leading hardware-independent\n                                    IEC 61131-3 automation software for developing and engineering controller\n                                    applications.\nCODESYS® is a registered trademark.\nCODESYS GmbH\nA member of the CODESYS Group\nMemminger Straße 151, 87439 Kempten\nGermany\nTel.:\n+49-831-54031-0\ninfo@codesys.com\nLegal Notice\nPrivacy Policy\nLinkedIn\nYoutube\nRSS\nDownloads\nLogin\nCODESYS Store\n© 2022 CODESYS GmbH\n| A member of the CODESYS Group",
  "tables": [
    {
      "headers": [
        "Scope",
        "Name",
        "Type",
        "Comment"
      ],
      "rows": [
        {
          "Scope": "Return",
          "Name": "BACnetUnregisterClientEventNotification",
          "Type": "IEC_BACNET_STATUS",
          "Comment": ""
        },
        {
          "Scope": "Input",
          "Name": "hCustomer",
          "Type": "IEC_BACNET_HANDLE",
          "Comment": "An handle to an created advanced BACnet client customer created byBACnetOpenClientCustomer."
        },
        [
          "devId",
          "IEC_BACNET_INST_NUMBER",
          "The device instance number from the remote or local device from which the events or\nalarms shall NOT be acquired anymore."
        ],
        [
          "notifClass",
          "IEC_BACNET_INST_NUMBER",
          "The notification class object instance number from the remote or local device from\nwhich the events or alarms shall NOT be acquired anymore."
        ]
      ]
    }
  ]
}